Workbook

Sheet 00_羅針盤
A1: 🧭 KHD羅針盤 — 家族の未来 × 事業の優先度（今日の1枚）
A2: 北極星=①家族の未来 ／ 海図=②医療GD ／ 計器盤=③司令塔(月次実績)。この羅針盤が3つを束ねて『今どこに時間を割くか』を決める。
A4: 🎯 センターピン（これを外さなければ倒れる1本）
A5: 家族の未来に要る“年間の事業CF”を1つの数字に確定し、それを最短・最確で生む順＝①医療テナント承継(客付き現金) ②不動産フック(資金化)で現金を作り、③AI医療④オーロラに仕込み、⑤クリニック買収は5年後の本丸(今は種・猪突猛進NG)。保険診療＝制度が客を連れてくる永久機関を握るのが終点。
A9: 今年（西暦） | B9: ='01_必要CF逆算'!$B$4
A11: 今年の必要事業CF（万） | B11: ='01_必要CF逆算'!$B$15 | C11: ①家族逆算が要求する世帯収入＝事業で作る額
A12: 02の貢献CF目標 合計（万） | B12: ='02_事業優先度'!$B$10 | C12: 事業ごとの今年CF目標の合計
A13: 今の純資産（万） | B13: 2893 | C13: ③司令塔/①起点を手入力。IMPORTRANGEで自動化可
A14: 法人現預金（万） | B14: 0 | C14: ③から手入力。赤信号判定に使う
A15: CF充足（目標−必要） | B15: =B12-B11 | C15: =IF(B12>=B11,"🟢 今年の家族コストは事業目標で賄える","🟡 不足：上位事業のCF目標を上げる/支出を見直す")
A16: 資金 赤信号 | B16: =IF(B14<100,"🔴 営業フル","🟢 OK") | C16: 法人現預金100万割れ／医療2ヶ月連続0成約→学習中断・営業フル（②赤信号ライン）
A18: ▶ 今週の1手（構想倒れ防止）
A19: 6/15週：京橋・山崎先生ヒアリングで①クラウド不安への回答(動画TTP)②運営中も使う継続診療圏コンサル の2点を実地検証。並行して福井ルートで医療テナント承継を1件/Qの複線化（今期センターピン＝現金）。
A23: 運用順序：①(年に要る金)→この羅針盤(どの事業で作るか優先度)→③(月次で実績入力・現在地)→②(案件ごとに目利き・査定)。月初=①と02見直し／週次=この00／日次=③入力。

Sheet 01_必要CF逆算
A1: 💰 必要CF逆算 — 家族の未来から『今年いくら事業で稼ぐか』
A2: ①家族の未来_逆算（世帯純収入シナリオ）と同じ数字。①が正本。ズレたらここを合わせる（末尾のIMPORTRANGEで自動化も可）。
A4: 今年（西暦） | B4: 2026
A6: ■ 必要事業CF シナリオ（万/年）※①の【2】世帯純収入と一致
A7: 年 | B7: 必要事業CF(万) | C7: 区分 | D7: メモ
A8: 2026 | B8: 400 | C8: 立上げ期 | D8: 給与ゼロ・栄町等スポット
A9: 2027 | B9: 550 | C9: 黒字化 | D9: 営業委譲開始・AI型化
A10: 2028 | B10: 750 | C10: 果実の入口 | D10: 複数事業CF・第2子
A11: 2029 | B11: 900 | C11: 成長
A12: 2030 | B12: 1000 | C12: 成長
A13: 2031 | B13: 1100 | C13: 安定〜 | D13: 仕組み化後の世帯手取り
A15: ▶ 今年の必要事業CF（自動） | B15: =IF($B$4<=2026,B8,IF($B$4=2027,B9,IF($B$4=2028,B10,IF($B$4=2029,B11,IF($B$4=2030,B12,B13))))) | C15: 00羅針盤と03フェーズがこの値を参照
A17: (参考) ゴール積立/年 家+車+留学 | B17: =38.5*12 | C17: ①02ゴール別逆算の積立合計。教育・老後は事業CFの果実で別途
A19: ■ 03フェーズ用 生年
A20: 研太 | B20: 1992
A21: 葵斗 | B21: 2026

Sheet 02_事業優先度
A1: 🧱 事業優先度マトリクス — 家族のお金をどの事業で・どの順に作るか
A2: 各項目1〜5で入力(🟡)。今期スコア=即金性×2+時間ROI×2+永久機関度+強み ／ 戦略スコア=永久機関度×2+強み+時間ROI。象限で“今すぐ現金/仕込み/本丸”を仕分け。出典②事業構造比較。
A3: 事業 | B3: 今年の貢献CF目標(万) | C3: 即金性 | D3: 永久機関度 | E3: 時間ROI | F3: KHD強み適合 | G3: 今期スコア | H3: 戦略スコア | I3: 象限 | J3: 今の一手 / 撤退ライン
A4: ①医療テナント承継(TAW/福井) | B4: 220 | C4: 5 | D4: 2 | E4: 5 | F4: 5 | G4: =C4*2+E4*2+D4+F4 | H4: =D4*2+F4+E4 | I4: =IF(AND(G4>=20,H4>=15),"両取り",IF(AND(G4>=20,H4<15),"現金源(深追禁)",IF(AND(G4<20,H4>=15),"仕込む(投資)","縮小/見送り"))) | J4: 福井ルート複線化・1件/Q。2ヶ月連続0→営業フル
A5: ②不動産 再販/紹介(フック) | B5: 200 | C5: 5 | D5: 1 | E5: 4 | F5: 5 | G5: =C5*2+E5*2+D5+F5 | H5: =D5*2+F5+E5 | I5: =IF(AND(G5>=20,H5>=15),"両取り",IF(AND(G5>=20,H5<15),"現金源(深追禁)",IF(AND(G5<20,H5>=15),"仕込む(投資)","縮小/見送り"))) | J5: 在庫の損切り完了→仕込み資金を医療へ。出口未確定の在庫を増やさない
A6: ③AI医療コンサル(My AI) | B6: 30 | C6: 2 | D6: 4 | E6: 4 | F6: 4 | G6: =C6*2+E6*2+D6+F6 | H6: =D6*2+F6+E6 | I6: =IF(AND(G6>=20,H6>=15),"両取り",IF(AND(G6>=20,H6<15),"現金源(深追禁)",IF(AND(G6<20,H6>=15),"仕込む(投資)","縮小/見送り"))) | J6: 山崎6/15ヒアリング→診断許可→月5万保守×院数
A7: ④オーロラ訪問医療FC | B7: -50 | C7: 2 | D7: 4 | E7: 3 | F7: 4 | G7: =C7*2+E7*2+D7+F7 | H7: =D7*2+F7+E7 | I7: =IF(AND(G7>=20,H7>=15),"両取り",IF(AND(G7>=20,H7<15),"現金源(深追禁)",IF(AND(G7<20,H7>=15),"仕込む(投資)","縮小/見送り"))) | J7: 公庫満額申請・採用1名・ケアマネ送客5/月。最大損700万で撤退
A8: ⑤クリニック買収(将来) | B8: 0 | C8: 1 | D8: 5 | E8: 3 | F8: 5 | G8: =C8*2+E8*2+D8+F8 | H8: =D8*2+F8+E8 | I8: =IF(AND(G8>=20,H8>=15),"両取り",IF(AND(G8>=20,H8<15),"現金源(深追禁)",IF(AND(G8<20,H8>=15),"仕込む(投資)","縮小/見送り"))) | J8: 今は種。Phase2まで猪突猛進しない・回収前に現金切らさない
A9: 貢献CF目標 合計 | B9: =SUM(B4:B8)
A11: 凡例：即金性=今年すぐ現金になる ／ 永久機関度=制度が客を連れる(ストック) ／ 時間ROI=粗利/投下時間 ／ 強み適合=目利き・営業・不動産がどれだけ活きるか。1=低 5=高。
A13: 読み：『現金源』=今の生命線(医療テナント・不動産)で食い扶持を作る。『仕込む』=オーロラ/買収に時間と金を投じ将来の永久機関にする。猪突猛進NGは買収。

Sheet 03_5年フェーズ
A1: 🗺 5年フェーズ羅針盤 — 家族イベント × 事業の手（①と②を1枚に）
A2: 必要事業CFは01から年で連動。主担当は02の象限(現金源/仕込む)に対応。②ロードマップと①家族イベントを統合した将来図。
A3: 年 | B3: 研太 | C3: 葵斗 | D3: 家族イベント | E3: 必要事業CF(万) | F3: 主担当(現金/仕込) | G3: 事業の打つ手 | H3: 守り・赤信号/撤退
A4: 2026 | B4: =$A4-'01_必要CF逆算'!$B$20 | C4: =IF($A4>='01_必要CF逆算'!$B$21,$A4-'01_必要CF逆算'!$B$21,"") | D4: 葵斗9/19誕生・結婚記念4周年 | E4: =IF($A4<=2026,'01_必要CF逆算'!$B$8,IF($A4=2027,'01_必要CF逆算'!$B$9,IF($A4=2028,'01_必要CF逆算'!$B$10,IF($A4=2029,'01_必要CF逆算'!$B$11,IF($A4=2030,'01_必要CF逆算'!$B$12,'01_必要CF逆算'!$B$13))))) | F4: 現金源：医療テナント+不動産 | G4: オーロラ開業・公庫融資／山崎AI初受注／栄町決済190 | H4: 最大損700万・現預金100万割れで営業フル
A5: 2027 | B5: =$A5-'01_必要CF逆算'!$B$20 | C5: =IF($A5>='01_必要CF逆算'!$B$21,$A5-'01_必要CF逆算'!$B$21,"") | D5: — | E5: =IF($A5<=2026,'01_必要CF逆算'!$B$8,IF($A5=2027,'01_必要CF逆算'!$B$9,IF($A5=2028,'01_必要CF逆算'!$B$10,IF($A5=2029,'01_必要CF逆算'!$B$11,IF($A5=2030,'01_必要CF逆算'!$B$12,'01_必要CF逆算'!$B$13))))) | F5: 現金源＋仕込：AI医療 | G5: 黒字化・役員報酬600／営業委譲開始・AI型化／調査士合格 | H5: 医療2ヶ月連続0→学習中断
A6: 2028 | B6: =$A6-'01_必要CF逆算'!$B$20 | C6: =IF($A6>='01_必要CF逆算'!$B$21,$A6-'01_必要CF逆算'!$B$21,"") | D6: 第2子誕生 | E6: =IF($A6<=2026,'01_必要CF逆算'!$B$8,IF($A6=2027,'01_必要CF逆算'!$B$9,IF($A6=2028,'01_必要CF逆算'!$B$10,IF($A6=2029,'01_必要CF逆算'!$B$11,IF($A6=2030,'01_必要CF逆算'!$B$12,'01_必要CF逆算'!$B$13))))) | F6: 仕込：オーロラ横展開 | G6: 複数事業の入口／買収候補リスト化／owned media | H6: 回収前に現金切らさない
A7: 2029 | B7: =$A7-'01_必要CF逆算'!$B$20 | C7: =IF($A7>='01_必要CF逆算'!$B$21,$A7-'01_必要CF逆算'!$B$21,"") | D7: 住み替え物件探し | E7: =IF($A7<=2026,'01_必要CF逆算'!$B$8,IF($A7=2027,'01_必要CF逆算'!$B$9,IF($A7=2028,'01_必要CF逆算'!$B$10,IF($A7=2029,'01_必要CF逆算'!$B$11,IF($A7=2030,'01_必要CF逆算'!$B$12,'01_必要CF逆算'!$B$13))))) | F7: 仕込：クリニック買収DD | G7: ★クリニック1号査定／医療モール用地(越谷) | H7: のれん毀損リスク・DD厳格に
A8: 2030 | B8: =$A8-'01_必要CF逆算'!$B$20 | C8: =IF($A8>='01_必要CF逆算'!$B$21,$A8-'01_必要CF逆算'!$B$21,"") | D8: 住み替え準備・事前審査 | E8: =IF($A8<=2026,'01_必要CF逆算'!$B$8,IF($A8=2027,'01_必要CF逆算'!$B$9,IF($A8=2028,'01_必要CF逆算'!$B$10,IF($A8=2029,'01_必要CF逆算'!$B$11,IF($A8=2030,'01_必要CF逆算'!$B$12,'01_必要CF逆算'!$B$13))))) | F8: 現金+資産 | G8: 役員報酬720／モール開発／買収2号査定 | H8: 住宅与信は3期黒字が前提
A9: 2031 | B9: =$A9-'01_必要CF逆算'!$B$20 | C9: =IF($A9>='01_必要CF逆算'!$B$21,$A9-'01_必要CF逆算'!$B$21,"") | D9: ★住み替え(住宅ローン6000)・第3子誕生 | E9: =IF($A9<=2026,'01_必要CF逆算'!$B$8,IF($A9=2027,'01_必要CF逆算'!$B$9,IF($A9=2028,'01_必要CF逆算'!$B$10,IF($A9=2029,'01_必要CF逆算'!$B$11,IF($A9=2030,'01_必要CF逆算'!$B$12,'01_必要CF逆算'!$B$13))))) | F9: 資産化 | G9: 住宅取得(資産)／MS法人化・TAW直下統合 | H9: 住替で現金を使い切らない
A10: 2033 | B10: =$A10-'01_必要CF逆算'!$B$20 | C10: =IF($A10>='01_必要CF逆算'!$B$21,$A10-'01_必要CF逆算'!$B$21,"") | D10: 葵斗 小学校入学 | E10: =IF($A10<=2026,'01_必要CF逆算'!$B$8,IF($A10=2027,'01_必要CF逆算'!$B$9,IF($A10=2028,'01_必要CF逆算'!$B$10,IF($A10=2029,'01_必要CF逆算'!$B$11,IF($A10=2030,'01_必要CF逆算'!$B$12,'01_必要CF逆算'!$B$13))))) | F10: 受動化へ | G10: 番頭運営・地域医療PF骨格／介護施設1号 | H10: 属人化(単一障害点)を外す
A11: 2039 | B11: =$A11-'01_必要CF逆算'!$B$20 | C11: =IF($A11>='01_必要CF逆算'!$B$21,$A11-'01_必要CF逆算'!$B$21,"") | D11: 葵斗 マレーシア留学 | E11: =IF($A11<=2026,'01_必要CF逆算'!$B$8,IF($A11=2027,'01_必要CF逆算'!$B$9,IF($A11=2028,'01_必要CF逆算'!$B$10,IF($A11=2029,'01_必要CF逆算'!$B$11,IF($A11=2030,'01_必要CF逆算'!$B$12,'01_必要CF逆算'!$B$13))))) | F11: 資産が生む | G11: 委譲完了・地域包括ケア網 | H11: 教育費ピーク入口
A12: 2046 | B12: =$A12-'01_必要CF逆算'!$B$20 | C12: =IF($A12>='01_必要CF逆算'!$B$21,$A12-'01_必要CF逆算'!$B$21,"") | D12: ★葵斗20歳 自立/承継 | E12: =IF($A12<=2026,'01_必要CF逆算'!$B$8,IF($A12=2027,'01_必要CF逆算'!$B$9,IF($A12=2028,'01_必要CF逆算'!$B$10,IF($A12=2029,'01_必要CF逆算'!$B$11,IF($A12=2030,'01_必要CF逆算'!$B$12,'01_必要CF逆算'!$B$13))))) | F12: 資産が生む | G12: 葵斗へバトン・地域医療介護PF完成＝FIRE | H12: —

Sheet 04_使い分けガイド
A1: 🧭 4スプシの使い分け・更新頻度・連動
A3: 役割 | B3: 正体 | C3: 使う頻度 | D3: horizon | E3: いつ開くか
A4: 北極星 ①家族の未来 | B4: いくら要るか(家計逆算) | C4: 月1/四半期 | D4: 35年・年次 | E4: 月初に必要CFを確認
A5: 羅針盤 (この本) | B5: どの事業で・どの順で作るか | C5: 週1(経営) | D5: 5〜20年 | E5: 毎週の経営判断・優先度設定
A6: 海図 ②医療GD | B6: 事業の地図・査定基準 | C6: 案件時/四半期 | D6: 20年 | E6: 承継/買収/開業の目利き時
A7: 計器盤 ③司令塔 | B7: 今月の実績・資金繰り | C7: 日次/月次 | D7: 今月〜今期 | E7: 日次の実績入力・現在地確認
A9: ■ ②医療GD のタブ整理（必須/低優先/移管）
A10: 区分 | B10: 対象タブ
A11: 🟢必須(常用) | B11: トップサマリ(顔/箱/エンジン+4論点+ロードマップ+今週1手) ／ 事業構造比較 ／ 逆算KPI(下中上) ／ 赤信号ライン
A12: 🟡必須(案件時) | B12: 共通チェックリストA-G ／ 倒産10要因 ／ 診療圏4フェーズ(コンサル商品設計)
A13: ⬜低優先(読み物/将来) | B13: 組織形態の進化(MS法人) ／ 横展開先 ／ 競合プレイヤー ／ AIコンサルTTP動画論点 → clinic_dx側へ
A14: ➡️移管 or 非表示 | B14: 家族タイムライン→この羅針盤03へ ／ 四半期業績→③司令塔へ ／ 幸福の資本論→①へ ／ 役員報酬→住宅ローン→①へ
A16: ■ クロス連動(任意・推奨)：Google Sheets化後、下を貼ると①③から自動取得できる（初回『アクセスを許可』クリック要）
A17: ①の今年収入を引く（00のB11へ）： =IMPORTRANGE("1LlWyTv8Qco6NprgezpK8vOKbDdJeGvWZPqtWgWsFSY4","03_生涯CF_子3人!H"&(今年-2026+5))
A18: ③の純資産/現預金を引く（00のB13/B14へ）： =IMPORTRANGE("1ofLJOFuW5175OHDSy0J0561LzrfAU-M015o7ByGH5wc","操縦席や06BSの該当セル")
A19: 凡例：🟡=手入力(変えると連動) ／ 緑字=他タブ参照 ／ 橙=センターピン ／ 紺=見出し。
