Workbook
Name chinryo_list: '9賃料一覧'!$A$3:$T$1500
Name current_year: settings!$L$3
Name dt: pivot!$A$1
Name id_settings: settings!$A$2:$D$542
Name id2_asset: asset!$F$4:$CC$112
Name id3_asset_sum: asset!$B$2:$E$96
Name kariire_list: '5借入一覧'!$A$1:$AC$278
Name tax_capital: settings!$L$21
Name tax_income: settings!$L$19
Name 修繕明細: A.BM集計!$A$33:$J$291

Sheet sold
A1: 売却済み物件
F3: 減価償却 | BC3: 維持費用明細(税込) | BK3: 土地建物 筆の一覧 固定資産税評価額/固定資産税/都市計画税額
C4: 仙台駅前コーポ | D4: あおばマンション | F4: 1.物件ID | G4: 2.対象物件 | H4: 3.法人ID | I4: 4.法人名 | J4: 5.資産種類名 | K4: 6.償却方法 | L4: 7.資産名称 | M4: 8.取得年月日 | N4: 9.耐用年数 (年) | O4: 10.取得後経過年(目安) | P4: 11.残存耐用年(目安) | Q4: 12.取得価額 | R4: 13.期首帳簿価額 | S4: 14.年間償却額 | T4: 15.期末帳簿価額 | U4: 16.購入後の CAPEX | V4: 17.摘要 | X4: 1.連番 | Y4: 2.物件ID | Z4: 3.物件名 | AA4: 4.区画名 | AB4: 5.専有面積 | AC4: 6.クラスID | AD4: 7.クラス | AE4: 8.間取り | AF4: 9.賃料 | AG4: 10.共益費 | AH4: 11.その他 | AI4: 12.消費税 | AJ4: 13.現況賃料税込(自動) | AK4: 14.再募集賃料税抜 | AL4: 15.再募集賃料税 | AM4: 16.再募集税込(自動) | AN4: 17.満室想定税込(自動) | AO4: 18.入居者国籍 | AP4: 19.賃貸用 | AQ4: 20.メモ | AR4: sepa1 | AS4: 31.区画ID | AT4: 32.購入時賃料税抜 | AU4: sepa2 | AV4: 41.入居中判定 | AW4: 42.満室想定税抜(自動) | AX4: 43.賃料増減余地(自動) | AY4: 44.購入後の賃料増加額税抜（自動） | AZ4: 45.物理区画判定(自動) | BA4: 46.論理区画判定(自動) | BC4: 物件ID | BD4: 物件名 | BE4: BM費用ID | BF4: BM費用項目(自動) | BG4: 月額合計 | BH4: 年換算(×12) | BI4: 摘要 | BK4: 連番 | BL4: 物件 ID | BM4: 物件名 | BN4: 資産クラスID | BO4: 資産クラス | BP4: 地番 | BQ4: 家屋番号 | BR4: 所有/ 借地権 | BS4: 面積ネット (持分按分後の実質) | BT4: 面積グロス (評価証明上の表記) | BU4: 共有持分 分子 | BV4: 共有持分 分母 | BW4: 区分 分子 | BX4: 区分 分母 | BY4: 当該資産 評価額 | BZ4: 当期固定資産税額 | CA4: 当期都市計画税額
A5: 11 | B5: 物件ID | C5: 110 | D5: 118
A6: 12 | B6: 物件概要
A7: 13 | B7: 現所有者 | C7: 410 | D7: 410
A8: 14 | B8: 交通 | C8: コアプラス沖縄株式会社 | D8: コアプラス沖縄株式会社
A9: 15 | B9: 住所 | C9: 東北本線「仙台」歩10分 | D9: 田園都市線「青葉台」歩5分
A10: 16 | B10: 一棟or区分 | C10: 宮城県仙台市宮城野区名掛丁991-55 | D10: 神奈川県横浜市青葉区青葉台9-25-1
A11: 17 | B11: 権利形態 | C11: 一棟 | D11: 一棟
A12: 18 | B12: 土地面積 | C12: 313.11 | D12: 732.25
A13: 19 | B13: 土地面積（坪） | C13: 94.715635 | D13: 221.5053
A14: 20 | B14: 建物のべ床 | C14: 528.43 | D14: 1110.34
A15: 21 | B15: 建物構造 | C15: 所有権 | D15: 所有権
A16: 22 | B16: 建物築年 | C16: RC/B1-5F | D16: RC/B1-5F
A17: 23 | B17: 建物経過年数 | C17: 31 | D17: 28
A18: 24 | B18: 総区画数 | C18: 24 | D18: 36
A19: 25 | B19: うち住居数 | C19: 22 | D19: 34
A20: 26 | B20: うち事務所/店舗数 | C20: 1 | D20: 0
A21: 27 | B21: うち駐車場 | C21: 0 | D21: 2
A22: 28 | B22: うちその他 | C22: 1 | D22: 0
A23: 29 | B23: 用途と計画 | C23: 34824 | D23: 34100
A24: 30 | B24: 購入年月 | C24: 44624 | D24: 44348
A25: 31 | B25: 購入価格 | C25: 227000000 | D25: 415000000
A26: 32 | B26: 物件メモ
A27: 91 | B27: 売却価格 | C27: 227000000 | D27: 415000000
A28: 92 | B28: 売却益概算 | C28: 30000000 | D28: 30000000
A29: 93 | B29: 売却時利回り | C29: 0.065 | D29: 0.07

Sheet pivot
A1: ピボットテーブルの一覧 | J1: Pivot1 | W1: Pivot2 | AC1: Pivot3 | AI1: Pivot4 | AR1: Pivot5 | BF1: Pivot8 | BT1: Pivot19 | CF1: Pivot9 | CJ1: Pivot10 | CO1: Pivot11 | DB1: Pivot12 | DF1: Pivot13 | DJ1: Pivot14 | DY1: Pivot15 | EG1: Pivot16 | EM1: Pivot17 | ES1: Pivot18 | FN1: Pivot20
A2: ピボット番号 | B2: リンク | C2: シート | D2: 項目 | E2: 条件1 | F2: 設定1 | G2: 条件2 | H2: 設定2 | J2: BM費用集計 | W2: 取得時簿価 | AC2: 2022年期首簿価 | AI2: 2022年(1年間)の償却額 | AR2: 満室想定賃料(税込・月額) | BF2: 現況賃料(税込・月額) | BT2: 現況賃料(税込・月額) | CF2: 資産クラス別（非賃貸を除く）金額ベース入居率 | CJ2: 賃料増減の推移(非賃貸を含む・月額) | CO2: 大口テナントの一覧(非賃貸を含む) | DB2: 賃貸用資産（非賃貸を除く）の賃料帯別ヒストグラム | DF2: 賃貸用資産（非賃貸を除く）の賃料帯別ヒストグラム | DJ2: 土地建物 筆の一覧 固定資産税評価額/固定資産税/都市計画税額 | DY2: 24 | DZ2: 総区画数 | EG2: C41 | EH2: ='3物件一覧'!B34 -> 残債2022年11月5日現在 | EM2: グループ全体P/L | ES2: 3物件一覧 | FN2: 5借入一覧
A3: Pivot1 | B3: =HYPERLINK("#pivot!"&ADDRESS(1,MATCH(A3,$A$1:$GE$1,0),4),A3) -> Pivot1 | C3: A.BM集計 | D3: BM費用集計 | J3: A.BM集計 | W3: 6減価償却 | AC3: 6減価償却 | AI3: 6減価償却 | AR3: 8賃料集計 | BF3: 8賃料集計 | BT3: 8賃料集計 | CF3: 8賃料集計 | CJ3: 8賃料集計 | CO3: 8賃料集計 | DB3: 住居系 | DC3: 8賃料集計 | DF3: 事務所・店舗系 | DG3: 8賃料集計 | DJ3: B筆一覧 | DY3: 3物件一覧 | EG3: 3物件一覧 | EH3: 対象物件 | EM3: 2法人連結 | ES3: 共同担保の提供状況 | FN3: 当初借入額集計
A4: Pivot2 | B4: =HYPERLINK("#pivot!"&ADDRESS(1,MATCH(A4,$A$1:$GE$1,0),4),A4) -> Pivot2 | C4: 6減価償却 | D4: 取得時簿価 | E4: 16.購入後の CAPEX | F4: 0 | J4: BM集計 | W4: 償却1 | AC4: 償却2 | AI4: 償却3 | AR4: 賃料1 | BF4: 賃料2 | BG4: 2002 | BT4: 賃料3 | BU4: 2004 | CF4: 46.論理区画判定(自動) | CG4: 1 | CJ4: 46.論理区画判定(自動) | CK4: 1 | DB4: 46.論理区画判定(自動) | DC4: 1 | DY4: 45.物理区画判定(自動) | DZ4: 1 | EG4: 行ラベル | EH4: 合計 / 22.元金返済月額 | EI4: 合計 / 23.利息月額 | EJ4: 合計 / 24.支払月額 | EK4: 合計 / 25.残債 | FN4: 2.状況 | FO4: 返済中
A5: Pivot3 | B5: =HYPERLINK("#pivot!"&ADDRESS(1,MATCH(A5,$A$1:$GE$1,0),4),A5) -> Pivot3 | C5: 6減価償却 | D5: 2022年期首簿価 | J5: 合計 / 年換算(×12) | K5: 列ラベル | W5: 16.購入後の CAPEX | X5: (複数のアイテム) | AC5: 合計 / 13.期首帳簿価額 | AD5: 列ラベル | AI5: 合計 / 14.年間償却額 | AJ5: 列ラベル | AR5: 賃貸用yes+noのすべて | AS5: 2001 | BF5: 46.論理区画判定(自動) | BG5: 1 | BT5: 46.論理区画判定(自動) | BU5: 1 | CF5: 19.賃貸用 | CG5: yes | CO5: 46.論理区画判定(自動) | CP5: 1 | DB5: 7.クラス | DC5: 住居 | DF5: 46.論理区画判定(自動) | DG5: 1 | DK5: 列ラベル | EG5: あおばマンション | EZ5: 671 | FA5: 672 | FB5: 673 | FC5: 674 | FD5: 675
A6: Pivot4 | B6: =HYPERLINK("#pivot!"&ADDRESS(1,MATCH(A6,$A$1:$GE$1,0),4),A6) -> Pivot4 | C6: 6減価償却 | D6: 2022年(1年間)の償却額 | J6: 行ラベル | K6: 建物管理料 | L6: 電気料金(電灯) | M6: 電気料金(低圧) | N6: その他 | O6: 火災保険料 | P6: 水道料金 | Q6: 区分管理費 | R6: 区分修繕積立金 | S6: (空白) | T6: 立替金 | U6: 総計 | AD6: 建物等 | AE6: 土地 | AF6: (空白) | AG6: 総計 | AI6: 行ラベル | AJ6: 器具備品 | AK6: 建物 | AL6: 建物附属設備 | AM6: 構築物 | AN6: 土地 | AO6: (空白) | AP6: 総計 | BT6: 19.賃貸用 | BU6: yes | CJ6: 行ラベル | CK6: 合計 / 32.購入時賃料税抜 | CL6: 合計 / 42.満室想定税抜(自動) | CM6: 合計 / 14.再募集賃料税抜 | DB6: 19.賃貸用 | DC6: yes | DF6: 19.賃貸用 | DG6: yes | DK6: 建物 | DO6: 土地3種 | DS6: 全体の 合計 / 面積ネット (持分按分後の実質) | DT6: 全体の 合計 / 当該資産 評価額 | DU6: 全体の 合計 / 当期固定資産税額 | DV6: 全体の 合計 / 当期都市計画税額 | DY6: 合計 / 45.物理区画判定(自動) | DZ6: 列ラベル | EG6: カーサ南池袋 | EH6: 437860 | EI6: 183356 | EJ6: 621216 | EK6: 146247653 | EY6: 1 | EZ6: 2 | FA6: 3 | FB6: 4 | FC6: 5 | FD6: 6 | FE6: 7 | FF6: 8 | FG6: 9 | FH6: 10 | FI6: 11 | FJ6: 12 | FK6: 13 | FL6: 14 | FN6: 行ラベル | FO6: 合計 / 14.当初借入額
A7: Pivot5 | B7: =HYPERLINK("#pivot!"&ADDRESS(1,MATCH(A7,$A$1:$GE$1,0),4),A7) -> Pivot5 | C7: 8賃料集計 | D7: 満室想定賃料(税込・月額) | E7: 賃貸用 | F7: yes+noのすべて | G7: 論理区画 | H7: あり | J7: カーサ南池袋 | K7: 394680 | L7: 210756 | M7: 84480 | O7: 12950 | U7: 702866 | W7: 合計 / 12.12.取得価額 | X7: 列ラベル | AC7: 行ラベル | AI7: カーサ南池袋 | AJ7: 88704 | AK7: 2967179 | AL7: 1454309 | AP7: 4510192 | AR7: 46.論理区画判定(自動) | AS7: 1 | BF7: 合計 / 13.現況賃料税込(自動) | BG7: 列ラベル | CF7: 行ラベル | CG7: 合計 / 17.満室想定税込(自動) | CH7: 合計 / 13.現況賃料税込(自動) | CJ7: カーサ南池袋 | CK7: 1402284 | CL7: 1523829 | CM7: 1519127 | CO7: 行ラベル | CP7: 合計 / 17.満室想定税込(自動) | CQ7: 合計 / 17.満室想定税込(自動)2 | CS7: 序列 | CT7: ID | CU7: 物件名 | CV7: 区画名 | CW7: クラス | CX7: 間取り | CY7: 満室想定税込(自動) | DZ7: 店舗事務所系物理区画 | EA7: アンテナ | EB7: 住居 | EC7: 倉庫 | ED7: 駐車場 | EE7: 総計 | EG7: カーサ目白台ハウス | EH7: 1049552 | EI7: 299492 | EJ7: 1349044 | EK7: 325693047 | EM7: 行ラベル | EN7: 合計 / 22.元金返済月額 | EO7: 合計 / 23.利息月額 | EP7: 合計 / 24.支払月額 | EQ7: 合計 / 25.残債 | ES7: 連番 | ET7: 担保提供種別ID | EU7: 共同担保物件ID | EV7: 行番号 | EW7: データ | EX7: 列 | EY7: 物件ID | EZ7: 共同担保, | FA7: 第一抵当, | FB7: 第二抵当, | FC7: 第三抵当, | FD7: 第四抵当, | FE7: 出力1 | FF7: 出力2 | FG7: 出力3 | FH7: 出力4 | FI7: 出力5 | FJ7: 文字列結合1 | FK7: 文字列結合2 | FL7: 文字列結合3 | FN7: 運転資金 | FO7: 11000000
A8: Pivot6 | B8: 削除 | C8: 8賃料集計 | D8: 満室想定賃料(税込・月額) | E8: 賃貸用 | F8: yesのみ | G8: 論理区画 | H8: あり | J8: カーサ目白台ハウス | K8: 1457280 | L8: 151992 | M8: 286488 | O8: 19430 | P8: 18744 | U8: 1933934 | X8: 建物等 | Y8: 土地 | Z8: (空白) | AA8: 総計 | AC8: カーサ南池袋 | AD8: 27798216 | AE8: 165375617 | AG8: 193173833 | AI8: カーサ目白台ハウス | AK8: 5828706 | AL8: 181266 | AP8: 6009972 | BF8: 行ラベル | BG8: アンテナ | BH8: その他 | BI8: 事務所 | BJ8: 自販機 | BK8: 住居 | BL8: 倉庫 | BM8: 駐車場 | BN8: 店舗 | BO8: (空白) | BP8: 総計 | BT8: 合計 / 13.現況賃料税込(自動) | BU8: 列ラベル | CF8: アンテナ | CG8: 247035 | CH8: 247035 | CJ8: カーサ目白台ハウス | CK8: 2898715 | CL8: 2944145 | CM8: 2929143 | CO8: 208 | CP8: 2530000 | CQ8: 1 | CS8: 1 | CT8: =VLOOKUP($CO8,chinryo_list,2,FALSE) -> 112 | CU8: =VLOOKUP($CO8,chinryo_list,3,FALSE) -> 豊島目白ビル | CV8: =VLOOKUP($CO8,chinryo_list,4,FALSE) -> 101 | CW8: =VLOOKUP($CO8,chinryo_list,7,FALSE) -> 事務所 | CX8: =VLOOKUP($CO8,chinryo_list,8,FALSE) -> 事務所 | CY8: =VLOOKUP($CO8,chinryo_list,17,FALSE) -> 2530000 | DB8: 行ラベル | DC8: 個数 / 17.満室想定税込(自動) | DD8: 合計 / 17.満室想定税込(自動)2 | DF8: 行ラベル | DG8: 個数 / 17.満室想定税込(自動) | DH8: 合計 / 17.満室想定税込(自動)2 | DJ8: 行ラベル | DK8: 合計 / 面積ネット (持分按分後の実質) | DL8: 合計 / 当該資産 評価額 | DM8: 合計 / 当期固定資産税額 | DN8: 合計 / 当期都市計画税額 | DO8: 合計 / 面積ネット (持分按分後の実質) | DP8: 合計 / 当該資産 評価額 | DQ8: 合計 / 当期固定資産税額 | DR8: 合計 / 当期都市計画税額 | DY8: 行ラベル | EA8: アンテナ | EB8: 住居 | EC8: 倉庫 | ED8: 駐車場 | EG8: コアプラスレジデンス梅田 | EH8: 738310 | EI8: 406469 | EJ8: 1144779 | EK8: 338136161 | EM8: 間接部門 | EN8: 338579 | EO8: 253711 | EP8: 592290 | EQ8: 113947016 | ES8: 1 | ET8: AG | EU8: AE | EV8: 2 | EW8: {=INDIRECT("'5借入一覧'!"&ET8&EV8)&INDIRECT("'5借入一覧'!"&EU8&EV8)} | EX8: 1 | EY8: 1 | EZ8: =VLOOKUP($EY8&EZ$5,$EW$7:$EX$1101,2,FALSE) -> #N/A | FA8: =VLOOKUP($EY8&FA$5,$EW$7:$EX$1101,2,FALSE) -> #N/A | FB8: =VLOOKUP($EY8&FB$5,$EW$7:$EX$1101,2,FALSE) -> #N/A | FC8: =VLOOKUP($EY8&FC$5,$EW$7:$EX$1101,2,FALSE) -> #N/A | FD8: =VLOOKUP($EY8&FD$5,$EW$7:$EX$1101,2,FALSE) -> #N/A | FE8: =IFERROR(IF(EZ8>0,EZ$7),"") | FF8: =IFERROR(IF(FA8>0,FA$7),"") | FG8: =IFERROR(IF(FB8>0,FB$7),"") | FH8: =IFERROR(IF(FC8>0,FC$7),"") | FI8: =IFERROR(IF(FD8>0,FD$7),"") | FJ8: =FE8&FF8&FG8&FH8&FI8 | FK8: =IF(FJ8<>"",LEFT(FJ8,LEN(FJ8)-1),"") | FL8: =IF(FK8<>"",FK8&"として提供中","無") -> 無 | FN8: 対象物件なし(運転資金) | FO8: 11000000
A9: Pivot7 | B9: 削除 | C9: 8賃料集計 | D9: 満室想定賃料(税込・月額) | E9: 賃貸用 | F9: noのみ | G9: 論理区画 | H9: あり | J9: コアプラスレジデンス梅田 | K9: 1160280 | L9: 101808 | M9: 259500 | N9: 132000 | O9: 20620 | P9: 22836 | U9: 1697044 | W9: 行ラベル | AC9: カーサ目白台ハウス | AD9: 113300805 | AE9: 264084489 | AG9: 377385294 | AI9: コアプラスレジデンス梅田 | AJ9: 83013 | AK9: 7073962 | AL9: 705692 | AP9: 7862667 | AR9: 合計 / 17.満室想定税込(自動) | AS9: 列ラベル | BF9: カーサ南池袋 | BG9: 72911 | BH9: 0 | BK9: 1417000 | BL9: 17600 | BM9: 27000 | BP9: 1534511 | BT9: 行ラベル | BU9: アンテナ | BV9: 事務所 | BW9: 自販機 | BX9: 住居 | BY9: 倉庫 | BZ9: 駐車場 | CA9: 店舗 | CB9: 総計 | CF9: その他 | CJ9: コアプラスレジデンス梅田 | CK9: 2282000 | CL9: 2429000 | CM9: 2341000 | CO9: 184 | CP9: 1758634 | CQ9: 2 | CS9: 2 | CT9: =VLOOKUP($CO9,chinryo_list,2,FALSE) -> 111 | CU9: =VLOOKUP($CO9,chinryo_list,3,FALSE) -> 目白カーサ二番館 | CV9: =VLOOKUP($CO9,chinryo_list,4,FALSE) -> SL1 | CW9: =VLOOKUP($CO9,chinryo_list,7,FALSE) -> 住居 | CX9: =VLOOKUP($CO9,chinryo_list,8,FALSE) -> 1K | CY9: =VLOOKUP($CO9,chinryo_list,17,FALSE) -> 1758634 | DB9: <0 または (空白) | DF9: <0 または (空白) | DJ9: カーサ南池袋 | DK9: 588.5 | DL9: 15015300 | DM9: 210214 | DN9: 45045 | DO9: 252.09 | DP9: 123284110 | DQ9: 249401 | DR9: 53443 | DS9: 840.59 | DT9: 138299410 | DU9: 459615 | DV9: 98488 | DY9: カーサ南池袋 | EA9: 2 | EB9: 12 | EC9: 1 | ED9: 1 | EE9: 16 | EG9: コアプラス大塚 | EH9: 902892 | EI9: 513702 | EJ9: 1416594 | EK9: 473298872 | EM9: その他(間接部門) | ES9: 2 | ET9: AG | EU9: AE | EV9: 3 | EW9: {=INDIRECT("'5借入一覧'!"&ET9&EV9)&INDIRECT("'5借入一覧'!"&EU9&EV9)} | EX9: 1 | EY9: 2 | EZ9: =VLOOKUP($EY9&EZ$5,$EW$7:$EX$1101,2,FALSE) -> #N/A | FA9: =VLOOKUP($EY9&FA$5,$EW$7:$EX$1101,2,FALSE) -> #N/A | FB9: =VLOOKUP($EY9&FB$5,$EW$7:$EX$1101,2,FALSE) -> #N/A | FC9: =VLOOKUP($EY9&FC$5,$EW$7:$EX$1101,2,FALSE) -> #N/A | FD9: =VLOOKUP($EY9&FD$5,$EW$7:$EX$1101,2,FALSE) -> #N/A | FE9: =IFERROR(IF(EZ9>0,EZ$7),"") | FF9: =IFERROR(IF(FA9>0,FA$7),"") | FG9: =IFERROR(IF(FB9>0,FB$7),"") | FH9: =IFERROR(IF(FC9>0,FC$7),"") | FI9: =IFERROR(IF(FD9>0,FD$7),"") | FJ9: =FE9&FF9&FG9&FH9&FI9 | FK9: =IF(FJ9<>"",LEFT(FJ9,LEN(FJ9)-1),"") | FL9: =IF(FK9<>"",FK9&"として提供中","無") -> 無 | FN9: 修繕資金 | FO9: 63456000
A10: Pivot8 | B10: =HYPERLINK("#pivot!"&ADDRESS(1,MATCH(A10,$A$1:$GE$1,0),4),A10) -> Pivot8 | C10: 8賃料集計 | D10: 現況賃料(税込・月額) | E10: 賃貸用 | F10: yes+noのすべて | G10: 論理区画 | H10: あり | J10: コアプラス大塚 | K10: 1301520 | L10: 240684 | M10: 295140 | O10: 34430 | P10: 45672 | U10: 1917446 | W10: カーサ南池袋 | X10: 26492683 | Y10: 165375617 | AA10: 191868300 | AC10: コアプラスレジデンス梅田 | AD10: 152141411 | AE10: 211645475 | AG10: 363786886 | AI10: コアプラス大塚 | AK10: 7773951 | AP10: 7773951 | AR10: 行ラベル | AS10: アンテナ | AT10: その他 | AU10: 事務所 | AV10: 自販機 | AW10: 住居 | AX10: 倉庫 | AY10: 駐車場 | AZ10: 店舗 | BA10: (空白) | BB10: 総計 | BF10: カーサ目白台ハウス | BI10: 643878 | BK10: 1913800 | BM10: 126500 | BN10: 363000 | BP10: 3047178 | BT10: カーサ南池袋 | BU10: 72911 | BX10: 1417000 | BY10: 17600 | BZ10: 27000 | CB10: 1534511 | CF10: 事務所 | CG10: 3737978 | CH10: 3702978 | CJ10: コアプラス大塚 | CK10: 3143630 | CL10: 3521704 | CM10: 3495703 | CO10: 165 | CP10: 1100000 | CQ10: 3 | CS10: 3 | CT10: =VLOOKUP($CO10,chinryo_list,2,FALSE) -> 107 | CU10: =VLOOKUP($CO10,chinryo_list,3,FALSE) -> メゾン雑司ヶ谷 | CV10: =VLOOKUP($CO10,chinryo_list,4,FALSE) -> 1F | CW10: =VLOOKUP($CO10,chinryo_list,7,FALSE) -> 店舗 | CX10: =VLOOKUP($CO10,chinryo_list,8,FALSE) -> 店舗 | CY10: =VLOOKUP($CO10,chinryo_list,17,FALSE) -> 1100000 | DB10: 0-9999 | DF10: アンテナ | DJ10: カーサ目白台ハウス | DK10: 887.19 | DL10: 58425900 | DM10: 817962 | DN10: 175277 | DO10: 395.33 | DP10: 176328930 | DQ10: 519513 | DR10: 111323 | DS10: 1282.52 | DT10: 234754830 | DU10: 1337475 | DV10: 286600 | DY10: カーサ目白台ハウス | DZ10: 6 | EB10: 9 | ED10: 3 | EE10: 18 | EG10: コアプラス池袋 | EH10: 328928 | EI10: 58976 | EJ10: 387904 | EK10: 70446823 | EM10: あおばマンション | ES10: 3 | ET10: AG | EU10: AE | EV10: 4 | EW10: {=INDIRECT("'5借入一覧'!"&ET10&EV10)&INDIRECT("'5借入一覧'!"&EU10&EV10)} | EX10: 1 | EY10: 3 | EZ10: =VLOOKUP($EY10&EZ$5,$EW$7:$EX$1101,2,FALSE) -> #N/A | FA10: =VLOOKUP($EY10&FA$5,$EW$7:$EX$1101,2,FALSE) -> #N/A | FB10: =VLOOKUP($EY10&FB$5,$EW$7:$EX$1101,2,FALSE) -> #N/A | FC10: =VLOOKUP($EY10&FC$5,$EW$7:$EX$1101,2,FALSE) -> #N/A | FD10: =VLOOKUP($EY10&FD$5,$EW$7:$EX$1101,2,FALSE) -> #N/A | FE10: =IFERROR(IF(EZ10>0,EZ$7),"") | FF10: =IFERROR(IF(FA10>0,FA$7),"") | FG10: =IFERROR(IF(FB10>0,FB$7),"") | FH10: =IFERROR(IF(FC10>0,FC$7),"") | FI10: =IFERROR(IF(FD10>0,FD$7),"") | FJ10: =FE10&FF10&FG10&FH10&FI10 | FK10: =IF(FJ10<>"",LEFT(FJ10,LEN(FJ10)-1),"") | FL10: =IF(FK10<>"",FK10&"として提供中","無") -> 無 | FN10: コアプラスレジデンス梅田 | FO10: 15000000
A11: Pivot9 | B11: =HYPERLINK("#pivot!"&ADDRESS(1,MATCH(A11,$A$1:$GE$1,0),4),A11) -> Pivot9 | C11: 8賃料集計 | D11: 資産クラス別（非賃貸を除く）金額ベース入居率 | G11: 論理区画 | H11: あり | J11: コアプラス池袋 | K11: 376200 | L11: 12372 | O11: 6600 | P11: 22836 | U11: 418008 | W11: カーサ目白台ハウス | X11: 149454010 | Y11: 264084489 | AA11: 413538499 | AC11: コアプラス大塚 | AD11: 213808751 | AE11: 300927161 | AG11: 514735912 | AI11: コアプラス池袋 | AK11: 864458 | AL11: 409639 | AM11: 60741 | AP11: 1334838 | AR11: no | AT11: 0 | AW11: 295000 | BB11: 295000 | BF11: コアプラスレジデンス梅田 | BG11: 13200 | BH11: 0 | BK11: 2041000 | BN11: 413600 | BP11: 2467800 | BT11: カーサ目白台ハウス | BV11: 643878 | BX11: 1913800 | BZ11: 126500 | CA11: 363000 | CB11: 3047178 | CF11: 自販機 | CG11: 0 | CH11: 0 | CJ11: コアプラス池袋 | CK11: 620000 | CL11: 722000 | CM11: 729000 | CO11: 292 | CP11: 413600 | CQ11: 4 | CS11: 4 | CT11: =VLOOKUP($CO11,chinryo_list,2,FALSE) -> 116 | CU11: =VLOOKUP($CO11,chinryo_list,3,FALSE) -> コアプラスレジデンス梅田 | CV11: =VLOOKUP($CO11,chinryo_list,4,FALSE) -> 101 | CW11: =VLOOKUP($CO11,chinryo_list,7,FALSE) -> 店舗 | CX11: =VLOOKUP($CO11,chinryo_list,8,FALSE) -> 店舗 | CY11: =VLOOKUP($CO11,chinryo_list,17,FALSE) -> 413600 | DB11: 10000-19999 | DF11: その他 | DJ11: コアプラスレジデンス梅田 | DK11: 966.35 | DL11: 53982400 | DM11: 755753 | DN11: 161947 | DO11: 207.8 | DP11: 114941450 | DQ11: 210432 | DR11: 45092 | DS11: 1174.15 | DT11: 168923850 | DU11: 966185 | DV11: 207039 | DY11: コアプラスレジデンス梅田 | DZ11: 1 | EA11: 1 | EB11: 14 | EE11: 16 | EG11: メゾン雑司ヶ谷 | EH11: 982474 | EI11: 314688 | EJ11: 1297162 | EK11: 313706389 | EM11: カーサ南池袋 | ES11: 4 | ET11: AG | EU11: AE | EV11: 5 | EW11: {=INDIRECT("'5借入一覧'!"&ET11&EV11)&INDIRECT("'5借入一覧'!"&EU11&EV11)} | EX11: 1 | EY11: 4 | EZ11: =VLOOKUP($EY11&EZ$5,$EW$7:$EX$1101,2,FALSE) -> #N/A | FA11: =VLOOKUP($EY11&FA$5,$EW$7:$EX$1101,2,FALSE) -> #N/A | FB11: =VLOOKUP($EY11&FB$5,$EW$7:$EX$1101,2,FALSE) -> #N/A | FC11: =VLOOKUP($EY11&FC$5,$EW$7:$EX$1101,2,FALSE) -> #N/A | FD11: =VLOOKUP($EY11&FD$5,$EW$7:$EX$1101,2,FALSE) -> #N/A | FE11: =IFERROR(IF(EZ11>0,EZ$7),"") | FF11: =IFERROR(IF(FA11>0,FA$7),"") | FG11: =IFERROR(IF(FB11>0,FB$7),"") | FH11: =IFERROR(IF(FC11>0,FC$7),"") | FI11: =IFERROR(IF(FD11>0,FD$7),"") | FJ11: =FE11&FF11&FG11&FH11&FI11 | FK11: =IF(FJ11<>"",LEFT(FJ11,LEN(FJ11)-1),"") | FL11: =IF(FK11<>"",FK11&"として提供中","無") -> 無 | FN11: プラウD目白301号 | FO11: 20556000
A12: Pivot10 | B12: =HYPERLINK("#pivot!"&ADDRESS(1,MATCH(A12,$A$1:$GE$1,0),4),A12) -> Pivot10 | C12: 8賃料集計 | D12: 賃料増減の推移(非賃貸を含む・月額) | G12: 論理区画 | H12: あり | J12: ビジネス新大阪123号 | O12: 2060 | Q12: 48600 | R12: 16200 | U12: 66860 | W12: コアプラスレジデンス梅田 | X12: 147620954 | Y12: 211645475 | AA12: 359266429 | AC12: コアプラス池袋 | AD12: 29536448 | AE12: 78084258 | AG12: 107620706 | AI12: ビジネス新大阪123号 | AK12: 256421 | AP12: 256421 | AR12: カーサ南池袋 | AT12: 0 | BB12: 0 | BF12: コアプラス大塚 | BG12: 13200 | BH12: 0 | BK12: 3011000 | BM12: 356481 | BN12: 192093 | BP12: 3572774 | BT12: コアプラスレジデンス梅田 | BU12: 13200 | BX12: 2041000 | CA12: 413600 | CB12: 2467800 | CF12: 住居 | CG12: 28235436 | CH12: 27943232 | CJ12: ビジネス新大阪123号 | CK12: 35000 | CL12: 35000 | CM12: 35000 | CO12: 275 | CP12: 356481 | CQ12: 5 | CS12: 5 | CT12: =VLOOKUP($CO12,chinryo_list,2,FALSE) -> 115 | CU12: =VLOOKUP($CO12,chinryo_list,3,FALSE) -> コアプラス大塚 | CV12: =VLOOKUP($CO12,chinryo_list,4,FALSE) -> BF1 | CW12: =VLOOKUP($CO12,chinryo_list,7,FALSE) -> 駐車場 | CX12: =VLOOKUP($CO12,chinryo_list,8,FALSE) -> 駐車場 | CY12: =VLOOKUP($CO12,chinryo_list,17,FALSE) -> 356481 | DB12: 20000-29999 | DF12: 事務所 | DJ12: コアプラス大塚 | DK12: 1490.43 | DL12: 123562400 | DM12: 1729873 | DN12: 370687 | DO12: 443.07 | DP12: 174271390 | DQ12: 363928 | DR12: 77984 | DS12: 1933.5 | DT12: 297833790 | DU12: 2093801 | DV12: 448671 | DY12: コアプラス大塚 | DZ12: 1 | EA12: 1 | EB12: 23 | ED12: 1 | EE12: 26 | EG12: レジデンス目白豊島 | EH12: 324776 | EI12: 180387 | EJ12: 505163 | EK12: 166191734 | EM12: カーサ目白台ハウス | ES12: 5 | ET12: AG | EU12: AE | EV12: 6 | EW12: {=INDIRECT("'5借入一覧'!"&ET12&EV12)&INDIRECT("'5借入一覧'!"&EU12&EV12)} | EX12: 1 | EY12: 5 | EZ12: =VLOOKUP($EY12&EZ$5,$EW$7:$EX$1101,2,FALSE) -> #N/A | FA12: =VLOOKUP($EY12&FA$5,$EW$7:$EX$1101,2,FALSE) -> #N/A | FB12: =VLOOKUP($EY12&FB$5,$EW$7:$EX$1101,2,FALSE) -> #N/A | FC12: =VLOOKUP($EY12&FC$5,$EW$7:$EX$1101,2,FALSE) -> #N/A | FD12: =VLOOKUP($EY12&FD$5,$EW$7:$EX$1101,2,FALSE) -> #N/A | FE12: =IFERROR(IF(EZ12>0,EZ$7),"") | FF12: =IFERROR(IF(FA12>0,FA$7),"") | FG12: =IFERROR(IF(FB12>0,FB$7),"") | FH12: =IFERROR(IF(FC12>0,FC$7),"") | FI12: =IFERROR(IF(FD12>0,FD$7),"") | FJ12: =FE12&FF12&FG12&FH12&FI12 | FK12: =IF(FJ12<>"",LEFT(FJ12,LEN(FJ12)-1),"") | FL12: =IF(FK12<>"",FK12&"として提供中","無") -> 無 | FN12: 目白アパート | FO12: 17900000
A13: Pivot11 | B13: =HYPERLINK("#pivot!"&ADDRESS(1,MATCH(A13,$A$1:$GE$1,0),4),A13) -> Pivot11 | C13: 8賃料集計 | D13: 大口テナントの一覧(非賃貸を含む) | G13: 論理区画 | H13: あり | J13: プラウD目白301号室 | W13: コアプラス大塚 | X13: 250772634 | Y13: 300927161 | AA13: 551699795 | AC13: ビジネス新大阪123号 | AD13: 2797363 | AE13: 2488575 | AG13: 5285938 | AI13: プラウD目白301号室 | AR13: カーサ目白台ハウス | BF13: コアプラス池袋 | BI13: 132000 | BK13: 367000 | BN13: 169400 | BP13: 668400 | BT13: コアプラス大塚 | BU13: 13200 | BX13: 3011000 | BZ13: 356481 | CA13: 192093 | CB13: 3572774 | CF13: 倉庫 | CG13: 282415 | CH13: 282415 | CJ13: メゾン雑司ヶ谷 | CK13: 2404000 | CL13: 2378700 | CM13: 2391700 | CO13: 317 | CP13: 330000 | CQ13: 6 | CS13: 6 | CT13: =VLOOKUP($CO13,chinryo_list,2,FALSE) -> 121 | CU13: =VLOOKUP($CO13,chinryo_list,3,FALSE) -> 目白アパート1号館 | CV13: =VLOOKUP($CO13,chinryo_list,4,FALSE) -> 101 | CW13: =VLOOKUP($CO13,chinryo_list,7,FALSE) -> 住居 | CX13: =VLOOKUP($CO13,chinryo_list,8,FALSE) -> 2LDK | CY13: =VLOOKUP($CO13,chinryo_list,17,FALSE) -> 330000 | DB13: 30000-39999 | DF13: 自販機 | DJ13: コアプラス池袋 | DK13: 177.12 | DL13: 8669000 | DM13: 121366 | DN13: 26007 | DO13: 137.3 | DP13: 57534050 | DQ13: 109261 | DR13: 23413 | DS13: 314.42 | DT13: 66203050 | DU13: 230627 | DV13: 49420 | DY13: コアプラス池袋 | DZ13: 2 | EB13: 6 | EE13: 8 | EG13: 高田馬場第4玉川ビル | EH13: 224843 | EI13: 146653 | EJ13: 371496 | EK13: 104842675 | EM13: コアプラスレジデンス梅田 | ES13: 6 | ET13: AG | EU13: AE | EV13: 7 | EW13: {=INDIRECT("'5借入一覧'!"&ET13&EV13)&INDIRECT("'5借入一覧'!"&EU13&EV13)} | EX13: 1 | EY13: 6 | EZ13: =VLOOKUP($EY13&EZ$5,$EW$7:$EX$1101,2,FALSE) -> #N/A | FA13: =VLOOKUP($EY13&FA$5,$EW$7:$EX$1101,2,FALSE) -> #N/A | FB13: =VLOOKUP($EY13&FB$5,$EW$7:$EX$1101,2,FALSE) -> #N/A | FC13: =VLOOKUP($EY13&FC$5,$EW$7:$EX$1101,2,FALSE) -> #N/A | FD13: =VLOOKUP($EY13&FD$5,$EW$7:$EX$1101,2,FALSE) -> #N/A | FE13: =IFERROR(IF(EZ13>0,EZ$7),"") | FF13: =IFERROR(IF(FA13>0,FA$7),"") | FG13: =IFERROR(IF(FB13>0,FB$7),"") | FH13: =IFERROR(IF(FC13>0,FC$7),"") | FI13: =IFERROR(IF(FD13>0,FD$7),"") | FJ13: =FE13&FF13&FG13&FH13&FI13 | FK13: =IF(FJ13<>"",LEFT(FJ13,LEN(FJ13)-1),"") | FL13: =IF(FK13<>"",FK13&"として提供中","無") -> 無 | FN13: 目白アパート1号館 | FO13: 10000000
A14: Pivot12 | B14: =HYPERLINK("#pivot!"&ADDRESS(1,MATCH(A14,$A$1:$GE$1,0),4),A14) -> Pivot12 | C14: 8賃料集計 | D14: 住居系_賃貸用資産（非賃貸を除く）の賃料帯別ヒストグラム | E14: クラス | F14: 住居 | G14: 論理区画 | H14: あり | J14: メゾン雑司ヶ谷 | K14: 869880 | L14: 52092 | M14: 107712 | O14: 20610 | P14: 22836 | U14: 1073130 | W14: コアプラス池袋 | X14: 16087719 | Y14: 78084258 | AA14: 94171977 | AC14: プラウD目白301号室 | AI14: メゾン雑司ヶ谷 | AJ14: 84480 | AK14: 4315064 | AL14: 212477 | AP14: 4612021 | AR14: コアプラスレジデンス梅田 | AT14: 0 | BB14: 0 | BF14: ビジネス新大阪123号 | BI14: 0 | BP14: 0 | BT14: コアプラス池袋 | BV14: 132000 | BX14: 367000 | CA14: 169400 | CB14: 668400 | CF14: 駐車場 | CG14: 809021 | CH14: 794721 | CJ14: レジデンス目白豊島 | CK14: 1239741 | CL14: 1261741 | CM14: 1274740 | CO14: 77 | CP14: 305800 | CQ14: 7 | CS14: 7 | CT14: =VLOOKUP($CO14,chinryo_list,2,FALSE) -> 103 | CU14: =VLOOKUP($CO14,chinryo_list,3,FALSE) -> カーサ目白台ハウス | CV14: =VLOOKUP($CO14,chinryo_list,4,FALSE) -> 503 | CW14: =VLOOKUP($CO14,chinryo_list,7,FALSE) -> 住居 | CX14: =VLOOKUP($CO14,chinryo_list,8,FALSE) -> 2LDK | CY14: =VLOOKUP($CO14,chinryo_list,17,FALSE) -> 305800 | DB14: 40000-49999 | DF14: 住居 | DJ14: ビジネス新大阪123号 | DK14: 19.9 | DL14: 892339.76 | DM14: 1761 | DN14: 754 | DS14: 19.9 | DT14: 892339.76 | DU14: 1761 | DV14: 754 | DY14: ビジネス新大阪123号 | DZ14: 1 | EE14: 1 | EG14: 西池袋駅前ビル | EH14: 712666 | EI14: 139065 | EJ14: 851731 | EK14: 166166517 | EM14: コアプラス大塚 | ES14: 7 | ET14: AG | EU14: AE | EV14: 8 | EW14: {=INDIRECT("'5借入一覧'!"&ET14&EV14)&INDIRECT("'5借入一覧'!"&EU14&EV14)} | EX14: 1 | EY14: 7 | EZ14: =VLOOKUP($EY14&EZ$5,$EW$7:$EX$1101,2,FALSE) -> #N/A | FA14: =VLOOKUP($EY14&FA$5,$EW$7:$EX$1101,2,FALSE) -> #N/A | FB14: =VLOOKUP($EY14&FB$5,$EW$7:$EX$1101,2,FALSE) -> #N/A | FC14: =VLOOKUP($EY14&FC$5,$EW$7:$EX$1101,2,FALSE) -> #N/A | FD14: =VLOOKUP($EY14&FD$5,$EW$7:$EX$1101,2,FALSE) -> #N/A | FE14: =IFERROR(IF(EZ14>0,EZ$7),"") | FF14: =IFERROR(IF(FA14>0,FA$7),"") | FG14: =IFERROR(IF(FB14>0,FB$7),"") | FH14: =IFERROR(IF(FC14>0,FC$7),"") | FI14: =IFERROR(IF(FD14>0,FD$7),"") | FJ14: =FE14&FF14&FG14&FH14&FI14 | FK14: =IF(FJ14<>"",LEFT(FJ14,LEN(FJ14)-1),"") | FL14: =IF(FK14<>"",FK14&"として提供中","無") -> 無 | FN14: 住宅ローン | FO14: 94000000
A15: Pivot13 | B15: =HYPERLINK("#pivot!"&ADDRESS(1,MATCH(A15,$A$1:$GE$1,0),4),A15) -> Pivot13 | C15: 8賃料集計 | D15: 事務所・店舗系_賃貸用資産（非賃貸を除く）の賃料帯別ヒストグラム | E15: クラス | F15: 住居以外複数 | G15: 論理区画 | H15: あり | J15: レジデンス目白豊島 | K15: 405240 | L15: 39024 | M15: 46992 | O15: 7710 | U15: 498966 | W15: ビジネス新大阪123号 | X15: 3052637 | Y15: 2488575 | AA15: 5541212 | AC15: メゾン雑司ヶ谷 | AD15: 73661130 | AE15: 286363375 | AG15: 360024505 | AI15: レジデンス目白豊島 | AK15: 2114406 | AP15: 2114406 | AR15: コアプラス大塚 | AT15: 0 | BB15: 0 | BF15: プラウD目白301号室 | BT15: ビジネス新大阪123号 | BV15: 0 | CB15: 0 | CF15: 店舗 | CG15: 2337093 | CH15: 2337093 | CJ15: 高田馬場第4玉川ビル | CK15: 844300 | CL15: 859000 | CM15: 852000 | CO15: 23 | CP15: 302500 | CQ15: 8 | CS15: 8 | CT15: =VLOOKUP($CO15,chinryo_list,2,FALSE) -> 101 | CU15: =VLOOKUP($CO15,chinryo_list,3,FALSE) -> 西池袋駅前ビル | CV15: =VLOOKUP($CO15,chinryo_list,4,FALSE) -> 100 | CW15: =VLOOKUP($CO15,chinryo_list,7,FALSE) -> 事務所 | CX15: =VLOOKUP($CO15,chinryo_list,8,FALSE) -> 事務所 | CY15: =VLOOKUP($CO15,chinryo_list,17,FALSE) -> 302500 | DB15: 50000-59999 | DC15: 10 | DD15: 564700 | DF15: 倉庫 | DJ15: プラウD目白301号室 | DY15: プラウD目白301号室 | EG15: 仙台駅前コーポ | EM15: コアプラス池袋 | ES15: 8 | ET15: AG | EU15: AE | EV15: 9 | EW15: {=INDIRECT("'5借入一覧'!"&ET15&EV15)&INDIRECT("'5借入一覧'!"&EU15&EV15)} | EX15: 1 | EY15: 8 | EZ15: =VLOOKUP($EY15&EZ$5,$EW$7:$EX$1101,2,FALSE) -> #N/A | FA15: =VLOOKUP($EY15&FA$5,$EW$7:$EX$1101,2,FALSE) -> #N/A | FB15: =VLOOKUP($EY15&FB$5,$EW$7:$EX$1101,2,FALSE) -> #N/A | FC15: =VLOOKUP($EY15&FC$5,$EW$7:$EX$1101,2,FALSE) -> #N/A | FD15: =VLOOKUP($EY15&FD$5,$EW$7:$EX$1101,2,FALSE) -> #N/A | FE15: =IFERROR(IF(EZ15>0,EZ$7),"") | FF15: =IFERROR(IF(FA15>0,FA$7),"") | FG15: =IFERROR(IF(FB15>0,FB$7),"") | FH15: =IFERROR(IF(FC15>0,FC$7),"") | FI15: =IFERROR(IF(FD15>0,FD$7),"") | FJ15: =FE15&FF15&FG15&FH15&FI15 | FK15: =IF(FJ15<>"",LEFT(FJ15,LEN(FJ15)-1),"") | FL15: =IF(FK15<>"",FK15&"として提供中","無") -> 無 | FN15: プラウD目白301号 | FO15: 94000000
A16: Pivot14 | B16: =HYPERLINK("#pivot!"&ADDRESS(1,MATCH(A16,$A$1:$GE$1,0),4),A16) -> Pivot14 | C16: B筆一覧 | D16: 土地建物 筆の一覧 固定資産税評価額/固定資産税/都市計画税額 | J16: 高田馬場第4玉川ビル | K16: 231000 | L16: 9156 | O16: 21200 | T16: -6000 | U16: 255356 | W16: プラウD目白301号室 | AC16: レジデンス目白豊島 | AD16: 42782673 | AE16: 154821009 | AG16: 197603682 | AI16: 高田馬場第4玉川ビル | AK16: 2704931 | AL16: 246267 | AP16: 2951198 | AR16: コアプラス池袋 | BF16: メゾン雑司ヶ谷 | BH16: 0 | BK16: 1378700 | BN16: 1100000 | BP16: 2478700 | BT16: メゾン雑司ヶ谷 | BX16: 1378700 | CA16: 1100000 | CB16: 2478700 | CF16: (空白) | CJ16: 西池袋駅前ビル | CK16: 1691000 | CL16: 1802800 | CM16: 1851800 | CO16: 316 | CP16: 295000 | CQ16: 9 | CS16: 9 | CT16: =VLOOKUP($CO16,chinryo_list,2,FALSE) -> 222 | CU16: =VLOOKUP($CO16,chinryo_list,3,FALSE) -> プラウD目白301号 | CV16: =VLOOKUP($CO16,chinryo_list,4,FALSE) -> 201 | CW16: =VLOOKUP($CO16,chinryo_list,7,FALSE) -> 住居 | CX16: =VLOOKUP($CO16,chinryo_list,8,FALSE) -> 2LDK | CY16: =VLOOKUP($CO16,chinryo_list,17,FALSE) -> 295000 | DB16: 60000-69999 | DC16: 49 | DD16: 3160800 | DF16: 駐車場 | DJ16: メゾン雑司ヶ谷 | DK16: 961.19 | DL16: 49095000 | DM16: 687330 | DN16: 147285 | DO16: 560.83 | DP16: 174332250 | DQ16: 371288 | DR16: 79561 | DS16: 1522.02 | DT16: 223427250 | DU16: 1058618 | DV16: 226846 | DY16: メゾン雑司ヶ谷 | DZ16: 1 | EB16: 22 | EE16: 23 | EG16: 対象物件なし(運転資金) | EH16: 168922 | EI16: 32278 | EJ16: 201200 | EK16: 22489146 | EM16: メゾン雑司ヶ谷 | ES16: 9 | ET16: AG | EU16: AE | EV16: 10 | EW16: {=INDIRECT("'5借入一覧'!"&ET16&EV16)&INDIRECT("'5借入一覧'!"&EU16&EV16)} | EX16: 1 | EY16: 9 | EZ16: =VLOOKUP($EY16&EZ$5,$EW$7:$EX$1101,2,FALSE) -> #N/A | FA16: =VLOOKUP($EY16&FA$5,$EW$7:$EX$1101,2,FALSE) -> #N/A | FB16: =VLOOKUP($EY16&FB$5,$EW$7:$EX$1101,2,FALSE) -> #N/A | FC16: =VLOOKUP($EY16&FC$5,$EW$7:$EX$1101,2,FALSE) -> #N/A | FD16: =VLOOKUP($EY16&FD$5,$EW$7:$EX$1101,2,FALSE) -> #N/A | FE16: =IFERROR(IF(EZ16>0,EZ$7),"") | FF16: =IFERROR(IF(FA16>0,FA$7),"") | FG16: =IFERROR(IF(FB16>0,FB$7),"") | FH16: =IFERROR(IF(FC16>0,FC$7),"") | FI16: =IFERROR(IF(FD16>0,FD$7),"") | FJ16: =FE16&FF16&FG16&FH16&FI16 | FK16: =IF(FJ16<>"",LEFT(FJ16,LEN(FJ16)-1),"") | FL16: =IF(FK16<>"",FK16&"として提供中","無") -> 無 | FN16: 親族借入 | FO16: 2000000
A17: Pivot15 | B17: =HYPERLINK("#pivot!"&ADDRESS(1,MATCH(A17,$A$1:$GE$1,0),4),A17) -> Pivot15 | C17: 3物件一覧 | D17: C24総区画数 | G17: 論理区画 | H17: あり | J17: 西池袋駅前ビル | K17: 596640 | L17: 251892 | N17: 144564 | O17: 11830 | P17: 18744 | U17: 1023670 | W17: メゾン雑司ヶ谷 | X17: 98069650 | Y17: 286363375 | AA17: 384433025 | AC17: 高田馬場第4玉川ビル | AD17: 15377543 | AE17: 113543242 | AG17: 128920785 | AI17: 西池袋駅前ビル | AJ17: 114456 | AK17: 1867320 | AL17: 49313 | AP17: 2031089 | AR17: ビジネス新大阪123号 | BF17: レジデンス目白豊島 | BI17: 94600 | BK17: 935000 | BL17: 264815 | BP17: 1294415 | BT17: レジデンス目白豊島 | BV17: 94600 | BX17: 935000 | BY17: 264815 | CB17: 1294415 | CF17: 総計 | CG17: 35648978 | CH17: 35307474 | CJ17: 第3目白ハイツ | CK17: 2897000 | CL17: 3004000 | CM17: 2948000 | CO17: 250 | CP17: 264815 | CQ17: 10 | CS17: 10 | CT17: =VLOOKUP($CO17,chinryo_list,2,FALSE) -> 114 | CU17: =VLOOKUP($CO17,chinryo_list,3,FALSE) -> レジデンス目白豊島 | CV17: =VLOOKUP($CO17,chinryo_list,4,FALSE) -> 101 | CW17: =VLOOKUP($CO17,chinryo_list,7,FALSE) -> 倉庫 | CX17: =VLOOKUP($CO17,chinryo_list,8,FALSE) -> 倉庫 | CY17: =VLOOKUP($CO17,chinryo_list,17,FALSE) -> 264815 | DB17: 70000-79999 | DC17: 22 | DD17: 1623000 | DF17: 店舗 | DJ17: レジデンス目白豊島 | DK17: 364.28 | DL17: 330468800 | DM17: 289150 | DN17: 61958 | DO17: 191.86 | DP17: 75806570 | DQ17: 148426 | DR17: 31805 | DS17: 556.14 | DT17: 406275370 | DU17: 437576 | DV17: 93763 | DY17: レジデンス目白豊島 | DZ17: 1 | EB17: 14 | EC17: 1 | EE17: 16 | EG17: 第3目白ハイツ | EH17: 1209934 | EI17: 468878 | EJ17: 1678812 | EK17: 407992887 | EM17: レジデンス目白豊島 | ES17: 10 | ET17: AG | EU17: AE | EV17: 11 | EW17: {=INDIRECT("'5借入一覧'!"&ET17&EV17)&INDIRECT("'5借入一覧'!"&EU17&EV17)} | EX17: 1 | EY17: 10 | EZ17: =VLOOKUP($EY17&EZ$5,$EW$7:$EX$1101,2,FALSE) -> #N/A | FA17: =VLOOKUP($EY17&FA$5,$EW$7:$EX$1101,2,FALSE) -> #N/A | FB17: =VLOOKUP($EY17&FB$5,$EW$7:$EX$1101,2,FALSE) -> #N/A | FC17: =VLOOKUP($EY17&FC$5,$EW$7:$EX$1101,2,FALSE) -> #N/A | FD17: =VLOOKUP($EY17&FD$5,$EW$7:$EX$1101,2,FALSE) -> #N/A | FE17: =IFERROR(IF(EZ17>0,EZ$7),"") | FF17: =IFERROR(IF(FA17>0,FA$7),"") | FG17: =IFERROR(IF(FB17>0,FB$7),"") | FH17: =IFERROR(IF(FC17>0,FC$7),"") | FI17: =IFERROR(IF(FD17>0,FD$7),"") | FJ17: =FE17&FF17&FG17&FH17&FI17 | FK17: =IF(FJ17<>"",LEFT(FJ17,LEN(FJ17)-1),"") | FL17: =IF(FK17<>"",FK17&"として提供中","無") -> 無 | FN17: 対象物件なし(運転資金) | FO17: 2000000
A18: Pivot16 | B18: =HYPERLINK("#pivot!"&ADDRESS(1,MATCH(A18,$A$1:$GE$1,0),4),A18) -> Pivot16 | C18: 3物件一覧 | D18: ="C41"&'3物件一覧'!B34 -> C41残債2022年11月5日現在 | J18: 第3目白ハイツ | K18: 848760 | L18: 91716 | M18: 282516 | O18: 51350 | P18: 45672 | U18: 1320014 | W18: レジデンス目白豊島 | X18: 52665555 | Y18: 154821009 | AA18: 207486564 | AC18: 西池袋駅前ビル | AD18: 40681559 | AE18: 168935000 | AG18: 209616559 | AI18: 第3目白ハイツ | AK18: 6299558 | AL18: 744405 | AM18: 151956 | AP18: 7195919 | AR18: メゾン雑司ヶ谷 | AT18: 0 | BB18: 0 | BF18: 高田馬場第4玉川ビル | BK18: 846000 | BM18: 0 | BP18: 846000 | BT18: 高田馬場第4玉川ビル | BX18: 846000 | BZ18: 0 | CB18: 846000 | CJ18: 池袋ハウス | CK18: 2801000 | CL18: 3092000 | CM18: 3109000 | CO18: 71 | CP18: 220000 | CQ18: 11 | CS18: 11 | CT18: =VLOOKUP($CO18,chinryo_list,2,FALSE) -> 103 | CU18: =VLOOKUP($CO18,chinryo_list,3,FALSE) -> カーサ目白台ハウス | CV18: =VLOOKUP($CO18,chinryo_list,4,FALSE) -> 303 | CW18: =VLOOKUP($CO18,chinryo_list,7,FALSE) -> 住居 | CX18: =VLOOKUP($CO18,chinryo_list,8,FALSE) -> 2LDK | CY18: =VLOOKUP($CO18,chinryo_list,17,FALSE) -> 220000 | DB18: 80000-89999 | DC18: 26 | DD18: 2172000 | DF18: (空白) | DJ18: 高田馬場第4玉川ビル | DK18: 343.46 | DL18: 10120600 | DM18: 141688 | DN18: 30361 | DO18: 179.23 | DP18: 75126040 | DQ18: 144698 | DR18: 31006 | DS18: 522.69 | DT18: 85246640 | DU18: 286386 | DV18: 61367 | DY18: 高田馬場第4玉川ビル | EB18: 8 | ED18: 1 | EE18: 9 | EG18: 池袋ハウス | EH18: 1050252 | EI18: 674466 | EJ18: 1724718 | EK18: 489470974 | EM18: 高田馬場第4玉川ビル | ES18: 11 | ET18: AG | EU18: AE | EV18: 12 | EW18: {=INDIRECT("'5借入一覧'!"&ET18&EV18)&INDIRECT("'5借入一覧'!"&EU18&EV18)} | EX18: 1 | EY18: 11 | EZ18: =VLOOKUP($EY18&EZ$5,$EW$7:$EX$1101,2,FALSE) -> #N/A | FA18: =VLOOKUP($EY18&FA$5,$EW$7:$EX$1101,2,FALSE) -> #N/A | FB18: =VLOOKUP($EY18&FB$5,$EW$7:$EX$1101,2,FALSE) -> #N/A | FC18: =VLOOKUP($EY18&FC$5,$EW$7:$EX$1101,2,FALSE) -> #N/A | FD18: =VLOOKUP($EY18&FD$5,$EW$7:$EX$1101,2,FALSE) -> #N/A | FE18: =IFERROR(IF(EZ18>0,EZ$7),"") | FF18: =IFERROR(IF(FA18>0,FA$7),"") | FG18: =IFERROR(IF(FB18>0,FB$7),"") | FH18: =IFERROR(IF(FC18>0,FC$7),"") | FI18: =IFERROR(IF(FD18>0,FD$7),"") | FJ18: =FE18&FF18&FG18&FH18&FI18 | FK18: =IF(FJ18<>"",LEFT(FJ18,LEN(FJ18)-1),"") | FL18: =IF(FK18<>"",FK18&"として提供中","無") -> 無 | FN18: 他業借入 | FO18: 11000000
A19: Pivot17 | B19: =HYPERLINK("#pivot!"&ADDRESS(1,MATCH(A19,$A$1:$GE$1,0),4),A19) -> Pivot17 | C19: 2法人連結 | D19: グループ全体P/L | J19: 池袋ハウス | K19: 1708080 | L19: 382320 | M19: 273012 | N19: 132000 | O19: 44050 | P19: 45672 | U19: 2585134 | W19: 高田馬場第4玉川ビル | X19: 24151178 | Y19: 113543242 | AA19: 137694420 | AC19: 第3目白ハイツ | AD19: 127400532 | AE19: 335018465 | AG19: 462418997 | AI19: 池袋ハウス | AK19: 6519475 | AL19: 302954 | AP19: 6822429 | AR19: レジデンス目白豊島 | BF19: 西池袋駅前ビル | BG19: 99000 | BH19: 0 | BI19: 302500 | BK19: 1437800 | BP19: 1839300 | BT19: 西池袋駅前ビル | BU19: 99000 | BV19: 302500 | BX19: 1437800 | CB19: 1839300 | CJ19: 東池袋ハイツ | CK19: 2820000 | CL19: 3096000 | CM19: 3072000 | CO19: 75 | CP19: 218000 | CQ19: 12 | CS19: 12 | CT19: =VLOOKUP($CO19,chinryo_list,2,FALSE) -> 103 | CU19: =VLOOKUP($CO19,chinryo_list,3,FALSE) -> カーサ目白台ハウス | CV19: =VLOOKUP($CO19,chinryo_list,4,FALSE) -> 501 | CW19: =VLOOKUP($CO19,chinryo_list,7,FALSE) -> 住居 | CX19: =VLOOKUP($CO19,chinryo_list,8,FALSE) -> 2LDK | CY19: =VLOOKUP($CO19,chinryo_list,17,FALSE) -> 218000 | DB19: 90000-99999 | DC19: 10 | DD19: 941612 | DF19: 0-99999 | DG19: 26 | DH19: 1040061 | DJ19: 西池袋駅前ビル | DK19: 528.43 | DL19: 33429500 | DM19: 468013 | DN19: 100288 | DO19: 313.11 | DP19: 130723720 | DQ19: 270901 | DR19: 58050 | DS19: 841.54 | DT19: 164153220 | DU19: 738914 | DV19: 158338 | DY19: 西池袋駅前ビル | DZ19: 1 | EA19: 1 | EB19: 22 | EE19: 24 | EG19: 東池袋ハイツ | EH19: 970634 | EI19: 241754 | EJ19: 1212388 | EK19: 289146337 | EM19: 西池袋駅前ビル | ES19: 12 | ET19: AG | EU19: AE | EV19: 13 | EW19: {=INDIRECT("'5借入一覧'!"&ET19&EV19)&INDIRECT("'5借入一覧'!"&EU19&EV19)} | EX19: 1 | EY19: 12 | EZ19: =VLOOKUP($EY19&EZ$5,$EW$7:$EX$1101,2,FALSE) -> #N/A | FA19: =VLOOKUP($EY19&FA$5,$EW$7:$EX$1101,2,FALSE) -> #N/A | FB19: =VLOOKUP($EY19&FB$5,$EW$7:$EX$1101,2,FALSE) -> #N/A | FC19: =VLOOKUP($EY19&FC$5,$EW$7:$EX$1101,2,FALSE) -> #N/A | FD19: =VLOOKUP($EY19&FD$5,$EW$7:$EX$1101,2,FALSE) -> #N/A | FE19: =IFERROR(IF(EZ19>0,EZ$7),"") | FF19: =IFERROR(IF(FA19>0,FA$7),"") | FG19: =IFERROR(IF(FB19>0,FB$7),"") | FH19: =IFERROR(IF(FC19>0,FC$7),"") | FI19: =IFERROR(IF(FD19>0,FD$7),"") | FJ19: =FE19&FF19&FG19&FH19&FI19 | FK19: =IF(FJ19<>"",LEFT(FJ19,LEN(FJ19)-1),"") | FL19: =IF(FK19<>"",FK19&"として提供中","無") -> 無 | FN19: 対象物件なし(運転資金) | FO19: 11000000
A20: Pivot18 | B20: =HYPERLINK("#pivot!"&ADDRESS(1,MATCH(A20,$A$1:$GE$1,0),4),A20) -> Pivot18 | C20: 3物件一覧 | D20: 共同担保の提供状況 | J20: 東池袋ハイツ | K20: 1801800 | L20: 277608 | M20: 164676 | O20: 45780 | P20: 18744 | U20: 2308608 | W20: 西池袋駅前ビル | X20: 51870000 | Y20: 168935000 | AA20: 220805000 | AC20: 池袋ハウス | AD20: 131180095 | AE20: 400269597 | AG20: 531449692 | AI20: 東池袋ハイツ | AJ20: 62964 | AK20: 6359913 | AP20: 6422877 | AR20: 高田馬場第4玉川ビル | BF20: 第3目白ハイツ | BH20: 0 | BK20: 2984000 | BM20: 22000 | BP20: 3006000 | BT20: 第3目白ハイツ | BX20: 2984000 | BZ20: 22000 | CB20: 3006000 | CJ20: 南池袋マンション | CK20: 894000 | CL20: 868000 | CM20: 866000 | CO20: 69 | CP20: 218000 | CQ20: 12 | CS20: 13 | CT20: =VLOOKUP($CO20,chinryo_list,2,FALSE) -> 103 | CU20: =VLOOKUP($CO20,chinryo_list,3,FALSE) -> カーサ目白台ハウス | CV20: =VLOOKUP($CO20,chinryo_list,4,FALSE) -> 301 | CW20: =VLOOKUP($CO20,chinryo_list,7,FALSE) -> 住居 | CX20: =VLOOKUP($CO20,chinryo_list,8,FALSE) -> 2LDK | CY20: =VLOOKUP($CO20,chinryo_list,17,FALSE) -> 218000 | DB20: 100000-109999 | DC20: 13 | DD20: 1346853 | DF20: アンテナ | DG20: 8 | DH20: 247035 | DJ20: 第3目白ハイツ | DK20: 1307.01 | DL20: 63199800 | DM20: 884796 | DN20: 189598 | DO20: 805.94 | DP20: 180415820 | DQ20: 377500 | DR20: 80892 | DS20: 2112.95 | DT20: 243615620 | DU20: 1262296 | DV20: 270490 | DY20: 第3目白ハイツ | EB20: 24 | ED20: 1 | EE20: 25 | EG20: 南池袋マンション | EH20: 294357 | EI20: 191699 | EJ20: 486056 | EK20: 139123336 | EM20: 仙台駅前コーポ | ES20: 13 | ET20: AG | EU20: AE | EV20: 14 | EW20: {=INDIRECT("'5借入一覧'!"&ET20&EV20)&INDIRECT("'5借入一覧'!"&EU20&EV20)} | EX20: 1 | EY20: 13 | EZ20: =VLOOKUP($EY20&EZ$5,$EW$7:$EX$1101,2,FALSE) -> #N/A | FA20: =VLOOKUP($EY20&FA$5,$EW$7:$EX$1101,2,FALSE) -> #N/A | FB20: =VLOOKUP($EY20&FB$5,$EW$7:$EX$1101,2,FALSE) -> #N/A | FC20: =VLOOKUP($EY20&FC$5,$EW$7:$EX$1101,2,FALSE) -> #N/A | FD20: =VLOOKUP($EY20&FD$5,$EW$7:$EX$1101,2,FALSE) -> #N/A | FE20: =IFERROR(IF(EZ20>0,EZ$7),"") | FF20: =IFERROR(IF(FA20>0,FA$7),"") | FG20: =IFERROR(IF(FB20>0,FB$7),"") | FH20: =IFERROR(IF(FC20>0,FC$7),"") | FI20: =IFERROR(IF(FD20>0,FD$7),"") | FJ20: =FE20&FF20&FG20&FH20&FI20 | FK20: =IF(FJ20<>"",LEFT(FJ20,LEN(FJ20)-1),"") | FL20: =IF(FK20<>"",FK20&"として提供中","無") -> 無 | FN20: 不動産購入 | FO20: 5170500000
A21: Pivot19 | B21: =HYPERLINK("#pivot!"&ADDRESS(1,MATCH(A21,$A$1:$GE$1,0),4),A21) -> Pivot19 | C21: 8賃料集計 | D21: 現況賃料(税込・月額) | E21: 賃貸用 | F21: yesのみ | G21: 論理区画 | H21: あり | J21: 南池袋マンション | K21: 303600 | L21: 121512 | M21: 43704 | N21: 15840 | O21: 13630 | P21: 18744 | U21: 517030 | W21: 第3目白ハイツ | X21: 149989486 | Y21: 335018465 | AA21: 485007951 | AC21: 東池袋ハイツ | AD21: 142832573 | AE21: 262709157 | AG21: 405541730 | AI21: 南池袋マンション | AK21: 1410700 | AL21: 227130 | AP21: 1637830 | AR21: 西池袋駅前ビル | AT21: 0 | BB21: 0 | BF21: 池袋ハウス | BH21: 0 | BK21: 3026000 | BM21: 72000 | BP21: 3098000 | BT21: 池袋ハウス | BX21: 3026000 | BZ21: 72000 | CB21: 3098000 | CJ21: 豊島目白ビル | CK21: 2500000 | CL21: 2300000 | CM21: 2300000 | CO21: 72 | CP21: 208000 | CQ21: 13 | CS21: 14 | CT21: =VLOOKUP($CO21,chinryo_list,2,FALSE) -> 103 | CU21: =VLOOKUP($CO21,chinryo_list,3,FALSE) -> カーサ目白台ハウス | CV21: =VLOOKUP($CO21,chinryo_list,4,FALSE) -> 401 | CW21: =VLOOKUP($CO21,chinryo_list,7,FALSE) -> 住居 | CX21: =VLOOKUP($CO21,chinryo_list,8,FALSE) -> 2LDK | CY21: =VLOOKUP($CO21,chinryo_list,17,FALSE) -> 208000 | DB21: 110000-119999 | DC21: 12 | DD21: 1370037 | DF21: その他 | DJ21: 池袋ハウス | DK21: 1110.34 | DL21: 75934400 | DM21: 1063081 | DN21: 227803 | DO21: 732.25 | DP21: 263268590 | DQ21: 520012 | DR21: 111430 | DS21: 1842.59 | DT21: 339202990 | DU21: 1583093 | DV21: 339233 | DY21: 池袋ハウス | EB21: 34 | ED21: 2 | EE21: 36 | EG21: 豊島目白ビル | EH21: 1111644 | EI21: 398578 | EJ21: 1510222 | EK21: 366807279 | EM21: 対象物件なし(運転資金) | ES21: 14 | ET21: AG | EU21: AE | EV21: 15 | EW21: {=INDIRECT("'5借入一覧'!"&ET21&EV21)&INDIRECT("'5借入一覧'!"&EU21&EV21)} | EX21: 1 | EY21: 14 | EZ21: =VLOOKUP($EY21&EZ$5,$EW$7:$EX$1101,2,FALSE) -> #N/A | FA21: =VLOOKUP($EY21&FA$5,$EW$7:$EX$1101,2,FALSE) -> #N/A | FB21: =VLOOKUP($EY21&FB$5,$EW$7:$EX$1101,2,FALSE) -> #N/A | FC21: =VLOOKUP($EY21&FC$5,$EW$7:$EX$1101,2,FALSE) -> #N/A | FD21: =VLOOKUP($EY21&FD$5,$EW$7:$EX$1101,2,FALSE) -> #N/A | FE21: =IFERROR(IF(EZ21>0,EZ$7),"") | FF21: =IFERROR(IF(FA21>0,FA$7),"") | FG21: =IFERROR(IF(FB21>0,FB$7),"") | FH21: =IFERROR(IF(FC21>0,FC$7),"") | FI21: =IFERROR(IF(FD21>0,FD$7),"") | FJ21: =FE21&FF21&FG21&FH21&FI21 | FK21: =IF(FJ21<>"",LEFT(FJ21,LEN(FJ21)-1),"") | FL21: =IF(FK21<>"",FK21&"として提供中","無") -> 無 | FN21: カーサ南池袋 | FO21: 180000000
A22: Pivot20 | B22: =HYPERLINK("#pivot!"&ADDRESS(1,MATCH(A22,$A$1:$GE$1,0),4),A22) -> Pivot20 | C22: 5借入一覧 | D22: 不動産当初借入額、返済中のみ | J22: 豊島目白ビル | K22: 659419 | O22: 10340 | U22: 669759 | W22: 池袋ハウス | X22: 155225603 | Y22: 400269597 | AA22: 555495200 | AC22: 南池袋マンション | AD22: 30483564 | AE22: 120828203 | AG22: 151311767 | AI22: 豊島目白ビル | AK22: 4817807 | AP22: 4817807 | AR22: 第3目白ハイツ | AT22: 0 | BB22: 0 | BF22: 東池袋ハイツ | BG22: 13200 | BH22: 0 | BK22: 3084000 | BP22: 3097200 | BT22: 東池袋ハイツ | BU22: 13200 | BX22: 3084000 | CB22: 3097200 | CJ22: 目白アパート | CK22: 2602124 | CL22: 2783347 | CM22: 2804220 | CO22: 70 | CP22: 208000 | CQ22: 13 | CS22: 15 | CT22: =VLOOKUP($CO22,chinryo_list,2,FALSE) -> 103 | CU22: =VLOOKUP($CO22,chinryo_list,3,FALSE) -> カーサ目白台ハウス | CV22: =VLOOKUP($CO22,chinryo_list,4,FALSE) -> 302 | CW22: =VLOOKUP($CO22,chinryo_list,7,FALSE) -> 住居 | CX22: =VLOOKUP($CO22,chinryo_list,8,FALSE) -> 2DK | CY22: =VLOOKUP($CO22,chinryo_list,17,FALSE) -> 208000 | DB22: 120000-129999 | DC22: 23 | DD22: 2874000 | DF22: 事務所 | DG22: 3 | DH22: 223886 | DJ22: 東池袋ハイツ | DK22: 1133.51 | DL22: 77454600 | DM22: 1084364 | DN22: 232363 | DO22: 286.9 | DP22: 149184550 | DQ22: 287722 | DR22: 61654 | DS22: 1420.41 | DT22: 226639150 | DU22: 1372086 | DV22: 294017 | DY22: 東池袋ハイツ | EA22: 1 | EB22: 21 | EE22: 22 | EG22: 目白アパート | EH22: 995627 | EI22: 166971 | EJ22: 1162598 | EK22: 199606609 | EM22: 第3目白ハイツ | ES22: 15 | ET22: AG | EU22: AE | EV22: 16 | EW22: {=INDIRECT("'5借入一覧'!"&ET22&EV22)&INDIRECT("'5借入一覧'!"&EU22&EV22)} | EX22: 1 | EY22: 15 | EZ22: =VLOOKUP($EY22&EZ$5,$EW$7:$EX$1101,2,FALSE) -> #N/A | FA22: =VLOOKUP($EY22&FA$5,$EW$7:$EX$1101,2,FALSE) -> #N/A | FB22: =VLOOKUP($EY22&FB$5,$EW$7:$EX$1101,2,FALSE) -> #N/A | FC22: =VLOOKUP($EY22&FC$5,$EW$7:$EX$1101,2,FALSE) -> #N/A | FD22: =VLOOKUP($EY22&FD$5,$EW$7:$EX$1101,2,FALSE) -> #N/A | FE22: =IFERROR(IF(EZ22>0,EZ$7),"") | FF22: =IFERROR(IF(FA22>0,FA$7),"") | FG22: =IFERROR(IF(FB22>0,FB$7),"") | FH22: =IFERROR(IF(FC22>0,FC$7),"") | FI22: =IFERROR(IF(FD22>0,FD$7),"") | FJ22: =FE22&FF22&FG22&FH22&FI22 | FK22: =IF(FJ22<>"",LEFT(FJ22,LEN(FJ22)-1),"") | FL22: =IF(FK22<>"",FK22&"として提供中","無") -> 無 | FN22: カーサ目白台ハウス | FO22: 413500000
J23: 目白アパート | K23: 1157640 | L23: 217104 | M23: 162288 | O23: 20710 | P23: 22836 | U23: 1580578 | W23: 賃貸資産以外の償却 | X23: 3756438 | AA23: 3756438 | AC23: 豊島目白ビル | AD23: 98680532 | AE23: 316421235 | AG23: 415101767 | AI23: 目白アパート | AK23: 8734332 | AL23: 1646415 | AM23: 80146 | AP23: 10460893 | AR23: 池袋ハウス | AT23: 0 | BB23: 0 | BF23: 南池袋マンション | BH23: 0 | BJ23: 0 | BK23: 868000 | BP23: 868000 | BT23: 南池袋マンション | BW23: 0 | BX23: 868000 | CB23: 868000 | CJ23: 目白カーサ二番館 | CK23: 1863350 | CL23: 1862034 | CM23: 1856107 | CO23: 76 | CP23: 198000 | CQ23: 14 | CS23: 16 | CT23: =VLOOKUP($CO23,chinryo_list,2,FALSE) -> 103 | CU23: =VLOOKUP($CO23,chinryo_list,3,FALSE) -> カーサ目白台ハウス | CV23: =VLOOKUP($CO23,chinryo_list,4,FALSE) -> 502 | CW23: =VLOOKUP($CO23,chinryo_list,7,FALSE) -> 住居 | CX23: =VLOOKUP($CO23,chinryo_list,8,FALSE) -> 1LDK | CY23: =VLOOKUP($CO23,chinryo_list,17,FALSE) -> 198000 | DB23: 130000-139999 | DC23: 32 | DD23: 4269000 | DF23: 自販機 | DG23: 1 | DH23: 0 | DJ23: 南池袋マンション | DK23: 349.27 | DL23: 18910900 | DM23: 264752 | DN23: 56732 | DO23: 306.83 | DP23: 79056190 | DQ23: 167336 | DR23: 35857 | DS23: 656.1 | DT23: 97967090 | DU23: 432088 | DV23: 92589 | DY23: 南池袋マンション | EB23: 9 | EE23: 9 | EG23: 目白カーサ二番館 | EH23: 692442 | EI23: 247247 | EJ23: 939689 | EK23: 227542871 | EM23: 池袋ハウス | ES23: 16 | ET23: AG | EU23: AE | EV23: 17 | EW23: {=INDIRECT("'5借入一覧'!"&ET23&EV23)&INDIRECT("'5借入一覧'!"&EU23&EV23)} | EX23: 1 | EY23: 16 | EZ23: =VLOOKUP($EY23&EZ$5,$EW$7:$EX$1101,2,FALSE) -> #N/A | FA23: =VLOOKUP($EY23&FA$5,$EW$7:$EX$1101,2,FALSE) -> #N/A | FB23: =VLOOKUP($EY23&FB$5,$EW$7:$EX$1101,2,FALSE) -> #N/A | FC23: =VLOOKUP($EY23&FC$5,$EW$7:$EX$1101,2,FALSE) -> #N/A | FD23: =VLOOKUP($EY23&FD$5,$EW$7:$EX$1101,2,FALSE) -> #N/A | FE23: =IFERROR(IF(EZ23>0,EZ$7),"") | FF23: =IFERROR(IF(FA23>0,FA$7),"") | FG23: =IFERROR(IF(FB23>0,FB$7),"") | FH23: =IFERROR(IF(FC23>0,FC$7),"") | FI23: =IFERROR(IF(FD23>0,FD$7),"") | FJ23: =FE23&FF23&FG23&FH23&FI23 | FK23: =IF(FJ23<>"",LEFT(FJ23,LEN(FJ23)-1),"") | FL23: =IF(FK23<>"",FK23&"として提供中","無") -> 無 | FN23: コアプラスレジデンス梅田 | FO23: 369000000
J24: 目白カーサ二番館 | K24: 838200 | L24: 136284 | M24: 245880 | O24: 19920 | P24: 18744 | U24: 1259028 | W24: 東池袋ハイツ | X24: 187056281 | Y24: 262709157 | AA24: 449765438 | AC24: 目白アパート | AD24: 70902303 | AE24: 192559845 | AG24: 263462148 | AI24: 目白カーサ二番館 | AK24: 4300138 | AP24: 4300138 | AR24: 東池袋ハイツ | AT24: 0 | BB24: 0 | BF24: 豊島目白ビル | BI24: 2530000 | BP24: 2530000 | BT24: 豊島目白ビル | BV24: 2530000 | CB24: 2530000 | CJ24: 目白アパート1号館 | CK24: 330000 | CL24: 330000 | CM24: 330000 | CO24: 73 | CP24: 198000 | CQ24: 14 | CS24: 17 | CT24: =VLOOKUP($CO24,chinryo_list,2,FALSE) -> 103 | CU24: =VLOOKUP($CO24,chinryo_list,3,FALSE) -> カーサ目白台ハウス | CV24: =VLOOKUP($CO24,chinryo_list,4,FALSE) -> 402 | CW24: =VLOOKUP($CO24,chinryo_list,7,FALSE) -> 住居 | CX24: =VLOOKUP($CO24,chinryo_list,8,FALSE) -> 2LDK | CY24: =VLOOKUP($CO24,chinryo_list,17,FALSE) -> 198000 | DB24: 140000-149999 | DC24: 8 | DD24: 1143000 | DF24: 倉庫 | DG24: 1 | DH24: 17600 | DJ24: 豊島目白ビル | DK24: 491.32 | DL24: 39293700 | DM24: 0 | DN24: 0 | DO24: 143.13 | DP24: 147431050 | DQ24: 785817 | DR24: 168388 | DS24: 634.45 | DT24: 186724750 | DU24: 785817 | DV24: 168388 | DY24: 豊島目白ビル | DZ24: 1 | EE24: 1 | EG24: (空白) | EM24: 東池袋ハイツ | ES24: 17 | ET24: AG | EU24: AE | EV24: 18 | EW24: {=INDIRECT("'5借入一覧'!"&ET24&EV24)&INDIRECT("'5借入一覧'!"&EU24&EV24)} | EX24: 1 | EY24: 17 | EZ24: =VLOOKUP($EY24&EZ$5,$EW$7:$EX$1101,2,FALSE) -> #N/A | FA24: =VLOOKUP($EY24&FA$5,$EW$7:$EX$1101,2,FALSE) -> #N/A | FB24: =VLOOKUP($EY24&FB$5,$EW$7:$EX$1101,2,FALSE) -> #N/A | FC24: =VLOOKUP($EY24&FC$5,$EW$7:$EX$1101,2,FALSE) -> #N/A | FD24: =VLOOKUP($EY24&FD$5,$EW$7:$EX$1101,2,FALSE) -> #N/A | FE24: =IFERROR(IF(EZ24>0,EZ$7),"") | FF24: =IFERROR(IF(FA24>0,FA$7),"") | FG24: =IFERROR(IF(FB24>0,FB$7),"") | FH24: =IFERROR(IF(FC24>0,FC$7),"") | FI24: =IFERROR(IF(FD24>0,FD$7),"") | FJ24: =FE24&FF24&FG24&FH24&FI24 | FK24: =IF(FJ24<>"",LEFT(FJ24,LEN(FJ24)-1),"") | FL24: =IF(FK24<>"",FK24&"として提供中","無") -> 無 | FN24: コアプラス大塚 | FO24: 530000000
J25: (空白) | W25: 南池袋マンション | X25: 33588101 | Y25: 120828203 | AA25: 154416304 | AC25: 目白カーサ二番館 | AD25: 34281663 | AE25: 252984606 | AG25: 287266269 | AI25: (空白) | AR25: 南池袋マンション | AT25: 0 | BB25: 0 | BF25: 目白アパート | BG25: 35524 | BH25: 0 | BK25: 2385298 | BM25: 77000 | BN25: 99000 | BP25: 2596822 | BT25: 目白アパート | BU25: 35524 | BX25: 2385298 | BZ25: 77000 | CA25: 99000 | CB25: 2596822 | CJ25: 目白アパート2号館 | CK25: 160000 | CL25: 160000 | CM25: 160000 | CO25: 66 | CP25: 198000 | CQ25: 14 | CS25: 18 | CT25: =VLOOKUP($CO25,chinryo_list,2,FALSE) -> 103 | CU25: =VLOOKUP($CO25,chinryo_list,3,FALSE) -> カーサ目白台ハウス | CV25: =VLOOKUP($CO25,chinryo_list,4,FALSE) -> 201 | CW25: =VLOOKUP($CO25,chinryo_list,7,FALSE) -> 店舗 | CX25: =VLOOKUP($CO25,chinryo_list,8,FALSE) -> 事務所 | CY25: =VLOOKUP($CO25,chinryo_list,17,FALSE) -> 198000 | DB25: 150000-159999 | DC25: 11 | DD25: 1673000 | DF25: 駐車場 | DG25: 12 | DH25: 452540 | DJ25: 目白アパート | DK25: 1072.93 | DL25: 42218400 | DM25: 591057 | DN25: 126655 | DO25: 342.64 | DP25: 102949060 | DQ25: 203175 | DR25: 43537 | DS25: 1415.57 | DT25: 145167460 | DU25: 794232 | DV25: 170192 | DY25: 目白アパート | DZ25: 1 | EA25: 2 | EB25: 24 | ED25: 2 | EE25: 29 | EG25: 目白アパート1号館 | EH25: 49298 | EI25: 14364 | EJ25: 63662 | EK25: 9268450 | EM25: 南池袋マンション | ES25: 18 | ET25: AG | EU25: AE | EV25: 19 | EW25: {=INDIRECT("'5借入一覧'!"&ET25&EV25)&INDIRECT("'5借入一覧'!"&EU25&EV25)} | EX25: 1 | EY25: 18 | EZ25: =VLOOKUP($EY25&EZ$5,$EW$7:$EX$1101,2,FALSE) -> #N/A | FA25: =VLOOKUP($EY25&FA$5,$EW$7:$EX$1101,2,FALSE) -> #N/A | FB25: =VLOOKUP($EY25&FB$5,$EW$7:$EX$1101,2,FALSE) -> #N/A | FC25: =VLOOKUP($EY25&FC$5,$EW$7:$EX$1101,2,FALSE) -> #N/A | FD25: =VLOOKUP($EY25&FD$5,$EW$7:$EX$1101,2,FALSE) -> #N/A | FE25: =IFERROR(IF(EZ25>0,EZ$7),"") | FF25: =IFERROR(IF(FA25>0,FA$7),"") | FG25: =IFERROR(IF(FB25>0,FB$7),"") | FH25: =IFERROR(IF(FC25>0,FC$7),"") | FI25: =IFERROR(IF(FD25>0,FD$7),"") | FJ25: =FE25&FF25&FG25&FH25&FI25 | FK25: =IF(FJ25<>"",LEFT(FJ25,LEN(FJ25)-1),"") | FL25: =IF(FK25<>"",FK25&"として提供中","無") -> 無 | FN25: コアプラス池袋 | FO25: 102000000
J26: 目白アパート1号館 | K26: 240000 | U26: 240000 | W26: 豊島目白ビル | X26: 126784406 | Y26: 316421235 | AA26: 443205641 | AC26: (空白) | AI26: 目白アパート1号館 | AK26: 2500000 | AN26: 0 | AP26: 2500000 | AR26: 豊島目白ビル | BF26: 目白カーサ二番館 | BK26: 1758634 | BM26: 113740 | BP26: 1872374 | BT26: 目白アパート1号館 | BX26: 330000 | CB26: 330000 | CJ26: プラウD目白301号 | CK26: 295000 | CL26: 295000 | CM26: 295000 | CO26: 274 | CP26: 192093 | CQ26: 15 | CS26: 19 | CT26: =VLOOKUP($CO26,chinryo_list,2,FALSE) -> 115 | CU26: =VLOOKUP($CO26,chinryo_list,3,FALSE) -> コアプラス大塚 | CV26: =VLOOKUP($CO26,chinryo_list,4,FALSE) -> 101 | CW26: =VLOOKUP($CO26,chinryo_list,7,FALSE) -> 店舗 | CX26: =VLOOKUP($CO26,chinryo_list,8,FALSE) -> 店舗 | CY26: =VLOOKUP($CO26,chinryo_list,17,FALSE) -> 192093 | DB26: 160000-169999 | DC26: 10 | DD26: 1635000 | DF26: 店舗 | DG26: 1 | DH26: 99000 | DJ26: 目白カーサ二番館 | DK26: 496.02 | DL26: 23300500 | DM26: 326207 | DN26: 69901 | DO26: 278.71 | DP26: 136851060 | DQ26: 276361 | DR26: 59220 | DS26: 774.73 | DT26: 160151560 | DU26: 602568 | DV26: 129121 | DY26: 目白カーサ二番館 | EB26: 10 | ED26: 11 | EE26: 21 | EG26: プラウD目白301号 | EH26: 496340 | EI26: 264250 | EJ26: 760590 | EK26: 108163551 | EM26: 豊島目白ビル | ES26: 19 | ET26: AG | EU26: AE | EV26: 20 | EW26: {=INDIRECT("'5借入一覧'!"&ET26&EV26)&INDIRECT("'5借入一覧'!"&EU26&EV26)} | EX26: 1 | EY26: 19 | EZ26: =VLOOKUP($EY26&EZ$5,$EW$7:$EX$1101,2,FALSE) -> #N/A | FA26: =VLOOKUP($EY26&FA$5,$EW$7:$EX$1101,2,FALSE) -> #N/A | FB26: =VLOOKUP($EY26&FB$5,$EW$7:$EX$1101,2,FALSE) -> #N/A | FC26: =VLOOKUP($EY26&FC$5,$EW$7:$EX$1101,2,FALSE) -> #N/A | FD26: =VLOOKUP($EY26&FD$5,$EW$7:$EX$1101,2,FALSE) -> #N/A | FE26: =IFERROR(IF(EZ26>0,EZ$7),"") | FF26: =IFERROR(IF(FA26>0,FA$7),"") | FG26: =IFERROR(IF(FB26>0,FB$7),"") | FH26: =IFERROR(IF(FC26>0,FC$7),"") | FI26: =IFERROR(IF(FD26>0,FD$7),"") | FJ26: =FE26&FF26&FG26&FH26&FI26 | FK26: =IF(FJ26<>"",LEFT(FJ26,LEN(FJ26)-1),"") | FL26: =IF(FK26<>"",FK26&"として提供中","無") -> 無 | FN26: メゾン雑司ヶ谷 | FO26: 392000000
J27: 目白アパート2号館 | K27: 240000 | U27: 240000 | W27: 目白アパート | X27: 113432893 | Y27: 192559845 | AA27: 305992738 | AC27: 目白アパート1号館 | AD27: 51251000 | AE27: 5112000 | AG27: 56363000 | AI27: 目白アパート2号館 | AK27: 2000000 | AN27: 0 | AP27: 2000000 | AR27: 目白アパート | AT27: 0 | BB27: 0 | BF27: (空白) | BT27: 目白アパート2号館 | BX27: 160000 | CB27: 160000 | CJ27: 総計 | CK27: 33723144 | CL27: 35268300 | CM27: 35159540 | CO27: 295 | CP27: 190000 | CQ27: 16 | CS27: 20 | CT27: =VLOOKUP($CO27,chinryo_list,2,FALSE) -> 117 | CU27: =VLOOKUP($CO27,chinryo_list,3,FALSE) -> 高田馬場第4玉川ビル | CV27: =VLOOKUP($CO27,chinryo_list,4,FALSE) -> 101 | CW27: =VLOOKUP($CO27,chinryo_list,7,FALSE) -> 住居 | CX27: =VLOOKUP($CO27,chinryo_list,8,FALSE) -> 2SLDK | CY27: =VLOOKUP($CO27,chinryo_list,17,FALSE) -> 190000 | DB27: 170000-179999 | DC27: 4 | DD27: 685000 | DF27: (空白) | DJ27: (空白) | DY27: (空白) | EG27: 目白アパート1号2号_二棟一括 | EH27: 213926 | EI27: 100486 | EJ27: 314412 | EK27: 75151106 | EM27: 目白アパート | ES27: 20 | ET27: AG | EU27: AE | EV27: 21 | EW27: {=INDIRECT("'5借入一覧'!"&ET27&EV27)&INDIRECT("'5借入一覧'!"&EU27&EV27)} | EX27: 1 | EY27: 20 | EZ27: =VLOOKUP($EY27&EZ$5,$EW$7:$EX$1101,2,FALSE) -> #N/A | FA27: =VLOOKUP($EY27&FA$5,$EW$7:$EX$1101,2,FALSE) -> #N/A | FB27: =VLOOKUP($EY27&FB$5,$EW$7:$EX$1101,2,FALSE) -> #N/A | FC27: =VLOOKUP($EY27&FC$5,$EW$7:$EX$1101,2,FALSE) -> #N/A | FD27: =VLOOKUP($EY27&FD$5,$EW$7:$EX$1101,2,FALSE) -> #N/A | FE27: =IFERROR(IF(EZ27>0,EZ$7),"") | FF27: =IFERROR(IF(FA27>0,FA$7),"") | FG27: =IFERROR(IF(FB27>0,FB$7),"") | FH27: =IFERROR(IF(FC27>0,FC$7),"") | FI27: =IFERROR(IF(FD27>0,FD$7),"") | FJ27: =FE27&FF27&FG27&FH27&FI27 | FK27: =IF(FJ27<>"",LEFT(FJ27,LEN(FJ27)-1),"") | FL27: =IF(FK27<>"",FK27&"として提供中","無") -> 無 | FN27: レジデンス目白豊島 | FO27: 189000000
J28: プラウD目白301号 | O28: 7360 | Q28: 163200 | R28: 174000 | U28: 344560 | W28: 目白カーサ二番館 | X28: 59724146 | Y28: 252984606 | AA28: 312708752 | AC28: 目白アパート2号館 | AD28: 31236000 | AE28: 5241000 | AG28: 36477000 | AI28: プラウD目白301号 | AK28: 1131918 | AL28: 574046 | AP28: 1705964 | AR28: 目白カーサ二番館 | BF28: 目白アパート1号館 | BK28: 330000 | BP28: 330000 | BT28: 目白カーサ二番館 | BX28: 1758634 | BZ28: 113740 | CB28: 1872374 | CO28: 64 | CP28: 189444 | CQ28: 17 | CS28: 21 | CT28: =VLOOKUP($CO28,chinryo_list,2,FALSE) -> 103 | CU28: =VLOOKUP($CO28,chinryo_list,3,FALSE) -> カーサ目白台ハウス | CV28: =VLOOKUP($CO28,chinryo_list,4,FALSE) -> 102 | CW28: =VLOOKUP($CO28,chinryo_list,7,FALSE) -> 事務所 | CX28: =VLOOKUP($CO28,chinryo_list,8,FALSE) -> 事務所 | CY28: =VLOOKUP($CO28,chinryo_list,17,FALSE) -> 189444 | DB28: 180000-189999 | DC28: 4 | DD28: 725000 | DF28: 100000-199999 | DG28: 8 | DH28: 1406085 | DJ28: 目白アパート1号館 | DK28: 79 | DL28: 79056190 | DM28: 167336 | DN28: 35857 | DO28: 79 | DP28: 18910900 | DQ28: 264752 | DR28: 56732 | DS28: 158 | DT28: 97967090 | DU28: 432088 | DV28: 92589 | DY28: 目白アパート1号館 | EB28: 1 | EE28: 1 | EG28: 総計 | EH28: 12955677 | EI28: 5043759 | EJ28: 17999436 | EK28: 4439492417 | EM28: 目白カーサ二番館 | ES28: 21 | ET28: AG | EU28: AE | EV28: 22 | EW28: {=INDIRECT("'5借入一覧'!"&ET28&EV28)&INDIRECT("'5借入一覧'!"&EU28&EV28)} | EX28: 1 | EY28: 21 | EZ28: =VLOOKUP($EY28&EZ$5,$EW$7:$EX$1101,2,FALSE) -> #N/A | FA28: =VLOOKUP($EY28&FA$5,$EW$7:$EX$1101,2,FALSE) -> #N/A | FB28: =VLOOKUP($EY28&FB$5,$EW$7:$EX$1101,2,FALSE) -> #N/A | FC28: =VLOOKUP($EY28&FC$5,$EW$7:$EX$1101,2,FALSE) -> #N/A | FD28: =VLOOKUP($EY28&FD$5,$EW$7:$EX$1101,2,FALSE) -> #N/A | FE28: =IFERROR(IF(EZ28>0,EZ$7),"") | FF28: =IFERROR(IF(FA28>0,FA$7),"") | FG28: =IFERROR(IF(FB28>0,FB$7),"") | FH28: =IFERROR(IF(FC28>0,FC$7),"") | FI28: =IFERROR(IF(FD28>0,FD$7),"") | FJ28: =FE28&FF28&FG28&FH28&FI28 | FK28: =IF(FJ28<>"",LEFT(FJ28,LEN(FJ28)-1),"") | FL28: =IF(FK28<>"",FK28&"として提供中","無") -> 無 | FN28: 高田馬場第4玉川ビル | FO28: 118000000
J29: 総計 | K29: 14590219 | L29: 2296320 | M29: 2252388 | N29: 424404 | O29: 370580 | P29: 322080 | Q29: 211800 | R29: 190200 | T29: -6000 | U29: 20651991 | W29: (空白) | AC29: プラウD目白301号 | AD29: 37501218 | AE29: 57130988 | AG29: 94632206 | AI29: 総計 | AJ29: 433617 | AK29: 79840239 | AL29: 6753913 | AM29: 292843 | AN29: 0 | AP29: 87320612 | AR29: (空白) | BF29: 目白アパート2号館 | BK29: 160000 | BP29: 160000 | BT29: (空白) | CO29: 65 | CP29: 187000 | CQ29: 18 | CS29: 22 | CT29: =VLOOKUP($CO29,chinryo_list,2,FALSE) -> 103 | CU29: =VLOOKUP($CO29,chinryo_list,3,FALSE) -> カーサ目白台ハウス | CV29: =VLOOKUP($CO29,chinryo_list,4,FALSE) -> 103 | CW29: =VLOOKUP($CO29,chinryo_list,7,FALSE) -> 事務所 | CX29: =VLOOKUP($CO29,chinryo_list,8,FALSE) -> 事務所 | CY29: =VLOOKUP($CO29,chinryo_list,17,FALSE) -> 187000 | DB29: 190000-200000 | DC29: 3 | DD29: 586000 | DF29: アンテナ | DJ29: 目白アパート2号館 | DK29: 79 | DL29: 79056190 | DM29: 167336 | DN29: 35857 | DO29: 79 | DP29: 18910900 | DQ29: 264752 | DR29: 56732 | DS29: 158 | DT29: 97967090 | DU29: 432088 | DV29: 92589 | DY29: 目白アパート2号館 | EB29: 1 | EE29: 1 | EM29: (空白) | ES29: 22 | ET29: AG | EU29: AE | EV29: 23 | EW29: {=INDIRECT("'5借入一覧'!"&ET29&EV29)&INDIRECT("'5借入一覧'!"&EU29&EV29)} -> 106671 | EX29: 1 | EY29: 22 | EZ29: =VLOOKUP($EY29&EZ$5,$EW$7:$EX$1101,2,FALSE) -> #N/A | FA29: =VLOOKUP($EY29&FA$5,$EW$7:$EX$1101,2,FALSE) -> #N/A | FB29: =VLOOKUP($EY29&FB$5,$EW$7:$EX$1101,2,FALSE) -> #N/A | FC29: =VLOOKUP($EY29&FC$5,$EW$7:$EX$1101,2,FALSE) -> #N/A | FD29: =VLOOKUP($EY29&FD$5,$EW$7:$EX$1101,2,FALSE) -> #N/A | FE29: =IFERROR(IF(EZ29>0,EZ$7),"") | FF29: =IFERROR(IF(FA29>0,FA$7),"") | FG29: =IFERROR(IF(FB29>0,FB$7),"") | FH29: =IFERROR(IF(FC29>0,FC$7),"") | FI29: =IFERROR(IF(FD29>0,FD$7),"") | FJ29: =FE29&FF29&FG29&FH29&FI29 | FK29: =IF(FJ29<>"",LEFT(FJ29,LEN(FJ29)-1),"") | FL29: =IF(FK29<>"",FK29&"として提供中","無") -> 無 | FN29: 西池袋駅前ビル | FO29: 226000000
W30: 目白アパート1号館 | X30: 51251000 | Y30: 5112000 | AA30: 56363000 | AC30: 総計 | AD30: 1467635379 | AE30: 3694543297 | AG30: 5162178676 | AR30: 目白アパート1号館 | BF30: プラウD目白301号 | BK30: 0 | BP30: 0 | BT30: プラウD目白301号 | CO30: 178 | CP30: 185000 | CQ30: 19 | CS30: 23 | CT30: =VLOOKUP($CO30,chinryo_list,2,FALSE) -> 109 | CU30: =VLOOKUP($CO30,chinryo_list,3,FALSE) -> カーサ南池袋 | CV30: =VLOOKUP($CO30,chinryo_list,4,FALSE) -> 332 | CW30: =VLOOKUP($CO30,chinryo_list,7,FALSE) -> 住居 | CX30: =VLOOKUP($CO30,chinryo_list,8,FALSE) -> 3LDK | CY30: =VLOOKUP($CO30,chinryo_list,17,FALSE) -> 185000 | DB30: >200000 | DC30: 8 | DD30: 3466434 | DF30: その他 | DJ30: プラウD目白301号 | DK30: 79 | DL30: 6972378.2 | DM30: 98408 | DN30: 21087 | DO30: 62.47 | DP30: 22311426 | DQ30: 47872 | DR30: 10257 | DS30: 141.47 | DT30: 29283805 | DU30: 146280 | DV30: 31344 | DY30: プラウD目白301号 | EB30: 1 | EE30: 1 | EM30: 目白アパート1号館 | ES30: 23 | ET30: AG | EU30: AE | EV30: 24 | EW30: {=INDIRECT("'5借入一覧'!"&ET30&EV30)&INDIRECT("'5借入一覧'!"&EU30&EV30)} -> 107673 | EX30: 1 | EY30: 23 | EZ30: =VLOOKUP($EY30&EZ$5,$EW$7:$EX$1101,2,FALSE) -> #N/A | FA30: =VLOOKUP($EY30&FA$5,$EW$7:$EX$1101,2,FALSE) -> #N/A | FB30: =VLOOKUP($EY30&FB$5,$EW$7:$EX$1101,2,FALSE) -> #N/A | FC30: =VLOOKUP($EY30&FC$5,$EW$7:$EX$1101,2,FALSE) -> #N/A | FD30: =VLOOKUP($EY30&FD$5,$EW$7:$EX$1101,2,FALSE) -> #N/A | FE30: =IFERROR(IF(EZ30>0,EZ$7),"") | FF30: =IFERROR(IF(FA30>0,FA$7),"") | FG30: =IFERROR(IF(FB30>0,FB$7),"") | FH30: =IFERROR(IF(FC30>0,FC$7),"") | FI30: =IFERROR(IF(FD30>0,FD$7),"") | FJ30: =FE30&FF30&FG30&FH30&FI30 | FK30: =IF(FJ30<>"",LEFT(FJ30,LEN(FJ30)-1),"") | FL30: =IF(FK30<>"",FK30&"として提供中","無") -> 無 | FN30: 第3目白ハイツ | FO30: 495000000
W31: 目白アパート2号館 | X31: 31236000 | Y31: 5241000 | AA31: 36477000 | AR31: 目白アパート2号館 | BF31: 総計 | BG31: 247035 | BH31: 0 | BI31: 3702978 | BJ31: 0 | BK31: 27943232 | BL31: 282415 | BM31: 794721 | BN31: 2337093 | BP31: 35307474 | BT31: 総計 | BU31: 247035 | BV31: 3702978 | BW31: 0 | BX31: 27943232 | BY31: 282415 | BZ31: 794721 | CA31: 2337093 | CB31: 35307474 | CO31: 139 | CP31: 180000 | CQ31: 20 | CS31: 24 | CT31: =VLOOKUP($CO31,chinryo_list,2,FALSE) -> 106 | CU31: =VLOOKUP($CO31,chinryo_list,3,FALSE) -> 東池袋ハイツ | CV31: =VLOOKUP($CO31,chinryo_list,4,FALSE) -> 602 | CW31: =VLOOKUP($CO31,chinryo_list,7,FALSE) -> 住居 | CX31: =VLOOKUP($CO31,chinryo_list,8,FALSE) -> 1LDK | CY31: =VLOOKUP($CO31,chinryo_list,17,FALSE) -> 180000 | DB31: 総計 | DC31: 245 | DD31: 28235436 | DF31: 事務所 | DG31: 4 | DH31: 681592 | DJ31: 総計 | DK31: 12524.25 | DL31: 1.1890583e+09 | DM31: 9870447 | DN31: 2115462 | DO31: 5797.49 | DP31: 2.2216381e+09 | DQ31: 5583147 | DR31: 1196376 | DS31: 18321.74 | DT31: 3.4106964e+09 | DU31: 15453594 | DV31: 3311838 | DY31: 総計 | DZ31: 16 | EA31: 8 | EB31: 255 | EC31: 2 | ED31: 22 | EE31: 303 | EM31: プラウD目白301号 | ES31: 24 | ET31: AG | EU31: AE | EV31: 25 | EW31: {=INDIRECT("'5借入一覧'!"&ET31&EV31)&INDIRECT("'5借入一覧'!"&EU31&EV31)} -> 109673 | EX31: 1 | EY31: 24 | EZ31: =VLOOKUP($EY31&EZ$5,$EW$7:$EX$1101,2,FALSE) -> #N/A | FA31: =VLOOKUP($EY31&FA$5,$EW$7:$EX$1101,2,FALSE) -> #N/A | FB31: =VLOOKUP($EY31&FB$5,$EW$7:$EX$1101,2,FALSE) -> #N/A | FC31: =VLOOKUP($EY31&FC$5,$EW$7:$EX$1101,2,FALSE) -> #N/A | FD31: =VLOOKUP($EY31&FD$5,$EW$7:$EX$1101,2,FALSE) -> #N/A | FE31: =IFERROR(IF(EZ31>0,EZ$7),"") | FF31: =IFERROR(IF(FA31>0,FA$7),"") | FG31: =IFERROR(IF(FB31>0,FB$7),"") | FH31: =IFERROR(IF(FC31>0,FC$7),"") | FI31: =IFERROR(IF(FD31>0,FD$7),"") | FJ31: =FE31&FF31&FG31&FH31&FI31 | FK31: =IF(FJ31<>"",LEFT(FJ31,LEN(FJ31)-1),"") | FL31: =IF(FK31<>"",FK31&"として提供中","無") -> 無 | FN31: 池袋ハウス | FO31: 550000000
W32: プラウD目白301号 | X32: 19286259 | Y32: 57130988 | AA32: 76417247 | AR32: プラウD目白301号 | AW32: 295000 | BB32: 295000 | CO32: 176 | CP32: 180000 | CQ32: 20 | CS32: 25 | CT32: =VLOOKUP($CO32,chinryo_list,2,FALSE) -> 109 | CU32: =VLOOKUP($CO32,chinryo_list,3,FALSE) -> カーサ南池袋 | CV32: =VLOOKUP($CO32,chinryo_list,4,FALSE) -> 222 | CW32: =VLOOKUP($CO32,chinryo_list,7,FALSE) -> 住居 | CX32: =VLOOKUP($CO32,chinryo_list,8,FALSE) -> 3LDK | CY32: =VLOOKUP($CO32,chinryo_list,17,FALSE) -> 180000 | DF32: 自販機 | EM32: 目白アパート1号2号_二棟一括 | ES32: 25 | ET32: AG | EU32: AE | EV32: 26 | EW32: {=INDIRECT("'5借入一覧'!"&ET32&EV32)&INDIRECT("'5借入一覧'!"&EU32&EV32)} -> 109671 | EX32: 1 | EY32: 25 | EZ32: =VLOOKUP($EY32&EZ$5,$EW$7:$EX$1101,2,FALSE) -> #N/A | FA32: =VLOOKUP($EY32&FA$5,$EW$7:$EX$1101,2,FALSE) -> #N/A | FB32: =VLOOKUP($EY32&FB$5,$EW$7:$EX$1101,2,FALSE) -> #N/A | FC32: =VLOOKUP($EY32&FC$5,$EW$7:$EX$1101,2,FALSE) -> #N/A | FD32: =VLOOKUP($EY32&FD$5,$EW$7:$EX$1101,2,FALSE) -> #N/A | FE32: =IFERROR(IF(EZ32>0,EZ$7),"") | FF32: =IFERROR(IF(FA32>0,FA$7),"") | FG32: =IFERROR(IF(FB32>0,FB$7),"") | FH32: =IFERROR(IF(FC32>0,FC$7),"") | FI32: =IFERROR(IF(FD32>0,FD$7),"") | FJ32: =FE32&FF32&FG32&FH32&FI32 | FK32: =IF(FJ32<>"",LEFT(FJ32,LEN(FJ32)-1),"") | FL32: =IF(FK32<>"",FK32&"として提供中","無") -> 無 | FN32: 東池袋ハイツ | FO32: 376000000
W33: 総計 | X33: 1751567633 | Y33: 3694543297 | AA33: 5446110930 | AR33: yes | AS33: 247035 | AU33: 3737978 | AV33: 0 | AW33: 28235436 | AX33: 282415 | AY33: 809021 | AZ33: 2337093 | BB33: 35648978 | CO33: 138 | CP33: 180000 | CQ33: 20 | CS33: 26 | CT33: =VLOOKUP($CO33,chinryo_list,2,FALSE) -> 106 | CU33: =VLOOKUP($CO33,chinryo_list,3,FALSE) -> 東池袋ハイツ | CV33: =VLOOKUP($CO33,chinryo_list,4,FALSE) -> 601 | CW33: =VLOOKUP($CO33,chinryo_list,7,FALSE) -> 住居 | CX33: =VLOOKUP($CO33,chinryo_list,8,FALSE) -> 3DK | CY33: =VLOOKUP($CO33,chinryo_list,17,FALSE) -> 180000 | DF33: 倉庫 | EM33: 運転資金 | EN33: 84461 | EO33: 16139 | EP33: 100600 | EQ33: 10244573 | ES33: 26 | ET33: AG | EU33: AE | EV33: 27 | EW33: {=INDIRECT("'5借入一覧'!"&ET33&EV33)&INDIRECT("'5借入一覧'!"&EU33&EV33)} | EX33: 1 | EY33: 26 | EZ33: =VLOOKUP($EY33&EZ$5,$EW$7:$EX$1101,2,FALSE) -> #N/A | FA33: =VLOOKUP($EY33&FA$5,$EW$7:$EX$1101,2,FALSE) -> #N/A | FB33: =VLOOKUP($EY33&FB$5,$EW$7:$EX$1101,2,FALSE) -> #N/A | FC33: =VLOOKUP($EY33&FC$5,$EW$7:$EX$1101,2,FALSE) -> #N/A | FD33: =VLOOKUP($EY33&FD$5,$EW$7:$EX$1101,2,FALSE) -> #N/A | FE33: =IFERROR(IF(EZ33>0,EZ$7),"") | FF33: =IFERROR(IF(FA33>0,FA$7),"") | FG33: =IFERROR(IF(FB33>0,FB$7),"") | FH33: =IFERROR(IF(FC33>0,FC$7),"") | FI33: =IFERROR(IF(FD33>0,FD$7),"") | FJ33: =FE33&FF33&FG33&FH33&FI33 | FK33: =IF(FJ33<>"",LEFT(FJ33,LEN(FJ33)-1),"") | FL33: =IF(FK33<>"",FK33&"として提供中","無") -> 無 | FN33: 南池袋マンション | FO33: 155000000
AR34: カーサ南池袋 | AS34: 72911 | AW34: 1417000 | AX34: 17600 | AY34: 27000 | BB34: 1534511 | CO34: 291 | CP34: 175000 | CQ34: 21 | CS34: 27 | CT34: =VLOOKUP($CO34,chinryo_list,2,FALSE) -> 116 | CU34: =VLOOKUP($CO34,chinryo_list,3,FALSE) -> コアプラスレジデンス梅田 | CV34: =VLOOKUP($CO34,chinryo_list,4,FALSE) -> 802 | CW34: =VLOOKUP($CO34,chinryo_list,7,FALSE) -> 住居 | CX34: =VLOOKUP($CO34,chinryo_list,8,FALSE) -> 2LDK | CY34: =VLOOKUP($CO34,chinryo_list,17,FALSE) -> 175000 | DF34: 駐車場 | EM34: あおばマンション | ES34: 27 | ET34: AG | EU34: AE | EV34: 28 | EW34: {=INDIRECT("'5借入一覧'!"&ET34&EV34)&INDIRECT("'5借入一覧'!"&EU34&EV34)} | EX34: 1 | EY34: 27 | EZ34: =VLOOKUP($EY34&EZ$5,$EW$7:$EX$1101,2,FALSE) -> #N/A | FA34: =VLOOKUP($EY34&FA$5,$EW$7:$EX$1101,2,FALSE) -> #N/A | FB34: =VLOOKUP($EY34&FB$5,$EW$7:$EX$1101,2,FALSE) -> #N/A | FC34: =VLOOKUP($EY34&FC$5,$EW$7:$EX$1101,2,FALSE) -> #N/A | FD34: =VLOOKUP($EY34&FD$5,$EW$7:$EX$1101,2,FALSE) -> #N/A | FE34: =IFERROR(IF(EZ34>0,EZ$7),"") | FF34: =IFERROR(IF(FA34>0,FA$7),"") | FG34: =IFERROR(IF(FB34>0,FB$7),"") | FH34: =IFERROR(IF(FC34>0,FC$7),"") | FI34: =IFERROR(IF(FD34>0,FD$7),"") | FJ34: =FE34&FF34&FG34&FH34&FI34 | FK34: =IF(FJ34<>"",LEFT(FJ34,LEN(FJ34)-1),"") | FL34: =IF(FK34<>"",FK34&"として提供中","無") -> 無 | FN34: 豊島目白ビル | FO34: 450000000
AR35: カーサ目白台ハウス | AU35: 643878 | AW35: 1913800 | AY35: 126500 | AZ35: 363000 | BB35: 3047178 | CO35: 63 | CP35: 173148 | CQ35: 22 | CS35: 28 | CT35: =VLOOKUP($CO35,chinryo_list,2,FALSE) -> 103 | CU35: =VLOOKUP($CO35,chinryo_list,3,FALSE) -> カーサ目白台ハウス | CV35: =VLOOKUP($CO35,chinryo_list,4,FALSE) -> 101 | CW35: =VLOOKUP($CO35,chinryo_list,7,FALSE) -> 事務所 | CX35: =VLOOKUP($CO35,chinryo_list,8,FALSE) -> 事務所 | CY35: =VLOOKUP($CO35,chinryo_list,17,FALSE) -> 173148 | DF35: 店舗 | DG35: 4 | DH35: 724493 | EM35: カーサ南池袋 | ES35: 28 | ET35: AG | EU35: AE | EV35: 29 | EW35: {=INDIRECT("'5借入一覧'!"&ET35&EV35)&INDIRECT("'5借入一覧'!"&EU35&EV35)} | EX35: 1 | EY35: 28 | EZ35: =VLOOKUP($EY35&EZ$5,$EW$7:$EX$1101,2,FALSE) -> #N/A | FA35: =VLOOKUP($EY35&FA$5,$EW$7:$EX$1101,2,FALSE) -> #N/A | FB35: =VLOOKUP($EY35&FB$5,$EW$7:$EX$1101,2,FALSE) -> #N/A | FC35: =VLOOKUP($EY35&FC$5,$EW$7:$EX$1101,2,FALSE) -> #N/A | FD35: =VLOOKUP($EY35&FD$5,$EW$7:$EX$1101,2,FALSE) -> #N/A | FE35: =IFERROR(IF(EZ35>0,EZ$7),"") | FF35: =IFERROR(IF(FA35>0,FA$7),"") | FG35: =IFERROR(IF(FB35>0,FB$7),"") | FH35: =IFERROR(IF(FC35>0,FC$7),"") | FI35: =IFERROR(IF(FD35>0,FD$7),"") | FJ35: =FE35&FF35&FG35&FH35&FI35 | FK35: =IF(FJ35<>"",LEFT(FJ35,LEN(FJ35)-1),"") | FL35: =IF(FK35<>"",FK35&"として提供中","無") -> 無 | FN35: 目白アパート | FO35: 265000000
AR36: コアプラスレジデンス梅田 | AS36: 13200 | AW36: 2041000 | AZ36: 413600 | BB36: 2467800 | CO36: 125 | CP36: 170000 | CQ36: 23 | CS36: 29 | CT36: =VLOOKUP($CO36,chinryo_list,2,FALSE) -> 106 | CU36: =VLOOKUP($CO36,chinryo_list,3,FALSE) -> 東池袋ハイツ | CV36: =VLOOKUP($CO36,chinryo_list,4,FALSE) -> 204 | CW36: =VLOOKUP($CO36,chinryo_list,7,FALSE) -> 住居 | CX36: =VLOOKUP($CO36,chinryo_list,8,FALSE) -> 3DK | CY36: =VLOOKUP($CO36,chinryo_list,17,FALSE) -> 170000 | DF36: (空白) | EM36: カーサ目白台ハウス | ES36: 29 | ET36: AG | EU36: AE | EV36: 30 | EW36: {=INDIRECT("'5借入一覧'!"&ET36&EV36)&INDIRECT("'5借入一覧'!"&EU36&EV36)} | EX36: 1 | EY36: 29 | EZ36: =VLOOKUP($EY36&EZ$5,$EW$7:$EX$1101,2,FALSE) -> #N/A | FA36: =VLOOKUP($EY36&FA$5,$EW$7:$EX$1101,2,FALSE) -> #N/A | FB36: =VLOOKUP($EY36&FB$5,$EW$7:$EX$1101,2,FALSE) -> #N/A | FC36: =VLOOKUP($EY36&FC$5,$EW$7:$EX$1101,2,FALSE) -> #N/A | FD36: =VLOOKUP($EY36&FD$5,$EW$7:$EX$1101,2,FALSE) -> #N/A | FE36: =IFERROR(IF(EZ36>0,EZ$7),"") | FF36: =IFERROR(IF(FA36>0,FA$7),"") | FG36: =IFERROR(IF(FB36>0,FB$7),"") | FH36: =IFERROR(IF(FC36>0,FC$7),"") | FI36: =IFERROR(IF(FD36>0,FD$7),"") | FJ36: =FE36&FF36&FG36&FH36&FI36 | FK36: =IF(FJ36<>"",LEFT(FJ36,LEN(FJ36)-1),"") | FL36: =IF(FK36<>"",FK36&"として提供中","無") -> 無 | FN36: 目白アパート1号2号_二棟一括 | FO36: 80000000
AR37: コアプラス大塚 | AS37: 13200 | AW37: 3011000 | AY37: 356481 | AZ37: 192093 | BB37: 3572774 | CO37: 129 | CP37: 170000 | CQ37: 23 | CS37: 30 | CT37: =VLOOKUP($CO37,chinryo_list,2,FALSE) -> 106 | CU37: =VLOOKUP($CO37,chinryo_list,3,FALSE) -> 東池袋ハイツ | CV37: =VLOOKUP($CO37,chinryo_list,4,FALSE) -> 304 | CW37: =VLOOKUP($CO37,chinryo_list,7,FALSE) -> 住居 | CX37: =VLOOKUP($CO37,chinryo_list,8,FALSE) -> 3DK | CY37: =VLOOKUP($CO37,chinryo_list,17,FALSE) -> 170000 | DF37: 200000-299999 | DG37: 1 | DH37: 264815 | EM37: コアプラスレジデンス梅田 | ES37: 30 | ET37: AG | EU37: AE | EV37: 31 | EW37: {=INDIRECT("'5借入一覧'!"&ET37&EV37)&INDIRECT("'5借入一覧'!"&EU37&EV37)} | EX37: 1 | EY37: 30 | EZ37: =VLOOKUP($EY37&EZ$5,$EW$7:$EX$1101,2,FALSE) -> #N/A | FA37: =VLOOKUP($EY37&FA$5,$EW$7:$EX$1101,2,FALSE) -> #N/A | FB37: =VLOOKUP($EY37&FB$5,$EW$7:$EX$1101,2,FALSE) -> #N/A | FC37: =VLOOKUP($EY37&FC$5,$EW$7:$EX$1101,2,FALSE) -> #N/A | FD37: =VLOOKUP($EY37&FD$5,$EW$7:$EX$1101,2,FALSE) -> #N/A | FE37: =IFERROR(IF(EZ37>0,EZ$7),"") | FF37: =IFERROR(IF(FA37>0,FA$7),"") | FG37: =IFERROR(IF(FB37>0,FB$7),"") | FH37: =IFERROR(IF(FC37>0,FC$7),"") | FI37: =IFERROR(IF(FD37>0,FD$7),"") | FJ37: =FE37&FF37&FG37&FH37&FI37 | FK37: =IF(FJ37<>"",LEFT(FJ37,LEN(FJ37)-1),"") | FL37: =IF(FK37<>"",FK37&"として提供中","無") -> 無 | FN37: 目白カーサ二番館 | FO37: 280000000
AR38: コアプラス池袋 | AU38: 132000 | AW38: 455000 | AZ38: 169400 | BB38: 756400 | CO38: 137 | CP38: 170000 | CQ38: 23 | CS38: 31 | CT38: =VLOOKUP($CO38,chinryo_list,2,FALSE) -> 106 | CU38: =VLOOKUP($CO38,chinryo_list,3,FALSE) -> 東池袋ハイツ | CV38: =VLOOKUP($CO38,chinryo_list,4,FALSE) -> 504 | CW38: =VLOOKUP($CO38,chinryo_list,7,FALSE) -> 住居 | CX38: =VLOOKUP($CO38,chinryo_list,8,FALSE) -> 1K | CY38: =VLOOKUP($CO38,chinryo_list,17,FALSE) -> 170000 | DF38: アンテナ | EM38: コアプラス大塚 | ES38: 31 | ET38: AG | EU38: AE | EV38: 32 | EW38: {=INDIRECT("'5借入一覧'!"&ET38&EV38)&INDIRECT("'5借入一覧'!"&EU38&EV38)} | EX38: 1 | EY38: 31 | EZ38: =VLOOKUP($EY38&EZ$5,$EW$7:$EX$1101,2,FALSE) -> #N/A | FA38: =VLOOKUP($EY38&FA$5,$EW$7:$EX$1101,2,FALSE) -> #N/A | FB38: =VLOOKUP($EY38&FB$5,$EW$7:$EX$1101,2,FALSE) -> #N/A | FC38: =VLOOKUP($EY38&FC$5,$EW$7:$EX$1101,2,FALSE) -> #N/A | FD38: =VLOOKUP($EY38&FD$5,$EW$7:$EX$1101,2,FALSE) -> #N/A | FE38: =IFERROR(IF(EZ38>0,EZ$7),"") | FF38: =IFERROR(IF(FA38>0,FA$7),"") | FG38: =IFERROR(IF(FB38>0,FB$7),"") | FH38: =IFERROR(IF(FC38>0,FC$7),"") | FI38: =IFERROR(IF(FD38>0,FD$7),"") | FJ38: =FE38&FF38&FG38&FH38&FI38 | FK38: =IF(FJ38<>"",LEFT(FJ38,LEN(FJ38)-1),"") | FL38: =IF(FK38<>"",FK38&"として提供中","無") -> 無 | FN38: 総計 | FO38: 5351956000
AR39: ビジネス新大阪123号 | AU39: 35000 | BB39: 35000 | CO39: 81 | CP39: 169400 | CQ39: 24 | CS39: 32 | CT39: =VLOOKUP($CO39,chinryo_list,2,FALSE) -> 104 | CU39: =VLOOKUP($CO39,chinryo_list,3,FALSE) -> コアプラス池袋 | CV39: =VLOOKUP($CO39,chinryo_list,4,FALSE) -> 101 | CW39: =VLOOKUP($CO39,chinryo_list,7,FALSE) -> 店舗 | CX39: =VLOOKUP($CO39,chinryo_list,8,FALSE) -> 店舗 | CY39: =VLOOKUP($CO39,chinryo_list,17,FALSE) -> 169400 | DF39: その他 | EM39: コアプラス池袋 | ES39: 32 | ET39: AG | EU39: AE | EV39: 33 | EW39: {=INDIRECT("'5借入一覧'!"&ET39&EV39)&INDIRECT("'5借入一覧'!"&EU39&EV39)} | EX39: 1 | EY39: 32 | EZ39: =VLOOKUP($EY39&EZ$5,$EW$7:$EX$1101,2,FALSE) -> #N/A | FA39: =VLOOKUP($EY39&FA$5,$EW$7:$EX$1101,2,FALSE) -> #N/A | FB39: =VLOOKUP($EY39&FB$5,$EW$7:$EX$1101,2,FALSE) -> #N/A | FC39: =VLOOKUP($EY39&FC$5,$EW$7:$EX$1101,2,FALSE) -> #N/A | FD39: =VLOOKUP($EY39&FD$5,$EW$7:$EX$1101,2,FALSE) -> #N/A | FE39: =IFERROR(IF(EZ39>0,EZ$7),"") | FF39: =IFERROR(IF(FA39>0,FA$7),"") | FG39: =IFERROR(IF(FB39>0,FB$7),"") | FH39: =IFERROR(IF(FC39>0,FC$7),"") | FI39: =IFERROR(IF(FD39>0,FD$7),"") | FJ39: =FE39&FF39&FG39&FH39&FI39 | FK39: =IF(FJ39<>"",LEFT(FJ39,LEN(FJ39)-1),"") | FL39: =IF(FK39<>"",FK39&"として提供中","無") -> 無
AR40: メゾン雑司ヶ谷 | AW40: 1378700 | AZ40: 1100000 | BB40: 2478700 | CO40: 59 | CP40: 169000 | CQ40: 25 | CS40: 33 | CT40: =VLOOKUP($CO40,chinryo_list,2,FALSE) -> 102 | CU40: =VLOOKUP($CO40,chinryo_list,3,FALSE) -> 池袋ハウス | CV40: =VLOOKUP($CO40,chinryo_list,4,FALSE) -> 407 | CW40: =VLOOKUP($CO40,chinryo_list,7,FALSE) -> 住居 | CX40: =VLOOKUP($CO40,chinryo_list,8,FALSE) -> 2DK | CY40: =VLOOKUP($CO40,chinryo_list,17,FALSE) -> 169000 | DF40: 事務所 | EM40: メゾン雑司ヶ谷 | ES40: 33 | ET40: AG | EU40: AE | EV40: 34 | EW40: {=INDIRECT("'5借入一覧'!"&ET40&EV40)&INDIRECT("'5借入一覧'!"&EU40&EV40)} | EX40: 1 | EY40: 33 | EZ40: =VLOOKUP($EY40&EZ$5,$EW$7:$EX$1101,2,FALSE) -> #N/A | FA40: =VLOOKUP($EY40&FA$5,$EW$7:$EX$1101,2,FALSE) -> #N/A | FB40: =VLOOKUP($EY40&FB$5,$EW$7:$EX$1101,2,FALSE) -> #N/A | FC40: =VLOOKUP($EY40&FC$5,$EW$7:$EX$1101,2,FALSE) -> #N/A | FD40: =VLOOKUP($EY40&FD$5,$EW$7:$EX$1101,2,FALSE) -> #N/A | FE40: =IFERROR(IF(EZ40>0,EZ$7),"") | FF40: =IFERROR(IF(FA40>0,FA$7),"") | FG40: =IFERROR(IF(FB40>0,FB$7),"") | FH40: =IFERROR(IF(FC40>0,FC$7),"") | FI40: =IFERROR(IF(FD40>0,FD$7),"") | FJ40: =FE40&FF40&FG40&FH40&FI40 | FK40: =IF(FJ40<>"",LEFT(FJ40,LEN(FJ40)-1),"") | FL40: =IF(FK40<>"",FK40&"として提供中","無") -> 無
AR41: レジデンス目白豊島 | AU41: 94600 | AW41: 935000 | AX41: 264815 | BB41: 1294415 | CO41: 121 | CP41: 167000 | CQ41: 26 | CS41: 34 | CT41: =VLOOKUP($CO41,chinryo_list,2,FALSE) -> 106 | CU41: =VLOOKUP($CO41,chinryo_list,3,FALSE) -> 東池袋ハイツ | CV41: =VLOOKUP($CO41,chinryo_list,4,FALSE) -> 102 | CW41: =VLOOKUP($CO41,chinryo_list,7,FALSE) -> 住居 | CX41: =VLOOKUP($CO41,chinryo_list,8,FALSE) -> 3DK | CY41: =VLOOKUP($CO41,chinryo_list,17,FALSE) -> 167000 | DF41: 自販機 | EM41: レジデンス目白豊島 | ES41: 34 | ET41: AG | EU41: AE | EV41: 35 | EW41: {=INDIRECT("'5借入一覧'!"&ET41&EV41)&INDIRECT("'5借入一覧'!"&EU41&EV41)} | EX41: 1 | EY41: 34 | EZ41: =VLOOKUP($EY41&EZ$5,$EW$7:$EX$1101,2,FALSE) -> #N/A | FA41: =VLOOKUP($EY41&FA$5,$EW$7:$EX$1101,2,FALSE) -> #N/A | FB41: =VLOOKUP($EY41&FB$5,$EW$7:$EX$1101,2,FALSE) -> #N/A | FC41: =VLOOKUP($EY41&FC$5,$EW$7:$EX$1101,2,FALSE) -> #N/A | FD41: =VLOOKUP($EY41&FD$5,$EW$7:$EX$1101,2,FALSE) -> #N/A | FE41: =IFERROR(IF(EZ41>0,EZ$7),"") | FF41: =IFERROR(IF(FA41>0,FA$7),"") | FG41: =IFERROR(IF(FB41>0,FB$7),"") | FH41: =IFERROR(IF(FC41>0,FC$7),"") | FI41: =IFERROR(IF(FD41>0,FD$7),"") | FJ41: =FE41&FF41&FG41&FH41&FI41 | FK41: =IF(FJ41<>"",LEFT(FJ41,LEN(FJ41)-1),"") | FL41: =IF(FK41<>"",FK41&"として提供中","無") -> 無
AR42: 高田馬場第4玉川ビル | AW42: 846000 | AY42: 14300 | BB42: 860300 | CO42: 296 | CP42: 165000 | CQ42: 27 | CS42: 35 | CT42: =VLOOKUP($CO42,chinryo_list,2,FALSE) -> 117 | CU42: =VLOOKUP($CO42,chinryo_list,3,FALSE) -> 高田馬場第4玉川ビル | CV42: =VLOOKUP($CO42,chinryo_list,4,FALSE) -> B101 | CW42: =VLOOKUP($CO42,chinryo_list,7,FALSE) -> 住居 | CX42: =VLOOKUP($CO42,chinryo_list,8,FALSE) -> 2SLDK | CY42: =VLOOKUP($CO42,chinryo_list,17,FALSE) -> 165000 | DF42: 倉庫 | DG42: 1 | DH42: 264815 | EM42: 高田馬場第4玉川ビル | ES42: 35 | ET42: AG | EU42: AE | EV42: 36 | EW42: {=INDIRECT("'5借入一覧'!"&ET42&EV42)&INDIRECT("'5借入一覧'!"&EU42&EV42)} | EX42: 1 | EY42: 35 | EZ42: =VLOOKUP($EY42&EZ$5,$EW$7:$EX$1101,2,FALSE) -> #N/A | FA42: =VLOOKUP($EY42&FA$5,$EW$7:$EX$1101,2,FALSE) -> #N/A | FB42: =VLOOKUP($EY42&FB$5,$EW$7:$EX$1101,2,FALSE) -> #N/A | FC42: =VLOOKUP($EY42&FC$5,$EW$7:$EX$1101,2,FALSE) -> #N/A | FD42: =VLOOKUP($EY42&FD$5,$EW$7:$EX$1101,2,FALSE) -> #N/A | FE42: =IFERROR(IF(EZ42>0,EZ$7),"") | FF42: =IFERROR(IF(FA42>0,FA$7),"") | FG42: =IFERROR(IF(FB42>0,FB$7),"") | FH42: =IFERROR(IF(FC42>0,FC$7),"") | FI42: =IFERROR(IF(FD42>0,FD$7),"") | FJ42: =FE42&FF42&FG42&FH42&FI42 | FK42: =IF(FJ42<>"",LEFT(FJ42,LEN(FJ42)-1),"") | FL42: =IF(FK42<>"",FK42&"として提供中","無") -> 無
AR43: 西池袋駅前ビル | AS43: 99000 | AU43: 302500 | AW43: 1437800 | BB43: 1839300 | CO43: 174 | CP43: 165000 | CQ43: 27 | CS43: 36 | CT43: =VLOOKUP($CO43,chinryo_list,2,FALSE) -> 109 | CU43: =VLOOKUP($CO43,chinryo_list,3,FALSE) -> カーサ南池袋 | CV43: =VLOOKUP($CO43,chinryo_list,4,FALSE) -> 112 | CW43: =VLOOKUP($CO43,chinryo_list,7,FALSE) -> 住居 | CX43: =VLOOKUP($CO43,chinryo_list,8,FALSE) -> 3LDK | CY43: =VLOOKUP($CO43,chinryo_list,17,FALSE) -> 165000 | DF43: 駐車場 | EM43: 西池袋駅前ビル | ES43: 36 | ET43: AG | EU43: AE | EV43: 37 | EW43: {=INDIRECT("'5借入一覧'!"&ET43&EV43)&INDIRECT("'5借入一覧'!"&EU43&EV43)} | EX43: 1 | EY43: 36 | EZ43: =VLOOKUP($EY43&EZ$5,$EW$7:$EX$1101,2,FALSE) -> #N/A | FA43: =VLOOKUP($EY43&FA$5,$EW$7:$EX$1101,2,FALSE) -> #N/A | FB43: =VLOOKUP($EY43&FB$5,$EW$7:$EX$1101,2,FALSE) -> #N/A | FC43: =VLOOKUP($EY43&FC$5,$EW$7:$EX$1101,2,FALSE) -> #N/A | FD43: =VLOOKUP($EY43&FD$5,$EW$7:$EX$1101,2,FALSE) -> #N/A | FE43: =IFERROR(IF(EZ43>0,EZ$7),"") | FF43: =IFERROR(IF(FA43>0,FA$7),"") | FG43: =IFERROR(IF(FB43>0,FB$7),"") | FH43: =IFERROR(IF(FC43>0,FC$7),"") | FI43: =IFERROR(IF(FD43>0,FD$7),"") | FJ43: =FE43&FF43&FG43&FH43&FI43 | FK43: =IF(FJ43<>"",LEFT(FJ43,LEN(FJ43)-1),"") | FL43: =IF(FK43<>"",FK43&"として提供中","無") -> 無
AR44: 第3目白ハイツ | AW44: 2984000 | AY44: 22000 | BB44: 3006000 | CO44: 67 | CP44: 165000 | CQ44: 27 | CS44: 37 | CT44: =VLOOKUP($CO44,chinryo_list,2,FALSE) -> 103 | CU44: =VLOOKUP($CO44,chinryo_list,3,FALSE) -> カーサ目白台ハウス | CV44: =VLOOKUP($CO44,chinryo_list,4,FALSE) -> 202 | CW44: =VLOOKUP($CO44,chinryo_list,7,FALSE) -> 店舗 | CX44: =VLOOKUP($CO44,chinryo_list,8,FALSE) -> 事務所 | CY44: =VLOOKUP($CO44,chinryo_list,17,FALSE) -> 165000 | DF44: 店舗 | EM44: 仙台駅前コーポ | ES44: 37 | ET44: AG | EU44: AE | EV44: 38 | EW44: {=INDIRECT("'5借入一覧'!"&ET44&EV44)&INDIRECT("'5借入一覧'!"&EU44&EV44)} | EX44: 1 | EY44: 37 | EZ44: =VLOOKUP($EY44&EZ$5,$EW$7:$EX$1101,2,FALSE) -> #N/A | FA44: =VLOOKUP($EY44&FA$5,$EW$7:$EX$1101,2,FALSE) -> #N/A | FB44: =VLOOKUP($EY44&FB$5,$EW$7:$EX$1101,2,FALSE) -> #N/A | FC44: =VLOOKUP($EY44&FC$5,$EW$7:$EX$1101,2,FALSE) -> #N/A | FD44: =VLOOKUP($EY44&FD$5,$EW$7:$EX$1101,2,FALSE) -> #N/A | FE44: =IFERROR(IF(EZ44>0,EZ$7),"") | FF44: =IFERROR(IF(FA44>0,FA$7),"") | FG44: =IFERROR(IF(FB44>0,FB$7),"") | FH44: =IFERROR(IF(FC44>0,FC$7),"") | FI44: =IFERROR(IF(FD44>0,FD$7),"") | FJ44: =FE44&FF44&FG44&FH44&FI44 | FK44: =IF(FJ44<>"",LEFT(FJ44,LEN(FJ44)-1),"") | FL44: =IF(FK44<>"",FK44&"として提供中","無") -> 無
AR45: 池袋ハウス | AW45: 3026000 | AY45: 72000 | BB45: 3098000 | CO45: 289 | CP45: 165000 | CQ45: 27 | CS45: 38 | CT45: =VLOOKUP($CO45,chinryo_list,2,FALSE) -> 116 | CU45: =VLOOKUP($CO45,chinryo_list,3,FALSE) -> コアプラスレジデンス梅田 | CV45: =VLOOKUP($CO45,chinryo_list,4,FALSE) -> 702 | CW45: =VLOOKUP($CO45,chinryo_list,7,FALSE) -> 住居 | CX45: =VLOOKUP($CO45,chinryo_list,8,FALSE) -> 3DK | CY45: =VLOOKUP($CO45,chinryo_list,17,FALSE) -> 165000 | DF45: (空白) | EM45: 対象物件なし(運転資金) | EN45: 84461 | EO45: 16139 | EP45: 100600 | EQ45: 10244573 | ES45: 38 | ET45: AG | EU45: AE | EV45: 39 | EW45: {=INDIRECT("'5借入一覧'!"&ET45&EV45)&INDIRECT("'5借入一覧'!"&EU45&EV45)} | EX45: 1 | EY45: 38 | EZ45: =VLOOKUP($EY45&EZ$5,$EW$7:$EX$1101,2,FALSE) -> #N/A | FA45: =VLOOKUP($EY45&FA$5,$EW$7:$EX$1101,2,FALSE) -> #N/A | FB45: =VLOOKUP($EY45&FB$5,$EW$7:$EX$1101,2,FALSE) -> #N/A | FC45: =VLOOKUP($EY45&FC$5,$EW$7:$EX$1101,2,FALSE) -> #N/A | FD45: =VLOOKUP($EY45&FD$5,$EW$7:$EX$1101,2,FALSE) -> #N/A | FE45: =IFERROR(IF(EZ45>0,EZ$7),"") | FF45: =IFERROR(IF(FA45>0,FA$7),"") | FG45: =IFERROR(IF(FB45>0,FB$7),"") | FH45: =IFERROR(IF(FC45>0,FC$7),"") | FI45: =IFERROR(IF(FD45>0,FD$7),"") | FJ45: =FE45&FF45&FG45&FH45&FI45 | FK45: =IF(FJ45<>"",LEFT(FJ45,LEN(FJ45)-1),"") | FL45: =IF(FK45<>"",FK45&"として提供中","無") -> 無
AR46: 東池袋ハイツ | AS46: 13200 | AW46: 3084000 | BB46: 3097200 | CO46: 56 | CP46: 162000 | CQ46: 28 | CS46: 39 | CT46: =VLOOKUP($CO46,chinryo_list,2,FALSE) -> 102 | CU46: =VLOOKUP($CO46,chinryo_list,3,FALSE) -> 池袋ハウス | CV46: =VLOOKUP($CO46,chinryo_list,4,FALSE) -> 403 | CW46: =VLOOKUP($CO46,chinryo_list,7,FALSE) -> 住居 | CX46: =VLOOKUP($CO46,chinryo_list,8,FALSE) -> 2DK | CY46: =VLOOKUP($CO46,chinryo_list,17,FALSE) -> 162000 | DF46: 300000-399999 | DG46: 2 | DH46: 658981 | EM46: 第3目白ハイツ | ES46: 39 | ET46: AG | EU46: AE | EV46: 40 | EW46: {=INDIRECT("'5借入一覧'!"&ET46&EV46)&INDIRECT("'5借入一覧'!"&EU46&EV46)} | EX46: 1 | EY46: 39 | EZ46: =VLOOKUP($EY46&EZ$5,$EW$7:$EX$1101,2,FALSE) -> #N/A | FA46: =VLOOKUP($EY46&FA$5,$EW$7:$EX$1101,2,FALSE) -> #N/A | FB46: =VLOOKUP($EY46&FB$5,$EW$7:$EX$1101,2,FALSE) -> #N/A | FC46: =VLOOKUP($EY46&FC$5,$EW$7:$EX$1101,2,FALSE) -> #N/A | FD46: =VLOOKUP($EY46&FD$5,$EW$7:$EX$1101,2,FALSE) -> #N/A | FE46: =IFERROR(IF(EZ46>0,EZ$7),"") | FF46: =IFERROR(IF(FA46>0,FA$7),"") | FG46: =IFERROR(IF(FB46>0,FB$7),"") | FH46: =IFERROR(IF(FC46>0,FC$7),"") | FI46: =IFERROR(IF(FD46>0,FD$7),"") | FJ46: =FE46&FF46&FG46&FH46&FI46 | FK46: =IF(FJ46<>"",LEFT(FJ46,LEN(FJ46)-1),"") | FL46: =IF(FK46<>"",FK46&"として提供中","無") -> 無
AR47: 南池袋マンション | AV47: 0 | AW47: 868000 | BB47: 868000 | CO47: 58 | CP47: 162000 | CQ47: 28 | CS47: 40 | CT47: =VLOOKUP($CO47,chinryo_list,2,FALSE) -> 102 | CU47: =VLOOKUP($CO47,chinryo_list,3,FALSE) -> 池袋ハウス | CV47: =VLOOKUP($CO47,chinryo_list,4,FALSE) -> 406 | CW47: =VLOOKUP($CO47,chinryo_list,7,FALSE) -> 住居 | CX47: =VLOOKUP($CO47,chinryo_list,8,FALSE) -> 2DK | CY47: =VLOOKUP($CO47,chinryo_list,17,FALSE) -> 162000 | DF47: アンテナ | EM47: 池袋ハウス | ES47: 40 | ET47: AG | EU47: AE | EV47: 41 | EW47: {=INDIRECT("'5借入一覧'!"&ET47&EV47)&INDIRECT("'5借入一覧'!"&EU47&EV47)} | EX47: 1 | EY47: 40 | EZ47: =VLOOKUP($EY47&EZ$5,$EW$7:$EX$1101,2,FALSE) -> #N/A | FA47: =VLOOKUP($EY47&FA$5,$EW$7:$EX$1101,2,FALSE) -> #N/A | FB47: =VLOOKUP($EY47&FB$5,$EW$7:$EX$1101,2,FALSE) -> #N/A | FC47: =VLOOKUP($EY47&FC$5,$EW$7:$EX$1101,2,FALSE) -> #N/A | FD47: =VLOOKUP($EY47&FD$5,$EW$7:$EX$1101,2,FALSE) -> #N/A | FE47: =IFERROR(IF(EZ47>0,EZ$7),"") | FF47: =IFERROR(IF(FA47>0,FA$7),"") | FG47: =IFERROR(IF(FB47>0,FB$7),"") | FH47: =IFERROR(IF(FC47>0,FC$7),"") | FI47: =IFERROR(IF(FD47>0,FD$7),"") | FJ47: =FE47&FF47&FG47&FH47&FI47 | FK47: =IF(FJ47<>"",LEFT(FJ47,LEN(FJ47)-1),"") | FL47: =IF(FK47<>"",FK47&"として提供中","無") -> 無
AR48: 豊島目白ビル | AU48: 2530000 | BB48: 2530000 | CO48: 318 | CP48: 160000 | CQ48: 29 | DF48: その他 | EM48: 東池袋ハイツ | ES48: 41 | ET48: AG | EU48: AE | EV48: 42 | EW48: {=INDIRECT("'5借入一覧'!"&ET48&EV48)&INDIRECT("'5借入一覧'!"&EU48&EV48)} | EX48: 1 | EY48: 41 | EZ48: =VLOOKUP($EY48&EZ$5,$EW$7:$EX$1101,2,FALSE) -> #N/A | FA48: =VLOOKUP($EY48&FA$5,$EW$7:$EX$1101,2,FALSE) -> #N/A | FB48: =VLOOKUP($EY48&FB$5,$EW$7:$EX$1101,2,FALSE) -> #N/A | FC48: =VLOOKUP($EY48&FC$5,$EW$7:$EX$1101,2,FALSE) -> #N/A | FD48: =VLOOKUP($EY48&FD$5,$EW$7:$EX$1101,2,FALSE) -> #N/A | FE48: =IFERROR(IF(EZ48>0,EZ$7),"") | FF48: =IFERROR(IF(FA48>0,FA$7),"") | FG48: =IFERROR(IF(FB48>0,FB$7),"") | FH48: =IFERROR(IF(FC48>0,FC$7),"") | FI48: =IFERROR(IF(FD48>0,FD$7),"") | FJ48: =FE48&FF48&FG48&FH48&FI48 | FK48: =IF(FJ48<>"",LEFT(FJ48,LEN(FJ48)-1),"") | FL48: =IF(FK48<>"",FK48&"として提供中","無") -> 無
AR49: 目白アパート | AS49: 35524 | AW49: 2589502 | AY49: 77000 | AZ49: 99000 | BB49: 2801026 | CO49: 136 | CP49: 160000 | CQ49: 29 | DF49: 事務所 | DG49: 1 | DH49: 302500 | EM49: 南池袋マンション | ES49: 42 | ET49: AG | EU49: AE | EV49: 43 | EW49: {=INDIRECT("'5借入一覧'!"&ET49&EV49)&INDIRECT("'5借入一覧'!"&EU49&EV49)} | EX49: 1 | EY49: 42 | EZ49: =VLOOKUP($EY49&EZ$5,$EW$7:$EX$1101,2,FALSE) -> #N/A | FA49: =VLOOKUP($EY49&FA$5,$EW$7:$EX$1101,2,FALSE) -> #N/A | FB49: =VLOOKUP($EY49&FB$5,$EW$7:$EX$1101,2,FALSE) -> #N/A | FC49: =VLOOKUP($EY49&FC$5,$EW$7:$EX$1101,2,FALSE) -> #N/A | FD49: =VLOOKUP($EY49&FD$5,$EW$7:$EX$1101,2,FALSE) -> #N/A | FE49: =IFERROR(IF(EZ49>0,EZ$7),"") | FF49: =IFERROR(IF(FA49>0,FA$7),"") | FG49: =IFERROR(IF(FB49>0,FB$7),"") | FH49: =IFERROR(IF(FC49>0,FC$7),"") | FI49: =IFERROR(IF(FD49>0,FD$7),"") | FJ49: =FE49&FF49&FG49&FH49&FI49 | FK49: =IF(FJ49<>"",LEFT(FJ49,LEN(FJ49)-1),"") | FL49: =IF(FK49<>"",FK49&"として提供中","無") -> 無
AR50: 目白カーサ二番館 | AW50: 1758634 | AY50: 113740 | BB50: 1872374 | CO50: 131 | CP50: 160000 | CQ50: 29 | DF50: 自販機 | EM50: 豊島目白ビル | ES50: 43 | ET50: AG | EU50: AE | EV50: 44 | EW50: {=INDIRECT("'5借入一覧'!"&ET50&EV50)&INDIRECT("'5借入一覧'!"&EU50&EV50)} | EX50: 1 | EY50: 43 | EZ50: =VLOOKUP($EY50&EZ$5,$EW$7:$EX$1101,2,FALSE) -> #N/A | FA50: =VLOOKUP($EY50&FA$5,$EW$7:$EX$1101,2,FALSE) -> #N/A | FB50: =VLOOKUP($EY50&FB$5,$EW$7:$EX$1101,2,FALSE) -> #N/A | FC50: =VLOOKUP($EY50&FC$5,$EW$7:$EX$1101,2,FALSE) -> #N/A | FD50: =VLOOKUP($EY50&FD$5,$EW$7:$EX$1101,2,FALSE) -> #N/A | FE50: =IFERROR(IF(EZ50>0,EZ$7),"") | FF50: =IFERROR(IF(FA50>0,FA$7),"") | FG50: =IFERROR(IF(FB50>0,FB$7),"") | FH50: =IFERROR(IF(FC50>0,FC$7),"") | FI50: =IFERROR(IF(FD50>0,FD$7),"") | FJ50: =FE50&FF50&FG50&FH50&FI50 | FK50: =IF(FJ50<>"",LEFT(FJ50,LEN(FJ50)-1),"") | FL50: =IF(FK50<>"",FK50&"として提供中","無") -> 無
AR51: (空白) | CO51: 283 | CP51: 158000 | CQ51: 30 | DF51: 倉庫 | EM51: 目白アパート | ES51: 44 | ET51: AG | EU51: AE | EV51: 45 | EW51: {=INDIRECT("'5借入一覧'!"&ET51&EV51)&INDIRECT("'5借入一覧'!"&EU51&EV51)} | EX51: 1 | EY51: 44 | EZ51: =VLOOKUP($EY51&EZ$5,$EW$7:$EX$1101,2,FALSE) -> #N/A | FA51: =VLOOKUP($EY51&FA$5,$EW$7:$EX$1101,2,FALSE) -> #N/A | FB51: =VLOOKUP($EY51&FB$5,$EW$7:$EX$1101,2,FALSE) -> #N/A | FC51: =VLOOKUP($EY51&FC$5,$EW$7:$EX$1101,2,FALSE) -> #N/A | FD51: =VLOOKUP($EY51&FD$5,$EW$7:$EX$1101,2,FALSE) -> #N/A | FE51: =IFERROR(IF(EZ51>0,EZ$7),"") | FF51: =IFERROR(IF(FA51>0,FA$7),"") | FG51: =IFERROR(IF(FB51>0,FB$7),"") | FH51: =IFERROR(IF(FC51>0,FC$7),"") | FI51: =IFERROR(IF(FD51>0,FD$7),"") | FJ51: =FE51&FF51&FG51&FH51&FI51 | FK51: =IF(FJ51<>"",LEFT(FJ51,LEN(FJ51)-1),"") | FL51: =IF(FK51<>"",FK51&"として提供中","無") -> 無
AR52: 目白アパート1号館 | AW52: 330000 | BB52: 330000 | CO52: 281 | CP52: 158000 | CQ52: 30 | DF52: 駐車場 | DG52: 1 | DH52: 356481 | EM52: 目白カーサ二番館 | ES52: 45 | ET52: AG | EU52: AE | EV52: 46 | EW52: {=INDIRECT("'5借入一覧'!"&ET52&EV52)&INDIRECT("'5借入一覧'!"&EU52&EV52)} | EX52: 1 | EY52: 45 | EZ52: =VLOOKUP($EY52&EZ$5,$EW$7:$EX$1101,2,FALSE) -> #N/A | FA52: =VLOOKUP($EY52&FA$5,$EW$7:$EX$1101,2,FALSE) -> #N/A | FB52: =VLOOKUP($EY52&FB$5,$EW$7:$EX$1101,2,FALSE) -> #N/A | FC52: =VLOOKUP($EY52&FC$5,$EW$7:$EX$1101,2,FALSE) -> #N/A | FD52: =VLOOKUP($EY52&FD$5,$EW$7:$EX$1101,2,FALSE) -> #N/A | FE52: =IFERROR(IF(EZ52>0,EZ$7),"") | FF52: =IFERROR(IF(FA52>0,FA$7),"") | FG52: =IFERROR(IF(FB52>0,FB$7),"") | FH52: =IFERROR(IF(FC52>0,FC$7),"") | FI52: =IFERROR(IF(FD52>0,FD$7),"") | FJ52: =FE52&FF52&FG52&FH52&FI52 | FK52: =IF(FJ52<>"",LEFT(FJ52,LEN(FJ52)-1),"") | FL52: =IF(FK52<>"",FK52&"として提供中","無") -> 無
AR53: 目白アパート2号館 | AW53: 160000 | BB53: 160000 | CO53: 135 | CP53: 155000 | CQ53: 31 | DF53: 店舗 | EM53: (空白) | ES53: 46 | ET53: AG | EU53: AE | EV53: 47 | EW53: {=INDIRECT("'5借入一覧'!"&ET53&EV53)&INDIRECT("'5借入一覧'!"&EU53&EV53)} | EX53: 1 | EY53: 46 | EZ53: =VLOOKUP($EY53&EZ$5,$EW$7:$EX$1101,2,FALSE) -> #N/A | FA53: =VLOOKUP($EY53&FA$5,$EW$7:$EX$1101,2,FALSE) -> #N/A | FB53: =VLOOKUP($EY53&FB$5,$EW$7:$EX$1101,2,FALSE) -> #N/A | FC53: =VLOOKUP($EY53&FC$5,$EW$7:$EX$1101,2,FALSE) -> #N/A | FD53: =VLOOKUP($EY53&FD$5,$EW$7:$EX$1101,2,FALSE) -> #N/A | FE53: =IFERROR(IF(EZ53>0,EZ$7),"") | FF53: =IFERROR(IF(FA53>0,FA$7),"") | FG53: =IFERROR(IF(FB53>0,FB$7),"") | FH53: =IFERROR(IF(FC53>0,FC$7),"") | FI53: =IFERROR(IF(FD53>0,FD$7),"") | FJ53: =FE53&FF53&FG53&FH53&FI53 | FK53: =IF(FJ53<>"",LEFT(FJ53,LEN(FJ53)-1),"") | FL53: =IF(FK53<>"",FK53&"として提供中","無") -> 無
AR54: プラウD目白301号 | CO54: 127 | CP54: 152000 | CQ54: 32 | DF54: (空白) | EM54: 目白アパート1号館 | ES54: 47 | ET54: AG | EU54: AE | EV54: 48 | EW54: {=INDIRECT("'5借入一覧'!"&ET54&EV54)&INDIRECT("'5借入一覧'!"&EU54&EV54)} | EX54: 1 | EY54: 47 | EZ54: =VLOOKUP($EY54&EZ$5,$EW$7:$EX$1101,2,FALSE) -> #N/A | FA54: =VLOOKUP($EY54&FA$5,$EW$7:$EX$1101,2,FALSE) -> #N/A | FB54: =VLOOKUP($EY54&FB$5,$EW$7:$EX$1101,2,FALSE) -> #N/A | FC54: =VLOOKUP($EY54&FC$5,$EW$7:$EX$1101,2,FALSE) -> #N/A | FD54: =VLOOKUP($EY54&FD$5,$EW$7:$EX$1101,2,FALSE) -> #N/A | FE54: =IFERROR(IF(EZ54>0,EZ$7),"") | FF54: =IFERROR(IF(FA54>0,FA$7),"") | FG54: =IFERROR(IF(FB54>0,FB$7),"") | FH54: =IFERROR(IF(FC54>0,FC$7),"") | FI54: =IFERROR(IF(FD54>0,FD$7),"") | FJ54: =FE54&FF54&FG54&FH54&FI54 | FK54: =IF(FJ54<>"",LEFT(FJ54,LEN(FJ54)-1),"") | FL54: =IF(FK54<>"",FK54&"として提供中","無") -> 無
AR55: 総計 | AS55: 247035 | AT55: 0 | AU55: 3737978 | AV55: 0 | AW55: 28530436 | AX55: 282415 | AY55: 809021 | AZ55: 2337093 | BB55: 35943978 | CO55: 126 | CP55: 150000 | CQ55: 33 | DF55: 400000-499999 | DG55: 1 | DH55: 413600 | EM55: プラウD目白301号 | ES55: 48 | ET55: AG | EU55: AE | EV55: 49 | EW55: {=INDIRECT("'5借入一覧'!"&ET55&EV55)&INDIRECT("'5借入一覧'!"&EU55&EV55)} | EX55: 1 | EY55: 48 | EZ55: =VLOOKUP($EY55&EZ$5,$EW$7:$EX$1101,2,FALSE) -> #N/A | FA55: =VLOOKUP($EY55&FA$5,$EW$7:$EX$1101,2,FALSE) -> #N/A | FB55: =VLOOKUP($EY55&FB$5,$EW$7:$EX$1101,2,FALSE) -> #N/A | FC55: =VLOOKUP($EY55&FC$5,$EW$7:$EX$1101,2,FALSE) -> #N/A | FD55: =VLOOKUP($EY55&FD$5,$EW$7:$EX$1101,2,FALSE) -> #N/A | FE55: =IFERROR(IF(EZ55>0,EZ$7),"") | FF55: =IFERROR(IF(FA55>0,FA$7),"") | FG55: =IFERROR(IF(FB55>0,FB$7),"") | FH55: =IFERROR(IF(FC55>0,FC$7),"") | FI55: =IFERROR(IF(FD55>0,FD$7),"") | FJ55: =FE55&FF55&FG55&FH55&FI55 | FK55: =IF(FJ55<>"",LEFT(FJ55,LEN(FJ55)-1),"") | FL55: =IF(FK55<>"",FK55&"として提供中","無") -> 無
CO56: 279 | CP56: 150000 | CQ56: 33 | DF56: アンテナ | EM56: 目白アパート1号2号_二棟一括 | ES56: 49 | ET56: AG | EU56: AE | EV56: 50 | EW56: {=INDIRECT("'5借入一覧'!"&ET56&EV56)&INDIRECT("'5借入一覧'!"&EU56&EV56)} | EX56: 1 | EY56: 49 | EZ56: =VLOOKUP($EY56&EZ$5,$EW$7:$EX$1101,2,FALSE) -> #N/A | FA56: =VLOOKUP($EY56&FA$5,$EW$7:$EX$1101,2,FALSE) -> #N/A | FB56: =VLOOKUP($EY56&FB$5,$EW$7:$EX$1101,2,FALSE) -> #N/A | FC56: =VLOOKUP($EY56&FC$5,$EW$7:$EX$1101,2,FALSE) -> #N/A | FD56: =VLOOKUP($EY56&FD$5,$EW$7:$EX$1101,2,FALSE) -> #N/A | FE56: =IFERROR(IF(EZ56>0,EZ$7),"") | FF56: =IFERROR(IF(FA56>0,FA$7),"") | FG56: =IFERROR(IF(FB56>0,FB$7),"") | FH56: =IFERROR(IF(FC56>0,FC$7),"") | FI56: =IFERROR(IF(FD56>0,FD$7),"") | FJ56: =FE56&FF56&FG56&FH56&FI56 | FK56: =IF(FJ56<>"",LEFT(FJ56,LEN(FJ56)-1),"") | FL56: =IF(FK56<>"",FK56&"として提供中","無") -> 無
CO57: 286 | CP57: 150000 | CQ57: 33 | DF57: その他 | EM57: 住宅ローン | EN57: 169657 | EO57: 221433 | EP57: 391090 | EQ57: 91457870 | ES57: 50 | ET57: AG | EU57: AE | EV57: 51 | EW57: {=INDIRECT("'5借入一覧'!"&ET57&EV57)&INDIRECT("'5借入一覧'!"&EU57&EV57)} | EX57: 1 | EY57: 50 | EZ57: =VLOOKUP($EY57&EZ$5,$EW$7:$EX$1101,2,FALSE) -> #N/A | FA57: =VLOOKUP($EY57&FA$5,$EW$7:$EX$1101,2,FALSE) -> #N/A | FB57: =VLOOKUP($EY57&FB$5,$EW$7:$EX$1101,2,FALSE) -> #N/A | FC57: =VLOOKUP($EY57&FC$5,$EW$7:$EX$1101,2,FALSE) -> #N/A | FD57: =VLOOKUP($EY57&FD$5,$EW$7:$EX$1101,2,FALSE) -> #N/A | FE57: =IFERROR(IF(EZ57>0,EZ$7),"") | FF57: =IFERROR(IF(FA57>0,FA$7),"") | FG57: =IFERROR(IF(FB57>0,FB$7),"") | FH57: =IFERROR(IF(FC57>0,FC$7),"") | FI57: =IFERROR(IF(FD57>0,FD$7),"") | FJ57: =FE57&FF57&FG57&FH57&FI57 | FK57: =IF(FJ57<>"",LEFT(FJ57,LEN(FJ57)-1),"") | FL57: =IF(FK57<>"",FK57&"として提供中","無") -> 無
CO58: 175 | CP58: 150000 | CQ58: 33 | DF58: 事務所 | EM58: あおばマンション | ES58: 51 | ET58: AG | EU58: AE | EV58: 52 | EW58: {=INDIRECT("'5借入一覧'!"&ET58&EV58)&INDIRECT("'5借入一覧'!"&EU58&EV58)} | EX58: 1 | EY58: 51 | EZ58: =VLOOKUP($EY58&EZ$5,$EW$7:$EX$1101,2,FALSE) -> #N/A | FA58: =VLOOKUP($EY58&FA$5,$EW$7:$EX$1101,2,FALSE) -> #N/A | FB58: =VLOOKUP($EY58&FB$5,$EW$7:$EX$1101,2,FALSE) -> #N/A | FC58: =VLOOKUP($EY58&FC$5,$EW$7:$EX$1101,2,FALSE) -> #N/A | FD58: =VLOOKUP($EY58&FD$5,$EW$7:$EX$1101,2,FALSE) -> #N/A | FE58: =IFERROR(IF(EZ58>0,EZ$7),"") | FF58: =IFERROR(IF(FA58>0,FA$7),"") | FG58: =IFERROR(IF(FB58>0,FB$7),"") | FH58: =IFERROR(IF(FC58>0,FC$7),"") | FI58: =IFERROR(IF(FD58>0,FD$7),"") | FJ58: =FE58&FF58&FG58&FH58&FI58 | FK58: =IF(FJ58<>"",LEFT(FJ58,LEN(FJ58)-1),"") | FL58: =IF(FK58<>"",FK58&"として提供中","無") -> 無
CO59: 123 | CP59: 150000 | CQ59: 33 | DF59: 自販機 | EM59: カーサ南池袋 | ES59: 52 | ET59: AG | EU59: AE | EV59: 53 | EW59: {=INDIRECT("'5借入一覧'!"&ET59&EV59)&INDIRECT("'5借入一覧'!"&EU59&EV59)} | EX59: 1 | EY59: 52 | EZ59: =VLOOKUP($EY59&EZ$5,$EW$7:$EX$1101,2,FALSE) -> #N/A | FA59: =VLOOKUP($EY59&FA$5,$EW$7:$EX$1101,2,FALSE) -> #N/A | FB59: =VLOOKUP($EY59&FB$5,$EW$7:$EX$1101,2,FALSE) -> #N/A | FC59: =VLOOKUP($EY59&FC$5,$EW$7:$EX$1101,2,FALSE) -> #N/A | FD59: =VLOOKUP($EY59&FD$5,$EW$7:$EX$1101,2,FALSE) -> #N/A | FE59: =IFERROR(IF(EZ59>0,EZ$7),"") | FF59: =IFERROR(IF(FA59>0,FA$7),"") | FG59: =IFERROR(IF(FB59>0,FB$7),"") | FH59: =IFERROR(IF(FC59>0,FC$7),"") | FI59: =IFERROR(IF(FD59>0,FD$7),"") | FJ59: =FE59&FF59&FG59&FH59&FI59 | FK59: =IF(FJ59<>"",LEFT(FJ59,LEN(FJ59)-1),"") | FL59: =IF(FK59<>"",FK59&"として提供中","無") -> 無
CO60: 177 | CP60: 150000 | CQ60: 33 | DF60: 倉庫 | EM60: カーサ目白台ハウス | ES60: 53 | ET60: AG | EU60: AE | EV60: 54 | EW60: {=INDIRECT("'5借入一覧'!"&ET60&EV60)&INDIRECT("'5借入一覧'!"&EU60&EV60)} | EX60: 1 | EY60: 53 | EZ60: =VLOOKUP($EY60&EZ$5,$EW$7:$EX$1101,2,FALSE) -> #N/A | FA60: =VLOOKUP($EY60&FA$5,$EW$7:$EX$1101,2,FALSE) -> #N/A | FB60: =VLOOKUP($EY60&FB$5,$EW$7:$EX$1101,2,FALSE) -> #N/A | FC60: =VLOOKUP($EY60&FC$5,$EW$7:$EX$1101,2,FALSE) -> #N/A | FD60: =VLOOKUP($EY60&FD$5,$EW$7:$EX$1101,2,FALSE) -> #N/A | FE60: =IFERROR(IF(EZ60>0,EZ$7),"") | FF60: =IFERROR(IF(FA60>0,FA$7),"") | FG60: =IFERROR(IF(FB60>0,FB$7),"") | FH60: =IFERROR(IF(FC60>0,FC$7),"") | FI60: =IFERROR(IF(FD60>0,FD$7),"") | FJ60: =FE60&FF60&FG60&FH60&FI60 | FK60: =IF(FJ60<>"",LEFT(FJ60,LEN(FJ60)-1),"") | FL60: =IF(FK60<>"",FK60&"として提供中","無") -> 無
CO61: 133 | CP61: 150000 | CQ61: 33 | DF61: 駐車場 | EM61: コアプラスレジデンス梅田 | ES61: 54 | ET61: AG | EU61: AE | EV61: 55 | EW61: {=INDIRECT("'5借入一覧'!"&ET61&EV61)&INDIRECT("'5借入一覧'!"&EU61&EV61)} | EX61: 1 | EY61: 54 | EZ61: =VLOOKUP($EY61&EZ$5,$EW$7:$EX$1101,2,FALSE) -> #N/A | FA61: =VLOOKUP($EY61&FA$5,$EW$7:$EX$1101,2,FALSE) -> #N/A | FB61: =VLOOKUP($EY61&FB$5,$EW$7:$EX$1101,2,FALSE) -> #N/A | FC61: =VLOOKUP($EY61&FC$5,$EW$7:$EX$1101,2,FALSE) -> #N/A | FD61: =VLOOKUP($EY61&FD$5,$EW$7:$EX$1101,2,FALSE) -> #N/A | FE61: =IFERROR(IF(EZ61>0,EZ$7),"") | FF61: =IFERROR(IF(FA61>0,FA$7),"") | FG61: =IFERROR(IF(FB61>0,FB$7),"") | FH61: =IFERROR(IF(FC61>0,FC$7),"") | FI61: =IFERROR(IF(FD61>0,FD$7),"") | FJ61: =FE61&FF61&FG61&FH61&FI61 | FK61: =IF(FJ61<>"",LEFT(FJ61,LEN(FJ61)-1),"") | FL61: =IF(FK61<>"",FK61&"として提供中","無") -> 無
CO62: 282 | CP62: 148000 | CQ62: 34 | DF62: 店舗 | DG62: 1 | DH62: 413600 | EM62: コアプラス大塚 | ES62: 55 | ET62: AG | EU62: AE | EV62: 56 | EW62: {=INDIRECT("'5借入一覧'!"&ET62&EV62)&INDIRECT("'5借入一覧'!"&EU62&EV62)} | EX62: 1 | EY62: 55 | EZ62: =VLOOKUP($EY62&EZ$5,$EW$7:$EX$1101,2,FALSE) -> #N/A | FA62: =VLOOKUP($EY62&FA$5,$EW$7:$EX$1101,2,FALSE) -> #N/A | FB62: =VLOOKUP($EY62&FB$5,$EW$7:$EX$1101,2,FALSE) -> #N/A | FC62: =VLOOKUP($EY62&FC$5,$EW$7:$EX$1101,2,FALSE) -> #N/A | FD62: =VLOOKUP($EY62&FD$5,$EW$7:$EX$1101,2,FALSE) -> #N/A | FE62: =IFERROR(IF(EZ62>0,EZ$7),"") | FF62: =IFERROR(IF(FA62>0,FA$7),"") | FG62: =IFERROR(IF(FB62>0,FB$7),"") | FH62: =IFERROR(IF(FC62>0,FC$7),"") | FI62: =IFERROR(IF(FD62>0,FD$7),"") | FJ62: =FE62&FF62&FG62&FH62&FI62 | FK62: =IF(FJ62<>"",LEFT(FJ62,LEN(FJ62)-1),"") | FL62: =IF(FK62<>"",FK62&"として提供中","無") -> 無
CO63: 128 | CP63: 145000 | CQ63: 35 | DF63: (空白) | EM63: コアプラス池袋 | ES63: 56 | ET63: AG | EU63: AE | EV63: 57 | EW63: {=INDIRECT("'5借入一覧'!"&ET63&EV63)&INDIRECT("'5借入一覧'!"&EU63&EV63)} | EX63: 1 | EY63: 56 | EZ63: =VLOOKUP($EY63&EZ$5,$EW$7:$EX$1101,2,FALSE) -> #N/A | FA63: =VLOOKUP($EY63&FA$5,$EW$7:$EX$1101,2,FALSE) -> #N/A | FB63: =VLOOKUP($EY63&FB$5,$EW$7:$EX$1101,2,FALSE) -> #N/A | FC63: =VLOOKUP($EY63&FC$5,$EW$7:$EX$1101,2,FALSE) -> #N/A | FD63: =VLOOKUP($EY63&FD$5,$EW$7:$EX$1101,2,FALSE) -> #N/A | FE63: =IFERROR(IF(EZ63>0,EZ$7),"") | FF63: =IFERROR(IF(FA63>0,FA$7),"") | FG63: =IFERROR(IF(FB63>0,FB$7),"") | FH63: =IFERROR(IF(FC63>0,FC$7),"") | FI63: =IFERROR(IF(FD63>0,FD$7),"") | FJ63: =FE63&FF63&FG63&FH63&FI63 | FK63: =IF(FJ63<>"",LEFT(FJ63,LEN(FJ63)-1),"") | FL63: =IF(FK63<>"",FK63&"として提供中","無") -> 無
CO64: 284 | CP64: 145000 | CQ64: 35 | DF64: 500000-599999 | EM64: メゾン雑司ヶ谷 | ES64: 57 | ET64: AG | EU64: AE | EV64: 58 | EW64: {=INDIRECT("'5借入一覧'!"&ET64&EV64)&INDIRECT("'5借入一覧'!"&EU64&EV64)} | EX64: 1 | EY64: 57 | EZ64: =VLOOKUP($EY64&EZ$5,$EW$7:$EX$1101,2,FALSE) -> #N/A | FA64: =VLOOKUP($EY64&FA$5,$EW$7:$EX$1101,2,FALSE) -> #N/A | FB64: =VLOOKUP($EY64&FB$5,$EW$7:$EX$1101,2,FALSE) -> #N/A | FC64: =VLOOKUP($EY64&FC$5,$EW$7:$EX$1101,2,FALSE) -> #N/A | FD64: =VLOOKUP($EY64&FD$5,$EW$7:$EX$1101,2,FALSE) -> #N/A | FE64: =IFERROR(IF(EZ64>0,EZ$7),"") | FF64: =IFERROR(IF(FA64>0,FA$7),"") | FG64: =IFERROR(IF(FB64>0,FB$7),"") | FH64: =IFERROR(IF(FC64>0,FC$7),"") | FI64: =IFERROR(IF(FD64>0,FD$7),"") | FJ64: =FE64&FF64&FG64&FH64&FI64 | FK64: =IF(FJ64<>"",LEFT(FJ64,LEN(FJ64)-1),"") | FL64: =IF(FK64<>"",FK64&"として提供中","無") -> 無
CO65: 173 | CP65: 145000 | CQ65: 35 | DF65: アンテナ | EM65: レジデンス目白豊島 | ES65: 58 | ET65: AG | EU65: AE | EV65: 59 | EW65: {=INDIRECT("'5借入一覧'!"&ET65&EV65)&INDIRECT("'5借入一覧'!"&EU65&EV65)} | EX65: 1 | EY65: 58 | EZ65: =VLOOKUP($EY65&EZ$5,$EW$7:$EX$1101,2,FALSE) -> #N/A | FA65: =VLOOKUP($EY65&FA$5,$EW$7:$EX$1101,2,FALSE) -> #N/A | FB65: =VLOOKUP($EY65&FB$5,$EW$7:$EX$1101,2,FALSE) -> #N/A | FC65: =VLOOKUP($EY65&FC$5,$EW$7:$EX$1101,2,FALSE) -> #N/A | FD65: =VLOOKUP($EY65&FD$5,$EW$7:$EX$1101,2,FALSE) -> #N/A | FE65: =IFERROR(IF(EZ65>0,EZ$7),"") | FF65: =IFERROR(IF(FA65>0,FA$7),"") | FG65: =IFERROR(IF(FB65>0,FB$7),"") | FH65: =IFERROR(IF(FC65>0,FC$7),"") | FI65: =IFERROR(IF(FD65>0,FD$7),"") | FJ65: =FE65&FF65&FG65&FH65&FI65 | FK65: =IF(FJ65<>"",LEFT(FJ65,LEN(FJ65)-1),"") | FL65: =IF(FK65<>"",FK65&"として提供中","無") -> 無
CO66: 74 | CP66: 140000 | CQ66: 36 | DF66: その他 | EM66: 高田馬場第4玉川ビル | ES66: 59 | ET66: AG | EU66: AE | EV66: 60 | EW66: {=INDIRECT("'5借入一覧'!"&ET66&EV66)&INDIRECT("'5借入一覧'!"&EU66&EV66)} | EX66: 1 | EY66: 59 | EZ66: =VLOOKUP($EY66&EZ$5,$EW$7:$EX$1101,2,FALSE) -> #N/A | FA66: =VLOOKUP($EY66&FA$5,$EW$7:$EX$1101,2,FALSE) -> #N/A | FB66: =VLOOKUP($EY66&FB$5,$EW$7:$EX$1101,2,FALSE) -> #N/A | FC66: =VLOOKUP($EY66&FC$5,$EW$7:$EX$1101,2,FALSE) -> #N/A | FD66: =VLOOKUP($EY66&FD$5,$EW$7:$EX$1101,2,FALSE) -> #N/A | FE66: =IFERROR(IF(EZ66>0,EZ$7),"") | FF66: =IFERROR(IF(FA66>0,FA$7),"") | FG66: =IFERROR(IF(FB66>0,FB$7),"") | FH66: =IFERROR(IF(FC66>0,FC$7),"") | FI66: =IFERROR(IF(FD66>0,FD$7),"") | FJ66: =FE66&FF66&FG66&FH66&FI66 | FK66: =IF(FJ66<>"",LEFT(FJ66,LEN(FJ66)-1),"") | FL66: =IF(FK66<>"",FK66&"として提供中","無") -> 無
CO67: 290 | CP67: 140000 | CQ67: 36 | DF67: 事務所 | EM67: 西池袋駅前ビル | ES67: 60 | ET67: AG | EU67: AE | EV67: 61 | EW67: {=INDIRECT("'5借入一覧'!"&ET67&EV67)&INDIRECT("'5借入一覧'!"&EU67&EV67)} | EX67: 1 | EY67: 60 | EZ67: =VLOOKUP($EY67&EZ$5,$EW$7:$EX$1101,2,FALSE) -> #N/A | FA67: =VLOOKUP($EY67&FA$5,$EW$7:$EX$1101,2,FALSE) -> #N/A | FB67: =VLOOKUP($EY67&FB$5,$EW$7:$EX$1101,2,FALSE) -> #N/A | FC67: =VLOOKUP($EY67&FC$5,$EW$7:$EX$1101,2,FALSE) -> #N/A | FD67: =VLOOKUP($EY67&FD$5,$EW$7:$EX$1101,2,FALSE) -> #N/A | FE67: =IFERROR(IF(EZ67>0,EZ$7),"") | FF67: =IFERROR(IF(FA67>0,FA$7),"") | FG67: =IFERROR(IF(FB67>0,FB$7),"") | FH67: =IFERROR(IF(FC67>0,FC$7),"") | FI67: =IFERROR(IF(FD67>0,FD$7),"") | FJ67: =FE67&FF67&FG67&FH67&FI67 | FK67: =IF(FJ67<>"",LEFT(FJ67,LEN(FJ67)-1),"") | FL67: =IF(FK67<>"",FK67&"として提供中","無") -> 無
CO68: 312 | CP68: 140000 | CQ68: 36 | DF68: 自販機 | EM68: 仙台駅前コーポ | ES68: 61 | ET68: AG | EU68: AE | EV68: 62 | EW68: {=INDIRECT("'5借入一覧'!"&ET68&EV68)&INDIRECT("'5借入一覧'!"&EU68&EV68)} | EX68: 1 | EY68: 61 | EZ68: =VLOOKUP($EY68&EZ$5,$EW$7:$EX$1101,2,FALSE) -> #N/A | FA68: =VLOOKUP($EY68&FA$5,$EW$7:$EX$1101,2,FALSE) -> #N/A | FB68: =VLOOKUP($EY68&FB$5,$EW$7:$EX$1101,2,FALSE) -> #N/A | FC68: =VLOOKUP($EY68&FC$5,$EW$7:$EX$1101,2,FALSE) -> #N/A | FD68: =VLOOKUP($EY68&FD$5,$EW$7:$EX$1101,2,FALSE) -> #N/A | FE68: =IFERROR(IF(EZ68>0,EZ$7),"") | FF68: =IFERROR(IF(FA68>0,FA$7),"") | FG68: =IFERROR(IF(FB68>0,FB$7),"") | FH68: =IFERROR(IF(FC68>0,FC$7),"") | FI68: =IFERROR(IF(FD68>0,FD$7),"") | FJ68: =FE68&FF68&FG68&FH68&FI68 | FK68: =IF(FJ68<>"",LEFT(FJ68,LEN(FJ68)-1),"") | FL68: =IF(FK68<>"",FK68&"として提供中","無") -> 無
CO69: 288 | CP69: 140000 | CQ69: 36 | DF69: 住居 | EM69: 対象物件なし(運転資金) | ES69: 62 | ET69: AG | EU69: AE | EV69: 63 | EW69: {=INDIRECT("'5借入一覧'!"&ET69&EV69)&INDIRECT("'5借入一覧'!"&EU69&EV69)} | EX69: 1 | EY69: 62 | EZ69: =VLOOKUP($EY69&EZ$5,$EW$7:$EX$1101,2,FALSE) -> #N/A | FA69: =VLOOKUP($EY69&FA$5,$EW$7:$EX$1101,2,FALSE) -> #N/A | FB69: =VLOOKUP($EY69&FB$5,$EW$7:$EX$1101,2,FALSE) -> #N/A | FC69: =VLOOKUP($EY69&FC$5,$EW$7:$EX$1101,2,FALSE) -> #N/A | FD69: =VLOOKUP($EY69&FD$5,$EW$7:$EX$1101,2,FALSE) -> #N/A | FE69: =IFERROR(IF(EZ69>0,EZ$7),"") | FF69: =IFERROR(IF(FA69>0,FA$7),"") | FG69: =IFERROR(IF(FB69>0,FB$7),"") | FH69: =IFERROR(IF(FC69>0,FC$7),"") | FI69: =IFERROR(IF(FD69>0,FD$7),"") | FJ69: =FE69&FF69&FG69&FH69&FI69 | FK69: =IF(FJ69<>"",LEFT(FJ69,LEN(FJ69)-1),"") | FL69: =IF(FK69<>"",FK69&"として提供中","無") -> 無
CO70: 89 | CP70: 139000 | CQ70: 37 | DF70: 倉庫 | EM70: 第3目白ハイツ | ES70: 63 | ET70: AG | EU70: AE | EV70: 64 | EW70: {=INDIRECT("'5借入一覧'!"&ET70&EV70)&INDIRECT("'5借入一覧'!"&EU70&EV70)} | EX70: 1 | EY70: 63 | EZ70: =VLOOKUP($EY70&EZ$5,$EW$7:$EX$1101,2,FALSE) -> #N/A | FA70: =VLOOKUP($EY70&FA$5,$EW$7:$EX$1101,2,FALSE) -> #N/A | FB70: =VLOOKUP($EY70&FB$5,$EW$7:$EX$1101,2,FALSE) -> #N/A | FC70: =VLOOKUP($EY70&FC$5,$EW$7:$EX$1101,2,FALSE) -> #N/A | FD70: =VLOOKUP($EY70&FD$5,$EW$7:$EX$1101,2,FALSE) -> #N/A | FE70: =IFERROR(IF(EZ70>0,EZ$7),"") | FF70: =IFERROR(IF(FA70>0,FA$7),"") | FG70: =IFERROR(IF(FB70>0,FB$7),"") | FH70: =IFERROR(IF(FC70>0,FC$7),"") | FI70: =IFERROR(IF(FD70>0,FD$7),"") | FJ70: =FE70&FF70&FG70&FH70&FI70 | FK70: =IF(FJ70<>"",LEFT(FJ70,LEN(FJ70)-1),"") | FL70: =IF(FK70<>"",FK70&"として提供中","無") -> 無
CO71: 272 | CP71: 139000 | CQ71: 37 | DF71: 駐車場 | EM71: 池袋ハウス | ES71: 64 | ET71: AG | EU71: AE | EV71: 65 | EW71: {=INDIRECT("'5借入一覧'!"&ET71&EV71)&INDIRECT("'5借入一覧'!"&EU71&EV71)} | EX71: 1 | EY71: 64 | EZ71: =VLOOKUP($EY71&EZ$5,$EW$7:$EX$1101,2,FALSE) -> #N/A | FA71: =VLOOKUP($EY71&FA$5,$EW$7:$EX$1101,2,FALSE) -> #N/A | FB71: =VLOOKUP($EY71&FB$5,$EW$7:$EX$1101,2,FALSE) -> #N/A | FC71: =VLOOKUP($EY71&FC$5,$EW$7:$EX$1101,2,FALSE) -> #N/A | FD71: =VLOOKUP($EY71&FD$5,$EW$7:$EX$1101,2,FALSE) -> #N/A | FE71: =IFERROR(IF(EZ71>0,EZ$7),"") | FF71: =IFERROR(IF(FA71>0,FA$7),"") | FG71: =IFERROR(IF(FB71>0,FB$7),"") | FH71: =IFERROR(IF(FC71>0,FC$7),"") | FI71: =IFERROR(IF(FD71>0,FD$7),"") | FJ71: =FE71&FF71&FG71&FH71&FI71 | FK71: =IF(FJ71<>"",LEFT(FJ71,LEN(FJ71)-1),"") | FL71: =IF(FK71<>"",FK71&"として提供中","無") -> 無
CO72: 263 | CP72: 137000 | CQ72: 38 | DF72: 店舗 | EM72: 東池袋ハイツ | ES72: 65 | ET72: AG | EU72: AE | EV72: 66 | EW72: {=INDIRECT("'5借入一覧'!"&ET72&EV72)&INDIRECT("'5借入一覧'!"&EU72&EV72)} | EX72: 1 | EY72: 65 | EZ72: =VLOOKUP($EY72&EZ$5,$EW$7:$EX$1101,2,FALSE) -> #N/A | FA72: =VLOOKUP($EY72&FA$5,$EW$7:$EX$1101,2,FALSE) -> #N/A | FB72: =VLOOKUP($EY72&FB$5,$EW$7:$EX$1101,2,FALSE) -> #N/A | FC72: =VLOOKUP($EY72&FC$5,$EW$7:$EX$1101,2,FALSE) -> #N/A | FD72: =VLOOKUP($EY72&FD$5,$EW$7:$EX$1101,2,FALSE) -> #N/A | FE72: =IFERROR(IF(EZ72>0,EZ$7),"") | FF72: =IFERROR(IF(FA72>0,FA$7),"") | FG72: =IFERROR(IF(FB72>0,FB$7),"") | FH72: =IFERROR(IF(FC72>0,FC$7),"") | FI72: =IFERROR(IF(FD72>0,FD$7),"") | FJ72: =FE72&FF72&FG72&FH72&FI72 | FK72: =IF(FJ72<>"",LEFT(FJ72,LEN(FJ72)-1),"") | FL72: =IF(FK72<>"",FK72&"として提供中","無") -> 無
CO73: 264 | CP73: 137000 | CQ73: 38 | DF73: (空白) | EM73: 南池袋マンション | ES73: 66 | ET73: AG | EU73: AE | EV73: 67 | EW73: {=INDIRECT("'5借入一覧'!"&ET73&EV73)&INDIRECT("'5借入一覧'!"&EU73&EV73)} | EX73: 1 | EY73: 66 | EZ73: =VLOOKUP($EY73&EZ$5,$EW$7:$EX$1101,2,FALSE) -> #N/A | FA73: =VLOOKUP($EY73&FA$5,$EW$7:$EX$1101,2,FALSE) -> #N/A | FB73: =VLOOKUP($EY73&FB$5,$EW$7:$EX$1101,2,FALSE) -> #N/A | FC73: =VLOOKUP($EY73&FC$5,$EW$7:$EX$1101,2,FALSE) -> #N/A | FD73: =VLOOKUP($EY73&FD$5,$EW$7:$EX$1101,2,FALSE) -> #N/A | FE73: =IFERROR(IF(EZ73>0,EZ$7),"") | FF73: =IFERROR(IF(FA73>0,FA$7),"") | FG73: =IFERROR(IF(FB73>0,FB$7),"") | FH73: =IFERROR(IF(FC73>0,FC$7),"") | FI73: =IFERROR(IF(FD73>0,FD$7),"") | FJ73: =FE73&FF73&FG73&FH73&FI73 | FK73: =IF(FJ73<>"",LEFT(FJ73,LEN(FJ73)-1),"") | FL73: =IF(FK73<>"",FK73&"として提供中","無") -> 無
CO74: 266 | CP74: 137000 | CQ74: 38 | DF74: 600000-699999 | EM74: 豊島目白ビル | ES74: 67 | ET74: AG | EU74: AE | EV74: 68 | EW74: {=INDIRECT("'5借入一覧'!"&ET74&EV74)&INDIRECT("'5借入一覧'!"&EU74&EV74)} | EX74: 1 | EY74: 67 | EZ74: =VLOOKUP($EY74&EZ$5,$EW$7:$EX$1101,2,FALSE) -> #N/A | FA74: =VLOOKUP($EY74&FA$5,$EW$7:$EX$1101,2,FALSE) -> #N/A | FB74: =VLOOKUP($EY74&FB$5,$EW$7:$EX$1101,2,FALSE) -> #N/A | FC74: =VLOOKUP($EY74&FC$5,$EW$7:$EX$1101,2,FALSE) -> #N/A | FD74: =VLOOKUP($EY74&FD$5,$EW$7:$EX$1101,2,FALSE) -> #N/A | FE74: =IFERROR(IF(EZ74>0,EZ$7),"") | FF74: =IFERROR(IF(FA74>0,FA$7),"") | FG74: =IFERROR(IF(FB74>0,FB$7),"") | FH74: =IFERROR(IF(FC74>0,FC$7),"") | FI74: =IFERROR(IF(FD74>0,FD$7),"") | FJ74: =FE74&FF74&FG74&FH74&FI74 | FK74: =IF(FJ74<>"",LEFT(FJ74,LEN(FJ74)-1),"") | FL74: =IF(FK74<>"",FK74&"として提供中","無") -> 無
... CO78: 130 | CP78: 135000 | CQ78: 39 | DF78: 自販機 | EM78: 目白アパート1号館 | ES78: 71 | ET78: AG | EU78: AE | EV78: 72 | EW78: {=INDIRECT("'5借入一覧'!"&ET78&EV78)&INDIRECT("'5借入一覧'!"&EU78&EV78)} | EX78: 1 | EY78: 71 | EZ78: =VLOOKUP($EY78&EZ$5,$EW$7:$EX$1101,2,FALSE) -> #N/A | FA78: =VLOOKUP($EY78&FA$5,$EW$7:$EX$1101,2,FALSE) -> #N/A | FB78: =VLOOKUP($EY78&FB$5,$EW$7:$EX$1101,2,FALSE) -> #N/A | FC78: =VLOOKUP($EY78&FC$5,$EW$7:$EX$1101,2,FALSE) -> #N/A | FD78: =VLOOKUP($EY78&FD$5,$EW$7:$EX$1101,2,FALSE) -> #N/A | FE78: =IFERROR(IF(EZ78>0,EZ$7),"") | FF78: =IFERROR(IF(FA78>0,FA$7),"") | FG78: =IFERROR(IF(FB78>0,FB$7),"") | FH78: =IFERROR(IF(FC78>0,FC$7),"") | FI78: =IFERROR(IF(FD78>0,FD$7),"") | FJ78: =FE78&FF78&FG78&FH78&FI78 | FK78: =IF(FJ78<>"",LEFT(FJ78,LEN(FJ78)-1),"") | FL78: =IF(FK78<>"",FK78&"として提供中","無") -> 無
CO79: 268 | CP79: 135000 | CQ79: 39 | DF79: 住居 | EM79: プラウD目白301号 | EN79: 169657 | EO79: 221433 | EP79: 391090 | EQ79: 91457870 | ES79: 72 | ET79: AG | EU79: AE | EV79: 73 | EW79: {=INDIRECT("'5借入一覧'!"&ET79&EV79)&INDIRECT("'5借入一覧'!"&EU79&EV79)} | EX79: 1 | EY79: 72 | EZ79: =VLOOKUP($EY79&EZ$5,$EW$7:$EX$1101,2,FALSE) -> #N/A | FA79: =VLOOKUP($EY79&FA$5,$EW$7:$EX$1101,2,FALSE) -> #N/A | FB79: =VLOOKUP($EY79&FB$5,$EW$7:$EX$1101,2,FALSE) -> #N/A | FC79: =VLOOKUP($EY79&FC$5,$EW$7:$EX$1101,2,FALSE) -> #N/A | FD79: =VLOOKUP($EY79&FD$5,$EW$7:$EX$1101,2,FALSE) -> #N/A | FE79: =IFERROR(IF(EZ79>0,EZ$7),"") | FF79: =IFERROR(IF(FA79>0,FA$7),"") | FG79: =IFERROR(IF(FB79>0,FB$7),"") | FH79: =IFERROR(IF(FC79>0,FC$7),"") | FI79: =IFERROR(IF(FD79>0,FD$7),"") | FJ79: =FE79&FF79&FG79&FH79&FI79 | FK79: =IF(FJ79<>"",LEFT(FJ79,LEN(FJ79)-1),"") | FL79: =IF(FK79<>"",FK79&"として提供中","無") -> 無
CO80: 132 | CP80: 135000 | CQ80: 39 | DF80: 倉庫 | EM80: 目白アパート1号2号_二棟一括 | ES80: 73 | ET80: AG | EU80: AE | EV80: 74 | EW80: {=INDIRECT("'5借入一覧'!"&ET80&EV80)&INDIRECT("'5借入一覧'!"&EU80&EV80)} | EX80: 1 | EY80: 73 | EZ80: =VLOOKUP($EY80&EZ$5,$EW$7:$EX$1101,2,FALSE) -> #N/A | FA80: =VLOOKUP($EY80&FA$5,$EW$7:$EX$1101,2,FALSE) -> #N/A | FB80: =VLOOKUP($EY80&FB$5,$EW$7:$EX$1101,2,FALSE) -> #N/A | FC80: =VLOOKUP($EY80&FC$5,$EW$7:$EX$1101,2,FALSE) -> #N/A | FD80: =VLOOKUP($EY80&FD$5,$EW$7:$EX$1101,2,FALSE) -> #N/A | FE80: =IFERROR(IF(EZ80>0,EZ$7),"") | FF80: =IFERROR(IF(FA80>0,FA$7),"") | FG80: =IFERROR(IF(FB80>0,FB$7),"") | FH80: =IFERROR(IF(FC80>0,FC$7),"") | FI80: =IFERROR(IF(FD80>0,FD$7),"") | FJ80: =FE80&FF80&FG80&FH80&FI80 | FK80: =IF(FJ80<>"",LEFT(FJ80,LEN(FJ80)-1),"") | FL80: =IF(FK80<>"",FK80&"として提供中","無") -> 無
CO81: 273 | CP81: 135000 | CQ81: 39 | DF81: 駐車場 | EM81: 親族借入 | EN81: 0 | EO81: 0 | EP81: 0 | EQ81: 2000000 | ES81: 74 | ET81: AG | EU81: AE | EV81: 75 | EW81: {=INDIRECT("'5借入一覧'!"&ET81&EV81)&INDIRECT("'5借入一覧'!"&EU81&EV81)} | EX81: 1 | EY81: 74 | EZ81: =VLOOKUP($EY81&EZ$5,$EW$7:$EX$1101,2,FALSE) -> #N/A | FA81: =VLOOKUP($EY81&FA$5,$EW$7:$EX$1101,2,FALSE) -> #N/A | FB81: =VLOOKUP($EY81&FB$5,$EW$7:$EX$1101,2,FALSE) -> #N/A | FC81: =VLOOKUP($EY81&FC$5,$EW$7:$EX$1101,2,FALSE) -> #N/A | FD81: =VLOOKUP($EY81&FD$5,$EW$7:$EX$1101,2,FALSE) -> #N/A | FE81: =IFERROR(IF(EZ81>0,EZ$7),"") | FF81: =IFERROR(IF(FA81>0,FA$7),"") | FG81: =IFERROR(IF(FB81>0,FB$7),"") | FH81: =IFERROR(IF(FC81>0,FC$7),"") | FI81: =IFERROR(IF(FD81>0,FD$7),"") | FJ81: =FE81&FF81&FG81&FH81&FI81 | FK81: =IF(FJ81<>"",LEFT(FJ81,LEN(FJ81)-1),"") | FL81: =IF(FK81<>"",FK81&"として提供中","無") -> 無
CO82: 220 | CP82: 135000 | CQ82: 39 | DF82: 店舗 | EM82: あおばマンション | ES82: 75 | ET82: AG | EU82: AE | EV82: 76 | EW82: {=INDIRECT("'5借入一覧'!"&ET82&EV82)&INDIRECT("'5借入一覧'!"&EU82&EV82)} | EX82: 1 | EY82: 75 | EZ82: =VLOOKUP($EY82&EZ$5,$EW$7:$EX$1101,2,FALSE) -> #N/A | FA82: =VLOOKUP($EY82&FA$5,$EW$7:$EX$1101,2,FALSE) -> #N/A | FB82: =VLOOKUP($EY82&FB$5,$EW$7:$EX$1101,2,FALSE) -> #N/A | FC82: =VLOOKUP($EY82&FC$5,$EW$7:$EX$1101,2,FALSE) -> #N/A | FD82: =VLOOKUP($EY82&FD$5,$EW$7:$EX$1101,2,FALSE) -> #N/A | FE82: =IFERROR(IF(EZ82>0,EZ$7),"") | FF82: =IFERROR(IF(FA82>0,FA$7),"") | FG82: =IFERROR(IF(FB82>0,FB$7),"") | FH82: =IFERROR(IF(FC82>0,FC$7),"") | FI82: =IFERROR(IF(FD82>0,FD$7),"") | FJ82: =FE82&FF82&FG82&FH82&FI82 | FK82: =IF(FJ82<>"",LEFT(FJ82,LEN(FJ82)-1),"") | FL82: =IF(FK82<>"",FK82&"として提供中","無") -> 無
CO83: 106 | CP83: 135000 | CQ83: 39 | DF83: (空白) | EM83: カーサ南池袋 | ES83: 76 | ET83: AG | EU83: AE | EV83: 77 | EW83: {=INDIRECT("'5借入一覧'!"&ET83&EV83)&INDIRECT("'5借入一覧'!"&EU83&EV83)} | EX83: 1 | EY83: 76 | EZ83: =VLOOKUP($EY83&EZ$5,$EW$7:$EX$1101,2,FALSE) -> #N/A | FA83: =VLOOKUP($EY83&FA$5,$EW$7:$EX$1101,2,FALSE) -> #N/A | FB83: =VLOOKUP($EY83&FB$5,$EW$7:$EX$1101,2,FALSE) -> #N/A | FC83: =VLOOKUP($EY83&FC$5,$EW$7:$EX$1101,2,FALSE) -> #N/A | FD83: =VLOOKUP($EY83&FD$5,$EW$7:$EX$1101,2,FALSE) -> #N/A | FE83: =IFERROR(IF(EZ83>0,EZ$7),"") | FF83: =IFERROR(IF(FA83>0,FA$7),"") | FG83: =IFERROR(IF(FB83>0,FB$7),"") | FH83: =IFERROR(IF(FC83>0,FC$7),"") | FI83: =IFERROR(IF(FD83>0,FD$7),"") | FJ83: =FE83&FF83&FG83&FH83&FI83 | FK83: =IF(FJ83<>"",LEFT(FJ83,LEN(FJ83)-1),"") | FL83: =IF(FK83<>"",FK83&"として提供中","無") -> 無
CO84: 219 | CP84: 135000 | CQ84: 39 | DF84: 700000-799999 | EM84: カーサ目白台ハウス | ES84: 77 | ET84: AG | EU84: AE | EV84: 78 | EW84: {=INDIRECT("'5借入一覧'!"&ET84&EV84)&INDIRECT("'5借入一覧'!"&EU84&EV84)} | EX84: 1 | EY84: 77 | EZ84: =VLOOKUP($EY84&EZ$5,$EW$7:$EX$1101,2,FALSE) -> #N/A | FA84: =VLOOKUP($EY84&FA$5,$EW$7:$EX$1101,2,FALSE) -> #N/A | FB84: =VLOOKUP($EY84&FB$5,$EW$7:$EX$1101,2,FALSE) -> #N/A | FC84: =VLOOKUP($EY84&FC$5,$EW$7:$EX$1101,2,FALSE) -> #N/A | FD84: =VLOOKUP($EY84&FD$5,$EW$7:$EX$1101,2,FALSE) -> #N/A | FE84: =IFERROR(IF(EZ84>0,EZ$7),"") | FF84: =IFERROR(IF(FA84>0,FA$7),"") | FG84: =IFERROR(IF(FB84>0,FB$7),"") | FH84: =IFERROR(IF(FC84>0,FC$7),"") | FI84: =IFERROR(IF(FD84>0,FD$7),"") | FJ84: =FE84&FF84&FG84&FH84&FI84 | FK84: =IF(FJ84<>"",LEFT(FJ84,LEN(FJ84)-1),"") | FL84: =IF(FK84<>"",FK84&"として提供中","無") -> 無
CO85: 124 | CP85: 134000 | CQ85: 40 | DF85: アンテナ | EM85: コアプラスレジデンス梅田 | ES85: 78 | ET85: AG | EU85: AE | EV85: 79 | EW85: {=INDIRECT("'5借入一覧'!"&ET85&EV85)&INDIRECT("'5借入一覧'!"&EU85&EV85)} | EX85: 1 | EY85: 78 | EZ85: =VLOOKUP($EY85&EZ$5,$EW$7:$EX$1101,2,FALSE) -> #N/A | FA85: =VLOOKUP($EY85&FA$5,$EW$7:$EX$1101,2,FALSE) -> #N/A | FB85: =VLOOKUP($EY85&FB$5,$EW$7:$EX$1101,2,FALSE) -> #N/A | FC85: =VLOOKUP($EY85&FC$5,$EW$7:$EX$1101,2,FALSE) -> #N/A | FD85: =VLOOKUP($EY85&FD$5,$EW$7:$EX$1101,2,FALSE) -> #N/A | FE85: =IFERROR(IF(EZ85>0,EZ$7),"") | FF85: =IFERROR(IF(FA85>0,FA$7),"") | FG85: =IFERROR(IF(FB85>0,FB$7),"") | FH85: =IFERROR(IF(FC85>0,FC$7),"") | FI85: =IFERROR(IF(FD85>0,FD$7),"") | FJ85: =FE85&FF85&FG85&FH85&FI85 | FK85: =IF(FJ85<>"",LEFT(FJ85,LEN(FJ85)-1),"") | FL85: =IF(FK85<>"",FK85&"として提供中","無") -> 無
CO86: 271 | CP86: 134000 | CQ86: 40 | DF86: その他 | EM86: コアプラス大塚 | ES86: 79 | ET86: AG | EU86: AE | EV86: 80 | EW86: {=INDIRECT("'5借入一覧'!"&ET86&EV86)&INDIRECT("'5借入一覧'!"&EU86&EV86)} | EX86: 1 | EY86: 79 | EZ86: =VLOOKUP($EY86&EZ$5,$EW$7:$EX$1101,2,FALSE) -> #N/A | FA86: =VLOOKUP($EY86&FA$5,$EW$7:$EX$1101,2,FALSE) -> #N/A | FB86: =VLOOKUP($EY86&FB$5,$EW$7:$EX$1101,2,FALSE) -> #N/A | FC86: =VLOOKUP($EY86&FC$5,$EW$7:$EX$1101,2,FALSE) -> #N/A | FD86: =VLOOKUP($EY86&FD$5,$EW$7:$EX$1101,2,FALSE) -> #N/A | FE86: =IFERROR(IF(EZ86>0,EZ$7),"") | FF86: =IFERROR(IF(FA86>0,FA$7),"") | FG86: =IFERROR(IF(FB86>0,FB$7),"") | FH86: =IFERROR(IF(FC86>0,FC$7),"") | FI86: =IFERROR(IF(FD86>0,FD$7),"") | FJ86: =FE86&FF86&FG86&FH86&FI86 | FK86: =IF(FJ86<>"",LEFT(FJ86,LEN(FJ86)-1),"") | FL86: =IF(FK86<>"",FK86&"として提供中","無") -> 無
CO87: 267 | CP87: 133000 | CQ87: 41 | DF87: 事務所 | EM87: コアプラス池袋 | ES87: 80 | ET87: AG | EU87: AE | EV87: 81 | EW87: {=INDIRECT("'5借入一覧'!"&ET87&EV87)&INDIRECT("'5借入一覧'!"&EU87&EV87)} | EX87: 1 | EY87: 80 | EZ87: =VLOOKUP($EY87&EZ$5,$EW$7:$EX$1101,2,FALSE) -> #N/A | FA87: =VLOOKUP($EY87&FA$5,$EW$7:$EX$1101,2,FALSE) -> #N/A | FB87: =VLOOKUP($EY87&FB$5,$EW$7:$EX$1101,2,FALSE) -> #N/A | FC87: =VLOOKUP($EY87&FC$5,$EW$7:$EX$1101,2,FALSE) -> #N/A | FD87: =VLOOKUP($EY87&FD$5,$EW$7:$EX$1101,2,FALSE) -> #N/A | FE87: =IFERROR(IF(EZ87>0,EZ$7),"") | FF87: =IFERROR(IF(FA87>0,FA$7),"") | FG87: =IFERROR(IF(FB87>0,FB$7),"") | FH87: =IFERROR(IF(FC87>0,FC$7),"") | FI87: =IFERROR(IF(FD87>0,FD$7),"") | FJ87: =FE87&FF87&FG87&FH87&FI87 | FK87: =IF(FJ87<>"",LEFT(FJ87,LEN(FJ87)-1),"") | FL87: =IF(FK87<>"",FK87&"として提供中","無") -> 無
CO88: 254 | CP88: 133000 | CQ88: 41 | DF88: 自販機 | EM88: メゾン雑司ヶ谷 | ES88: 81 | ET88: AG | EU88: AE | EV88: 82 | EW88: {=INDIRECT("'5借入一覧'!"&ET88&EV88)&INDIRECT("'5借入一覧'!"&EU88&EV88)} | EX88: 1 | EY88: 81 | EZ88: =VLOOKUP($EY88&EZ$5,$EW$7:$EX$1101,2,FALSE) -> #N/A | FA88: =VLOOKUP($EY88&FA$5,$EW$7:$EX$1101,2,FALSE) -> #N/A | FB88: =VLOOKUP($EY88&FB$5,$EW$7:$EX$1101,2,FALSE) -> #N/A | FC88: =VLOOKUP($EY88&FC$5,$EW$7:$EX$1101,2,FALSE) -> #N/A | FD88: =VLOOKUP($EY88&FD$5,$EW$7:$EX$1101,2,FALSE) -> #N/A | FE88: =IFERROR(IF(EZ88>0,EZ$7),"") | FF88: =IFERROR(IF(FA88>0,FA$7),"") | FG88: =IFERROR(IF(FB88>0,FB$7),"") | FH88: =IFERROR(IF(FC88>0,FC$7),"") | FI88: =IFERROR(IF(FD88>0,FD$7),"") | FJ88: =FE88&FF88&FG88&FH88&FI88 | FK88: =IF(FJ88<>"",LEFT(FJ88,LEN(FJ88)-1),"") | FL88: =IF(FK88<>"",FK88&"として提供中","無") -> 無
CO89: 82 | CP89: 132000 | CQ89: 42 | DF89: 住居 | EM89: レジデンス目白豊島 | ES89: 82 | ET89: AG | EU89: AE | EV89: 83 | EW89: {=INDIRECT("'5借入一覧'!"&ET89&EV89)&INDIRECT("'5借入一覧'!"&EU89&EV89)} | EX89: 1 | EY89: 82 | EZ89: =VLOOKUP($EY89&EZ$5,$EW$7:$EX$1101,2,FALSE) -> #N/A | FA89: =VLOOKUP($EY89&FA$5,$EW$7:$EX$1101,2,FALSE) -> #N/A | FB89: =VLOOKUP($EY89&FB$5,$EW$7:$EX$1101,2,FALSE) -> #N/A | FC89: =VLOOKUP($EY89&FC$5,$EW$7:$EX$1101,2,FALSE) -> #N/A | FD89: =VLOOKUP($EY89&FD$5,$EW$7:$EX$1101,2,FALSE) -> #N/A | FE89: =IFERROR(IF(EZ89>0,EZ$7),"") | FF89: =IFERROR(IF(FA89>0,FA$7),"") | FG89: =IFERROR(IF(FB89>0,FB$7),"") | FH89: =IFERROR(IF(FC89>0,FC$7),"") | FI89: =IFERROR(IF(FD89>0,FD$7),"") | FJ89: =FE89&FF89&FG89&FH89&FI89 | FK89: =IF(FJ89<>"",LEFT(FJ89,LEN(FJ89)-1),"") | FL89: =IF(FK89<>"",FK89&"として提供中","無") -> 無
CO90: 221 | CP90: 132000 | CQ90: 42 | DF90: 倉庫 | EM90: 高田馬場第4玉川ビル | ES90: 83 | ET90: AG | EU90: AE | EV90: 84 | EW90: {=INDIRECT("'5借入一覧'!"&ET90&EV90)&INDIRECT("'5借入一覧'!"&EU90&EV90)} | EX90: 1 | EY90: 83 | EZ90: =VLOOKUP($EY90&EZ$5,$EW$7:$EX$1101,2,FALSE) -> #N/A | FA90: =VLOOKUP($EY90&FA$5,$EW$7:$EX$1101,2,FALSE) -> #N/A | FB90: =VLOOKUP($EY90&FB$5,$EW$7:$EX$1101,2,FALSE) -> #N/A | FC90: =VLOOKUP($EY90&FC$5,$EW$7:$EX$1101,2,FALSE) -> #N/A | FD90: =VLOOKUP($EY90&FD$5,$EW$7:$EX$1101,2,FALSE) -> #N/A | FE90: =IFERROR(IF(EZ90>0,EZ$7),"") | FF90: =IFERROR(IF(FA90>0,FA$7),"") | FG90: =IFERROR(IF(FB90>0,FB$7),"") | FH90: =IFERROR(IF(FC90>0,FC$7),"") | FI90: =IFERROR(IF(FD90>0,FD$7),"") | FJ90: =FE90&FF90&FG90&FH90&FI90 | FK90: =IF(FJ90<>"",LEFT(FJ90,LEN(FJ90)-1),"") | FL90: =IF(FK90<>"",FK90&"として提供中","無") -> 無
CO91: 261 | CP91: 132000 | CQ91: 42 | DF91: 駐車場 | EM91: 西池袋駅前ビル | ES91: 84 | ET91: AG | EU91: AE | EV91: 85 | EW91: {=INDIRECT("'5借入一覧'!"&ET91&EV91)&INDIRECT("'5借入一覧'!"&EU91&EV91)} | EX91: 1 | EY91: 84 | EZ91: =VLOOKUP($EY91&EZ$5,$EW$7:$EX$1101,2,FALSE) -> #N/A | FA91: =VLOOKUP($EY91&FA$5,$EW$7:$EX$1101,2,FALSE) -> #N/A | FB91: =VLOOKUP($EY91&FB$5,$EW$7:$EX$1101,2,FALSE) -> #N/A | FC91: =VLOOKUP($EY91&FC$5,$EW$7:$EX$1101,2,FALSE) -> #N/A | FD91: =VLOOKUP($EY91&FD$5,$EW$7:$EX$1101,2,FALSE) -> #N/A | FE91: =IFERROR(IF(EZ91>0,EZ$7),"") | FF91: =IFERROR(IF(FA91>0,FA$7),"") | FG91: =IFERROR(IF(FB91>0,FB$7),"") | FH91: =IFERROR(IF(FC91>0,FC$7),"") | FI91: =IFERROR(IF(FD91>0,FD$7),"") | FJ91: =FE91&FF91&FG91&FH91&FI91 | FK91: =IF(FJ91<>"",LEFT(FJ91,LEN(FJ91)-1),"") | FL91: =IF(FK91<>"",FK91&"として提供中","無") -> 無
CO92: 232 | CP92: 131000 | CQ92: 43 | DF92: 店舗 | EM92: 仙台駅前コーポ | ES92: 85 | ET92: AG | EU92: AE | EV92: 86 | EW92: {=INDIRECT("'5借入一覧'!"&ET92&EV92)&INDIRECT("'5借入一覧'!"&EU92&EV92)} | EX92: 1 | EY92: 85 | EZ92: =VLOOKUP($EY92&EZ$5,$EW$7:$EX$1101,2,FALSE) -> #N/A | FA92: =VLOOKUP($EY92&FA$5,$EW$7:$EX$1101,2,FALSE) -> #N/A | FB92: =VLOOKUP($EY92&FB$5,$EW$7:$EX$1101,2,FALSE) -> #N/A | FC92: =VLOOKUP($EY92&FC$5,$EW$7:$EX$1101,2,FALSE) -> #N/A | FD92: =VLOOKUP($EY92&FD$5,$EW$7:$EX$1101,2,FALSE) -> #N/A | FE92: =IFERROR(IF(EZ92>0,EZ$7),"") | FF92: =IFERROR(IF(FA92>0,FA$7),"") | FG92: =IFERROR(IF(FB92>0,FB$7),"") | FH92: =IFERROR(IF(FC92>0,FC$7),"") | FI92: =IFERROR(IF(FD92>0,FD$7),"") | FJ92: =FE92&FF92&FG92&FH92&FI92 | FK92: =IF(FJ92<>"",LEFT(FJ92,LEN(FJ92)-1),"") | FL92: =IF(FK92<>"",FK92&"として提供中","無") -> 無
CO93: 259 | CP93: 131000 | CQ93: 43 | DF93: (空白) | EM93: 対象物件なし(運転資金) | EN93: 0 | EO93: 0 | EP93: 0 | EQ93: 2000000 | ES93: 86 | ET93: AG | EU93: AE | EV93: 87 | EW93: {=INDIRECT("'5借入一覧'!"&ET93&EV93)&INDIRECT("'5借入一覧'!"&EU93&EV93)} | EX93: 1 | EY93: 86 | EZ93: =VLOOKUP($EY93&EZ$5,$EW$7:$EX$1101,2,FALSE) -> #N/A | FA93: =VLOOKUP($EY93&FA$5,$EW$7:$EX$1101,2,FALSE) -> #N/A | FB93: =VLOOKUP($EY93&FB$5,$EW$7:$EX$1101,2,FALSE) -> #N/A | FC93: =VLOOKUP($EY93&FC$5,$EW$7:$EX$1101,2,FALSE) -> #N/A | FD93: =VLOOKUP($EY93&FD$5,$EW$7:$EX$1101,2,FALSE) -> #N/A | FE93: =IFERROR(IF(EZ93>0,EZ$7),"") | FF93: =IFERROR(IF(FA93>0,FA$7),"") | FG93: =IFERROR(IF(FB93>0,FB$7),"") | FH93: =IFERROR(IF(FC93>0,FC$7),"") | FI93: =IFERROR(IF(FD93>0,FD$7),"") | FJ93: =FE93&FF93&FG93&FH93&FI93 | FK93: =IF(FJ93<>"",LEFT(FJ93,LEN(FJ93)-1),"") | FL93: =IF(FK93<>"",FK93&"として提供中","無") -> 無
CO94: 269 | CP94: 130000 | CQ94: 44 | DF94: 800000-899999 | EM94: 第3目白ハイツ | ES94: 87 | ET94: AG | EU94: AE | EV94: 88 | EW94: {=INDIRECT("'5借入一覧'!"&ET94&EV94)&INDIRECT("'5借入一覧'!"&EU94&EV94)} | EX94: 1 | EY94: 87 | EZ94: =VLOOKUP($EY94&EZ$5,$EW$7:$EX$1101,2,FALSE) -> #N/A | FA94: =VLOOKUP($EY94&FA$5,$EW$7:$EX$1101,2,FALSE) -> #N/A | FB94: =VLOOKUP($EY94&FB$5,$EW$7:$EX$1101,2,FALSE) -> #N/A | FC94: =VLOOKUP($EY94&FC$5,$EW$7:$EX$1101,2,FALSE) -> #N/A | FD94: =VLOOKUP($EY94&FD$5,$EW$7:$EX$1101,2,FALSE) -> #N/A | FE94: =IFERROR(IF(EZ94>0,EZ$7),"") | FF94: =IFERROR(IF(FA94>0,FA$7),"") | FG94: =IFERROR(IF(FB94>0,FB$7),"") | FH94: =IFERROR(IF(FC94>0,FC$7),"") | FI94: =IFERROR(IF(FD94>0,FD$7),"") | FJ94: =FE94&FF94&FG94&FH94&FI94 | FK94: =IF(FJ94<>"",LEFT(FJ94,LEN(FJ94)-1),"") | FL94: =IF(FK94<>"",FK94&"として提供中","無") -> 無
CO95: 255 | CP95: 130000 | CQ95: 44 | DF95: アンテナ | EM95: 池袋ハウス | ES95: 88 | ET95: AG | EU95: AE | EV95: 89 | EW95: {=INDIRECT("'5借入一覧'!"&ET95&EV95)&INDIRECT("'5借入一覧'!"&EU95&EV95)} | EX95: 1 | EY95: 88 | EZ95: =VLOOKUP($EY95&EZ$5,$EW$7:$EX$1101,2,FALSE) -> #N/A | FA95: =VLOOKUP($EY95&FA$5,$EW$7:$EX$1101,2,FALSE) -> #N/A | FB95: =VLOOKUP($EY95&FB$5,$EW$7:$EX$1101,2,FALSE) -> #N/A | FC95: =VLOOKUP($EY95&FC$5,$EW$7:$EX$1101,2,FALSE) -> #N/A | FD95: =VLOOKUP($EY95&FD$5,$EW$7:$EX$1101,2,FALSE) -> #N/A | FE95: =IFERROR(IF(EZ95>0,EZ$7),"") | FF95: =IFERROR(IF(FA95>0,FA$7),"") | FG95: =IFERROR(IF(FB95>0,FB$7),"") | FH95: =IFERROR(IF(FC95>0,FC$7),"") | FI95: =IFERROR(IF(FD95>0,FD$7),"") | FJ95: =FE95&FF95&FG95&FH95&FI95 | FK95: =IF(FJ95<>"",LEFT(FJ95,LEN(FJ95)-1),"") | FL95: =IF(FK95<>"",FK95&"として提供中","無") -> 無
CO96: 229 | CP96: 130000 | CQ96: 44 | DF96: その他 | EM96: 東池袋ハイツ | ES96: 89 | ET96: AG | EU96: AE | EV96: 90 | EW96: {=INDIRECT("'5借入一覧'!"&ET96&EV96)&INDIRECT("'5借入一覧'!"&EU96&EV96)} | EX96: 1 | EY96: 89 | EZ96: =VLOOKUP($EY96&EZ$5,$EW$7:$EX$1101,2,FALSE) -> #N/A | FA96: =VLOOKUP($EY96&FA$5,$EW$7:$EX$1101,2,FALSE) -> #N/A | FB96: =VLOOKUP($EY96&FB$5,$EW$7:$EX$1101,2,FALSE) -> #N/A | FC96: =VLOOKUP($EY96&FC$5,$EW$7:$EX$1101,2,FALSE) -> #N/A | FD96: =VLOOKUP($EY96&FD$5,$EW$7:$EX$1101,2,FALSE) -> #N/A | FE96: =IFERROR(IF(EZ96>0,EZ$7),"") | FF96: =IFERROR(IF(FA96>0,FA$7),"") | FG96: =IFERROR(IF(FB96>0,FB$7),"") | FH96: =IFERROR(IF(FC96>0,FC$7),"") | FI96: =IFERROR(IF(FD96>0,FD$7),"") | FJ96: =FE96&FF96&FG96&FH96&FI96 | FK96: =IF(FJ96<>"",LEFT(FJ96,LEN(FJ96)-1),"") | FL96: =IF(FK96<>"",FK96&"として提供中","無") -> 無
CO97: 252 | CP97: 130000 | CQ97: 44 | DF97: 事務所 | EM97: 南池袋マンション | ES97: 90 | ET97: AG | EU97: AE | EV97: 91 | EW97: {=INDIRECT("'5借入一覧'!"&ET97&EV97)&INDIRECT("'5借入一覧'!"&EU97&EV97)} | EX97: 1 | EY97: 90 | EZ97: =VLOOKUP($EY97&EZ$5,$EW$7:$EX$1101,2,FALSE) -> #N/A | FA97: =VLOOKUP($EY97&FA$5,$EW$7:$EX$1101,2,FALSE) -> #N/A | FB97: =VLOOKUP($EY97&FB$5,$EW$7:$EX$1101,2,FALSE) -> #N/A | FC97: =VLOOKUP($EY97&FC$5,$EW$7:$EX$1101,2,FALSE) -> #N/A | FD97: =VLOOKUP($EY97&FD$5,$EW$7:$EX$1101,2,FALSE) -> #N/A | FE97: =IFERROR(IF(EZ97>0,EZ$7),"") | FF97: =IFERROR(IF(FA97>0,FA$7),"") | FG97: =IFERROR(IF(FB97>0,FB$7),"") | FH97: =IFERROR(IF(FC97>0,FC$7),"") | FI97: =IFERROR(IF(FD97>0,FD$7),"") | FJ97: =FE97&FF97&FG97&FH97&FI97 | FK97: =IF(FJ97<>"",LEFT(FJ97,LEN(FJ97)-1),"") | FL97: =IF(FK97<>"",FK97&"として提供中","無") -> 無
CO98: 222 | CP98: 130000 | CQ98: 44 | DF98: 自販機 | EM98: 豊島目白ビル | ES98: 91 | ET98: AG | EU98: AE | EV98: 92 | EW98: {=INDIRECT("'5借入一覧'!"&ET98&EV98)&INDIRECT("'5借入一覧'!"&EU98&EV98)} | EX98: 1 | EY98: 91 | EZ98: =VLOOKUP($EY98&EZ$5,$EW$7:$EX$1101,2,FALSE) -> #N/A | FA98: =VLOOKUP($EY98&FA$5,$EW$7:$EX$1101,2,FALSE) -> #N/A | FB98: =VLOOKUP($EY98&FB$5,$EW$7:$EX$1101,2,FALSE) -> #N/A | FC98: =VLOOKUP($EY98&FC$5,$EW$7:$EX$1101,2,FALSE) -> #N/A | FD98: =VLOOKUP($EY98&FD$5,$EW$7:$EX$1101,2,FALSE) -> #N/A | FE98: =IFERROR(IF(EZ98>0,EZ$7),"") | FF98: =IFERROR(IF(FA98>0,FA$7),"") | FG98: =IFERROR(IF(FB98>0,FB$7),"") | FH98: =IFERROR(IF(FC98>0,FC$7),"") | FI98: =IFERROR(IF(FD98>0,FD$7),"") | FJ98: =FE98&FF98&FG98&FH98&FI98 | FK98: =IF(FJ98<>"",LEFT(FJ98,LEN(FJ98)-1),"") | FL98: =IF(FK98<>"",FK98&"として提供中","無") -> 無
CO99: 262 | CP99: 130000 | CQ99: 44 | DF99: 住居 | EM99: 目白アパート | ES99: 92 | ET99: AG | EU99: AE | EV99: 93 | EW99: {=INDIRECT("'5借入一覧'!"&ET99&EV99)&INDIRECT("'5借入一覧'!"&EU99&EV99)} | EX99: 1 | EY99: 92 | EZ99: =VLOOKUP($EY99&EZ$5,$EW$7:$EX$1101,2,FALSE) -> #N/A | FA99: =VLOOKUP($EY99&FA$5,$EW$7:$EX$1101,2,FALSE) -> #N/A | FB99: =VLOOKUP($EY99&FB$5,$EW$7:$EX$1101,2,FALSE) -> #N/A | FC99: =VLOOKUP($EY99&FC$5,$EW$7:$EX$1101,2,FALSE) -> #N/A | FD99: =VLOOKUP($EY99&FD$5,$EW$7:$EX$1101,2,FALSE) -> #N/A | FE99: =IFERROR(IF(EZ99>0,EZ$7),"") | FF99: =IFERROR(IF(FA99>0,FA$7),"") | FG99: =IFERROR(IF(FB99>0,FB$7),"") | FH99: =IFERROR(IF(FC99>0,FC$7),"") | FI99: =IFERROR(IF(FD99>0,FD$7),"") | FJ99: =FE99&FF99&FG99&FH99&FI99 | FK99: =IF(FJ99<>"",LEFT(FJ99,LEN(FJ99)-1),"") | FL99: =IF(FK99<>"",FK99&"として提供中","無") -> 無
CO100: 260 | CP100: 130000 | CQ100: 44 | DF100: 倉庫 | EM100: 目白カーサ二番館 | ES100: 93 | ET100: AG | EU100: AE | EV100: 94 | EW100: {=INDIRECT("'5借入一覧'!"&ET100&EV100)&INDIRECT("'5借入一覧'!"&EU100&EV100)} | EX100: 1 | EY100: 93 | EZ100: =VLOOKUP($EY100&EZ$5,$EW$7:$EX$1101,2,FALSE) -> #N/A | FA100: =VLOOKUP($EY100&FA$5,$EW$7:$EX$1101,2,FALSE) -> #N/A | FB100: =VLOOKUP($EY100&FB$5,$EW$7:$EX$1101,2,FALSE) -> #N/A | FC100: =VLOOKUP($EY100&FC$5,$EW$7:$EX$1101,2,FALSE) -> #N/A | FD100: =VLOOKUP($EY100&FD$5,$EW$7:$EX$1101,2,FALSE) -> #N/A | FE100: =IFERROR(IF(EZ100>0,EZ$7),"") | FF100: =IFERROR(IF(FA100>0,FA$7),"") | FG100: =IFERROR(IF(FB100>0,FB$7),"") | FH100: =IFERROR(IF(FC100>0,FC$7),"") | FI100: =IFERROR(IF(FD100>0,FD$7),"") | FJ100: =FE100&FF100&FG100&FH100&FI100 | FK100: =IF(FJ100<>"",LEFT(FJ100,LEN(FJ100)-1),"") | FL100: =IF(FK100<>"",FK100&"として提供中","無") -> 無
CO101: 287 | CP101: 130000 | CQ101: 44 | DF101: 駐車場 | EM101: (空白) | ES101: 94 | ET101: AG | EU101: AE | EV101: 95 | EW101: {=INDIRECT("'5借入一覧'!"&ET101&EV101)&INDIRECT("'5借入一覧'!"&EU101&EV101)} | EX101: 1 | EY101: 94 | EZ101: =VLOOKUP($EY101&EZ$5,$EW$7:$EX$1101,2,FALSE) -> #N/A | FA101: =VLOOKUP($EY101&FA$5,$EW$7:$EX$1101,2,FALSE) -> #N/A | FB101: =VLOOKUP($EY101&FB$5,$EW$7:$EX$1101,2,FALSE) -> #N/A | FC101: =VLOOKUP($EY101&FC$5,$EW$7:$EX$1101,2,FALSE) -> #N/A | FD101: =VLOOKUP($EY101&FD$5,$EW$7:$EX$1101,2,FALSE) -> #N/A | FE101: =IFERROR(IF(EZ101>0,EZ$7),"") | FF101: =IFERROR(IF(FA101>0,FA$7),"") | FG101: =IFERROR(IF(FB101>0,FB$7),"") | FH101: =IFERROR(IF(FC101>0,FC$7),"") | FI101: =IFERROR(IF(FD101>0,FD$7),"") | FJ101: =FE101&FF101&FG101&FH101&FI101 | FK101: =IF(FJ101<>"",LEFT(FJ101,LEN(FJ101)-1),"") | FL101: =IF(FK101<>"",FK101&"として提供中","無") -> 無
CO102: 223 | CP102: 130000 | CQ102: 44 | DF102: 店舗 | EM102: 目白アパート1号館 | ES102: 95 | ET102: AG | EU102: AE | EV102: 96 | EW102: {=INDIRECT("'5借入一覧'!"&ET102&EV102)&INDIRECT("'5借入一覧'!"&EU102&EV102)} | EX102: 1 | EY102: 95 | EZ102: =VLOOKUP($EY102&EZ$5,$EW$7:$EX$1101,2,FALSE) -> #N/A | FA102: =VLOOKUP($EY102&FA$5,$EW$7:$EX$1101,2,FALSE) -> #N/A | FB102: =VLOOKUP($EY102&FB$5,$EW$7:$EX$1101,2,FALSE) -> #N/A | FC102: =VLOOKUP($EY102&FC$5,$EW$7:$EX$1101,2,FALSE) -> #N/A | FD102: =VLOOKUP($EY102&FD$5,$EW$7:$EX$1101,2,FALSE) -> #N/A | FE102: =IFERROR(IF(EZ102>0,EZ$7),"") | FF102: =IFERROR(IF(FA102>0,FA$7),"") | FG102: =IFERROR(IF(FB102>0,FB$7),"") | FH102: =IFERROR(IF(FC102>0,FC$7),"") | FI102: =IFERROR(IF(FD102>0,FD$7),"") | FJ102: =FE102&FF102&FG102&FH102&FI102 | FK102: =IF(FJ102<>"",LEFT(FJ102,LEN(FJ102)-1),"") | FL102: =IF(FK102<>"",FK102&"として提供中","無") -> 無
CO103: 102 | CP103: 129000 | CQ103: 45 | DF103: (空白) | EM103: プラウD目白301号 | ES103: 96 | ET103: AG | EU103: AE | EV103: 97 | EW103: {=INDIRECT("'5借入一覧'!"&ET103&EV103)&INDIRECT("'5借入一覧'!"&EU103&EV103)} | EX103: 1 | EY103: 96 | EZ103: =VLOOKUP($EY103&EZ$5,$EW$7:$EX$1101,2,FALSE) -> #N/A | FA103: =VLOOKUP($EY103&FA$5,$EW$7:$EX$1101,2,FALSE) -> #N/A | FB103: =VLOOKUP($EY103&FB$5,$EW$7:$EX$1101,2,FALSE) -> #N/A | FC103: =VLOOKUP($EY103&FC$5,$EW$7:$EX$1101,2,FALSE) -> #N/A | FD103: =VLOOKUP($EY103&FD$5,$EW$7:$EX$1101,2,FALSE) -> #N/A | FE103: =IFERROR(IF(EZ103>0,EZ$7),"") | FF103: =IFERROR(IF(FA103>0,FA$7),"") | FG103: =IFERROR(IF(FB103>0,FB$7),"") | FH103: =IFERROR(IF(FC103>0,FC$7),"") | FI103: =IFERROR(IF(FD103>0,FD$7),"") | FJ103: =FE103&FF103&FG103&FH103&FI103 | FK103: =IF(FJ103<>"",LEFT(FJ103,LEN(FJ103)-1),"") | FL103: =IF(FK103<>"",FK103&"として提供中","無") -> 無
...

Sheet settings
A1: 名称マスタ | D1: 水色のセルのみ入力します。 | G1: 基本設定1 | L1: 水色のセルのみ入力します。 | N1: 整合性ベリファイ | R1: =IF(SUM(R3:R296)<>0,"■エラーあり","") -> ■エラーあり
A2: ID | B2: 値 | C2: 摘要1 | D2: 摘要2 | E2: 摘要3 | G2: ID | H2: シート | I2: 項目 | J2: 解説 | K2: 入力規則 | L2: 入力値 | N2: ID | O2: シート | P2: 項目 | Q2: 金額 | R2: 整合性
A3: 101 | B3: 西池袋駅前ビル | C3: 一棟名称 | G3: 1 | H3: 全体 | I3: 現在の西暦 | J3: 今日の日付(年) | K3: 自動 | L3: =YEAR(NOW()) -> 2023 | N3: 1 | O3: 全体PLBS | P3: 資産合計 | Q3: ='2法人連結'!C21 -> 7577667250 | R3: =Q3-Q5 -> 0
A4: 102 | B4: 池袋ハウス | C4: 一棟名称 | G4: 2 | H4: 全体 | I4: 現在の事業年度 | J4: ユーザー設定入力 | K4: 西暦4桁 | L4: 2021 | N4: 2 | O4: 全体PLBS | P4: 純資産合計 | Q4: ='2法人連結'!E21 -> 3063467948 | R4: =Q3+Q6-Q4 -> 0
A5: 103 | B5: カーサ目白台ハウス | C5: 一棟名称 | G5: 3 | H5: 1法人概要 | I5: 本資料作成日: | J5: Excelデータ作成日 | K5: 日付形式 | L5: 44870 | N5: 3 | O5: 全体PLBS | P5: 負債純資産合計 | Q5: ='2法人連結'!E21-'2法人連結'!E16 -> 7577667250 | R5: =Q5-Q3 -> 0
A6: 104 | B6: コアプラス池袋 | C6: 一棟名称 | G6: 4 | H6: 2法人連結 | I6: G全体B/S基準日 | J6: 通常は本日現在 | K6: 日付形式 | L6: 44870 | N6: 4 | O6: 全体PLBS | P6: 負債合計 | Q6: ='2法人連結'!E16 -> -4514199302 | R6: =Q3-Q4+Q6 -> 0
A7: 105 | B7: 目白アパート | C7: 一棟名称 | G7: 5 | H7: 2法人連結 | I7: G全体P/L集計期間 | J7: 2022年1月～12月予測など | K7: 文字列 | L7: 2023年1月～12月予測 | N7: 5 | O7: 借入集計 | P7: 金融機関別借入 | Q7: =GETPIVOTDATA("25.残債",'4借入集計'!$A$5) -> 4439492417 | R7: =Q7-Q8 -> 0
A8: 106 | B8: 東池袋ハイツ | C8: 一棟名称 | G8: 6 | H8: 2法人連結 | I8: G全体C/F集計期間 | J8: 2022年1月～12月予測など | K8: 文字列 | L8: 2023年1月～12月予測 | N8: 6 | O8: 借入集計 | P8: 会社別銀行借入 | Q8: =GETPIVOTDATA("25.残債",'4借入集計'!$A$23) -> 4439492417 | R8: =Q8-Q9 -> 0
A9: 107 | B9: メゾン雑司ヶ谷 | C9: 一棟名称 | G9: 7 | H9: 3物件一覧 | I9: 作成基準日 | J9: ユーザー設定入力 | K9: 日付形式 | L9: 44870 | N9: 7 | O9: 借入集計 | P9: 物件別銀行借入 | Q9: =GETPIVOTDATA("残債",'4借入集計'!$A$59) -> 4439492417 | R9: =Q9-Q7 -> 0
A10: 109 | B10: カーサ南池袋 | C10: 一棟名称 | G10: 8 | H10: 4借入集計 | I10: 作成基準日 | J10: ユーザー設定入力 | K10: 日付形式 | L10: 44870 | N10: 8 | O10: 9賃料一覧 | P10: 全論理あり区画満室想定 | Q10: =SUMIF('9賃料一覧'!$AD:$AD,1,'9賃料一覧'!$Q:$Q) -> 35943978 | R10: =Q10-Q12 -> 0
A11: 110 | B11: 仙台駅前コーポ | C11: 一棟名称 | D11: 売却済み | G11: 9 | H11: 6減価償却 | I11: 作成基準日 | J11: ユーザー設定入力 | K11: 日付形式 | L11: 44561 | N11: 9 | O11: 9賃料一覧 | P11: 全論理なし区画満室想定 | Q11: =SUMIF('9賃料一覧'!$AD:$AD,0,'9賃料一覧'!$Q:$Q) -> 1003500
A12: 111 | B12: 目白カーサ二番館 | C12: 一棟名称 | G12: 10 | H12: 6減価償却 | I12: 期首期末簿価の年度 | J12: ユーザー設定入力 | K12: 文字列 | L12: 2022 | N12: 10 | O12: 8賃料集計 | P12: 満室想定 | Q12: ='8賃料集計'!L25 -> 35943978
A13: 112 | B13: 豊島目白ビル | C13: 一棟名称 | G13: 11 | H13: 8賃料集計 | I13: 作成基準日 | J13: ユーザー設定入力 | K13: 日付形式 | L13: 44870 | N13: 11 | O13: pivot | P13: 満室想定(全) | Q13: =GETPIVOTDATA("17.満室想定税込(自動)",pivot!$AR$9) -> 35943978
A14: 113 | B14: 第3目白ハイツ | C14: 一棟名称 | G14: 12 | H14: A.BM集計 | I14: 作成基準日 | J14: ユーザー設定入力 | K14: 日付形式 | L14: 44561 | N14: 12 | O14: pivot | P14: 満室想定(賃貸区画yes) | Q14: =IFERROR(GETPIVOTDATA("17.満室想定税込(自動)",pivot!$AR$9,"19.賃貸用","yes"),0) -> 35648978
A15: 114 | B15: レジデンス目白豊島 | C15: 一棟名称 | G15: 13 | H15: B筆一覧 | I15: 評価額と固都税年度 | J15: ユーザー設定入力 | K15: 文字列 | L15: 令和3年度 | N15: 13 | O15: pivot | P15: 満室想定(賃貸区画no) | Q15: =IFERROR(GETPIVOTDATA("17.満室想定税込(自動)",pivot!$AR$9,"19.賃貸用","no"),0) -> 295000 | R15: =Q12-Q14-Q15 -> 0
A16: 115 | B16: コアプラス大塚 | C16: 一棟名称 | N16: 14 | O16: asset | P16: 物件関連残債総計 | Q16: =asset!E36 -> 4417003271
A17: 116 | B17: コアプラスレジデンス梅田 | C17: 一棟名称 | G17: 基本設定2 | N17: 15 | O17: asset | P17: 物件関連金利総計(月額) | Q17: =asset!E37 -> 5011481
A18: 117 | B18: 高田馬場第4玉川ビル | C18: 一棟名称 | G18: ID | H18: シート | I18: 項目 | J18: 解説 | K18: 入力規則 | L18: 入力値 | N18: 16 | O18: asset | P18: 物件関連元金総計(月額) | Q18: =asset!E38 -> 12786755
A19: 118 | B19: あおばマンション | C19: 一棟名称 | D19: 売却済み | G19: 21 | H19: 複数 | I19: 賃料収入への税率 | J19: ユーザー設定税率 | K19: 数値% | L19: 0.3 | N19: 17 | O19: asset | P19: 物件関連支払総計(月額) | Q19: =asset!E39 -> 17798236
A20: 120 | B20: 南池袋マンション | C20: 一棟名称 | G20: 22 | H20: 2法人連結 | I20: 想定税率 | J20: 法人全体への想定税率 | K20: 数値% | L20: 0.35 | N20: 18 | O20: 4借入集計 | P20: 借入総額 | Q20: =GETPIVOTDATA("25.残債",'4借入集計'!$A$5) -> 4439492417
A21: 121 | B21: 目白アパート1号館 | C21: 一棟名称 | D21: 二棟一括購入 | G21: 23 | H21: 3物件一覧 | I21: 物件譲渡益の税率 | J21: ユーザー設定税率 | K21: 数値% | L21: 0.37 | N21: 19 | O21: 4借入集計 | P21: 621対象物件なし(運転資金) | Q21: =SUMIF('5借入一覧'!$J:$J,621,'5借入一覧'!$Y:$Y) -> 22489146
A22: 122 | B22: 目白アパート2号館 | C22: 一棟名称 | D22: 二棟一括購入 | N22: 20 | O22: 4借入集計 | P22: 622複数の物件一括 | Q22: =SUMIF('5借入一覧'!$J:$J,622,'5借入一覧'!$Y:$Y) -> 0
A23: 123 | B23: アーバンキューブ | C23: 一棟名称 | D23: 高松二丁目・一括購入 | G23: 基本設定3 | N23: 21 | O23: 4借入集計 | P23: 総額-621-622 | Q23: =Q20-Q21-Q22 -> 4417003271 | R23: =Q23-Q16 -> 0
A24: 124 | B24: 花みずき貸家 | C24: 一棟名称 | D24: 高松二丁目・一括購入(3棟) | G24: ID | H24: シート | I24: 項目 | J24: 解説 | K24: 入力規則 | L24: 入力値 | N24: 22 | O24: 4借入集計 | P24: 月額金利総額 | Q24: =GETPIVOTDATA("利息月額",'4借入集計'!$A$59) -> 5043759
A25: 125 | B25: 物件名予備5 | C25: 一棟名称 | G25: 31 | H25: 2法人連結 | I25: 法人株式・債券等証券投資 | J25: 法人による証券投資額 | K25: 数値\ | L25: 10000000 | N25: 23 | O25: 4借入集計 | P25: 621対象物件なし(運転資金) | Q25: =SUMIF('5借入一覧'!$J:$J,621,'5借入一覧'!$W:$W) -> 32278
A26: 126 | B26: 物件名予備6 | C26: 一棟名称 | G26: 32 | H26: 2法人連結 | I26: 個人預金等 | J26: 個人保有預金等の額 | K26: 数値\ | L26: 30000000 | N26: 24 | O26: 4借入集計 | P26: 622複数の物件一括 | Q26: =SUMIF('5借入一覧'!$J:$J,622,'5借入一覧'!$W:$W) -> 0
A27: 127 | B27: 物件名予備7 | C27: 一棟名称 | G27: 33 | H27: 2法人連結 | I27: 個人株式・債券等証券投資 | J27: 個人で保有する額 | K27: 数値\ | L27: 15000000 | N27: 25 | O27: 4借入集計 | P27: 総額-621-622 | Q27: =Q24-Q25-Q26 -> 5011481 | R27: =Q27-Q17 -> 0
A28: 128 | B28: 物件名予備8 | C28: 一棟名称 | G28: 34 | H28: 2法人連結 | I28: その他資産 | J28: 相続予定の親資産など | K28: 数値\ | L28: 5000000 | N28: 26 | O28: 4借入集計 | P28: 月額元金総額 | Q28: =GETPIVOTDATA("合計 / 22.元金返済月額",pivot!$EG$4) -> 12955677
A29: 129 | B29: 物件名予備9 | C29: 一棟名称 | G29: 35 | H29: 2法人連結 | I29: 会社経費/年 | J29: 人件費以外の販管費 | K29: 数値\ | L29: 3000000 | N29: 27 | O29: 4借入集計 | P29: 621対象物件なし(運転資金) | Q29: =SUMIF('5借入一覧'!$J:$J,621,'5借入一覧'!$V:$V) -> 168922
A30: 130 | B30: 物件名予備10 | C30: 一棟名称 | G30: 36 | H30: 2法人連結 | I30: 役員報酬・人件費/年 | J30: ユーザー任意入力 | K30: 数値\ | L30: 3000000 | N30: 28 | O30: 4借入集計 | P30: 622複数の物件一括 | Q30: =SUMIF('5借入一覧'!$J:$J,622,'5借入一覧'!$V:$V) -> 0
A31: 131 | B31: 物件名予備11 | C31: 一棟名称 | N31: 29 | O31: 4借入集計 | P31: 総額-621-622 | Q31: =Q28-Q29-Q30 -> 12786755 | R31: =Q31-Q18 -> 0
A32: 132 | B32: 物件名予備12 | C32: 一棟名称 | N32: 30 | O32: 8賃料集計 | P32: 3.賃貸用資産の入居率（非賃貸を除く・金額ベース）入居率 | Q32: ='8賃料集計'!F78 -> 0.99042037
A33: 133 | B33: 物件名予備13 | C33: 一棟名称 | G33: 玉川式 財務資料Excelシート GO30B Enterprise Edition. | N33: 31 | O33: 8賃料集計 | P33: 4.資産クラス別入居率（非賃貸を除く・金額ベース）入居率 | Q33: ='8賃料集計'!F92 -> 0.99042037 | R33: =Q32-Q33 -> 0
A34: 134 | B34: 物件名予備14 | C34: 一棟名称 | G34: Rev.9 2023.07.23 | N34: 32 | O34: 8賃料集計 | P34: 3.賃貸用資産の入居率（非賃貸を除く・金額ベース）a | Q34: ='8賃料集計'!C78 -> 35648978
A35: 135 | B35: 物件名予備15 | C35: 一棟名称 | G35: https://ytamagawa.com/ | N35: 33 | O35: 8賃料集計 | P35: 4.資産クラス別入居率（非賃貸を除く・金額ベース）e | Q35: ='8賃料集計'!C92 -> 35648978 | R35: =Q35-Q34 -> 0
A36: 136 | B36: 物件名予備16 | C36: 一棟名称 | G36: このExcelシートの著作権は玉川陽介に帰属します。 | N36: 34 | O36: 8賃料集計 | P36: 7.賃貸用資産の賃料帯別ヒストグラム（非賃貸を除く）住居系 | Q36: ='8賃料集計'!M136 -> 28235436
A37: 137 | B37: 物件名予備17 | C37: 一棟名称 | G37: ご自身の資産管理の範囲内に限り金融機関に提出するなどを含めて商利用可能です。 | N37: 35 | O37: 8賃料集計 | P37: 7.賃貸用資産の賃料帯別ヒストグラム（非賃貸を除く）事務所・店舗系 | Q37: ='8賃料集計'!M151 -> 7413542 | R37: =Q35-Q36-Q37 -> 0
A38: 138 | B38: 物件名予備18 | C38: 一棟名称 | G38: ただし、不特定多数の顧客へ送付するなど再頒布すること、保護パスワードを解除して改造することは | N38: 36 | O38: asset | P38: NOI/年 | Q38: =asset!E66 -> 3.0461331e+08
A39: 139 | B39: 物件名予備19 | C39: 一棟名称 | G39: 利用規約により禁止されています。詳しくは上記のサイトをご覧ください。 | N39: 37 | O39: 3物件一覧 | P39: NOI | Q39: ='3物件一覧'!C65*10000 -> 3.0461331e+08 | R39: =Q39-Q38 -> 0
A40: 140 | B40: 物件名予備20 | C40: 一棟名称 | G40: このExcelシートの利用により生じた損害について筆者は一切の責任を負いません。 | N40: 38 | O40: asset | P40: 物件関連金利総計(月額) | Q40: =asset!E37*12 -> 60137772
A41: 141 | B41: 物件名予備21 | C41: 一棟名称 | N41: 39 | O41: 3物件一覧 | P41: 金利支払(賃貸部門+住宅ローン) | Q41: ='3物件一覧'!C66*10000 -> -60137772
A42: 142 | B42: 物件名予備22 | C42: 一棟名称 | N42: 40 | O42: asset | P42: 想定税額 | Q42: =asset!E70*-1 -> -49500032
A43: 143 | B43: 物件名予備23 | C43: 一棟名称 | N43: 41 | O43: 3物件一覧 | P43: 想定税額 | Q43: ='3物件一覧'!C70*10000 -> -47146477 | R43: =Q43-Q42 -> 2353554.4 | S43: ※差額あっても異常ではない
A44: 144 | B44: 物件名予備24 | C44: 一棟名称 | N44: 42 | O44: asset | P44: 想定税引後利益 | Q44: =asset!E71*-1 -> -1.0765489e+08
A45: 145 | B45: 物件名予備25 | C45: 一棟名称 | N45: 43 | O45: 3物件一覧 | P45: 想定税引後利益 | Q45: ='3物件一覧'!C71*10000*-1 -> -1.1000845e+08 | R45: =Q45-Q44 -> -2353554.4 | S45: ※差額あっても異常ではない
A46: 146 | B46: 物件名予備26 | C46: 一棟名称 | N46: 44 | O46: asset | P46: 物件関連元金総計(月額)*12 | Q46: =asset!E38*12 -> 153441060
A47: 147 | B47: 物件名予備27 | C47: 一棟名称 | N47: 45 | O47: 3物件一覧 | P47: 元金返済/年額 | Q47: ='3物件一覧'!C72*10000 -> -153441060 | R47: =Q46+Q47 -> 0
A48: 148 | B48: 物件名予備28 | C48: 一棟名称 | N48: 46 | O48: asset | P48: 想定税引後CF | Q48: =asset!E72 -> 41534445
A49: 149 | B49: 物件名予備29 | C49: 一棟名称 | N49: 47 | O49: 3物件一覧 | P49: 想定税引後CF | Q49: ='3物件一覧'!C73*10000 -> 43887999
A50: 150 | B50: 物件名予備30 | C50: 一棟名称 | N50: 48 | O50: n/a | P50: 上記差額 | Q50: =Q49-Q48 -> 2353554.4 | R50: =Q50-R43 -> -5.2154064e-08
A51: 151 | B51: 物件名予備31 | C51: 一棟名称
A52: 152 | B52: 物件名予備32 | C52: 一棟名称
A53: 153 | B53: 物件名予備33 | C53: 一棟名称
A54: 154 | B54: 物件名予備34 | C54: 一棟名称
A55: 155 | B55: 物件名予備35 | C55: 一棟名称
A56: 156 | B56: 物件名予備36 | C56: 一棟名称
A57: 157 | B57: 物件名予備37 | C57: 一棟名称
A58: 158 | B58: 物件名予備38 | C58: 一棟名称
A59: 159 | B59: 物件名予備39 | C59: 一棟名称
A60: 160 | B60: 物件名予備40 | C60: 一棟名称
A61: 221 | B61: ビジネス新大阪123号 | C61: 区分名称
A62: 222 | B62: プラウD目白301号 | C62: 区分名称
... A222: 570 | B222: 金融機関予備58 | C222: 金融機関名
A223: 601 | B223: 不動産購入 | C223: 借入一覧 | D223: 使途ID | E223: 変更不可
A224: 602 | B224: 修繕資金 | C224: 借入一覧 | D224: 使途ID | E224: 変更不可
A225: 603 | B225: 運転資金 | C225: 借入一覧 | D225: 使途ID | E225: 変更不可
A226: 604 | B226: 他業借入 | C226: 借入一覧 | D226: 使途ID | E226: 変更不可
A227: 605 | B227: 住宅ローン | C227: 借入一覧 | D227: 使途ID | E227: 変更不可
A228: 606 | B228: 親族借入 | C228: 借入一覧 | D228: 使途ID | E228: 変更不可
A229: 607 | B229: その他(間接部門) | C229: 借入一覧 | D229: 使途ID | E229: 変更不可
A230: 608 | B230: その他(賃貸部門) | C230: 借入一覧 | D230: 使途ID | E230: 変更不可
A231: 611 | B231: 無担保 | C231: 借入一覧 | D231: 担保物件ID | E231: 変更不可
A232: 612 | B232: 預金担保 | C232: 借入一覧 | D232: 担保物件ID | E232: 変更不可
A233: 613 | B233: ユーザー定義担保物件 | C233: 借入一覧 | D233: 担保物件ID
A234: 621 | B234: 対象物件なし(運転資金) | C234: 借入一覧 | D234: 対象物件ID | E234: 変更不可
A235: 622 | B235: 複数の物件一括 | C235: 借入一覧 | D235: 対象物件ID | E235: 変更不可
A236: 623 | B236: ユーザー定義対象物件 | C236: 借入一覧 | D236: 対象物件ID
A237: 631 | B237: 住居 | C237: 賃料一覧 | D237: クラスID | E237: 変更不可
A238: 632 | B238: 事務所 | C238: 賃料一覧 | D238: クラスID | E238: 変更不可
A239: 633 | B239: 店舗 | C239: 賃料一覧 | D239: クラスID | E239: 変更不可
A240: 634 | B240: 駐車場 | C240: 賃料一覧 | D240: クラスID | E240: 変更不可
A241: 635 | B241: アンテナ | C241: 賃料一覧 | D241: クラスID | E241: 変更不可
A242: 636 | B242: 倉庫 | C242: 賃料一覧 | D242: クラスID | E242: 変更不可
A243: 637 | B243: 自販機 | C243: 賃料一覧 | D243: クラスID | E243: 変更不可
A244: 638 | B244: オペレーショナル | C244: 賃料一覧 | D244: クラスID | E244: 変更不可
A245: 639 | B245: その他 | C245: 賃料一覧 | D245: クラスID | E245: 変更不可
A246: 640 | B246: ユーザー設定クラス | C246: 賃料一覧 | D246: クラスID
A247: 651 | B247: 火災保険料 | C247: BM集計 | D247: BM費用ID | E247: 変更不可
A248: 652 | B248: 水道料金 | C248: BM集計 | D248: BM費用ID | E248: 変更不可
A249: 653 | B249: 電気料金(電灯) | C249: BM集計 | D249: BM費用ID | E249: 変更不可
A250: 654 | B250: 電気料金(低圧) | C250: BM集計 | D250: BM費用ID | E250: 変更不可
A251: 655 | B251: 建物管理料 | C251: BM集計 | D251: BM費用ID | E251: 変更不可
A252: 656 | B252: 区分管理費 | C252: BM集計 | D252: BM費用ID | E252: 変更不可
A253: 657 | B253: 区分修繕積立金 | C253: BM集計 | D253: BM費用ID | E253: 変更不可
A254: 658 | B254: その他 | C254: BM集計 | D254: BM費用ID | E254: 変更不可
A255: 659 | B255: 立替金 | C255: BM集計 | D255: BM費用ID | E255: 変更不可
A256: 660 | B256: ユーザー設定BM費用 | C256: BM集計 | D256: BM費用ID
A257: 661 | B257: 土地 | C257: 筆一覧 | D257: 資産クラスID | E257: 変更不可
A258: 662 | B258: 土地(道路) | C258: 筆一覧 | D258: 資産クラスID | E258: 変更不可
A259: 663 | B259: 土地(私道) | C259: 筆一覧 | D259: 資産クラスID | E259: 変更不可
...

Sheet asset
A1: 物件情報入力 | F1: 水色のセルのみ入力します。
A2: ID | B2: 項目 | C2: 規則 | D2: 入力 | E2: 合計 | F2: 物件1 | G2: 物件2 | H2: 物件3 | I2: 物件4 | J2: 物件5 | K2: 物件6 | L2: 物件7 | M2: 物件8 | N2: 物件9 | O2: 物件10 | P2: 物件11 | Q2: 物件12 | R2: 物件13 | S2: 物件14 | T2: 物件15 | U2: 物件16 | V2: 物件17 | W2: 物件18 | X2: 物件19 | Y2: 物件20 | Z2: 物件21 | AA2: 物件22 | AB2: 物件23 | AC2: 物件24 | AD2: 物件25 | AE2: 物件26 | AF2: 物件27 | AG2: 物件28 | AH2: 物件29 | AI2: 物件30 | AJ2: 物件31 | AK2: 物件32 | AL2: 物件33 | AM2: 物件34 | AN2: 物件35 | AO2: 物件36 | AP2: 物件37 | AQ2: 物件38 | AR2: 物件39 | AS2: 物件40 | AT2: 物件41 | AU2: 物件42 | AV2: 物件43 | AW2: 物件44 | AX2: 物件45 | AY2: 物件46 | AZ2: 物件47 | BA2: 物件48 | BB2: 物件49 | BC2: 物件50 | BD2: 物件51 | BE2: 物件52 | BF2: 物件53 | BG2: 物件54 | BH2: 物件55 | BI2: 物件56 | BJ2: 物件57 | BK2: 物件58 | BL2: 物件59 | BM2: 物件60 | BN2: 物件61 | BO2: 物件62 | BP2: 物件63 | BQ2: 物件64 | BR2: 物件65 | BS2: 物件66 | BT2: 物件67 | BU2: 物件68 | BV2: 物件69 | BW2: 物件70 | BX2: 物件71 | BY2: 物件72 | BZ2: 物件73 | CA2: 物件74 | CB2: 物件75
A3: 0 | B3: 物件設定 | C3: - | D3: - | E3: - | F3: - | G3: - | H3: - | I3: - | J3: - | K3: - | L3: - | M3: - | N3: - | O3: - | P3: - | Q3: - | R3: - | S3: - | T3: - | U3: - | V3: - | W3: - | X3: - | Y3: - | Z3: - | AA3: - | AB3: - | AC3: - | AD3: - | AE3: - | AF3: - | AG3: - | AH3: - | AI3: - | AJ3: - | AK3: - | AL3: - | AM3: - | AN3: - | AO3: - | AP3: - | AQ3: - | AR3: - | AS3: - | AT3: - | AU3: - | AV3: - | AW3: - | AX3: - | AY3: - | AZ3: - | BA3: - | BB3: - | BC3: - | BD3: - | BE3: - | BF3: - | BG3: - | BH3: - | BI3: - | BJ3: - | BK3: - | BL3: - | BM3: - | BN3: - | BO3: - | BP3: - | BQ3: - | BR3: - | BS3: - | BT3: - | BU3: - | BV3: - | BW3: - | BX3: - | BY3: - | BZ3: - | CA3: - | CB3: -
A4: 1 | B4: 物件ID | C4: 数値（3桁） | D4: 必須 | E4: - | F4: 101 | G4: 102 | H4: 103 | I4: 104 | J4: 105 | K4: 106 | L4: 107 | M4: 109 | N4: 110 | O4: 111 | P4: 112 | Q4: 113 | R4: 114 | S4: 115 | T4: 116 | U4: 117 | V4: 118 | W4: 120 | X4: 221 | Y4: 222 | Z4: 121 | AA4: 122 | AB4: 123 | AC4: 124
A5: 2 | B5: 売却済みフラグ | C5: yes/no | D5: 必須 | E5: - | F5: no | G5: no | H5: no | I5: no | J5: no | K5: no | L5: no | M5: no | N5: yes | O5: no | P5: no | Q5: no | R5: no | S5: no | T5: no | U5: no | V5: yes | W5: no | X5: no | Y5: no | Z5: no | AA5: no | AB5: no | AC5: no
A6: 3 | B6: 物件名称 | C6: 自動 | D6: - | E6: - | F6: =VLOOKUP(F4,id_settings,2,FALSE) -> 西池袋駅前ビル | G6: =VLOOKUP(G4,id_settings,2,FALSE) -> 池袋ハウス | H6: =VLOOKUP(H4,id_settings,2,FALSE) -> カーサ目白台ハウス | I6: =VLOOKUP(I4,id_settings,2,FALSE) -> コアプラス池袋 | J6: =VLOOKUP(J4,id_settings,2,FALSE) -> 目白アパート | K6: =VLOOKUP(K4,id_settings,2,FALSE) -> 東池袋ハイツ | L6: =VLOOKUP(L4,id_settings,2,FALSE) -> メゾン雑司ヶ谷 | M6: =VLOOKUP(M4,id_settings,2,FALSE) -> カーサ南池袋 | ... CB6: =VLOOKUP(CB4,id_settings,2,FALSE) -> #N/A
A7: 4 | B7: 物件概要 | C7: - | D7: - | E7: - | F7: - | G7: - | H7: - | I7: - | J7: - | K7: - | L7: - | M7: - | N7: - | O7: - | P7: - | Q7: - | R7: - | S7: - | T7: - | U7: - | V7: - | W7: - | X7: - | Y7: - | Z7: - | AA7: - | AB7: - | AC7: - | AD7: - | AE7: - | AF7: - | AG7: - | AH7: - | AI7: - | AJ7: - | AK7: - | AL7: - | AM7: - | AN7: - | AO7: - | AP7: - | AQ7: - | AR7: - | AS7: - | AT7: - | AU7: - | AV7: - | AW7: - | AX7: - | AY7: - | AZ7: - | BA7: - | BB7: - | BC7: - | BD7: - | BE7: - | BF7: - | BG7: - | BH7: - | BI7: - | BJ7: - | BK7: - | BL7: - | BM7: - | BN7: - | BO7: - | BP7: - | BQ7: - | BR7: - | BS7: - | BT7: - | BU7: - | BV7: - | BW7: - | BX7: - | BY7: - | BZ7: - | CA7: - | CB7: -
A8: 5 | B8: 所有法人ID | C8: 数値（3桁） | D8: 必須 | E8: - | F8: 401 | G8: 402 | H8: 403 | I8: 404 | J8: 405 | K8: 406 | L8: 407 | M8: 409 | N8: 410 | O8: 401 | P8: 402 | Q8: 404 | R8: 404 | S8: 405 | T8: 406 | U8: 407 | V8: 410 | W8: 408 | X8: 408 | Y8: 401 | Z8: 408 | AA8: 408 | AB8: 412 | AC8: 412
A9: 6 | B9: 現所有者 | C9: 自動 | D9: - | E9: - | F9: =VLOOKUP(F8,id_settings,2,FALSE) -> コアプラス東京株式会社 | G9: =VLOOKUP(G8,id_settings,2,FALSE) -> コアプラス名古屋株式会社 | H9: =VLOOKUP(H8,id_settings,2,FALSE) -> 有限会社コアプラス2号 | I9: =VLOOKUP(I8,id_settings,2,FALSE) -> コアプラス大阪株式会社 | J9: =VLOOKUP(J8,id_settings,2,FALSE) -> コアプラス仙台株式会社 | K9: =VLOOKUP(K8,id_settings,2,FALSE) -> コアプラス札幌株式会社 | L9: =VLOOKUP(L8,id_settings,2,FALSE) -> コアプラス福岡株式会社 | M9: =VLOOKUP(M8,id_settings,2,FALSE) -> コアプラス四国株式会社 | ... CB9: =VLOOKUP(CB8,id_settings,2,FALSE) -> #N/A
A10: 7 | B10: 交通 | C10: 文字列 | D10: - | E10: - | F10: 山手線「池袋」歩7分 | G10: 山手線「池袋」歩8分 | H10: 山手線「目白」歩10分 | I10: 山手線「池袋」歩10分 | J10: 西武池袋線｢椎名町｣歩7分 | K10: 中央線「高円寺」 歩4分 | L10: 東京メトロ副都心線「雑司ヶ谷」歩8分 | M10: 山手線「池袋」歩7分 | N10: 東北本線「仙台」歩10分 | O10: 山手線「目白」歩10分 | P10: 山手線「池袋」歩10分 | Q10: 西武池袋線｢椎名町｣歩7分 | R10: 中央線「高円寺」 歩4分 | S10: 東京メトロ副都心線「雑司ヶ谷」歩8分 | T10: 御堂筋線「梅田」歩7分 | U10: 御堂筋線「梅田」歩7分 | V10: 田園都市線「青葉台」歩5分 | W10: 山手線「池袋」歩10分 都電荒川線「雑司ヶ谷」歩5分 | X10: 西武池袋線｢椎名町｣歩7分 | Y10: 山手線「目白」歩10分 | Z10: 山手線「目白」歩10分 | AA10: 山手線「目白」歩10分 | AB10: 盛岡市高松エリア | AC10: 盛岡市高松エリア
A11: 8 | B11: 住所 | C11: 文字列 | D11: - | E11: - | F11: 豊島区西池袋3-7-21 | G11: 豊島区池袋6-1-22 | H11: 文京区目白台7-1-19 | I11: 豊島区池袋9-2-1 | J11: 豊島区目白6-11-21 | K11: 杉並区高円寺9-1-6 | L11: 豊島区西池袋3-7-21 | M11: 文京区目白台7-1-19 | N11: 宮城県仙台市宮城野区名掛丁991-55 | O11: 豊島区目白6-11-21 | P11: 豊島区目白6-11-21 | Q11: 文京区目白台7-1-19 | R11: 杉並区高円寺9-1-6 | S11: 豊島区池袋9-2-1 | T11: 大阪府大阪市北区梅田3-9-9 | U11: 大阪府大阪市北区梅田3-9-9 | V11: 神奈川県横浜市青葉区青葉台9-25-1 | W11: 豊島区池袋6-1-22 | X11: 豊島区目白6-11-21 | Y11: 豊島区目白7-11-9 | Z11: 豊島区目白7-15-5 | AA11: 豊島区目白7-15-6 | AB11: 岩手県盛岡市高松二丁目 | AC11: 岩手県盛岡市高松二丁目
A12: 9 | B12: 一棟or区分 | C12: 文字列 | D12: - | E12: - | F12: 一棟 | G12: 一棟 | H12: 一棟 | I12: 一棟 | J12: 一棟 | K12: 一棟 | L12: 一棟 | M12: 一棟 | N12: 一棟 | O12: 一棟 | P12: 一棟 | Q12: 一棟 | R12: 一棟 | S12: 一棟 | T12: 一棟 | U12: 一棟 | V12: 一棟 | W12: 一棟 | X12: 区分 | Y12: 区分 | Z12: 区分 | AA12: 区分 | AB12: 一棟 | AC12: 一棟
A13: 10 | B13: 権利形態 | C13: 文字列 | D13: - | E13: - | F13: 所有権 | G13: 所有権 | H13: 所有権 | I13: 所有権 | J13: 所有権 | K13: 所有権 | L13: 所有権 | M13: 所有権 | N13: 所有権 | O13: 所有権 | P13: 所有権 | Q13: 所有権 | R13: 所有権 | S13: 所有権 | T13: 所有権 | U13: 所有権 | V13: 所有権 | W13: 所有権 | X13: 借地権 | Y13: 所有権 | Z13: 所有権 | AA13: 所有権 | AB13: 所有権 | AC13: 所有権
A14: 11 | B14: 建物構造 | C14: 文字列 | D14: - | E14: - | F14: RC/B1F-4F | G14: RC/B1F-3F | H14: RC/1-6F | I14: RC/1-5F | J14: RC/B1-5F | K14: 鉄骨造/1-8F | L14: 鉄骨造/1-8F | M14: RC/1-5F | N14: RC/B1-5F | O14: RC/1-11F | P14: RC/1-4F | Q14: 鉄骨/B1-3F | R14: SRC/1-8F | S14: RC/B1-5F | T14: RC/1-4F | U14: RC/1-4F | V14: RC/B1-5F | W14: 鉄骨造/1-4F | X14: RC/1-4F | Y14: RC/B1-5F | Z14: 木造/B1-2F | AA14: 木造/B1-2F | AB14: 要確認 | AC14: 木造・貸家3棟（要確認）
A15: 12 | B15: 建物築年 | C15: 日付 | D15: - | E15: - | F15: 33639 | G15: 34852 | H15: 36647 | I15: 28501 | J15: 37053 | K15: 37296 | L15: 33639 | M15: 36647 | N15: 34824 | O15: 37053 | P15: 37296 | Q15: 33639 | R15: 34852 | S15: 36647 | T15: 28501 | U15: 28501 | V15: 34100 | W15: 34852 | X15: 37053 | Y15: 37296 | Z15: 37296 | AA15: 37296
A16: 13 | B16: 用途と計画 | C16: 文字列 | D16: - | E16: - | F16: 長期保有 | G16: 短期転売 | H16: 長期保有 | I16: 長期保有 | J16: 長期保有 | K16: 長期保有 | L16: 長期保有 | M16: 長期保有 | N16: 売却済み | O16: 長期保有 | P16: 長期保有 | Q16: 長期保有 | R16: 長期保有 | S16: 長期保有 | T16: 長期保有 | U16: 長期保有 | V16: 売却済み | W16: 長期保有 | X16: 大阪拠点 | Y16: 社長自宅 | Z16: 長期保有 | AA16: 長期保有 | AB16: 長期保有 | AC16: 長期保有（将来解体・新築検討）
A17: 14 | B17: 購入年月 | C17: 日付 | D17: - | E17: - | F17: 44624 | G17: 44348 | H17: 44352 | I17: 43894 | J17: 43926 | K17: 43836 | L17: 43621 | M17: 43256 | N17: 42615 | O17: 43227 | P17: 42979 | Q17: 42887 | R17: 42525 | S17: 42523 | T17: 42039 | U17: 42039 | V17: 42342 | W17: 43717 | X17: 44146 | Y17: 43507 | Z17: 43507 | AA17: 43507 | AB17: 2026/8/14 | AC17: 2026/8/14
A18: 15 | B18: 賃貸資産当初購入価格 | C18: 数値（\） | D18: 必須 | E18: =SUMIF(F5:CH5,"no",F18:CH18) -> 5239100000 | F18: 227000000 | G18: 415000000 | H18: 420000000 | I18: 94750000 | J18: 295000000 | K18: 436000000 | L18: 392000000 | M18: 190000000 | N18: 392000000 | O18: 300000000 | P18: 440000000 | Q18: 480000000 | R18: 210000000 | S18: 550000000 | T18: 354000000 | U18: 130000000 | V18: 436000000 | W18: 145000000 | X18: 5350000 | Y18: 75000000 | Z18: 50000000 | AA18: 30000000 | AB18: 37000000 | AC18: 0
A19: 16 | B19: 物件メモ | C19: 文字列 | D19: - | E19: - | F19: 駅前立地 | Z19: 二棟一括購入 | AA19: 二棟一括購入 | AB19: 花みずきと一括3,700万円。案分は契約書確定後修正。管理:大学生協 | AC19: 価格はアーバンキューブ側へ一括計上中（案分未定）。管理:トラステン。10-6北側塀の越境確認中
A20: 17 | B20: 主たる借入 | C20: - | D20: - | E20: - | F20: - | G20: - | H20: - | I20: - | J20: - | K20: - | L20: - | M20: - | N20: - | O20: - | P20: - | Q20: - | R20: - | S20: - | T20: - | U20: - | V20: - | W20: - | X20: - | Y20: - | Z20: - | AA20: - | AB20: - | AC20: - | AD20: - | AE20: - | AF20: - | AG20: - | AH20: - | AI20: - | AJ20: - | AK20: - | AL20: - | AM20: - | AN20: - | AO20: - | AP20: - | AQ20: - | AR20: - | AS20: - | AT20: - | AU20: - | AV20: - | AW20: - | AX20: - | AY20: - | AZ20: - | BA20: - | BB20: - | BC20: - | BD20: - | BE20: - | BF20: - | BG20: - | BH20: - | BI20: - | BJ20: - | BK20: - | BL20: - | BM20: - | BN20: - | BO20: - | BP20: - | BQ20: - | BR20: - | BS20: - | BT20: - | BU20: - | BV20: - | BW20: - | BX20: - | BY20: - | BZ20: - | CA20: - | CB20: -
A21: 18 | B21: 主たる融資ID | C21: 数値（3桁） | D21: - | E21: - | F21: 806 | G21: 801 | H21: 807 | I21: 802 | J21: 803 | K21: 805 | L21: 808 | M21: 809 | N21: - | O21: 811 | P21: 812 | Q21: 813 | R21: 814 | S21: 815 | T21: 816 | U21: 817 | V21: 111 | W21: 820 | Y21: 825 | Z21: 821 | AA21: 821 | AB21: 833 | AC21: 833
A22: 19 | B22: 借入金融機関 | C22: 自動 | D22: - | E22: - | F22: =VLOOKUP(F21,kariire_list,4,FALSE) -> 嘉手納銀行 | G22: =VLOOKUP(G21,kariire_list,4,FALSE) -> 首里信金 | H22: =VLOOKUP(H21,kariire_list,4,FALSE) -> 奄美信金 | I22: =VLOOKUP(I21,kariire_list,4,FALSE) -> 名護信金 | J22: =VLOOKUP(J21,kariire_list,4,FALSE) -> 読谷信金 | K22: =VLOOKUP(K21,kariire_list,4,FALSE) -> 恩納銀行 | L22: =VLOOKUP(L21,kariire_list,4,FALSE) -> 竹富信金 | M22: =VLOOKUP(M21,kariire_list,4,FALSE) -> 西表信金 | ... CB22: =VLOOKUP(CB21,kariire_list,4,FALSE) -> #N/A
A23: 20 | B23: 当初借入金額 | C23: 自動 | D23: - | E23: =IFERROR(GETPIVOTDATA("14.当初借入額",pivot!$FN$6,"9.使途","不動産購入"),0)+IFERROR(GETPIVOTDATA("14.当初借入額",pivot!$FN$6,"9.使途","住宅ローン"),0) -> 5264500000 | F23: =IFERROR(VLOOKUP(F21,kariire_list,14,FALSE),"") -> 226000000 | G23: =IFERROR(VLOOKUP(G21,kariire_list,14,FALSE),"") -> 550000000 | H23: =IFERROR(VLOOKUP(H21,kariire_list,14,FALSE),"") -> 413500000 | I23: =IFERROR(VLOOKUP(I21,kariire_list,14,FALSE),"") -> 85000000 | J23: =IFERROR(VLOOKUP(J21,kariire_list,14,FALSE),"") -> 265000000 | K23: =IFERROR(VLOOKUP(K21,kariire_list,14,FALSE),"") -> 376000000 | L23: =IFERROR(VLOOKUP(L21,kariire_list,14,FALSE),"") -> 392000000 | M23: =IFERROR(VLOOKUP(M21,kariire_list,14,FALSE),"") -> 180000000 | ... CB23: =IFERROR(VLOOKUP(CB21,kariire_list,14,FALSE),"")
A24: 21 | B24: 購入時自己資金 | C24: 自動 | D24: - | E24: =E18-E23 -> -25400000 | F24: =IFERROR(F18-F23,"") -> 1000000 | G24: =IFERROR(G18-G23,"") -> -135000000 | H24: =IFERROR(H18-H23,"") -> 6500000 | I24: =IFERROR(I18-I23,"") -> 9750000 | J24: =IFERROR(J18-J23,"") -> 30000000 | K24: =IFERROR(K18-K23,"") -> 60000000 | L24: =IFERROR(L18-L23,"") -> 0 | M24: =IFERROR(M18-M23,"") -> 10000000 | ... CB24: =IFERROR(CB18-CB23,"")
A25: 22 | B25: 金利 | C25: 自動 | D25: - | E25: - | F25: =VLOOKUP(F21,kariire_list,16,FALSE) -> 1 | G25: =VLOOKUP(G21,kariire_list,16,FALSE) -> 1.65 | H25: =VLOOKUP(H21,kariire_list,16,FALSE) -> 1.1 | I25: =VLOOKUP(I21,kariire_list,16,FALSE) -> 1 | J25: =VLOOKUP(J21,kariire_list,16,FALSE) -> 1 | K25: =VLOOKUP(K21,kariire_list,16,FALSE) -> 1 | L25: =VLOOKUP(L21,kariire_list,16,FALSE) -> 1.2 | M25: =VLOOKUP(M21,kariire_list,16,FALSE) -> 1.5 | ... CB25: =VLOOKUP(CB21,kariire_list,16,FALSE) -> #N/A
A26: 23 | B26: 融資期間 | C26: 自動 | D26: - | E26: - | F26: =VLOOKUP(F21,kariire_list,18,FALSE) -> 25 | G26: =VLOOKUP(G21,kariire_list,18,FALSE) -> 35 | H26: =VLOOKUP(H21,kariire_list,18,FALSE) -> 30 | I26: =VLOOKUP(I21,kariire_list,18,FALSE) -> 25 | J26: =VLOOKUP(J21,kariire_list,18,FALSE) -> 25 | K26: =VLOOKUP(K21,kariire_list,18,FALSE) -> 30 | L26: =VLOOKUP(L21,kariire_list,18,FALSE) -> 30 | M26: =VLOOKUP(M21,kariire_list,18,FALSE) -> 30 | ... CB26: =VLOOKUP(CB21,kariire_list,18,FALSE) -> #N/A
A27: 24 | B27: 借入返済 | F27: - | G27: - | H27: - | I27: - | J27: - | K27: - | L27: - | M27: - | N27: - | O27: - | P27: - | Q27: - | R27: - | S27: - | T27: - | U27: - | V27: - | W27: - | X27: - | Y27: - | Z27: - | AA27: - | AB27: - | AC27: - | AD27: - | AE27: - | AF27: - | AG27: - | AH27: - | AI27: - | AJ27: - | AK27: - | AL27: - | AM27: - | AN27: - | AO27: - | AP27: - | AQ27: - | AR27: - | AS27: - | AT27: - | AU27: - | AV27: - | AW27: - | AX27: - | AY27: - | AZ27: - | BA27: - | BB27: - | BC27: - | BD27: - | BE27: - | BF27: - | BG27: - | BH27: - | BI27: - | BJ27: - | BK27: - | BL27: - | BM27: - | BN27: - | BO27: - | BP27: - | BQ27: - | BR27: - | BS27: - | BT27: - | BU27: - | BV27: - | BW27: - | BX27: - | BY27: - | BZ27: - | CA27: - | CB27: -
A28: 25 | B28: 複数棟一括融資の名称 | C28: 文字列 | D28: - | Z28: 目白アパート1号2号_二棟一括 | AA28: 目白アパート1号2号_二棟一括
A29: 26 | B29: 複数棟一括融資の按分率 | C29: 数値（%） | D29: - | Z29: =5/8 -> 0.625 | AA29: =3/8 -> 0.375
A30: 27 | B30: 複数棟一括融資の残債 | C30: 自動 | D30: - | E30: =SUMIF(F5:CH5,"no",F30:CH30) -> 75151106 | F30: =IFERROR( (GETPIVOTDATA("合計 / 25.残債",pivot!$EG$4,"11.対象物件",F28))*F29,0) -> 0 | G30: =IFERROR( (GETPIVOTDATA("合計 / 25.残債",pivot!$EG$4,"11.対象物件",G28))*G29,0) -> 0 | H30: =IFERROR( (GETPIVOTDATA("合計 / 25.残債",pivot!$EG$4,"11.対象物件",H28))*H29,0) -> 0 | I30: =IFERROR( (GETPIVOTDATA("合計 / 25.残債",pivot!$EG$4,"11.対象物件",I28))*I29,0) -> 0 | J30: =IFERROR( (GETPIVOTDATA("合計 / 25.残債",pivot!$EG$4,"11.対象物件",J28))*J29,0) -> 0 | K30: =IFERROR( (GETPIVOTDATA("合計 / 25.残債",pivot!$EG$4,"11.対象物件",K28))*K29,0) -> 0 | L30: =IFERROR( (GETPIVOTDATA("合計 / 25.残債",pivot!$EG$4,"11.対象物件",L28))*L29,0) -> 0 | M30: =IFERROR( (GETPIVOTDATA("合計 / 25.残債",pivot!$EG$4,"11.対象物件",M28))*M29,0) -> 0 | ... CB30: =IFERROR( (GETPIVOTDATA("合計 / 25.残債",pivot!$EG$4,"11.対象物件",CB28))*CB29,0) -> 0
A31: 28 | B31: 物件ID単体に対する残債計 | C31: 自動 | D31: - | E31: =SUMIF(F5:CH5,"no",F31:CH31) -> 4341852165 | F31: =IFERROR(GETPIVOTDATA("合計 / 25.残債",pivot!$EG$4,"11.対象物件",F6),0) -> 166166517 | G31: =IFERROR(GETPIVOTDATA("合計 / 25.残債",pivot!$EG$4,"11.対象物件",G6),0) -> 489470974 | H31: =IFERROR(GETPIVOTDATA("合計 / 25.残債",pivot!$EG$4,"11.対象物件",H6),0) -> 325693047 | I31: =IFERROR(GETPIVOTDATA("合計 / 25.残債",pivot!$EG$4,"11.対象物件",I6),0) -> 70446823 | J31: =IFERROR(GETPIVOTDATA("合計 / 25.残債",pivot!$EG$4,"11.対象物件",J6),0) -> 199606609 | K31: =IFERROR(GETPIVOTDATA("合計 / 25.残債",pivot!$EG$4,"11.対象物件",K6),0) -> 289146337 | L31: =IFERROR(GETPIVOTDATA("合計 / 25.残債",pivot!$EG$4,"11.対象物件",L6),0) -> 313706389 | M31: =IFERROR(GETPIVOTDATA("合計 / 25.残債",pivot!$EG$4,"11.対象物件",M6),0) -> 146247653 | ... CB31: =IFERROR(GETPIVOTDATA("合計 / 25.残債",pivot!$EG$4,"11.対象物件",CB6),0) -> 0
A32: 29 | B32: 複数棟一括融資の金利(月額) | C32: 自動 | D32: - | E32: =SUMIF(F5:CH5,"no",F32:CH32) -> 100486 | F32: =IFERROR((GETPIVOTDATA("合計 / 23.利息月額",pivot!$EG$4,"11.対象物件",F28)*F29),0) -> 0 | G32: =IFERROR((GETPIVOTDATA("合計 / 23.利息月額",pivot!$EG$4,"11.対象物件",G28)*G29),0) -> 0 | H32: =IFERROR((GETPIVOTDATA("合計 / 23.利息月額",pivot!$EG$4,"11.対象物件",H28)*H29),0) -> 0 | I32: =IFERROR((GETPIVOTDATA("合計 / 23.利息月額",pivot!$EG$4,"11.対象物件",I28)*I29),0) -> 0 | J32: =IFERROR((GETPIVOTDATA("合計 / 23.利息月額",pivot!$EG$4,"11.対象物件",J28)*J29),0) -> 0 | K32: =IFERROR((GETPIVOTDATA("合計 / 23.利息月額",pivot!$EG$4,"11.対象物件",K28)*K29),0) -> 0 | L32: =IFERROR((GETPIVOTDATA("合計 / 23.利息月額",pivot!$EG$4,"11.対象物件",L28)*L29),0) -> 0 | M32: =IFERROR((GETPIVOTDATA("合計 / 23.利息月額",pivot!$EG$4,"11.対象物件",M28)*M29),0) -> 0 | ... CB32: =IFERROR((GETPIVOTDATA("合計 / 23.利息月額",pivot!$EG$4,"11.対象物件",CB28)*CB29),0) -> 0
A33: 30 | B33: 物件ID単体に対する金利計(月額) | C33: 自動 | D33: - | E33: =SUMIF(F5:CH5,"no",F33:CH33) -> 4910995 | F33: =IFERROR(GETPIVOTDATA("合計 / 23.利息月額",pivot!$EG$4,"11.対象物件",F6),0) -> 139065 | G33: =IFERROR(GETPIVOTDATA("合計 / 23.利息月額",pivot!$EG$4,"11.対象物件",G6),0) -> 674466 | H33: =IFERROR(GETPIVOTDATA("合計 / 23.利息月額",pivot!$EG$4,"11.対象物件",H6),0) -> 299492 | I33: =IFERROR(GETPIVOTDATA("合計 / 23.利息月額",pivot!$EG$4,"11.対象物件",I6),0) -> 58976 | J33: =IFERROR(GETPIVOTDATA("合計 / 23.利息月額",pivot!$EG$4,"11.対象物件",J6),0) -> 166971 | K33: =IFERROR(GETPIVOTDATA("合計 / 23.利息月額",pivot!$EG$4,"11.対象物件",K6),0) -> 241754 | L33: =IFERROR(GETPIVOTDATA("合計 / 23.利息月額",pivot!$EG$4,"11.対象物件",L6),0) -> 314688 | M33: =IFERROR(GETPIVOTDATA("合計 / 23.利息月額",pivot!$EG$4,"11.対象物件",M6),0) -> 183356 | ... CB33: =IFERROR(GETPIVOTDATA("合計 / 23.利息月額",pivot!$EG$4,"11.対象物件",CB6),0) -> 0
A34: 31 | B34: 複数棟一括融資の元金(月額) | C34: 自動 | D34: - | E34: =SUMIF(F5:CH5,"no",F34:CH34) -> 213926 | F34: =IFERROR((GETPIVOTDATA("合計 / 22.元金返済月額",pivot!$EG$4,"11.対象物件",F28)*F29),0) -> 0 | G34: =IFERROR((GETPIVOTDATA("合計 / 22.元金返済月額",pivot!$EG$4,"11.対象物件",G28)*G29),0) -> 0 | H34: =IFERROR((GETPIVOTDATA("合計 / 22.元金返済月額",pivot!$EG$4,"11.対象物件",H28)*H29),0) -> 0 | I34: =IFERROR((GETPIVOTDATA("合計 / 22.元金返済月額",pivot!$EG$4,"11.対象物件",I28)*I29),0) -> 0 | J34: =IFERROR((GETPIVOTDATA("合計 / 22.元金返済月額",pivot!$EG$4,"11.対象物件",J28)*J29),0) -> 0 | K34: =IFERROR((GETPIVOTDATA("合計 / 22.元金返済月額",pivot!$EG$4,"11.対象物件",K28)*K29),0) -> 0 | L34: =IFERROR((GETPIVOTDATA("合計 / 22.元金返済月額",pivot!$EG$4,"11.対象物件",L28)*L29),0) -> 0 | M34: =IFERROR((GETPIVOTDATA("合計 / 22.元金返済月額",pivot!$EG$4,"11.対象物件",M28)*M29),0) -> 0 | ... CB34: =IFERROR((GETPIVOTDATA("合計 / 22.元金返済月額",pivot!$EG$4,"11.対象物件",CB28)*CB29),0) -> 0
A35: 32 | B35: 物件ID単体に対する元金計(月額) | C35: 自動 | D35: - | E35: =SUMIF(F5:CH5,"no",F35:CH35) -> 12572829 | F35: =IFERROR(GETPIVOTDATA("合計 / 22.元金返済月額",pivot!$EG$4,"11.対象物件",F6),0) -> 712666 | G35: =IFERROR(GETPIVOTDATA("合計 / 22.元金返済月額",pivot!$EG$4,"11.対象物件",G6),0) -> 1050252 | H35: =IFERROR(GETPIVOTDATA("合計 / 22.元金返済月額",pivot!$EG$4,"11.対象物件",H6),0) -> 1049552 | I35: =IFERROR(GETPIVOTDATA("合計 / 22.元金返済月額",pivot!$EG$4,"11.対象物件",I6),0) -> 328928 | J35: =IFERROR(GETPIVOTDATA("合計 / 22.元金返済月額",pivot!$EG$4,"11.対象物件",J6),0) -> 995627 | K35: =IFERROR(GETPIVOTDATA("合計 / 22.元金返済月額",pivot!$EG$4,"11.対象物件",K6),0) -> 970634 | L35: =IFERROR(GETPIVOTDATA("合計 / 22.元金返済月額",pivot!$EG$4,"11.対象物件",L6),0) -> 982474 | M35: =IFERROR(GETPIVOTDATA("合計 / 22.元金返済月額",pivot!$EG$4,"11.対象物件",M6),0) -> 437860 | ... CB35: =IFERROR(GETPIVOTDATA("合計 / 22.元金返済月額",pivot!$EG$4,"11.対象物件",CB6),0) -> 0
A36: 33 | B36: 物件関連残債総計 | C36: 自動 | D36: - | E36: =E30+E31 -> 4417003271 | F36: =F30+F31 -> 166166517 | G36: =G30+G31 -> 489470974 | H36: =H30+H31 -> 325693047 | I36: =I30+I31 -> 70446823 | J36: =J30+J31 -> 199606609 | K36: =K30+K31 -> 289146337 | L36: =L30+L31 -> 313706389 | ... CB36: =CB30+CB31 -> 0
A37: 34 | B37: 物件関連金利総計(月額) | C37: 自動 | D37: - | E37: =SUMIF(F5:CH5,"no",F37:CH37) -> 5011481 | F37: =F32+F33 -> 139065 | G37: =G32+G33 -> 674466 | H37: =H32+H33 -> 299492 | I37: =I32+I33 -> 58976 | J37: =J32+J33 -> 166971 | K37: =K32+K33 -> 241754 | L37: =L32+L33 -> 314688 | M37: =M32+M33 -> 183356 | ... CB37: =CB32+CB33 -> 0
A38: 35 | B38: 物件関連元金総計(月額) | C38: 自動 | D38: - | E38: =SUMIF(F5:CH5,"no",F38:CH38) -> 12786755 | F38: =F34+F35 -> 712666 | G38: =G34+G35 -> 1050252 | H38: =H34+H35 -> 1049552 | I38: =I34+I35 -> 328928 | J38: =J34+J35 -> 995627 | K38: =K34+K35 -> 970634 | L38: =L34+L35 -> 982474 | M38: =M34+M35 -> 437860 | ... CB38: =CB34+CB35 -> 0
A39: 36 | B39: 物件関連支払総計(月額) | C39: 自動 | D39: - | E39: =E38+E37 -> 17798236 | F39: =F38+F37 -> 851731 | G39: =G38+G37 -> 1724718 | H39: =H38+H37 -> 1349044 | I39: =I38+I37 -> 387904 | J39: =J38+J37 -> 1162598 | K39: =K38+K37 -> 1212388 | L39: =L38+L37 -> 1297162 | ... CB39: =CB38+CB37 -> 0
A40: 37 | B40: 評価額 | C40: - | D40: - | E40: - | F40: - | G40: - | H40: - | I40: - | J40: - | K40: - | L40: - | M40: - | N40: - | O40: - | P40: - | Q40: - | R40: - | S40: - | T40: - | U40: - | V40: - | W40: - | X40: - | Y40: - | Z40: - | AA40: - | AB40: - | AC40: - | AD40: - | AE40: - | AF40: - | AG40: - | AH40: - | AI40: - | AJ40: - | AK40: - | AL40: - | AM40: - | AN40: - | AO40: - | AP40: - | AQ40: - | AR40: - | AS40: - | AT40: - | AU40: - | AV40: - | AW40: - | AX40: - | AY40: - | AZ40: - | BA40: - | BB40: - | BC40: - | BD40: - | BE40: - | BF40: - | BG40: - | BH40: - | BI40: - | BJ40: - | BK40: - | BL40: - | BM40: - | BN40: - | BO40: - | BP40: - | BQ40: - | BR40: - | BS40: - | BT40: - | BU40: - | BV40: - | BW40: - | BX40: - | BY40: - | BZ40: - | CA40: - | CB40: -
A41: 38 | B41: 固定資産税路線価 | C41: 数値（\） | D41: - | E41: - | F41: 501000 | G41: 117000 | H41: 366000 | I41: 162100 | J41: 646000 | K41: 412000 | L41: 220000 | M41: 434000 | N41: 売却済み | O41: 436000 | P41: 420000 | Q41: 565000 | R41: 389000 | S41: 418000 | T41: 267000 | U41: 267000 | V41: 売却済み | W41: 655000 | X41: n/a | Y41: n/a | Z41: 655000 | AA41: 655000
A42: 39 | B42: 相続税路線価 | C42: 文字列 | D42: - | E42: - | F42: 580C | G42: 135D | H42: 430C | I42: 180D | J42: 770C | K42: 470C | L42: 270D | M42: 510C | N42: 売却済み | O42: 530C | P42: 550D | Q42: 620C | R42: 450C | S42: 460C | T42: 310D | U42: 310D | V42: 売却済み | W42: 760C | X42: n/a | Y42: n/a | Z42: 760C | AA42: 760C
A43: 40 | B43: 収益指標（参考値） | C43: - | D43: - | E43: - | F43: - | G43: - | H43: - | I43: - | J43: - | K43: - | L43: - | M43: - | N43: - | O43: - | P43: - | Q43: - | R43: - | S43: - | T43: - | U43: - | V43: - | W43: - | X43: - | Y43: - | Z43: - | AA43: - | AB43: - | AC43: - | AD43: - | AE43: - | AF43: - | AG43: - | AH43: - | AI43: - | AJ43: - | AK43: - | AL43: - | AM43: - | AN43: - | AO43: - | AP43: - | AQ43: - | AR43: - | AS43: - | AT43: - | AU43: - | AV43: - | AW43: - | AX43: - | AY43: - | AZ43: - | BA43: - | BB43: - | BC43: - | BD43: - | BE43: - | BF43: - | BG43: - | BH43: - | BI43: - | BJ43: - | BK43: - | BL43: - | BM43: - | BN43: - | BO43: - | BP43: - | BQ43: - | BR43: - | BS43: - | BT43: - | BU43: - | BV43: - | BW43: - | BX43: - | BY43: - | BZ43: - | CA43: - | CB43: -
A44: 41 | B44: 想定売却表面利回り | C44: 数値(%) | D44: - | F44: 0.065 | G44: 0.068 | H44: 0.075 | I44: 0.058 | J44: 0.059 | K44: 0.061 | L44: 0.065 | M44: 0.075 | N44: 売却済み | O44: 0.059 | P44: 0.061 | Q44: 0.065 | R44: 0.068 | S44: 0.075 | T44: 0.058 | U44: 0.058 | V44: 売却済み | W44: 0.068 | X44: 0.059 | Z44: 0.05 | AA44: 0.05 | AB44: 0.08 | AC44: 0.08
A45: 42 | B45: 想定物件時価 | C45: 自動 | D45: 必須 | E45: =SUMIF(F5:CH5,"no",F45:CH45) -> 6684000000 | F45: =IFERROR(ROUND(F53/F44,-6),0) -> 340000000 | G45: =IFERROR(ROUND(G53/G44,-6),0) -> 547000000 | H45: =IFERROR(ROUND(H53/H44,-6),0) -> 488000000 | I45: =IFERROR(ROUND(I53/I44,-6),0) -> 156000000 | J45: =IFERROR(ROUND(J53/J44,-6),0) -> 570000000 | K45: =IFERROR(ROUND(K53/K44,-6),0) -> 609000000 | L45: =IFERROR(ROUND(L53/L44,-6),0) -> 458000000 | M45: =IFERROR(ROUND(M53/M44,-6),0) -> 246000000 | ... X45: =IFERROR(ROUND(X53/X44,-6),0) -> 7000000 | Y45: 70000000 | Z45: =IFERROR(ROUND(Z53/Z44,-6),0) -> 79000000 | AA45: =IFERROR(ROUND(AA53/AA44,-6),0) -> 38000000 | AB45: =IFERROR(ROUND(AB53/AB44,-6),0) -> 0 | AC45: =IFERROR(ROUND(AC53/AC44,-6),0) -> 0 | AD45: =IFERROR(ROUND(AD53/AD44,-6),0) -> 0 | AE45: =IFERROR(ROUND(AE53/AE44,-6),0) -> 0 | AF45: =IFERROR(ROUND(AF53/AF44,-6),0) -> 0 | AG45: =IFERROR(ROUND(AG53/AG44,-6),0) -> 0 | ... CB45: =IFERROR(ROUND(CB53/CB44,-6),0) -> 0
A46: 43 | B46: 賃貸設定 | C46: - | D46: - | E46: - | F46: - | G46: - | H46: - | I46: - | J46: - | K46: - | L46: - | M46: - | N46: - | O46: - | P46: - | Q46: - | R46: - | S46: - | T46: - | U46: - | V46: - | W46: - | X46: - | Y46: - | Z46: - | AA46: - | AB46: - | AC46: - | AD46: - | AE46: - | AF46: - | AG46: - | AH46: - | AI46: - | AJ46: - | AK46: - | AL46: - | AM46: - | AN46: - | AO46: - | AP46: - | AQ46: - | AR46: - | AS46: - | AT46: - | AU46: - | AV46: - | AW46: - | AX46: - | AY46: - | AZ46: - | BA46: - | BB46: - | BC46: - | BD46: - | BE46: - | BF46: - | BG46: - | BH46: - | BI46: - | BJ46: - | BK46: - | BL46: - | BM46: - | BN46: - | BO46: - | BP46: - | BQ46: - | BR46: - | BS46: - | BT46: - | BU46: - | BV46: - | BW46: - | BX46: - | BY46: - | BZ46: - | CA46: - | CB46: -
A47: 44 | B47: 管理会社 | C47: 文字列 | D47: - | E47: - | F47: 慶良間管理(株) | G47: 自主管理 | H47: 慶良間管理(株) | I47: 慶良間管理(株) | J47: 慶良間管理(株) | K47: 慶良間管理(株) | L47: 慶良間管理(株) | M47: 慶良間管理(株) | N47: 売却済み | O47: 慶良間管理(株) | P47: 慶良間管理(株) | Q47: 慶良間管理(株) | R47: 慶良間管理(株) | S47: 慶良間管理(株) | T47: 大阪住居管理(株) | U47: 大阪住居管理(株) | V47: 売却済み | W47: 慶良間管理(株) | X47: 自主管理 | Y47: 自主管理 | Z47: 自主管理 | AA47: 自主管理 | AB47: 大学生協 | AC47: 不動産管理トラステン合同会社
A48: 45 | B48: PM管理料率(税込) | C48: 数値(%) | D48: 必須 | E48: - | F48: 0.055 | G48: 0.045 | H48: 0.055 | I48: 0.055 | J48: 0.055 | K48: 0.055 | L48: 0.055 | M48: 0.055 | N48: 売却済み | O48: 0.055 | P48: 0.055 | Q48: 0.055 | R48: 0.055 | S48: 0.055 | T48: 0.055 | U48: 0.055 | V48: 売却済み | W48: 0.055 | X48: 0 | Y48: 0 | Z48: 0 | AA48: 0 | AB48: 0.055 | AC48: 0.055
A49: 46 | B49: 平均入居年数(年) | C49: 数値 | D49: 必須 | E49: - | F49: 3 | G49: 3 | H49: 3 | I49: 3 | J49: 3 | K49: 3 | L49: 3 | M49: 3 | N49: 売却済み | O49: 3 | P49: 3 | Q49: 3 | R49: 3 | S49: 3 | T49: 3 | U49: 3 | V49: 売却済み | W49: 3 | X49: 3 | Y49: 3 | Z49: 3 | AA49: 3 | AB49: 3 | AC49: 3
A50: 47 | B50: 募集にかかる平均期間（月） | C50: 数値 | D50: 必須 | E50: - | F50: 1.7 | G50: 1.7 | H50: 1.7 | I50: 1.7 | J50: 1.7 | K50: 1.7 | L50: 1.7 | M50: 1.7 | N50: 売却済み | O50: 1.7 | P50: 1.7 | Q50: 1.7 | R50: 1.7 | S50: 1.7 | T50: 1.7 | U50: 1.7 | V50: 売却済み | W50: 1.7 | X50: 1.7 | Y50: 1.7 | Z50: 1.7 | AA50: 1.7 | AB50: 1.7 | AC50: 1.7
A51: 48 | B51: 平均募集費用(カ月) | C51: 数値 | D51: 必須 | E51: - | F51: 2 | G51: 2 | H51: 2 | I51: 2 | J51: 2 | K51: 2 | L51: 2 | M51: 2 | N51: 売却済み | O51: 2 | P51: 2 | Q51: 2 | R51: 2 | S51: 2 | T51: 2 | U51: 2 | V51: 売却済み | W51: 2 | X51: 2 | Y51: 2 | Z51: 2 | AA51: 2 | AB51: 2 | AC51: 2
A52: 49 | B52: 平均原状回復費用(カ月) | C52: 数値 | D52: 必須 | E52: - | F52: 1.5 | G52: 1.5 | H52: 1.5 | I52: 1.5 | J52: 1.5 | K52: 1.5 | L52: 1.5 | M52: 1.5 | N52: 売却済み | O52: 1.7 | P52: 1.7 | Q52: 1.7 | R52: 1.7 | S52: 1.7 | T52: 1.7 | U52: 1.7 | V52: 売却済み | W52: 2 | X52: 2 | Y52: 2 | Z52: 2 | AA52: 2 | AB52: 1.5 | AC52: 1.5
A53: 50 | B53: 満室想定賃料/年(非賃貸含む) | C53: 自動 | D53: - | E53: =SUMIF(F5:CH5,"no",F53:CH53) -> 431327736 | F53: =IFERROR(GETPIVOTDATA("17.満室想定税込(自動)",pivot!$AR$9,"3.物件名",F6,"19.賃貸用","no"),0)*12+IFERROR(GETPIVOTDATA("17.満室想定税込(自動)",pivot!$AR$9,"3.物件名",F6,"19.賃貸用","yes"),0)*12 -> 22071600 | G53: =IFERROR(GETPIVOTDATA("17.満室想定税込(自動)",pivot!$AR$9,"3.物件名",G6,"19.賃貸用","no"),0)*12+IFERROR(GETPIVOTDATA("17.満室想定税込(自動)",pivot!$AR$9,"3.物件名",G6,"19.賃貸用","yes"),0)*12 -> 37176000 | H53: =IFERROR(GETPIVOTDATA("17.満室想定税込(自動)",pivot!$AR$9,"3.物件名",H6,"19.賃貸用","no"),0)*12+IFERROR(GETPIVOTDATA("17.満室想定税込(自動)",pivot!$AR$9,"3.物件名",H6,"19.賃貸用","yes"),0)*12 -> 36566136 | I53: =IFERROR(GETPIVOTDATA("17.満室想定税込(自動)",pivot!$AR$9,"3.物件名",I6,"19.賃貸用","no"),0)*12+IFERROR(GETPIVOTDATA("17.満室想定税込(自動)",pivot!$AR$9,"3.物件名",I6,"19.賃貸用","yes"),0)*12 -> 9076800 | J53: =IFERROR(GETPIVOTDATA("17.満室想定税込(自動)",pivot!$AR$9,"3.物件名",J6,"19.賃貸用","no"),0)*12+IFERROR(GETPIVOTDATA("17.満室想定税込(自動)",pivot!$AR$9,"3.物件名",J6,"19.賃貸用","yes"),0)*12 -> 33612312 | K53: =IFERROR(GETPIVOTDATA("17.満室想定税込(自動)",pivot!$AR$9,"3.物件名",K6,"19.賃貸用","no"),0)*12+IFERROR(GETPIVOTDATA("17.満室想定税込(自動)",pivot!$AR$9,"3.物件名",K6,"19.賃貸用","yes"),0)*12 -> 37166400 | L53: =IFERROR(GETPIVOTDATA("17.満室想定税込(自動)",pivot!$AR$9,"3.物件名",L6,"19.賃貸用","no"),0)*12+IFERROR(GETPIVOTDATA("17.満室想定税込(自動)",pivot!$AR$9,"3.物件名",L6,"19.賃貸用","yes"),0)*12 -> 29744400 | M53: =IFERROR(GETPIVOTDATA("17.満室想定税込(自動)",pivot!$AR$9,"3.物件名",M6,"19.賃貸用","no"),0)*12+IFERROR(GETPIVOTDATA("17.満室想定税込(自動)",pivot!$AR$9,"3.物件名",M6,"19.賃貸用","yes"),0)*12 -> 18414132 | ... CB53: =IFERROR(GETPIVOTDATA("17.満室想定税込(自動)",pivot!$AR$9,"3.物件名",CB6,"19.賃貸用","no"),0)*12+IFERROR(GETPIVOTDATA("17.満室想定税込(自動)",pivot!$AR$9,"3.物件名",CB6,"19.賃貸用","yes"),0)*12 -> 0
A54: 51 | B54: 満室想定賃料/年(非賃貸除く) | C54: 自動 | D54: - | E54: =SUMIF(F5:CH5,"no",F54:CH54) -> 427787736 | F54: =IFERROR(GETPIVOTDATA("17.満室想定税込(自動)",pivot!$AR$9,"3.物件名",F6,"19.賃貸用","yes"),0)*12 -> 22071600 | G54: =IFERROR(GETPIVOTDATA("17.満室想定税込(自動)",pivot!$AR$9,"3.物件名",G6,"19.賃貸用","yes"),0)*12 -> 37176000 | H54: =IFERROR(GETPIVOTDATA("17.満室想定税込(自動)",pivot!$AR$9,"3.物件名",H6,"19.賃貸用","yes"),0)*12 -> 36566136 | I54: =IFERROR(GETPIVOTDATA("17.満室想定税込(自動)",pivot!$AR$9,"3.物件名",I6,"19.賃貸用","yes"),0)*12 -> 9076800 | J54: =IFERROR(GETPIVOTDATA("17.満室想定税込(自動)",pivot!$AR$9,"3.物件名",J6,"19.賃貸用","yes"),0)*12 -> 33612312 | K54: =IFERROR(GETPIVOTDATA("17.満室想定税込(自動)",pivot!$AR$9,"3.物件名",K6,"19.賃貸用","yes"),0)*12 -> 37166400 | L54: =IFERROR(GETPIVOTDATA("17.満室想定税込(自動)",pivot!$AR$9,"3.物件名",L6,"19.賃貸用","yes"),0)*12 -> 29744400 | M54: =IFERROR(GETPIVOTDATA("17.満室想定税込(自動)",pivot!$AR$9,"3.物件名",M6,"19.賃貸用","yes"),0)*12 -> 18414132 | ... CB54: =IFERROR(GETPIVOTDATA("17.満室想定税込(自動)",pivot!$AR$9,"3.物件名",CB6,"19.賃貸用","yes"),0)*12 -> 0
A55: 52 | B55: 想定入居率 | C55: 数値 | D55: - | E55: =1-(E58/E54) -> 0.95490716 | F55: =IFERROR((F49*12)/(F49*12+F50),0) -> 0.95490716 | G55: =IFERROR((G49*12)/(G49*12+G50),0) -> 0.95490716 | H55: =IFERROR((H49*12)/(H49*12+H50),0) -> 0.95490716 | I55: =IFERROR((I49*12)/(I49*12+I50),0) -> 0.95490716 | J55: =IFERROR((J49*12)/(J49*12+J50),0) -> 0.95490716 | K55: =IFERROR((K49*12)/(K49*12+K50),0) -> 0.95490716 | L55: =IFERROR((L49*12)/(L49*12+L50),0) -> 0.95490716 | M55: =IFERROR((M49*12)/(M49*12+M50),0) -> 0.95490716 | ... CB55: =IFERROR((CB49*12)/(CB49*12+CB50),0) -> 0
A56: 53 | B56: 想定入居金額 | C56: 自動 | D56: - | E56: =SUMIF(F5:CH5,"no",F56:CH56) -> 4.0849757e+08 | F56: =IFERROR(F55*F54,"") -> 21076329 | G56: =IFERROR(G55*G54,"") -> 35499629 | H56: =IFERROR(H55*H54,"") -> 34917265 | I56: =IFERROR(I55*I54,"") -> 8667501.3 | J56: =IFERROR(J55*J54,"") -> 32096637 | K56: =IFERROR(K55*K54,"") -> 35490462 | L56: =IFERROR(L55*L54,"") -> 28403141 | M56: =IFERROR(M55*M54,"") -> 17583787 | ... CB56: =IFERROR(CB55*CB54,"") -> 0
A57: 54 | B57: 現況賃料/年 | C57: 自動 | D57: - | E57: =SUMIF(F5:CH5,"no",F57:CH57) -> 423689688 | F57: =IFERROR(GETPIVOTDATA("13.現況賃料税込(自動)",pivot!$BF$7,"3.物件名",F6)*12,"") -> 22071600 | G57: =IFERROR(GETPIVOTDATA("13.現況賃料税込(自動)",pivot!$BF$7,"3.物件名",G6)*12,"") -> 37176000 | H57: =IFERROR(GETPIVOTDATA("13.現況賃料税込(自動)",pivot!$BF$7,"3.物件名",H6)*12,"") -> 36566136 | I57: =IFERROR(GETPIVOTDATA("13.現況賃料税込(自動)",pivot!$BF$7,"3.物件名",I6)*12,"") -> 8020800 | J57: =IFERROR(GETPIVOTDATA("13.現況賃料税込(自動)",pivot!$BF$7,"3.物件名",J6)*12,"") -> 31161864 | K57: =IFERROR(GETPIVOTDATA("13.現況賃料税込(自動)",pivot!$BF$7,"3.物件名",K6)*12,"") -> 37166400 | L57: =IFERROR(GETPIVOTDATA("13.現況賃料税込(自動)",pivot!$BF$7,"3.物件名",L6)*12,"") -> 29744400 | M57: =IFERROR(GETPIVOTDATA("13.現況賃料税込(自動)",pivot!$BF$7,"3.物件名",M6)*12,"") -> 18414132 | ... CB57: =IFERROR(GETPIVOTDATA("13.現況賃料税込(自動)",pivot!$BF$7,"3.物件名",CB6)*12,"")
A58: 55 | B58: 想定空室損 | C58: 自動 | D58: - | E58: =SUMIF(F5:CH5,"no",F58:CH58) -> 19290163 | F58: =IFERROR(F54-F56,"") -> 995271.09 | G58: =IFERROR(G54-G56,"") -> 1676371.4 | H58: =IFERROR(H54-H56,"") -> 1648870.9 | I58: =IFERROR(I54-I56,"") -> 409298.67 | J58: =IFERROR(J54-J56,"") -> 1515674.5 | K58: =IFERROR(K54-K56,"") -> 1675938.5 | L58: =IFERROR(L54-L56,"") -> 1341259.4 | M58: =IFERROR(M54-M56,"") -> 830345.47 | ... CB58: =IFERROR(CB54-CB56,"") -> 0
A59: 56 | B59: 入居者管理料(PM)/年 | C59: 自動 | D59: - | E59: =SUMIF(F5:CH5,"no",F59:CH59) -> 21781495 | F59: =IFERROR((F54-F58)*F48,"") -> 1159198.1 | G59: =IFERROR((G54-G58)*G48,"") -> 1597483.3 | H59: =IFERROR((H54-H58)*H48,"") -> 1920449.6 | I59: =IFERROR((I54-I58)*I48,"") -> 476712.57 | J59: =IFERROR((J54-J58)*J48,"") -> 1765315.1 | K59: =IFERROR((K54-K58)*K48,"") -> 1951975.4 | L59: =IFERROR((L54-L58)*L48,"") -> 1562172.7 | M59: =IFERROR((M54-M58)*M48,"") -> 967108.26 | ... CB59: =IFERROR((CB54-CB58)*CB48,"") -> 0
A60: 57 | B60: BM固定費等/年 | C60: 自動 | D60: - | E60: =GETPIVOTDATA("年換算(×12)",pivot!$J$5) -> 20651991 | F60: =IFERROR(GETPIVOTDATA("年換算(×12)",pivot!$J$5,"物件名",F$6),"") -> 1023670 | G60: =IFERROR(GETPIVOTDATA("年換算(×12)",pivot!$J$5,"物件名",G$6),"") -> 2585134 | H60: =IFERROR(GETPIVOTDATA("年換算(×12)",pivot!$J$5,"物件名",H$6),"") -> 1933934 | I60: =IFERROR(GETPIVOTDATA("年換算(×12)",pivot!$J$5,"物件名",I$6),"") -> 418008 | J60: =IFERROR(GETPIVOTDATA("年換算(×12)",pivot!$J$5,"物件名",J$6),"") -> 1580578 | K60: =IFERROR(GETPIVOTDATA("年換算(×12)",pivot!$J$5,"物件名",K$6),"") -> 2308608 | L60: =IFERROR(GETPIVOTDATA("年換算(×12)",pivot!$J$5,"物件名",L$6),"") -> 1073130 | M60: =IFERROR(GETPIVOTDATA("年換算(×12)",pivot!$J$5,"物件名",M$6),"") -> 702866 | ... CB60: =IFERROR(GETPIVOTDATA("年換算(×12)",pivot!$J$5,"物件名",CB$6),"")
A61: 58 | B61: 募集費用/年 | C61: 自動 | D61: - | E61: =SUMIF(F5:CH5,"no",F61:CH61) -> 23765985 | F61: =IFERROR((F54/12*F51)/F49,"") -> 1226200 | G61: =IFERROR((G54/12*G51)/G49,"") -> 2065333.3 | H61: =IFERROR((H54/12*H51)/H49,"") -> 2031452 | I61: =IFERROR((I54/12*I51)/I49,"") -> 504266.67 | J61: =IFERROR((J54/12*J51)/J49,"") -> 1867350.7 | K61: =IFERROR((K54/12*K51)/K49,"") -> 2064800 | L61: =IFERROR((L54/12*L51)/L49,"") -> 1652466.7 | M61: =IFERROR((M54/12*M51)/M49,"") -> 1023007.3 | ... CB61: =IFERROR((CB54/12*CB51)/CB49,"")
A62: 59 | B62: 修繕・原状回復費用/年 | C62: 自動 | D62: - | E62: =SUMIF(F5:CH5,"no",F62:CH62) -> 18919361 | F62: =IFERROR((F57/12*F52)/F49,"") -> 919650 | G62: =IFERROR((G57/12*G52)/G49,"") -> 1549000 | H62: =IFERROR((H57/12*H52)/H49,"") -> 1523589 | I62: =IFERROR((I57/12*I52)/I49,"") -> 334200 | J62: =IFERROR((J57/12*J52)/J49,"") -> 1298411 | K62: =IFERROR((K57/12*K52)/K49,"") -> 1548600 | L62: =IFERROR((L57/12*L52)/L49,"") -> 1239350 | M62: =IFERROR((M57/12*M52)/M49,"") -> 767255.5 | ... CB62: =IFERROR((CB57/12*CB52)/CB49,"")
A63: 60 | B63: 固定資産税+都市計画税 | C63: 自動 | D63: - | E63: =GETPIVOTDATA("合計 / 当期固定資産税額",pivot!$DJ$5)+GETPIVOTDATA("合計 / 当期都市計画税額",pivot!$DJ$5) -> 18765432 | F63: =IFERROR(GETPIVOTDATA("合計 / 当期固定資産税額",pivot!$DJ$5,"物件名",F$6)+GETPIVOTDATA("合計 / 当期都市計画税額",pivot!$DJ$5,"物件名",F$6),"") -> 897252 | G63: =IFERROR(GETPIVOTDATA("合計 / 当期固定資産税額",pivot!$DJ$5,"物件名",G$6)+GETPIVOTDATA("合計 / 当期都市計画税額",pivot!$DJ$5,"物件名",G$6),"") -> 1922326 | H63: =IFERROR(GETPIVOTDATA("合計 / 当期固定資産税額",pivot!$DJ$5,"物件名",H$6)+GETPIVOTDATA("合計 / 当期都市計画税額",pivot!$DJ$5,"物件名",H$6),"") -> 1624075 | I63: =IFERROR(GETPIVOTDATA("合計 / 当期固定資産税額",pivot!$DJ$5,"物件名",I$6)+GETPIVOTDATA("合計 / 当期都市計画税額",pivot!$DJ$5,"物件名",I$6),"") -> 280047 | J63: =IFERROR(GETPIVOTDATA("合計 / 当期固定資産税額",pivot!$DJ$5,"物件名",J$6)+GETPIVOTDATA("合計 / 当期都市計画税額",pivot!$DJ$5,"物件名",J$6),"") -> 964424 | K63: =IFERROR(GETPIVOTDATA("合計 / 当期固定資産税額",pivot!$DJ$5,"物件名",K$6)+GETPIVOTDATA("合計 / 当期都市計画税額",pivot!$DJ$5,"物件名",K$6),"") -> 1666103 | L63: =IFERROR(GETPIVOTDATA("合計 / 当期固定資産税額",pivot!$DJ$5,"物件名",L$6)+GETPIVOTDATA("合計 / 当期都市計画税額",pivot!$DJ$5,"物件名",L$6),"") -> 1285464 | M63: =IFERROR(GETPIVOTDATA("合計 / 当期固定資産税額",pivot!$DJ$5,"物件名",M$6)+GETPIVOTDATA("合計 / 当期都市計画税額",pivot!$DJ$5,"物件名",M$6),"") -> 558103 | ... CB63: =IFERROR(GETPIVOTDATA("合計 / 当期固定資産税額",pivot!$DJ$5,"物件名",CB$6)+GETPIVOTDATA("合計 / 当期都市計画税額",pivot!$DJ$5,"物件名",CB$6),"")
A64: 61 | B64: 賃貸経費合計(空室損含む) | C64: 自動 | D64: - | E64: =E58+E59+E61+E62+E60+E63 -> 1.2317443e+08 | F64: =IFERROR(F58+F59+F61+F62+F60+F63,"") -> 6221241.2 | G64: =IFERROR(G58+G59+G61+G62+G60+G63,"") -> 11395648 | H64: =IFERROR(H58+H59+H61+H62+H60+H63,"") -> 10682370 | I64: =IFERROR(I58+I59+I61+I62+I60+I63,"") -> 2422532.9 | J64: =IFERROR(J58+J59+J61+J62+J60+J63,"") -> 8991753.3 | K64: =IFERROR(K58+K59+K61+K62+K60+K63,"") -> 11216025 | L64: =IFERROR(L58+L59+L61+L62+L60+L63,"") -> 8153842.8 | M64: =IFERROR(M58+M59+M61+M62+M60+M63,"") -> 4848685.6 | ... CB64: =IFERROR(CB58+CB59+CB61+CB62+CB60+CB63,"")
A65: 62 | B65: 賃貸経費率 | C65: 自動 | D65: - | E65: =IFERROR(E64/E54,0) -> 0.28793352 | F65: =IFERROR(F64/F54,"") -> 0.28186634 | G65: =IFERROR(G64/G54,"") -> 0.30653239 | H65: =IFERROR(H64/H54,"") -> 0.29213834 | I65: =IFERROR(I64/I54,"") -> 0.26689284 | J65: =IFERROR(J64/J54,"") -> 0.26751368 | K65: =IFERROR(K64/K54,"") -> 0.30177862 | L65: =IFERROR(L64/L54,"") -> 0.27413035 | M65: =IFERROR(M64/M54,"") -> 0.26331328 | ... CB65: =IFERROR(CB64/CB54,"")
A66: 63 | B66: NOI/年 | C66: 自動 | D66: - | E66: =E54-E64 -> 3.0461331e+08 | F66: =IFERROR(F54-F64,"") -> 15850359 | G66: =IFERROR(G54-G64,"") -> 25780352 | H66: =IFERROR(H54-H64,"") -> 25883766 | I66: =IFERROR(I54-I64,"") -> 6654267.1 | J66: =IFERROR(J54-J64,"") -> 24620559 | K66: =IFERROR(K54-K64,"") -> 25950375 | L66: =IFERROR(L54-L64,"") -> 21590557 | M66: =IFERROR(M54-M64,"") -> 13565446 | ... CB66: =IFERROR(CB54-CB64,"")
A67: 64 | B67: 金利差引後利益(スプレッド) | C67: 自動 | D67: - | E67: =SUMIF(F5:CH5,"no",F67:CH67) -> 2.4447554e+08 | F67: =IFERROR(F66-F37*12,"") -> 14181579 | G67: =IFERROR(G66-G37*12,"") -> 17686760 | H67: =IFERROR(H66-H37*12,"") -> 22289862 | I67: =IFERROR(I66-I37*12,"") -> 5946555.1 | J67: =IFERROR(J66-J37*12,"") -> 22616907 | K67: =IFERROR(K66-K37*12,"") -> 23049327 | L67: =IFERROR(L66-L37*12,"") -> 17814301 | M67: =IFERROR(M66-M37*12,"") -> 11365174 | ... CB67: =IFERROR(CB66-CB37*12,"")
A68: 65 | B68: 減価償却 | C68: 自動 | D68: - | E68: =SUMIF(F5:CH5,"no",F68:CH68) -> 87320612 | F68: =IFERROR(GETPIVOTDATA("14.年間償却額",pivot!$AI$5,"2.対象物件",F6),"") -> 2031089 | G68: =IFERROR(GETPIVOTDATA("14.年間償却額",pivot!$AI$5,"2.対象物件",G6),"") -> 6822429 | H68: =IFERROR(GETPIVOTDATA("14.年間償却額",pivot!$AI$5,"2.対象物件",H6),"") -> 6009972 | I68: =IFERROR(GETPIVOTDATA("14.年間償却額",pivot!$AI$5,"2.対象物件",I6),"") -> 1334838 | J68: =IFERROR(GETPIVOTDATA("14.年間償却額",pivot!$AI$5,"2.対象物件",J6),"") -> 10460893 | K68: =IFERROR(GETPIVOTDATA("14.年間償却額",pivot!$AI$5,"2.対象物件",K6),"") -> 6422877 | L68: =IFERROR(GETPIVOTDATA("14.年間償却額",pivot!$AI$5,"2.対象物件",L6),"") -> 4612021 | M68: =IFERROR(GETPIVOTDATA("14.年間償却額",pivot!$AI$5,"2.対象物件",M6),"") -> 4510192 | ... CB68: =IFERROR(GETPIVOTDATA("14.年間償却額",pivot!$AI$5,"2.対象物件",CB6),"")
A69: 66 | B69: 想定税引前利益 | C69: 自動 | D69: - | E69: =SUMIF(F5:CH5,"no",F69:CH69) -> 1.5715492e+08 | F69: =IFERROR(F67-F68,"") -> 12150490 | G69: =IFERROR(G67-G68,"") -> 10864331 | H69: =IFERROR(H67-H68,"") -> 16279890 | I69: =IFERROR(I67-I68,"") -> 4611717.1 | J69: =IFERROR(J67-J68,"") -> 12156014 | K69: =IFERROR(K67-K68,"") -> 16626450 | L69: =IFERROR(L67-L68,"") -> 13202280 | M69: =IFERROR(M67-M68,"") -> 6854982.4 | ... CB69: =IFERROR(CB67-CB68,"")
A70: 67 | B70: 想定税額 | C70: 自動 | D70: - | E70: =SUMIF(F5:CH5,"no",F70:CH70) -> 49500032 | F70: =IFERROR(IF(F69>0,F69*tax_income,0),"") -> 3645146.9 | G70: =IFERROR(IF(G69>0,G69*tax_income,0),"") -> 3259299.3 | H70: =IFERROR(IF(H69>0,H69*tax_income,0),"") -> 4883966.9 | I70: =IFERROR(IF(I69>0,I69*tax_income,0),"") -> 1383515.1 | J70: =IFERROR(IF(J69>0,J69*tax_income,0),"") -> 3646804.1 | K70: =IFERROR(IF(K69>0,K69*tax_income,0),"") -> 4987935 | L70: =IFERROR(IF(L69>0,L69*tax_income,0),"") -> 3960684.1 | M70: =IFERROR(IF(M69>0,M69*tax_income,0),"") -> 2056494.7 | ... CB70: =IFERROR(IF(CB69>0,CB69*tax_income,0),"")
A71: 68 | B71: 想定税引後利益 | C71: 自動 | D71: - | E71: =SUMIF(F5:CH5,"no",F71:CH71) -> 1.0765489e+08 | F71: =IFERROR(F69-F70,"") -> 8505342.9 | G71: =IFERROR(G69-G70,"") -> 7605031.7 | H71: =IFERROR(H69-H70,"") -> 11395923 | I71: =IFERROR(I69-I70,"") -> 3228202 | J71: =IFERROR(J69-J70,"") -> 8509209.6 | K71: =IFERROR(K69-K70,"") -> 11638515 | L71: =IFERROR(L69-L70,"") -> 9241596.1 | M71: =IFERROR(M69-M70,"") -> 4798487.7 | ... CB71: =IFERROR(CB69-CB70,"")
A72: 69 | B72: 想定税引後CF | C72: 自動 | D72: - | E72: =IFERROR(E67-E70-E38*12,"") -> 41534445 | F72: =IFERROR(F67-F70-F38*12,"") -> 1984439.9 | G72: =IFERROR(G67-G70-G38*12,"") -> 1824436.7 | H72: =IFERROR(H67-H70-H38*12,"") -> 4811270.7 | I72: =IFERROR(I67-I70-I38*12,"") -> 615903.96 | J72: =IFERROR(J67-J70-J38*12,"") -> 7022578.6 | K72: =IFERROR(K67-K70-K38*12,"") -> 6413784.1 | L72: =IFERROR(L67-L70-L38*12,"") -> 2063929.1 | ... CB72: =IFERROR(CB67-CB70-CB38*12,"")
A73: 70 | B73: 売却試算 | C73: - | D73: - | E73: -
A74: 71 | B74: 簿価合計 | C74: 自動 | E74: =SUMIF(F5:CH5,"no",F74:CH74) -> 5162178676 | F74: =IFERROR(GETPIVOTDATA("13.期首帳簿価額",pivot!$AC$5,"2.対象物件",F6),"") -> 209616559 | G74: =IFERROR(GETPIVOTDATA("13.期首帳簿価額",pivot!$AC$5,"2.対象物件",G6),"") -> 531449692 | H74: =IFERROR(GETPIVOTDATA("13.期首帳簿価額",pivot!$AC$5,"2.対象物件",H6),"") -> 377385294 | I74: =IFERROR(GETPIVOTDATA("13.期首帳簿価額",pivot!$AC$5,"2.対象物件",I6),"") -> 107620706 | J74: =IFERROR(GETPIVOTDATA("13.期首帳簿価額",pivot!$AC$5,"2.対象物件",J6),"") -> 263462148 | K74: =IFERROR(GETPIVOTDATA("13.期首帳簿価額",pivot!$AC$5,"2.対象物件",K6),"") -> 405541730 | L74: =IFERROR(GETPIVOTDATA("13.期首帳簿価額",pivot!$AC$5,"2.対象物件",L6),"") -> 360024505 | M74: =IFERROR(GETPIVOTDATA("13.期首帳簿価額",pivot!$AC$5,"2.対象物件",M6),"") -> 193173833 | ... CB74: =IFERROR(GETPIVOTDATA("13.期首帳簿価額",pivot!$AC$5,"2.対象物件",CB6),"")
A75: 72 | B75: 譲渡益課税 | C75: 自動 | D75: - | E75: =SUMIF(F5:CH5,"no",F75:CH75) -> 5.6307389e+08 | F75: =IFERROR((F45-F74)*tax_capital,"") -> 48241873 | G75: =IFERROR((G45-G74)*tax_capital,"") -> 5753614 | H75: =IFERROR((H45-H74)*tax_capital,"") -> 40927441 | I75: =IFERROR((I45-I74)*tax_capital,"") -> 17900339 | J75: =IFERROR((J45-J74)*tax_capital,"") -> 1.1341901e+08 | K75: =IFERROR((K45-K74)*tax_capital,"") -> 75279560 | L75: =IFERROR((L45-L74)*tax_capital,"") -> 36250933 | M75: =IFERROR((M45-M74)*tax_capital,"") -> 19545682 | ... CB75: =IFERROR((CB45-CB74)*tax_capital,"")
A76: 73 | B76: 解散価値 | C76: 自動 | D76: - | E76: =SUMIF(F5:CH5,"no",F76:CH76) -> 1.7039228e+09 | F76: =IFERROR(F45-F75-F36,"") -> 1.2559161e+08 | G76: =IFERROR(G45-G75-G36,"") -> 51775412 | H76: =IFERROR(H45-H75-H36,"") -> 1.2137951e+08 | I76: =IFERROR(I45-I75-I36,"") -> 67652838 | J76: =IFERROR(J45-J75-J36,"") -> 2.5697439e+08 | K76: =IFERROR(K45-K75-K36,"") -> 2.445741e+08 | L76: =IFERROR(L45-L75-L36,"") -> 1.0804268e+08 | M76: =IFERROR(M45-M75-M36,"") -> 80206665 | ... CB76: =IFERROR(CB45-CB75-CB36,"")
A77: 74 | B77: 印刷欄外メモ | C77: - | D77: - | E77: - | F77: - | G77: - | H77: - | I77: - | J77: - | K77: - | L77: - | M77: - | N77: - | O77: - | P77: - | Q77: - | R77: - | S77: - | T77: - | U77: - | V77: - | W77: - | X77: - | Y77: - | Z77: - | AA77: - | AB77: - | AC77: - | AD77: - | AE77: - | AF77: - | AG77: - | AH77: - | AI77: - | AJ77: - | AK77: - | AL77: - | AM77: - | AN77: - | AO77: - | AP77: - | AQ77: - | AR77: - | AS77: - | AT77: - | AU77: - | AV77: - | AW77: - | AX77: - | AY77: - | AZ77: - | BA77: - | BB77: - | BC77: - | BD77: - | BE77: - | BF77: - | BG77: - | BH77: - | BI77: - | BJ77: - | BK77: - | BL77: - | BM77: - | BN77: - | BO77: - | BP77: - | BQ77: - | BR77: - | BS77: - | BT77: - | BU77: - | BV77: - | BW77: - | BX77: - | BY77: - | BZ77: - | CA77: - | CB77: -
A78: 75 | B78: 竣工図原本 | C78: 文字列 | D78: - | E78: - | F78: あり | G78: あり | H78: あり | I78: あり | J78: あり | K78: あり | L78: あり | M78: あり | N78: 売却済み | O78: あり | P78: あり | Q78: あり | R78: あり | S78: あり | T78: あり | U78: あり | V78: 売却済み | W78: あり | X78: あり | Y78: あり | Z78: あり | AA78: あり
A79: 76 | B79: 構造計算書原本 | C79: 文字列 | D79: - | E79: - | F79: あり | G79: あり | H79: あり | I79: あり | J79: あり | K79: あり | L79: あり | M79: あり | N79: 売却済み | O79: あり | P79: あり | Q79: あり | R79: あり | S79: あり | T79: あり | U79: あり | V79: 売却済み | W79: あり | X79: 非該当 | Y79: 非該当 | Z79: 非該当 | AA79: 非該当
A80: 77 | B80: 私道協定書原本 | C80: 文字列 | D80: - | E80: - | F80: なし | G80: なし | H80: なし | I80: なし | J80: なし | K80: なし | L80: なし | M80: なし | N80: 売却済み | O80: なし | P80: なし | Q80: なし | R80: なし | S80: なし | T80: なし | U80: なし | V80: 売却済み | W80: なし | X80: 非該当 | Y80: 非該当 | Z80: 非該当 | AA80: 非該当
A81: 78 | B81: その他協定書原本 | C81: 文字列 | D81: - | E81: - | F81: なし | G81: なし | H81: なし | I81: なし | J81: なし | K81: なし | L81: なし | M81: なし | N81: 売却済み | O81: なし | P81: なし | Q81: なし | R81: なし | S81: なし | T81: なし | U81: なし | V81: 売却済み | W81: なし | X81: 非該当 | Y81: 非該当 | Z81: 非該当 | AA81: 非該当
A82: 79 | B82: 筆界民民全確定済み | C82: 文字列 | D82: - | E82: - | F82: 済み | G82: 済み | H82: 済み | I82: 済み | J82: 未済み | K82: 未済み | L82: 済み | M82: 済み | N82: 売却済み | O82: 済み | P82: 済み | Q82: 済み | R82: 済み | S82: 済み | T82: 済み | U82: 済み | V82: 売却済み | W82: 済み | X82: 非該当 | Y82: 非該当 | Z82: 非該当 | AA82: 非該当
A83: 80 | B83: 筆界官民全確定済み | C83: 文字列 | D83: - | E83: - | F83: 済み | G83: 済み | H83: 済み | I83: 済み | J83: 済み | K83: 済み | L83: 未済み | M83: 済み | N83: 売却済み | O83: 済み | P83: 済み | Q83: 済み | R83: 済み | S83: 済み | T83: 済み | U83: 済み | V83: 売却済み | W83: 未済み | X83: 非該当 | Y83: 非該当 | Z83: 非該当 | AA83: 非該当
A84: 81 | B84: 筆界民隣地総数 | C84: 数値 | D84: - | E84: - | F84: 6 | G84: 8 | H84: 2 | I84: 5 | J84: 4 | K84: 6 | L84: 2 | M84: 6 | N84: 売却済み | O84: 2 | P84: 5 | Q84: 4 | R84: 6 | S84: 2 | T84: 5 | U84: 5 | V84: 売却済み | W84: 5 | X84: 非該当 | Y84: 非該当 | Z84: 非該当 | AA84: 非該当
A85: 82 | B85: 定期消防点検指摘事項 | C85: 文字列 | D85: - | E85: - | F85: なし | G85: なし | H85: なし | I85: なし | J85: なし | K85: なし | L85: なし | M85: なし | N85: 売却済み | O85: なし | P85: なし | Q85: なし | R85: なし | S85: なし | T85: なし | U85: なし | V85: 売却済み | W85: なし | X85: 非該当 | Y85: 非該当 | Z85: 非該当 | AA85: 非該当
A86: 83 | B86: 水質検査定期実施 | C86: 文字列 | D86: - | E86: - | F86: あり | G86: あり | H86: あり | I86: あり | J86: あり | K86: あり | L86: あり | M86: あり | N86: 売却済み | O86: あり | P86: あり | Q86: あり | R86: あり | S86: あり | T86: あり | U86: あり | V86: 売却済み | W86: あり | X86: 非該当 | Y86: 非該当 | Z86: 非該当 | AA86: 非該当
A87: 84 | B87: 特殊建物定期調査 | C87: 文字列 | D87: - | E87: - | F87: 非該当 | G87: あり | H87: 非該当 | I87: 非該当 | J87: 非該当 | K87: 非該当 | L87: 非該当 | M87: 非該当 | N87: 売却済み | O87: 非該当 | P87: 非該当 | Q87: 非該当 | R87: 非該当 | S87: 非該当 | T87: 非該当 | U87: 非該当 | V87: 売却済み | W87: 非該当 | X87: 非該当 | Y87: 非該当 | Z87: 非該当 | AA87: 非該当
A88: 85 | B88: 検査済証 | C88: 文字列 | D88: - | E88: - | F88: あり | G88: あり | H88: あり | I88: あり | J88: あり | K88: あり | L88: あり | M88: あり | N88: 売却済み | O88: あり | P88: あり | Q88: あり | R88: あり | S88: あり | T88: あり | U88: あり | V88: 売却済み | W88: あり | X88: あり | Y88: あり | Z88: あり | AA88: あり
A89: 86 | B89: 遵法性 | C89: 文字列 | D89: - | E89: - | F89: 適法 | G89: 適法 | H89: 適法 | I89: 適法 | J89: 適法 | K89: 適法 | L89: 適法 | M89: 適法 | N89: 売却済み | O89: 適法 | P89: 適法 | Q89: 適法 | R89: 適法 | S89: 適法 | T89: 適法 | U89: 適法 | V89: 売却済み | W89: 適法 | X89: 適法 | Y89: 適法 | Z89: 適法 | AA89: 適法
A90: 87 | B90: 過去データ蓄積 | C90: - | D90: - | E90: - | F90: - | G90: - | H90: - | I90: - | J90: - | K90: - | L90: - | M90: - | N90: - | O90: - | P90: - | Q90: - | R90: - | S90: - | T90: - | U90: - | V90: - | W90: - | X90: - | Y90: - | Z90: - | AA90: - | AB90: - | AC90: - | AD90: - | AE90: - | AF90: - | AG90: - | AH90: - | AI90: - | AJ90: - | AK90: - | AL90: - | AM90: - | AN90: - | AO90: - | AP90: - | AQ90: - | AR90: - | AS90: - | AT90: - | AU90: - | AV90: - | AW90: - | AX90: - | AY90: - | AZ90: - | BA90: - | BB90: - | BC90: - | BD90: - | BE90: - | BF90: - | BG90: - | BH90: - | BI90: - | BJ90: - | BK90: - | BL90: - | BM90: - | BN90: - | BO90: - | BP90: - | BQ90: - | BR90: - | BS90: - | BT90: - | BU90: - | BV90: - | BW90: - | BX90: - | BY90: - | BZ90: - | CA90: - | CB90: -
A91: 88 | B91: R3固定資産税路線価 | C91: 数値（\） | D91: - | E91: - | F91: 501000 | G91: 117000 | H91: 366000 | I91: 162100 | J91: 646000 | K91: 412000 | L91: 220000 | M91: 434000 | N91: 売却済み | O91: 436000 | P91: 420000 | Q91: 565000 | R91: 565000 | S91: 565000 | T91: 565000 | U91: 565000 | V91: 売却済み | W91: 655000 | X91: 565000 | Y91: 565000 | Z91: 565000 | AA91: 565000
A92: 89 | B92: R3相続税路線価 | C92: 文字列 | D92: - | E92: - | F92: 580C | G92: 135D | H92: 430C | I92: 180D | J92: 770C | K92: 470C | L92: 270D | M92: 510C | N92: 売却済み | O92: 530C | P92: 550D | Q92: 620C | R92: 620C | S92: 620C | T92: 620C | U92: 620C | V92: 売却済み | W92: 760C | X92: 620C | Y92: 620C | Z92: 620C | AA92: 620C
A93: 90 | B93: R2固定資産税路線価 | C93: 数値（\） | D93: - | E93: - | F93: 501000 | G93: 117000 | H93: 366000 | I93: 162100 | J93: 646000 | K93: 412000 | L93: 220000 | M93: 434000 | N93: 売却済み | O93: 436000 | P93: 420000 | Q93: 565000 | R93: 565000 | S93: 565000 | T93: 565000 | U93: 565000 | V93: 売却済み | W93: 655000 | X93: 565000 | Y93: 565000 | Z93: 565000 | AA93: 565000
A94: 91 | B94: R2相続税路線価 | C94: 文字列 | D94: - | E94: - | F94: 580C | G94: 135D | H94: 430C | I94: 180D | J94: 770C | K94: 470C | L94: 270D | M94: 510C | N94: 売却済み | O94: 530C | P94: 550D | Q94: 620C | R94: 620C | S94: 620C | T94: 620C | U94: 620C | V94: 売却済み | W94: 760C | X94: 620C | Y94: 620C | Z94: 620C | AA94: 620C
A95: 92 | B95: R1固定資産税路線価 | C95: 数値（\） | D95: - | E95: - | F95: 501000 | G95: 117000 | H95: 366000 | I95: 162100 | J95: 646000 | K95: 412000 | L95: 220000 | M95: 434000 | N95: 売却済み | O95: 436000 | P95: 420000 | Q95: 565000 | R95: 565000 | S95: 565000 | T95: 565000 | U95: 565000 | V95: 売却済み | W95: 655000 | X95: 565000 | Y95: 565000 | Z95: 565000 | AA95: 565000
A96: 93 | B96: R1相続税路線価 | C96: 文字列 | D96: - | E96: - | F96: 580C | G96: 135D | H96: 430C | I96: 180D | J96: 770C | K96: 470C | L96: 270D | M96: 510C | N96: 売却済み | O96: 530C | P96: 550D | Q96: 620C | R96: 620C | S96: 620C | T96: 620C | U96: 620C | V96: 売却済み | W96: 760C | X96: 620C | Y96: 620C | Z96: 620C | AA96: 620C

Sheet 1法人概要
A3: グループ法人概要
A4: 本資料作成日: | C4: =settings!L5 -> 44870
A8: グループ法人と個人
A9: 法人ID | B9: 会社名/氏名 | D9: 住所 | E9: 代表名 | F9: 役割 | G9: 設立日/生年月日 | H9: 資本金 | I9: 決算期 | J9: 前回決算の事業年度 | K9: 株主 | L9: 法人番号 | M9: 令和4年消費税区分 | N9: インボイス登録番号
A10: 301 | B10: =VLOOKUP(A10,id_settings,2,FALSE) -> 玉川陽介 | D10: 東京都豊島区目白1丁目5番1号 | E10: - | F10: 代表 | G10: 28491 | H10: - | I10: - | J10: - | K10: - | L10: - | M10: 免税(給与所得のみ) | N10: -
A11: 302 | B11: =VLOOKUP(A11,id_settings,2,FALSE) -> 玉川花子 | D11: 東京都豊島区目白1丁目5番1号 | E11: - | F11: 妻(相続人) | G11: 29253 | H11: - | I11: - | J11: - | K11: - | L11: - | M11: 免税(給与所得のみ) | N11: -
A12: 303 | B12: =VLOOKUP(A12,id_settings,2,FALSE) -> 玉川太郎 | D12: 東京都豊島区目白1丁目5番1号 | E12: - | F12: 子(相続人) | G12: 44686 | H12: - | I12: - | J12: - | K12: - | L12: - | M12: - | N12: -
A13: 304 | B13: =VLOOKUP(A13,id_settings,2,FALSE) -> 鈴木次郎 | D13: 沖縄県国頭郡恩納村名嘉真1967-1 | E13: - | F13: 養子(相続人) | G13: 33030 | H13: - | I13: - | J13: - | K13: - | L13: - | M13: - | N13: -
A14: 401 | B14: =VLOOKUP(A14,id_settings,2,FALSE) -> コアプラス東京株式会社 | D14: 東京都豊島区西池袋3丁目7番6号 | E14: 玉川陽介 | F14: 賃料回収等 | G14: 40180 | H14: 1000 | I14: 12末 | J14: 13 | K14: コアプラスHD 100% | L14: 1234567890123 | M14: 原則 | N14: 1234567890123
A15: 402 | B15: =VLOOKUP(A15,id_settings,2,FALSE) -> コアプラス名古屋株式会社 | D15: 東京都豊島区西池袋3丁目7番6号 | E15: 玉川陽介 | F15: 資産保有 | G15: 37290 | H15: 300 | I15: 12末 | J15: 20 | K15: コアプラスHD 100% | L15: 2469135780246 | M15: 免税 | N15: -
A16: 404 | B16: =VLOOKUP(A16,id_settings,2,FALSE) -> コアプラス大阪株式会社 | D16: 大阪市東淀川区西淡路1丁目1-9 | E16: 玉川陽介 | F16: 大阪での資産保有 | G16: 41337 | H16: 500 | I16: 12末 | J16: 10 | K16: コアプラスHD 100% | L16: 4938271560492 | M16: 簡易 | N16: 4938271560492
A17: 405 | B17: =VLOOKUP(A17,id_settings,2,FALSE) -> コアプラス仙台株式会社 | D17: 東京都豊島区西池袋3丁目7番6号 | E17: 玉川陽介 | F17: 資産保有 | G17: 41369 | H17: 500 | I17: 12末 | J17: 9 | K17: コアプラスHD 100% | L17: 9876543120984 | M17: 免税 | N17: -
A18: 406 | B18: =VLOOKUP(A18,id_settings,2,FALSE) -> コアプラス札幌株式会社 | D18: 東京都豊島区西池袋3丁目7番6号 | E18: 玉川陽介 | F18: 資産保有 | G18: 41765 | H18: 1000 | I18: 12末 | J18: 8 | K18: コアプラスHD 100% | L18: 1975308624196 | M18: 免税 | N18: -
A19: 407 | B19: =VLOOKUP(A19,id_settings,2,FALSE) -> コアプラス福岡株式会社 | D19: 東京都豊島区西池袋3丁目7番6号 | E19: 玉川陽介 | F19: 資産保有 | G19: 42162 | H19: 1000 | I19: 12末 | J19: 7 | K19: コアプラスHD 100% | L19: 3950617248392 | M19: 簡易 | N19: 3950617248392
A20: 408 | B20: =VLOOKUP(A20,id_settings,2,FALSE) -> コアプラス京都株式会社 | D20: 東京都豊島区西池袋3丁目7番6号 | E20: 玉川陽介 | F20: 資産保有 | G20: 42193 | H20: 100 | I20: 12末 | J20: 7 | K20: コアプラスHD 100% | L20: 7901234496784 | M20: 簡易 | N20: 7901234496784
A21: 409 | B21: =VLOOKUP(A21,id_settings,2,FALSE) -> コアプラス四国株式会社 | D21: 東京都豊島区西池袋3丁目7番6号 | E21: 玉川陽介 | F21: 資産保有 | G21: 42225 | H21: 100 | I21: 12末 | J21: 7 | K21: コアプラスHD 100% | L21: 1580246899356 | M21: 免税 | N21: -
A22: 410 | B22: =VLOOKUP(A22,id_settings,2,FALSE) -> コアプラス沖縄株式会社 | D22: 東京都豊島区西池袋3丁目7番6号 | E22: 玉川陽介 | F22: 資産保有 | G22: 42623 | H22: 100 | I22: 12末 | J22: 6 | K22: コアプラスHD 100% | L22: 3160493798712 | M22: 免税 | N22: -
A23: 411 | B23: =VLOOKUP(A23,id_settings,2,FALSE) -> コアプラスホールディングス株式会社 | D23: 東京都豊島区西池袋3丁目7番6号 | E23: 玉川陽介 | F23: 持株会社 | G23: 43587 | H23: 1000 | I23: 12末 | J23: 3 | K23: 玉川陽介 100% | L23: 1580241299356 | M23: 免税 | N23: -
A24: 解散
A25: 403 | B25: =VLOOKUP(A25,id_settings,2,FALSE) -> 有限会社コアプラス2号 | D25: N/A | E25: 玉川陽介 | F25: すでに解散 | G25: 41153 | H25: 500 | I25: 12末 | J25: - | K25: 玉川陽介 100% | L25: 2345678902345 | M25: - | N25: -
A26: ※金融機関のみなさまへ。本資料は融資を検討頂くことのみを目的とした機微な個人情報を含む機密資料であり金融機関内部限りです。不動産、金融証券業者、税理士ほか第三者との共有はご遠慮ください。

Sheet 2法人連結
B3: 全法人連結による貸借対照表、損益計算書、キャッシュフローの試算
B5: 1.グループ全体B/S | E5: =settings!L6 -> 44870
B6: 資産 | D6: 負債と純資産
B7: 資産名 | C7: 合計額 | D7: 負債資産名 | E7: 合計額
B8: 不動産時価 | C8: =SUMIF(asset!B5:CH5,"no",asset!B45:CH45) -> 6684000000 | D8: 借入金 | E8: =GETPIVOTDATA("残債",'4借入集計'!$A$5)*-1 -> -4439492417 | F8: ※不動産価格は自己評価による時価
B9: 法人現預金等 | C9: =VLOOKUP("107現金･預金合計",C直近決算!$A:$C,2,FALSE) -> 791757250 | D9: 敷金預かり債務 | E9: =VLOOKUP("289預り保証金",C直近決算!$A:$C,2,FALSE)*-1 -> -74706885 | F9: ※借入金は5借入一覧シートに計と一致する
B10: 法人株式・債券等証券投資 | C10: =settings!L25 -> 10000000
B11: 信用金庫等出資金 | C11: =VLOOKUP("210出資金",C直近決算!$A:$C,2,FALSE) -> 41910000
B12: 個人預金等 | C12: =settings!L26 -> 30000000
B13: 個人株式・債券等証券投資 | C13: =settings!L27 -> 15000000
B14: その他資産 | C14: =settings!L28 -> 5000000
D16: 負債合計 | E16: =SUM(E8:E15) -> -4514199302
D17: 現金同等物 | E17: =C21-C8 -> 893667250
D18: 不動産解散価値(時価評価) | E18: =C8+E9+E8 -> 2169800698
F19: ※不動産解散価値(時価評価)は税引前
B21: 資産合計 | C21: =SUM(C8:C20) -> 7577667250 | D21: 純資産合計 | E21: =SUM(E17:E20) -> 3063467948
B24: 2.グループ全体P/L | E24: =settings!L7 -> 2023年1月～12月予測
B25: 収支概要 | C25: 重要指標 | D25: 年額 | E25: 月額
B26: 賃料収入と賃貸経費
B27: 満室想定賃料 | D27: =asset!E54/10000 -> 42778.774 | E27: =D27/12 -> 3564.8978 | F27: ※非賃貸除く満室想定
B28: 空室損率 | D28: =1-asset!E55 -> 0.045092838 | E28: -
B29: 賃貸経費 | D29: =asset!E64/10000*-1 -> -12317.443 | E29: =D29/12 -> -1026.4536 | F29: ※空室損を含む賃貸経費計
B30: 経費率 | C30: ◆ | D30: =D29/D27*-1 -> 0.28793352 | E30: -
B31: NOI | C31: ◆ | D31: =asset!E66/10000 -> 30461.331 | E31: =D31/12 -> 2538.4442
B32: 賃貸資産当初購入価格 | D32: =VLOOKUP(B32,id3_asset_sum,4,FALSE)/10000 -> 523910
B33: NOI% | C33: ◆ | D33: =D31/D32 -> 0.058142297 | E33: - | F33: ※NOI/購入価格
B34: 賃貸部門のみ借入
B35: 賃貸部門金利（不動産購入・修繕等） | D35: =E35*12 -> -5748.0576 | E35: =GETPIVOTDATA("合計 / 23.利息月額",pivot!$EM$7,"9.使途2","賃貸部門")/10000*-1 -> -479.0048 | F35: ※不動産購入、修繕などのみの金利
B36: 賃貸部門借入残高 | D36: =GETPIVOTDATA("合計 / 25.残債",pivot!$EM$7,"9.使途2","賃貸部門")/10000 -> 432554.54
B37: 賃貸部門加重平均借入金利 | D37: =D35/D36*-1 -> 0.013288631 | E37: -
B38: 賃貸部門のみ税引前利益
B39: NOI | D39: =D31 -> 30461.331 | E39: =E31 -> 2538.4442 | F39: ※再掲
B40: 賃貸部門金利（物件購入・修繕等） | D40: =D35 -> -5748.0576 | E40: =E35 -> -479.0048 | F40: ※再掲
B41: 金利差引後利益(スプレッド) | D41: =D39+D40 -> 24713.273 | E41: =E39+E40 -> 2059.4394 | F41: ※長期の賃貸不動産部門のみ
B42: 減価償却 | D42: =GETPIVOTDATA("14.年間償却額",pivot!$AI$5)/10000*-1 -> -8732.0612 | E42: =D42/12 -> -727.67177
B43: 賃貸部門税引前利益 | D43: =D41+D42 -> 15981.212 | E43: =E41+E42 -> 1331.7677
B44: 想定税率 | D44: =tax_income -> 0.3 | E44: -
B45: 想定税額 | D45: =D43*D44*-1 -> -4794.3636 | E45: -
B46: 想定税引後利益 | D46: =D43+D45 -> 11186.848 | E46: -
B47: グループ運営経費を含めた決算書上の利益
B48: 賃貸部門税引前利益 | D48: =D43 -> 15981.212 | E48: =D48/12 -> 1331.7677 | F48: ※再掲
B49: 会社経費 | D49: =settings!L29/10000*-1 -> -300 | E49: =D49/12 -> -25 | F49: ※前年度から推計
B50: 役員報酬・人件費 | D50: =settings!L30/10000*-1 -> -300 | E50: =D50/12 -> -25 | F50: ※前年度から推計
B51: 間接部門金利(運転資金等) | D51: =E51*12 -> -304.4532 | E51: =GETPIVOTDATA("合計 / 23.利息月額",pivot!$EM$7,"9.使途2","間接部門")/10000*-1 -> -25.3711 | F51: ※運転資金、住宅ローン、その他金利計
B52: 税引前利益 | C52: ◆ | D52: =D48+D49+D50+D51 -> 15076.759 | E52: =E48+E49+E50+E51 -> 1256.3966
B53: 想定税率 | D53: =settings!L20 -> 0.35 | E53: -
B54: 税額 | D54: =D52*D53*-1 -> -5276.8656 | E54: -
B55: 税引後利益 | D55: =D52+D54 -> 9799.8932 | E55: -
B57: 3.グループ全体C/F | E57: =settings!L8 -> 2023年1月～12月予測
B58: 収支概要 | C58: 重要指標 | D58: 年額 | E58: 月額
B59: 賃貸部門のみC/F
B60: 金利差引後利益(スプレッド) | D60: =D41 -> 24713.273 | E60: =D60/12 -> 2059.4394 | F60: ※再掲
B61: 賃貸部門元金返済 | D61: =E61*12 -> -15140.518 | E61: =GETPIVOTDATA("合計 / 22.元金返済月額",pivot!$EM$7,"9.使途2","賃貸部門")/10000*-1 -> -1261.7098
B62: 賃貸部門税引前CF | D62: =D60+D61 -> 9572.7556 | E62: =E60+E61 -> 797.72964
B63: 想定税額 | D63: =D45 -> -4794.3636 | E63: - | F63: ※再掲
B64: 想定税引後CF | C64: ◆ | D64: =D62+D63 -> 4778.392 | E64: =D64/12 -> 398.19934
B65: グループ全体C/F
B66: 間接部門元金返済(運転資金等) | D66: =E66*12 -> -406.2948 | E66: =GETPIVOTDATA("合計 / 22.元金返済月額",pivot!$EM$7,"9.使途2","間接部門")/10000*-1 -> -33.8579
B67: 運転経費差引後税引前CF | D67: =D52+D66+D61-D42 -> 8262.0076 | E67: -
B68: 税額 | D68: =D54 -> -5276.8656 | E68: - | F68: ※再掲
B69: 税引後CF | C69: ◆ | D69: =D67+D68 -> 2985.142 | E69: =D69/12 -> 248.76184

Sheet 3物件一覧
B1: =settings!L9 -> 44870 | C1: 合計 または加重平均 | D1: =VLOOKUP(D2,id_settings,2,FALSE)&"" -> 西池袋駅前ビル | E1: =VLOOKUP(E2,id_settings,2,FALSE)&"" -> 池袋ハウス | F1: =VLOOKUP(F2,id_settings,2,FALSE)&"" -> カーサ目白台ハウス | G1: =VLOOKUP(G2,id_settings,2,FALSE)&"" -> コアプラス池袋 | H1: =VLOOKUP(H2,id_settings,2,FALSE)&"" -> 目白アパート | I1: =VLOOKUP(I2,id_settings,2,FALSE)&"" -> 東池袋ハイツ | J1: =VLOOKUP(J2,id_settings,2,FALSE)&"" -> メゾン雑司ヶ谷 | K1: =VLOOKUP(K2,id_settings,2,FALSE)&"" -> カーサ南池袋 | ... BA1: =VLOOKUP(BA2,id_settings,2,FALSE)&"" -> #N/A
A2: 11 | B2: 物件ID | C2: =COUNTIF(asset!$5:$5,"no") -> 20 | D2: 101 | E2: 102 | F2: 103 | G2: 104 | H2: 105 | I2: 106 | J2: 107 | K2: 109 | L2: 111 | M2: 112 | N2: 113 | O2: 114 | P2: 115 | Q2: 116 | R2: 117 | S2: 120 | T2: 121 | U2: 122 | V2: 221 | W2: 222
A3: 12 | B3: 物件概要
A4: 13 | B4: 現所有者 | D4: =HLOOKUP(D$2,id2_asset,asset!$A9,FALSE)&"" -> コアプラス東京株式会社 | E4: =HLOOKUP(E$2,id2_asset,asset!$A9,FALSE)&"" -> コアプラス名古屋株式会社 | F4: =HLOOKUP(F$2,id2_asset,asset!$A9,FALSE)&"" -> 有限会社コアプラス2号 | G4: =HLOOKUP(G$2,id2_asset,asset!$A9,FALSE)&"" -> コアプラス大阪株式会社 | H4: =HLOOKUP(H$2,id2_asset,asset!$A9,FALSE)&"" -> コアプラス仙台株式会社 | I4: =HLOOKUP(I$2,id2_asset,asset!$A9,FALSE)&"" -> コアプラス札幌株式会社 | J4: =HLOOKUP(J$2,id2_asset,asset!$A9,FALSE)&"" -> コアプラス福岡株式会社 | K4: =HLOOKUP(K$2,id2_asset,asset!$A9,FALSE)&"" -> コアプラス四国株式会社 | ... BA4: =HLOOKUP(BA$2,id2_asset,asset!$A9,FALSE)&"" -> #N/A
A5: 14 | B5: 交通 | D5: =HLOOKUP(D$2,id2_asset,asset!$A10,FALSE)&"" -> 山手線「池袋」歩7分 | E5: =HLOOKUP(E$2,id2_asset,asset!$A10,FALSE)&"" -> 山手線「池袋」歩8分 | F5: =HLOOKUP(F$2,id2_asset,asset!$A10,FALSE)&"" -> 山手線「目白」歩10分 | G5: =HLOOKUP(G$2,id2_asset,asset!$A10,FALSE)&"" -> 山手線「池袋」歩10分 | H5: =HLOOKUP(H$2,id2_asset,asset!$A10,FALSE)&"" -> 西武池袋線｢椎名町｣歩7分 | I5: =HLOOKUP(I$2,id2_asset,asset!$A10,FALSE)&"" -> 中央線「高円寺」 歩4分 | J5: =HLOOKUP(J$2,id2_asset,asset!$A10,FALSE)&"" -> 東京メトロ副都心線「雑司ヶ谷」歩8分 | K5: =HLOOKUP(K$2,id2_asset,asset!$A10,FALSE)&"" -> 山手線「池袋」歩7分 | ... BA5: =HLOOKUP(BA$2,id2_asset,asset!$A10,FALSE)&"" -> #N/A
A6: 15 | B6: 住所 | D6: =HLOOKUP(D$2,id2_asset,asset!$A11,FALSE)&"" -> 豊島区西池袋3-7-21 | E6: =HLOOKUP(E$2,id2_asset,asset!$A11,FALSE)&"" -> 豊島区池袋6-1-22 | F6: =HLOOKUP(F$2,id2_asset,asset!$A11,FALSE)&"" -> 文京区目白台7-1-19 | G6: =HLOOKUP(G$2,id2_asset,asset!$A11,FALSE)&"" -> 豊島区池袋9-2-1 | H6: =HLOOKUP(H$2,id2_asset,asset!$A11,FALSE)&"" -> 豊島区目白6-11-21 | I6: =HLOOKUP(I$2,id2_asset,asset!$A11,FALSE)&"" -> 杉並区高円寺9-1-6 | J6: =HLOOKUP(J$2,id2_asset,asset!$A11,FALSE)&"" -> 豊島区西池袋3-7-21 | K6: =HLOOKUP(K$2,id2_asset,asset!$A11,FALSE)&"" -> 文京区目白台7-1-19 | ... BA6: =HLOOKUP(BA$2,id2_asset,asset!$A11,FALSE)&"" -> #N/A
A7: 16 | B7: 一棟or区分 | D7: =HLOOKUP(D$2,id2_asset,asset!$A12,FALSE)&"" -> 一棟 | E7: =HLOOKUP(E$2,id2_asset,asset!$A12,FALSE)&"" -> 一棟 | F7: =HLOOKUP(F$2,id2_asset,asset!$A12,FALSE)&"" -> 一棟 | G7: =HLOOKUP(G$2,id2_asset,asset!$A12,FALSE)&"" -> 一棟 | H7: =HLOOKUP(H$2,id2_asset,asset!$A12,FALSE)&"" -> 一棟 | I7: =HLOOKUP(I$2,id2_asset,asset!$A12,FALSE)&"" -> 一棟 | J7: =HLOOKUP(J$2,id2_asset,asset!$A12,FALSE)&"" -> 一棟 | K7: =HLOOKUP(K$2,id2_asset,asset!$A12,FALSE)&"" -> 一棟 | ... BA7: =HLOOKUP(BA$2,id2_asset,asset!$A12,FALSE)&"" -> #N/A
A8: 17 | B8: 権利形態 | D8: =HLOOKUP(D$2,id2_asset,asset!$A13,FALSE)&"" -> 所有権 | E8: =HLOOKUP(E$2,id2_asset,asset!$A13,FALSE)&"" -> 所有権 | F8: =HLOOKUP(F$2,id2_asset,asset!$A13,FALSE)&"" -> 所有権 | G8: =HLOOKUP(G$2,id2_asset,asset!$A13,FALSE)&"" -> 所有権 | H8: =HLOOKUP(H$2,id2_asset,asset!$A13,FALSE)&"" -> 所有権 | I8: =HLOOKUP(I$2,id2_asset,asset!$A13,FALSE)&"" -> 所有権 | J8: =HLOOKUP(J$2,id2_asset,asset!$A13,FALSE)&"" -> 所有権 | K8: =HLOOKUP(K$2,id2_asset,asset!$A13,FALSE)&"" -> 所有権 | ... BA8: =HLOOKUP(BA$2,id2_asset,asset!$A13,FALSE)&"" -> #N/A
A9: 18 | B9: 土地面積 | C9: 課税明細より | D9: =GETPIVOTDATA("合計 / 面積ネット (持分按分後の実質)",pivot!$DJ$5,"物件名",D1,"資産クラス2","土地3種") -> 313.11 | E9: =GETPIVOTDATA("合計 / 面積ネット (持分按分後の実質)",pivot!$DJ$5,"物件名",E1,"資産クラス2","土地3種") -> 732.25 | F9: =GETPIVOTDATA("合計 / 面積ネット (持分按分後の実質)",pivot!$DJ$5,"物件名",F1,"資産クラス2","土地3種") -> 395.33 | G9: =GETPIVOTDATA("合計 / 面積ネット (持分按分後の実質)",pivot!$DJ$5,"物件名",G1,"資産クラス2","土地3種") -> 137.3 | H9: =GETPIVOTDATA("合計 / 面積ネット (持分按分後の実質)",pivot!$DJ$5,"物件名",H1,"資産クラス2","土地3種") -> 342.64 | I9: =GETPIVOTDATA("合計 / 面積ネット (持分按分後の実質)",pivot!$DJ$5,"物件名",I1,"資産クラス2","土地3種") -> 286.9 | J9: =GETPIVOTDATA("合計 / 面積ネット (持分按分後の実質)",pivot!$DJ$5,"物件名",J1,"資産クラス2","土地3種") -> 560.83 | K9: =GETPIVOTDATA("合計 / 面積ネット (持分按分後の実質)",pivot!$DJ$5,"物件名",K1,"資産クラス2","土地3種") -> 252.09 | ... BA9: =GETPIVOTDATA("合計 / 面積ネット (持分按分後の実質)",pivot!$DJ$5,"物件名",BA1,"資産クラス2","土地3種") -> #REF!
A10: 19 | B10: 土地面積（坪） | C10: 〃 | D10: =D9/3.30579 -> 94.715635 | E10: =E9/3.30579 -> 221.5053 | F10: =F9/3.30579 -> 119.58715 | G10: =G9/3.30579 -> 41.533189 | H10: =H9/3.30579 -> 103.64845 | I10: =I9/3.30579 -> 86.787122 | J10: =J9/3.30579 -> 169.65082 | K10: =K9/3.30579 -> 76.257113 | ... BA10: =BA9/3.30579 -> #REF!
A11: 20 | B11: 建物のべ床 | C11: 〃 | D11: =GETPIVOTDATA("合計 / 面積ネット (持分按分後の実質)",pivot!$DJ$5,"物件名",D1,"資産クラス2","建物") -> 528.43 | E11: =GETPIVOTDATA("合計 / 面積ネット (持分按分後の実質)",pivot!$DJ$5,"物件名",E1,"資産クラス2","建物") -> 1110.34 | F11: =GETPIVOTDATA("合計 / 面積ネット (持分按分後の実質)",pivot!$DJ$5,"物件名",F1,"資産クラス2","建物") -> 887.19 | G11: =GETPIVOTDATA("合計 / 面積ネット (持分按分後の実質)",pivot!$DJ$5,"物件名",G1,"資産クラス2","建物") -> 177.12 | H11: =GETPIVOTDATA("合計 / 面積ネット (持分按分後の実質)",pivot!$DJ$5,"物件名",H1,"資産クラス2","建物") -> 1072.93 | I11: =GETPIVOTDATA("合計 / 面積ネット (持分按分後の実質)",pivot!$DJ$5,"物件名",I1,"資産クラス2","建物") -> 1133.51 | J11: =GETPIVOTDATA("合計 / 面積ネット (持分按分後の実質)",pivot!$DJ$5,"物件名",J1,"資産クラス2","建物") -> 961.19 | K11: =GETPIVOTDATA("合計 / 面積ネット (持分按分後の実質)",pivot!$DJ$5,"物件名",K1,"資産クラス2","建物") -> 588.5 | ... BA11: =GETPIVOTDATA("合計 / 面積ネット (持分按分後の実質)",pivot!$DJ$5,"物件名",BA1,"資産クラス2","建物") -> #REF!
A12: 21 | B12: 建物構造 | D12: =HLOOKUP(D$2,id2_asset,asset!$A14,FALSE)&"" -> RC/B1F-4F | E12: =HLOOKUP(E$2,id2_asset,asset!$A14,FALSE)&"" -> RC/B1F-3F | F12: =HLOOKUP(F$2,id2_asset,asset!$A14,FALSE)&"" -> RC/1-6F | G12: =HLOOKUP(G$2,id2_asset,asset!$A14,FALSE)&"" -> RC/1-5F | H12: =HLOOKUP(H$2,id2_asset,asset!$A14,FALSE)&"" -> RC/B1-5F | I12: =HLOOKUP(I$2,id2_asset,asset!$A14,FALSE)&"" -> 鉄骨造/1-8F | J12: =HLOOKUP(J$2,id2_asset,asset!$A14,FALSE)&"" -> 鉄骨造/1-8F | K12: =HLOOKUP(K$2,id2_asset,asset!$A14,FALSE)&"" -> RC/1-5F | ... BA12: =HLOOKUP(BA$2,id2_asset,asset!$A14,FALSE)&"" -> #N/A
A13: 22 | B13: 建物築年 | D13: =HLOOKUP(D$2,id2_asset,asset!$A15,FALSE) -> 33639 | E13: =HLOOKUP(E$2,id2_asset,asset!$A15,FALSE) -> 34852 | F13: =HLOOKUP(F$2,id2_asset,asset!$A15,FALSE) -> 36647 | G13: =HLOOKUP(G$2,id2_asset,asset!$A15,FALSE) -> 28501 | H13: =HLOOKUP(H$2,id2_asset,asset!$A15,FALSE) -> 37053 | I13: =HLOOKUP(I$2,id2_asset,asset!$A15,FALSE) -> 37296 | J13: =HLOOKUP(J$2,id2_asset,asset!$A15,FALSE) -> 33639 | K13: =HLOOKUP(K$2,id2_asset,asset!$A15,FALSE) -> 36647 | ... BA13: =HLOOKUP(BA$2,id2_asset,asset!$A15,FALSE) -> #N/A
A14: 23 | B14: 建物経過年数 | D14: =current_year-YEAR(D13) -> 31 | E14: =current_year-YEAR(E13) -> 28 | F14: =current_year-YEAR(F13) -> 23 | G14: =current_year-YEAR(G13) -> 45 | H14: =current_year-YEAR(H13) -> 22 | I14: =current_year-YEAR(I13) -> 21 | J14: =current_year-YEAR(J13) -> 31 | K14: =current_year-YEAR(K13) -> 23 | ... BA14: =current_year-YEAR(BA13) -> #N/A
A15: 24 | B15: 総区画数 | C15: =GETPIVOTDATA("45.物理区画判定(自動)",pivot!$DY$6) -> 303 | D15: =IFERROR(GETPIVOTDATA("45.物理区画判定(自動)",pivot!$DY$6,"3.物件名",D$1),0) -> 24 | E15: =IFERROR(GETPIVOTDATA("45.物理区画判定(自動)",pivot!$DY$6,"3.物件名",E$1),0) -> 36 | F15: =IFERROR(GETPIVOTDATA("45.物理区画判定(自動)",pivot!$DY$6,"3.物件名",F$1),0) -> 18 | G15: =IFERROR(GETPIVOTDATA("45.物理区画判定(自動)",pivot!$DY$6,"3.物件名",G$1),0) -> 8 | H15: =IFERROR(GETPIVOTDATA("45.物理区画判定(自動)",pivot!$DY$6,"3.物件名",H$1),0) -> 29 | I15: =IFERROR(GETPIVOTDATA("45.物理区画判定(自動)",pivot!$DY$6,"3.物件名",I$1),0) -> 22 | J15: =IFERROR(GETPIVOTDATA("45.物理区画判定(自動)",pivot!$DY$6,"3.物件名",J$1),0) -> 23 | K15: =IFERROR(GETPIVOTDATA("45.物理区画判定(自動)",pivot!$DY$6,"3.物件名",K$1),0) -> 16 | ... BA15: =IFERROR(GETPIVOTDATA("45.物理区画判定(自動)",pivot!$DY$6,"3.物件名",BA$1),0) -> 0
A16: 25 | B16: うち住居数 | C16: =IFERROR(GETPIVOTDATA("45.物理区画判定(自動)",pivot!$DY$6,"7.クラス","住居","7.クラス2","住居"),0) -> 255 | D16: =IFERROR(GETPIVOTDATA("45.物理区画判定(自動)",pivot!$DY$6,"3.物件名",D1,"7.クラス","住居","7.クラス2","住居"),0) -> 22 | E16: =IFERROR(GETPIVOTDATA("45.物理区画判定(自動)",pivot!$DY$6,"3.物件名",E1,"7.クラス","住居","7.クラス2","住居"),0) -> 34 | F16: =IFERROR(GETPIVOTDATA("45.物理区画判定(自動)",pivot!$DY$6,"3.物件名",F1,"7.クラス","住居","7.クラス2","住居"),0) -> 9 | G16: =IFERROR(GETPIVOTDATA("45.物理区画判定(自動)",pivot!$DY$6,"3.物件名",G1,"7.クラス","住居","7.クラス2","住居"),0) -> 6 | H16: =IFERROR(GETPIVOTDATA("45.物理区画判定(自動)",pivot!$DY$6,"3.物件名",H1,"7.クラス","住居","7.クラス2","住居"),0) -> 24 | I16: =IFERROR(GETPIVOTDATA("45.物理区画判定(自動)",pivot!$DY$6,"3.物件名",I1,"7.クラス","住居","7.クラス2","住居"),0) -> 21 | J16: =IFERROR(GETPIVOTDATA("45.物理区画判定(自動)",pivot!$DY$6,"3.物件名",J1,"7.クラス","住居","7.クラス2","住居"),0) -> 22 | K16: =IFERROR(GETPIVOTDATA("45.物理区画判定(自動)",pivot!$DY$6,"3.物件名",K1,"7.クラス","住居","7.クラス2","住居"),0) -> 12 | ... BA16: =IFERROR(GETPIVOTDATA("45.物理区画判定(自動)",pivot!$DY$6,"3.物件名",BA1,"7.クラス","住居","7.クラス2","住居"),0) -> 0
A17: 26 | B17: うち事務所/店舗数 | C17: =IFERROR(GETPIVOTDATA("45.物理区画判定(自動)",pivot!$DY$6,"7.クラス2","店舗事務所系物理区画"),0) -> 16 | D17: =IFERROR(GETPIVOTDATA("45.物理区画判定(自動)",pivot!$DY$6,"3.物件名",D1,"7.クラス2","店舗事務所系物理区画"),0) -> 1 | E17: =IFERROR(GETPIVOTDATA("45.物理区画判定(自動)",pivot!$DY$6,"3.物件名",E1,"7.クラス2","店舗事務所系物理区画"),0) -> 0 | F17: =IFERROR(GETPIVOTDATA("45.物理区画判定(自動)",pivot!$DY$6,"3.物件名",F1,"7.クラス2","店舗事務所系物理区画"),0) -> 6 | G17: =IFERROR(GETPIVOTDATA("45.物理区画判定(自動)",pivot!$DY$6,"3.物件名",G1,"7.クラス2","店舗事務所系物理区画"),0) -> 2 | H17: =IFERROR(GETPIVOTDATA("45.物理区画判定(自動)",pivot!$DY$6,"3.物件名",H1,"7.クラス2","店舗事務所系物理区画"),0) -> 1 | I17: =IFERROR(GETPIVOTDATA("45.物理区画判定(自動)",pivot!$DY$6,"3.物件名",I1,"7.クラス2","店舗事務所系物理区画"),0) -> 0 | J17: =IFERROR(GETPIVOTDATA("45.物理区画判定(自動)",pivot!$DY$6,"3.物件名",J1,"7.クラス2","店舗事務所系物理区画"),0) -> 1 | K17: =IFERROR(GETPIVOTDATA("45.物理区画判定(自動)",pivot!$DY$6,"3.物件名",K1,"7.クラス2","店舗事務所系物理区画"),0) -> 0 | ... BA17: =IFERROR(GETPIVOTDATA("45.物理区画判定(自動)",pivot!$DY$6,"3.物件名",BA1,"7.クラス2","店舗事務所系物理区画"),0) -> 0
