Workbook

Sheet 00_前提入力
A1: 🌱 家族の未来 逆算プランニング（子3人版）— 前提入力
A2: 凡例：🟡黄=ここを変えるとすべて再計算 ／ 黒=自動計算 ／ 緑=他タブが参照 ／ 赤=赤字の年（02・03で表示）
A3: ※第2子(2028)・第3子(2031)は想定。葵斗は2026/9/19生まれが正。数字は保守シナリオ＝事業が伸びれば上振れ。
A5: 【1】家族の生年（西暦）
A6: 研太 | B6: 1992 | C6: 2026年に34歳
A7: 麻梨奈 | B7: 1993 | C7: 1993/6/26・2026年に33歳
A8: 葵斗（あおと） | B8: 2026 | C8: 2026/9/19生・小学校2033/4
A9: 第2子（想定） | B9: 2028 | C9: 想定。変われば修正
A10: 第3子（想定） | B10: 2031 | C10: 想定。変われば修正
A13: 【2】世帯純収入（手取り・万/年）※可変シナリオ
A14: 2026 立上げ期 | B14: 400 | C14: 給与ゼロ・オーロラ立上げ赤字／栄町等スポット
A15: 2027 黒字化 | B15: 550 | C15: オーロラ営業委譲開始・AI医療型化
A16: 2028 果実の入口 | B16: 750 | C16: 複数事業CF・第2子
A17: 2029 | B17: 900
A18: 2030 | B18: 1000
A19: 2031〜2056 安定 | B19: 1100 | C19: 仕組み化後の世帯手取り（保守）
A20: 2057〜 老後(年金) | B20: 240 | C20: 夫婦年金 月20万。不足は資産取崩し
A22: 【3】支出前提（万/年）
A23: 基礎生活費（夫婦） | B23: 361 | C23: 月30.1万（家賃・教育は別計上）
A24: 子1人あたり追加生活費 | B24: 40 | C24: 扶養 0〜22歳の各児
A25: 教育費（1人/年） | B25: 100 | C25: 就学6〜22歳・国公立＋塾。3人で約5,100万
A26: 家賃（賃貸期） | B26: 180 | C26: 月15万・2030年まで
A27: 住替後の住居維持費 | B27: 75 | C27: ローン利息＋管理修繕（元本は資産で中立）
A29: 【4】ライフイベント（万）
A30: 車（1回の買替） | B30: 350
A31: 車 次回更新年 | B31: 2030 | C31: ここから周期ごとに買替
A32: 車 更新周期（年） | B32: 7
A33: 留学（1人分） | B33: 400 | C33: 200万×2年・マレーシア帰国子女化
A34: 留学する年齢 | B34: 13 | C34: 中学1年で渡航想定
A35: 出産費（1回） | B35: 50 | C35: 第2子・第3子で各1回
A36: 住み替え 諸費用 | B36: 400 | C36: 頭金以外の諸費用・税。2031に計上
A37: 住み替え 実行年 | B37: 2031 | C37: 葵斗 小学校前
A39: 【5】資産の起点・長期目標
A40: 純資産（2026年初・万） | B40: 2893 | C40: 現金886＋株＋不動産等。6/1監査で確認
A41: 老後資金 目標（万） | B41: 18000 | C41: 夫婦の老後1.8億。事業CFの果実で
A42: 住み替え 物件価格（万） | B42: 6000 | C42: 都内・即売れる中古/値上り新築

Sheet 01_直近3年詳細
A1: 📅 直近3年 半期詳細（2026〜2028）— 種まきの中身
A3: 項目（万） | B3: 2026H1 | C3: 2026H2 | D3: 2027H1 | E3: 2027H2 | F3: 2028H1 | G3: 2028H2
A4: オーロラFC（訪問医療） | B4: 0 | C4: -60 | D4: -20 | E4: 60 | F4: 120 | G4: 160
A5: AI医療コンサル | B5: 0 | C5: 10 | D5: 30 | E5: 50 | F5: 70 | G5: 90
A6: 不動産 紹介ザオラル | B6: 50 | C6: 80 | D6: 60 | E6: 100 | F6: 80 | G6: 120
A7: 医療テナント承継 | B7: 0 | C7: 55 | D7: 0 | E7: 55 | F7: 55 | G7: 55
A8: 事業CF 計 | B8: =SUM(B4:B7) | C8: =SUM(C4:C7) | D8: =SUM(D4:D7) | E8: =SUM(E4:E7) | F8: =SUM(F4:F7) | G8: =SUM(G4:G7)
A9: 世帯 生活費（半期） | B9: =-('00_前提入力'!$B$23/2+'00_前提入力'!$B$26/2) | C9: =-('00_前提入力'!$B$23/2+'00_前提入力'!$B$26/2) | D9: =-('00_前提入力'!$B$23/2+'00_前提入力'!$B$26/2) | E9: =-('00_前提入力'!$B$23/2+'00_前提入力'!$B$26/2) | F9: =-('00_前提入力'!$B$23/2+'00_前提入力'!$B$26/2) | G9: =-('00_前提入力'!$B$23/2+'00_前提入力'!$B$26/2)
A10: 半期 収支 | B10: =B8+B9 | C10: =C8+C9 | D10: =D8+D9 | E10: =E8+E9 | F10: =F8+F9 | G10: =G8+G9
A11: 累積（事業CF視点） | B11: =B10 | C11: =B11+C10 | D11: =C11+D10 | E11: =D11+E10 | F11: =E11+F10 | G11: =F11+G10
A13: 家族イベント
A14: 2026: 9/19 葵斗誕生・6/25 結婚記念／オーロラ開業・公庫融資 ｜ 2027: 黒字化・役員報酬600 ｜ 2028: 第2子・複数事業の入口

Sheet 02_ゴール別逆算
A1: 🎯 ゴール別 逆算（麻梨奈さんと一緒に見る1枚）
A2: 「いつ・いくら・毎月いくら」。家・車・留学は“積立で届く”、教育・老後は“事業CFの果実”で賄う。
A4: ゴール | B4: いつ（年） | C4: 総額（万） | D4: 準備年数 | E4: 毎月いくら（万） | F4: 賄い方
A5: 🏠 家（自己資金） | B5: ='00_前提入力'!$B$37 | C5: ='00_前提入力'!$B$42*0.2+'00_前提入力'!$B$36 | D5: ='00_前提入力'!$B$37-2026 | E5: =C5/(D5*12) | F5: 積立で届く
A6: 🚗 車（1台・周期） | B6: ='00_前提入力'!$B$31 | C6: ='00_前提入力'!$B$30 | D6: ='00_前提入力'!$B$32 | E6: =C6/(D6*12) | F6: 積立で届く
A7: ✈️ 留学（3人分） | B7: ='00_前提入力'!$B$8+'00_前提入力'!$B$34 | C7: ='00_前提入力'!$B$33*3 | D7: ='00_前提入力'!$B$8+'00_前提入力'!$B$34-2026 | E7: =C7/(D7*12) | F7: 積立で届く
A8: 🎓 教育（3人） | B8: ='00_前提入力'!$B$10+22 | C8: ='00_前提入力'!$B$25*17*3 | D8: ='00_前提入力'!$B$10+22-2026 | E8: =C8/(D8*12) | F8: 事業CFの果実
A9: 👶 出産（2回） | B9: ='00_前提入力'!$B$10 | C9: ='00_前提入力'!$B$35*2 | D9: ='00_前提入力'!$B$10-2026 | E9: =C9/(D9*12) | F9: 当年CFで吸収
A10: 🛋 老後（65歳〜） | B10: ='00_前提入力'!$B$6+65 | C10: ='00_前提入力'!$B$41 | D10: ='00_前提入力'!$B$6+65-2026 | E10: =C10/(D10*12) | F10: 事業CFの果実＋運用
A12: ▼ 積立で届く分の毎月合計 | E12: =E5+E6+E7 | F12: 万/月
A14: 💡 結論（妻へ）：家・車・留学は毎月の積立で届く。教育（3人で約5,100万）と老後（1.8億）は、立上げた事業のCF＝“果実”で賄う設計。 今は種まき（赤字＋住み替え＋第2子）→ 2027黒字化 → 2028複数事業の入口 → 子3人でも純資産は右肩上がり（03で確認）。

Sheet 03_生涯CF_子3人
A1: 📈 生涯キャッシュフロー（子3人・2026〜2060）— 純資産は右肩上がり
A2: 赤=その年の収支がマイナス（投資・住替・留学等）／純資産（緑列）はトレンドで増える。純資産は“家購入＝資産組換え”で目減りさせないモデル。
A4: 年 | B4: 研太 | C4: 麻梨奈 | D4: 葵斗 | E4: 第2子 | F4: 第3子 | G4: 主なイベント | H4: 収入 | I4: 支出 | J4: 収支 | K4: 純資産
A5: 2026 | B5: =$A5-'00_前提入力'!$B$6 | C5: =$A5-'00_前提入力'!$B$7 | D5: =IF($A5>='00_前提入力'!$B$8,$A5-'00_前提入力'!$B$8,"") | E5: =IF($A5>='00_前提入力'!$B$9,$A5-'00_前提入力'!$B$9,"") | F5: =IF($A5>='00_前提入力'!$B$10,$A5-'00_前提入力'!$B$10,"") | G5: 9/19 葵斗誕生・結婚記念4周年／オーロラ開業・公庫融資 | H5: =IF($A5<=2026,'00_前提入力'!$B$14,IF($A5=2027,'00_前提入力'!$B$15,IF($A5=2028,'00_前提入力'!$B$16,IF($A5=2029,'00_前提入力'!$B$17,IF($A5=2030,'00_前提入力'!$B$18,IF($A5<=2056,'00_前提入力'!$B$19,'00_前提入力'!$B$20)))))) | I5: ='00_前提入力'!$B$23+(IF(AND($A5>='00_前提入力'!$B$8,$A5-'00_前提入力'!$B$8<=22),1,0)+IF(AND($A5>='00_前提入力'!$B$9,$A5-'00_前提入力'!$B$9<=22),1,0)+IF(AND($A5>='00_前提入力'!$B$10,$A5-'00_前提入力'!$B$10<=22),1,0))*'00_前提入力'!$B$24+(IF(AND($A5-'00_前提入力'!$B$8>=6,$A5-'00_前提入力'!$B$8<=22),1,0)+IF(AND($A5-'00_前提入力'!$B$9>=6,$A5-'00_前提入力'!$B$9<=22),1,0)+IF(AND($A5-'00_前提入力'!$B$10>=6,$A5-'00_前提入力'!$B$10<=22),1,0))*'00_前提入力'!$B$25+IF($A5<'00_前提入力'!$B$37,'00_前提入力'!$B$26,'00_前提入力'!$B$27)+IF(AND($A5>='00_前提入力'!$B$31,MOD($A5-'00_前提入力'!$B$31,'00_前提入力'!$B$32)=0),'00_前提入力'!$B$30,0)+(IF($A5-'00_前提入力'!$B$8='00_前提入力'!$B$34,1,0)+IF($A5-'00_前提入力'!$B$9='00_前提入力'!$B$34,1,0)+IF($A5-'00_前提入力'!$B$10='00_前提入力'!$B$34,1,0))*'00_前提入力'!$B$33+(IF($A5='00_前提入力'!$B$9,'00_前提入力'!$B$35,0)+IF($A5='00_前提入力'!$B$10,'00_前提入力'!$B$35,0))+IF($A5='00_前提入力'!$B$37,'00_前提入力'!$B$36,0) | J5: =H5-I5 | K5: ='00_前提入力'!$B$40+J5
A6: 2027 | B6: =$A6-'00_前提入力'!$B$6 | C6: =$A6-'00_前提入力'!$B$7 | D6: =IF($A6>='00_前提入力'!$B$8,$A6-'00_前提入力'!$B$8,"") | E6: =IF($A6>='00_前提入力'!$B$9,$A6-'00_前提入力'!$B$9,"") | F6: =IF($A6>='00_前提入力'!$B$10,$A6-'00_前提入力'!$B$10,"") | G6: オーロラ営業委譲開始・役員報酬600 | H6: =IF($A6<=2026,'00_前提入力'!$B$14,IF($A6=2027,'00_前提入力'!$B$15,IF($A6=2028,'00_前提入力'!$B$16,IF($A6=2029,'00_前提入力'!$B$17,IF($A6=2030,'00_前提入力'!$B$18,IF($A6<=2056,'00_前提入力'!$B$19,'00_前提入力'!$B$20)))))) | I6: ='00_前提入力'!$B$23+(IF(AND($A6>='00_前提入力'!$B$8,$A6-'00_前提入力'!$B$8<=22),1,0)+IF(AND($A6>='00_前提入力'!$B$9,$A6-'00_前提入力'!$B$9<=22),1,0)+IF(AND($A6>='00_前提入力'!$B$10,$A6-'00_前提入力'!$B$10<=22),1,0))*'00_前提入力'!$B$24+(IF(AND($A6-'00_前提入力'!$B$8>=6,$A6-'00_前提入力'!$B$8<=22),1,0)+IF(AND($A6-'00_前提入力'!$B$9>=6,$A6-'00_前提入力'!$B$9<=22),1,0)+IF(AND($A6-'00_前提入力'!$B$10>=6,$A6-'00_前提入力'!$B$10<=22),1,0))*'00_前提入力'!$B$25+IF($A6<'00_前提入力'!$B$37,'00_前提入力'!$B$26,'00_前提入力'!$B$27)+IF(AND($A6>='00_前提入力'!$B$31,MOD($A6-'00_前提入力'!$B$31,'00_前提入力'!$B$32)=0),'00_前提入力'!$B$30,0)+(IF($A6-'00_前提入力'!$B$8='00_前提入力'!$B$34,1,0)+IF($A6-'00_前提入力'!$B$9='00_前提入力'!$B$34,1,0)+IF($A6-'00_前提入力'!$B$10='00_前提入力'!$B$34,1,0))*'00_前提入力'!$B$33+(IF($A6='00_前提入力'!$B$9,'00_前提入力'!$B$35,0)+IF($A6='00_前提入力'!$B$10,'00_前提入力'!$B$35,0))+IF($A6='00_前提入力'!$B$37,'00_前提入力'!$B$36,0) | J6: =H6-I6 | K6: =K5+J6
A7: 2028 | B7: =$A7-'00_前提入力'!$B$6 | C7: =$A7-'00_前提入力'!$B$7 | D7: =IF($A7>='00_前提入力'!$B$8,$A7-'00_前提入力'!$B$8,"") | E7: =IF($A7>='00_前提入力'!$B$9,$A7-'00_前提入力'!$B$9,"") | F7: =IF($A7>='00_前提入力'!$B$10,$A7-'00_前提入力'!$B$10,"") | G7: 第2子誕生・複数事業の入口 | H7: =IF($A7<=2026,'00_前提入力'!$B$14,IF($A7=2027,'00_前提入力'!$B$15,IF($A7=2028,'00_前提入力'!$B$16,IF($A7=2029,'00_前提入力'!$B$17,IF($A7=2030,'00_前提入力'!$B$18,IF($A7<=2056,'00_前提入力'!$B$19,'00_前提入力'!$B$20)))))) | I7: ='00_前提入力'!$B$23+(IF(AND($A7>='00_前提入力'!$B$8,$A7-'00_前提入力'!$B$8<=22),1,0)+IF(AND($A7>='00_前提入力'!$B$9,$A7-'00_前提入力'!$B$9<=22),1,0)+IF(AND($A7>='00_前提入力'!$B$10,$A7-'00_前提入力'!$B$10<=22),1,0))*'00_前提入力'!$B$24+(IF(AND($A7-'00_前提入力'!$B$8>=6,$A7-'00_前提入力'!$B$8<=22),1,0)+IF(AND($A7-'00_前提入力'!$B$9>=6,$A7-'00_前提入力'!$B$9<=22),1,0)+IF(AND($A7-'00_前提入力'!$B$10>=6,$A7-'00_前提入力'!$B$10<=22),1,0))*'00_前提入力'!$B$25+IF($A7<'00_前提入力'!$B$37,'00_前提入力'!$B$26,'00_前提入力'!$B$27)+IF(AND($A7>='00_前提入力'!$B$31,MOD($A7-'00_前提入力'!$B$31,'00_前提入力'!$B$32)=0),'00_前提入力'!$B$30,0)+(IF($A7-'00_前提入力'!$B$8='00_前提入力'!$B$34,1,0)+IF($A7-'00_前提入力'!$B$9='00_前提入力'!$B$34,1,0)+IF($A7-'00_前提入力'!$B$10='00_前提入力'!$B$34,1,0))*'00_前提入力'!$B$33+(IF($A7='00_前提入力'!$B$9,'00_前提入力'!$B$35,0)+IF($A7='00_前提入力'!$B$10,'00_前提入力'!$B$35,0))+IF($A7='00_前提入力'!$B$37,'00_前提入力'!$B$36,0) | J7: =H7-I7 | K7: =K6+J7
A8: 2029 | B8: =$A8-'00_前提入力'!$B$6 | C8: =$A8-'00_前提入力'!$B$7 | D8: =IF($A8>='00_前提入力'!$B$8,$A8-'00_前提入力'!$B$8,"") | E8: =IF($A8>='00_前提入力'!$B$9,$A8-'00_前提入力'!$B$9,"") | F8: =IF($A8>='00_前提入力'!$B$10,$A8-'00_前提入力'!$B$10,"") | H8: =IF($A8<=2026,'00_前提入力'!$B$14,IF($A8=2027,'00_前提入力'!$B$15,IF($A8=2028,'00_前提入力'!$B$16,IF($A8=2029,'00_前提入力'!$B$17,IF($A8=2030,'00_前提入力'!$B$18,IF($A8<=2056,'00_前提入力'!$B$19,'00_前提入力'!$B$20)))))) | I8: ='00_前提入力'!$B$23+(IF(AND($A8>='00_前提入力'!$B$8,$A8-'00_前提入力'!$B$8<=22),1,0)+IF(AND($A8>='00_前提入力'!$B$9,$A8-'00_前提入力'!$B$9<=22),1,0)+IF(AND($A8>='00_前提入力'!$B$10,$A8-'00_前提入力'!$B$10<=22),1,0))*'00_前提入力'!$B$24+(IF(AND($A8-'00_前提入力'!$B$8>=6,$A8-'00_前提入力'!$B$8<=22),1,0)+IF(AND($A8-'00_前提入力'!$B$9>=6,$A8-'00_前提入力'!$B$9<=22),1,0)+IF(AND($A8-'00_前提入力'!$B$10>=6,$A8-'00_前提入力'!$B$10<=22),1,0))*'00_前提入力'!$B$25+IF($A8<'00_前提入力'!$B$37,'00_前提入力'!$B$26,'00_前提入力'!$B$27)+IF(AND($A8>='00_前提入力'!$B$31,MOD($A8-'00_前提入力'!$B$31,'00_前提入力'!$B$32)=0),'00_前提入力'!$B$30,0)+(IF($A8-'00_前提入力'!$B$8='00_前提入力'!$B$34,1,0)+IF($A8-'00_前提入力'!$B$9='00_前提入力'!$B$34,1,0)+IF($A8-'00_前提入力'!$B$10='00_前提入力'!$B$34,1,0))*'00_前提入力'!$B$33+(IF($A8='00_前提入力'!$B$9,'00_前提入力'!$B$35,0)+IF($A8='00_前提入力'!$B$10,'00_前提入力'!$B$35,0))+IF($A8='00_前提入力'!$B$37,'00_前提入力'!$B$36,0) | J8: =H8-I8 | K8: =K7+J8
A9: 2030 | B9: =$A9-'00_前提入力'!$B$6 | C9: =$A9-'00_前提入力'!$B$7 | D9: =IF($A9>='00_前提入力'!$B$8,$A9-'00_前提入力'!$B$8,"") | E9: =IF($A9>='00_前提入力'!$B$9,$A9-'00_前提入力'!$B$9,"") | F9: =IF($A9>='00_前提入力'!$B$10,$A9-'00_前提入力'!$B$10,"") | G9: 車 買替 | H9: =IF($A9<=2026,'00_前提入力'!$B$14,IF($A9=2027,'00_前提入力'!$B$15,IF($A9=2028,'00_前提入力'!$B$16,IF($A9=2029,'00_前提入力'!$B$17,IF($A9=2030,'00_前提入力'!$B$18,IF($A9<=2056,'00_前提入力'!$B$19,'00_前提入力'!$B$20)))))) | I9: ='00_前提入力'!$B$23+(IF(AND($A9>='00_前提入力'!$B$8,$A9-'00_前提入力'!$B$8<=22),1,0)+IF(AND($A9>='00_前提入力'!$B$9,$A9-'00_前提入力'!$B$9<=22),1,0)+IF(AND($A9>='00_前提入力'!$B$10,$A9-'00_前提入力'!$B$10<=22),1,0))*'00_前提入力'!$B$24+(IF(AND($A9-'00_前提入力'!$B$8>=6,$A9-'00_前提入力'!$B$8<=22),1,0)+IF(AND($A9-'00_前提入力'!$B$9>=6,$A9-'00_前提入力'!$B$9<=22),1,0)+IF(AND($A9-'00_前提入力'!$B$10>=6,$A9-'00_前提入力'!$B$10<=22),1,0))*'00_前提入力'!$B$25+IF($A9<'00_前提入力'!$B$37,'00_前提入力'!$B$26,'00_前提入力'!$B$27)+IF(AND($A9>='00_前提入力'!$B$31,MOD($A9-'00_前提入力'!$B$31,'00_前提入力'!$B$32)=0),'00_前提入力'!$B$30,0)+(IF($A9-'00_前提入力'!$B$8='00_前提入力'!$B$34,1,0)+IF($A9-'00_前提入力'!$B$9='00_前提入力'!$B$34,1,0)+IF($A9-'00_前提入力'!$B$10='00_前提入力'!$B$34,1,0))*'00_前提入力'!$B$33+(IF($A9='00_前提入力'!$B$9,'00_前提入力'!$B$35,0)+IF($A9='00_前提入力'!$B$10,'00_前提入力'!$B$35,0))+IF($A9='00_前提入力'!$B$37,'00_前提入力'!$B$36,0) | J9: =H9-I9 | K9: =K8+J9
A10: 2031 | B10: =$A10-'00_前提入力'!$B$6 | C10: =$A10-'00_前提入力'!$B$7 | D10: =IF($A10>='00_前提入力'!$B$8,$A10-'00_前提入力'!$B$8,"") | E10: =IF($A10>='00_前提入力'!$B$9,$A10-'00_前提入力'!$B$9,"") | F10: =IF($A10>='00_前提入力'!$B$10,$A10-'00_前提入力'!$B$10,"") | G10: ★住み替え（都内6000万）・第3子誕生 | H10: =IF($A10<=2026,'00_前提入力'!$B$14,IF($A10=2027,'00_前提入力'!$B$15,IF($A10=2028,'00_前提入力'!$B$16,IF($A10=2029,'00_前提入力'!$B$17,IF($A10=2030,'00_前提入力'!$B$18,IF($A10<=2056,'00_前提入力'!$B$19,'00_前提入力'!$B$20)))))) | I10: ='00_前提入力'!$B$23+(IF(AND($A10>='00_前提入力'!$B$8,$A10-'00_前提入力'!$B$8<=22),1,0)+IF(AND($A10>='00_前提入力'!$B$9,$A10-'00_前提入力'!$B$9<=22),1,0)+IF(AND($A10>='00_前提入力'!$B$10,$A10-'00_前提入力'!$B$10<=22),1,0))*'00_前提入力'!$B$24+(IF(AND($A10-'00_前提入力'!$B$8>=6,$A10-'00_前提入力'!$B$8<=22),1,0)+IF(AND($A10-'00_前提入力'!$B$9>=6,$A10-'00_前提入力'!$B$9<=22),1,0)+IF(AND($A10-'00_前提入力'!$B$10>=6,$A10-'00_前提入力'!$B$10<=22),1,0))*'00_前提入力'!$B$25+IF($A10<'00_前提入力'!$B$37,'00_前提入力'!$B$26,'00_前提入力'!$B$27)+IF(AND($A10>='00_前提入力'!$B$31,MOD($A10-'00_前提入力'!$B$31,'00_前提入力'!$B$32)=0),'00_前提入力'!$B$30,0)+(IF($A10-'00_前提入力'!$B$8='00_前提入力'!$B$34,1,0)+IF($A10-'00_前提入力'!$B$9='00_前提入力'!$B$34,1,0)+IF($A10-'00_前提入力'!$B$10='00_前提入力'!$B$34,1,0))*'00_前提入力'!$B$33+(IF($A10='00_前提入力'!$B$9,'00_前提入力'!$B$35,0)+IF($A10='00_前提入力'!$B$10,'00_前提入力'!$B$35,0))+IF($A10='00_前提入力'!$B$37,'00_前提入力'!$B$36,0) | J10: =H10-I10 | K10: =K9+J10
A11: 2032 | B11: =$A11-'00_前提入力'!$B$6 | C11: =$A11-'00_前提入力'!$B$7 | D11: =IF($A11>='00_前提入力'!$B$8,$A11-'00_前提入力'!$B$8,"") | E11: =IF($A11>='00_前提入力'!$B$9,$A11-'00_前提入力'!$B$9,"") | F11: =IF($A11>='00_前提入力'!$B$10,$A11-'00_前提入力'!$B$10,"") | H11: =IF($A11<=2026,'00_前提入力'!$B$14,IF($A11=2027,'00_前提入力'!$B$15,IF($A11=2028,'00_前提入力'!$B$16,IF($A11=2029,'00_前提入力'!$B$17,IF($A11=2030,'00_前提入力'!$B$18,IF($A11<=2056,'00_前提入力'!$B$19,'00_前提入力'!$B$20)))))) | I11: ='00_前提入力'!$B$23+(IF(AND($A11>='00_前提入力'!$B$8,$A11-'00_前提入力'!$B$8<=22),1,0)+IF(AND($A11>='00_前提入力'!$B$9,$A11-'00_前提入力'!$B$9<=22),1,0)+IF(AND($A11>='00_前提入力'!$B$10,$A11-'00_前提入力'!$B$10<=22),1,0))*'00_前提入力'!$B$24+(IF(AND($A11-'00_前提入力'!$B$8>=6,$A11-'00_前提入力'!$B$8<=22),1,0)+IF(AND($A11-'00_前提入力'!$B$9>=6,$A11-'00_前提入力'!$B$9<=22),1,0)+IF(AND($A11-'00_前提入力'!$B$10>=6,$A11-'00_前提入力'!$B$10<=22),1,0))*'00_前提入力'!$B$25+IF($A11<'00_前提入力'!$B$37,'00_前提入力'!$B$26,'00_前提入力'!$B$27)+IF(AND($A11>='00_前提入力'!$B$31,MOD($A11-'00_前提入力'!$B$31,'00_前提入力'!$B$32)=0),'00_前提入力'!$B$30,0)+(IF($A11-'00_前提入力'!$B$8='00_前提入力'!$B$34,1,0)+IF($A11-'00_前提入力'!$B$9='00_前提入力'!$B$34,1,0)+IF($A11-'00_前提入力'!$B$10='00_前提入力'!$B$34,1,0))*'00_前提入力'!$B$33+(IF($A11='00_前提入力'!$B$9,'00_前提入力'!$B$35,0)+IF($A11='00_前提入力'!$B$10,'00_前提入力'!$B$35,0))+IF($A11='00_前提入力'!$B$37,'00_前提入力'!$B$36,0) | J11: =H11-I11 | K11: =K10+J11
A12: 2033 | B12: =$A12-'00_前提入力'!$B$6 | C12: =$A12-'00_前提入力'!$B$7 | D12: =IF($A12>='00_前提入力'!$B$8,$A12-'00_前提入力'!$B$8,"") | E12: =IF($A12>='00_前提入力'!$B$9,$A12-'00_前提入力'!$B$9,"") | F12: =IF($A12>='00_前提入力'!$B$10,$A12-'00_前提入力'!$B$10,"") | G12: 葵斗 小学校入学 | H12: =IF($A12<=2026,'00_前提入力'!$B$14,IF($A12=2027,'00_前提入力'!$B$15,IF($A12=2028,'00_前提入力'!$B$16,IF($A12=2029,'00_前提入力'!$B$17,IF($A12=2030,'00_前提入力'!$B$18,IF($A12<=2056,'00_前提入力'!$B$19,'00_前提入力'!$B$20)))))) | I12: ='00_前提入力'!$B$23+(IF(AND($A12>='00_前提入力'!$B$8,$A12-'00_前提入力'!$B$8<=22),1,0)+IF(AND($A12>='00_前提入力'!$B$9,$A12-'00_前提入力'!$B$9<=22),1,0)+IF(AND($A12>='00_前提入力'!$B$10,$A12-'00_前提入力'!$B$10<=22),1,0))*'00_前提入力'!$B$24+(IF(AND($A12-'00_前提入力'!$B$8>=6,$A12-'00_前提入力'!$B$8<=22),1,0)+IF(AND($A12-'00_前提入力'!$B$9>=6,$A12-'00_前提入力'!$B$9<=22),1,0)+IF(AND($A12-'00_前提入力'!$B$10>=6,$A12-'00_前提入力'!$B$10<=22),1,0))*'00_前提入力'!$B$25+IF($A12<'00_前提入力'!$B$37,'00_前提入力'!$B$26,'00_前提入力'!$B$27)+IF(AND($A12>='00_前提入力'!$B$31,MOD($A12-'00_前提入力'!$B$31,'00_前提入力'!$B$32)=0),'00_前提入力'!$B$30,0)+(IF($A12-'00_前提入力'!$B$8='00_前提入力'!$B$34,1,0)+IF($A12-'00_前提入力'!$B$9='00_前提入力'!$B$34,1,0)+IF($A12-'00_前提入力'!$B$10='00_前提入力'!$B$34,1,0))*'00_前提入力'!$B$33+(IF($A12='00_前提入力'!$B$9,'00_前提入力'!$B$35,0)+IF($A12='00_前提入力'!$B$10,'00_前提入力'!$B$35,0))+IF($A12='00_前提入力'!$B$37,'00_前提入力'!$B$36,0) | J12: =H12-I12 | K12: =K11+J12
A13: 2034 | B13: =$A13-'00_前提入力'!$B$6 | C13: =$A13-'00_前提入力'!$B$7 | D13: =IF($A13>='00_前提入力'!$B$8,$A13-'00_前提入力'!$B$8,"") | E13: =IF($A13>='00_前提入力'!$B$9,$A13-'00_前提入力'!$B$9,"") | F13: =IF($A13>='00_前提入力'!$B$10,$A13-'00_前提入力'!$B$10,"") | H13: =IF($A13<=2026,'00_前提入力'!$B$14,IF($A13=2027,'00_前提入力'!$B$15,IF($A13=2028,'00_前提入力'!$B$16,IF($A13=2029,'00_前提入力'!$B$17,IF($A13=2030,'00_前提入力'!$B$18,IF($A13<=2056,'00_前提入力'!$B$19,'00_前提入力'!$B$20)))))) | I13: ='00_前提入力'!$B$23+(IF(AND($A13>='00_前提入力'!$B$8,$A13-'00_前提入力'!$B$8<=22),1,0)+IF(AND($A13>='00_前提入力'!$B$9,$A13-'00_前提入力'!$B$9<=22),1,0)+IF(AND($A13>='00_前提入力'!$B$10,$A13-'00_前提入力'!$B$10<=22),1,0))*'00_前提入力'!$B$24+(IF(AND($A13-'00_前提入力'!$B$8>=6,$A13-'00_前提入力'!$B$8<=22),1,0)+IF(AND($A13-'00_前提入力'!$B$9>=6,$A13-'00_前提入力'!$B$9<=22),1,0)+IF(AND($A13-'00_前提入力'!$B$10>=6,$A13-'00_前提入力'!$B$10<=22),1,0))*'00_前提入力'!$B$25+IF($A13<'00_前提入力'!$B$37,'00_前提入力'!$B$26,'00_前提入力'!$B$27)+IF(AND($A13>='00_前提入力'!$B$31,MOD($A13-'00_前提入力'!$B$31,'00_前提入力'!$B$32)=0),'00_前提入力'!$B$30,0)+(IF($A13-'00_前提入力'!$B$8='00_前提入力'!$B$34,1,0)+IF($A13-'00_前提入力'!$B$9='00_前提入力'!$B$34,1,0)+IF($A13-'00_前提入力'!$B$10='00_前提入力'!$B$34,1,0))*'00_前提入力'!$B$33+(IF($A13='00_前提入力'!$B$9,'00_前提入力'!$B$35,0)+IF($A13='00_前提入力'!$B$10,'00_前提入力'!$B$35,0))+IF($A13='00_前提入力'!$B$37,'00_前提入力'!$B$36,0) | J13: =H13-I13 | K13: =K12+J13
A14: 2035 | B14: =$A14-'00_前提入力'!$B$6 | C14: =$A14-'00_前提入力'!$B$7 | D14: =IF($A14>='00_前提入力'!$B$8,$A14-'00_前提入力'!$B$8,"") | E14: =IF($A14>='00_前提入力'!$B$9,$A14-'00_前提入力'!$B$9,"") | F14: =IF($A14>='00_前提入力'!$B$10,$A14-'00_前提入力'!$B$10,"") | H14: =IF($A14<=2026,'00_前提入力'!$B$14,IF($A14=2027,'00_前提入力'!$B$15,IF($A14=2028,'00_前提入力'!$B$16,IF($A14=2029,'00_前提入力'!$B$17,IF($A14=2030,'00_前提入力'!$B$18,IF($A14<=2056,'00_前提入力'!$B$19,'00_前提入力'!$B$20)))))) | I14: ='00_前提入力'!$B$23+(IF(AND($A14>='00_前提入力'!$B$8,$A14-'00_前提入力'!$B$8<=22),1,0)+IF(AND($A14>='00_前提入力'!$B$9,$A14-'00_前提入力'!$B$9<=22),1,0)+IF(AND($A14>='00_前提入力'!$B$10,$A14-'00_前提入力'!$B$10<=22),1,0))*'00_前提入力'!$B$24+(IF(AND($A14-'00_前提入力'!$B$8>=6,$A14-'00_前提入力'!$B$8<=22),1,0)+IF(AND($A14-'00_前提入力'!$B$9>=6,$A14-'00_前提入力'!$B$9<=22),1,0)+IF(AND($A14-'00_前提入力'!$B$10>=6,$A14-'00_前提入力'!$B$10<=22),1,0))*'00_前提入力'!$B$25+IF($A14<'00_前提入力'!$B$37,'00_前提入力'!$B$26,'00_前提入力'!$B$27)+IF(AND($A14>='00_前提入力'!$B$31,MOD($A14-'00_前提入力'!$B$31,'00_前提入力'!$B$32)=0),'00_前提入力'!$B$30,0)+(IF($A14-'00_前提入力'!$B$8='00_前提入力'!$B$34,1,0)+IF($A14-'00_前提入力'!$B$9='00_前提入力'!$B$34,1,0)+IF($A14-'00_前提入力'!$B$10='00_前提入力'!$B$34,1,0))*'00_前提入力'!$B$33+(IF($A14='00_前提入力'!$B$9,'00_前提入力'!$B$35,0)+IF($A14='00_前提入力'!$B$10,'00_前提入力'!$B$35,0))+IF($A14='00_前提入力'!$B$37,'00_前提入力'!$B$36,0) | J14: =H14-I14 | K14: =K13+J14
A15: 2036 | B15: =$A15-'00_前提入力'!$B$6 | C15: =$A15-'00_前提入力'!$B$7 | D15: =IF($A15>='00_前提入力'!$B$8,$A15-'00_前提入力'!$B$8,"") | E15: =IF($A15>='00_前提入力'!$B$9,$A15-'00_前提入力'!$B$9,"") | F15: =IF($A15>='00_前提入力'!$B$10,$A15-'00_前提入力'!$B$10,"") | H15: =IF($A15<=2026,'00_前提入力'!$B$14,IF($A15=2027,'00_前提入力'!$B$15,IF($A15=2028,'00_前提入力'!$B$16,IF($A15=2029,'00_前提入力'!$B$17,IF($A15=2030,'00_前提入力'!$B$18,IF($A15<=2056,'00_前提入力'!$B$19,'00_前提入力'!$B$20)))))) | I15: ='00_前提入力'!$B$23+(IF(AND($A15>='00_前提入力'!$B$8,$A15-'00_前提入力'!$B$8<=22),1,0)+IF(AND($A15>='00_前提入力'!$B$9,$A15-'00_前提入力'!$B$9<=22),1,0)+IF(AND($A15>='00_前提入力'!$B$10,$A15-'00_前提入力'!$B$10<=22),1,0))*'00_前提入力'!$B$24+(IF(AND($A15-'00_前提入力'!$B$8>=6,$A15-'00_前提入力'!$B$8<=22),1,0)+IF(AND($A15-'00_前提入力'!$B$9>=6,$A15-'00_前提入力'!$B$9<=22),1,0)+IF(AND($A15-'00_前提入力'!$B$10>=6,$A15-'00_前提入力'!$B$10<=22),1,0))*'00_前提入力'!$B$25+IF($A15<'00_前提入力'!$B$37,'00_前提入力'!$B$26,'00_前提入力'!$B$27)+IF(AND($A15>='00_前提入力'!$B$31,MOD($A15-'00_前提入力'!$B$31,'00_前提入力'!$B$32)=0),'00_前提入力'!$B$30,0)+(IF($A15-'00_前提入力'!$B$8='00_前提入力'!$B$34,1,0)+IF($A15-'00_前提入力'!$B$9='00_前提入力'!$B$34,1,0)+IF($A15-'00_前提入力'!$B$10='00_前提入力'!$B$34,1,0))*'00_前提入力'!$B$33+(IF($A15='00_前提入力'!$B$9,'00_前提入力'!$B$35,0)+IF($A15='00_前提入力'!$B$10,'00_前提入力'!$B$35,0))+IF($A15='00_前提入力'!$B$37,'00_前提入力'!$B$36,0) | J15: =H15-I15 | K15: =K14+J15
A16: 2037 | B16: =$A16-'00_前提入力'!$B$6 | C16: =$A16-'00_前提入力'!$B$7 | D16: =IF($A16>='00_前提入力'!$B$8,$A16-'00_前提入力'!$B$8,"") | E16: =IF($A16>='00_前提入力'!$B$9,$A16-'00_前提入力'!$B$9,"") | F16: =IF($A16>='00_前提入力'!$B$10,$A16-'00_前提入力'!$B$10,"") | G16: 車 買替 | H16: =IF($A16<=2026,'00_前提入力'!$B$14,IF($A16=2027,'00_前提入力'!$B$15,IF($A16=2028,'00_前提入力'!$B$16,IF($A16=2029,'00_前提入力'!$B$17,IF($A16=2030,'00_前提入力'!$B$18,IF($A16<=2056,'00_前提入力'!$B$19,'00_前提入力'!$B$20)))))) | I16: ='00_前提入力'!$B$23+(IF(AND($A16>='00_前提入力'!$B$8,$A16-'00_前提入力'!$B$8<=22),1,0)+IF(AND($A16>='00_前提入力'!$B$9,$A16-'00_前提入力'!$B$9<=22),1,0)+IF(AND($A16>='00_前提入力'!$B$10,$A16-'00_前提入力'!$B$10<=22),1,0))*'00_前提入力'!$B$24+(IF(AND($A16-'00_前提入力'!$B$8>=6,$A16-'00_前提入力'!$B$8<=22),1,0)+IF(AND($A16-'00_前提入力'!$B$9>=6,$A16-'00_前提入力'!$B$9<=22),1,0)+IF(AND($A16-'00_前提入力'!$B$10>=6,$A16-'00_前提入力'!$B$10<=22),1,0))*'00_前提入力'!$B$25+IF($A16<'00_前提入力'!$B$37,'00_前提入力'!$B$26,'00_前提入力'!$B$27)+IF(AND($A16>='00_前提入力'!$B$31,MOD($A16-'00_前提入力'!$B$31,'00_前提入力'!$B$32)=0),'00_前提入力'!$B$30,0)+(IF($A16-'00_前提入力'!$B$8='00_前提入力'!$B$34,1,0)+IF($A16-'00_前提入力'!$B$9='00_前提入力'!$B$34,1,0)+IF($A16-'00_前提入力'!$B$10='00_前提入力'!$B$34,1,0))*'00_前提入力'!$B$33+(IF($A16='00_前提入力'!$B$9,'00_前提入力'!$B$35,0)+IF($A16='00_前提入力'!$B$10,'00_前提入力'!$B$35,0))+IF($A16='00_前提入力'!$B$37,'00_前提入力'!$B$36,0) | J16: =H16-I16 | K16: =K15+J16
A17: 2038 | B17: =$A17-'00_前提入力'!$B$6 | C17: =$A17-'00_前提入力'!$B$7 | D17: =IF($A17>='00_前提入力'!$B$8,$A17-'00_前提入力'!$B$8,"") | E17: =IF($A17>='00_前提入力'!$B$9,$A17-'00_前提入力'!$B$9,"") | F17: =IF($A17>='00_前提入力'!$B$10,$A17-'00_前提入力'!$B$10,"") | H17: =IF($A17<=2026,'00_前提入力'!$B$14,IF($A17=2027,'00_前提入力'!$B$15,IF($A17=2028,'00_前提入力'!$B$16,IF($A17=2029,'00_前提入力'!$B$17,IF($A17=2030,'00_前提入力'!$B$18,IF($A17<=2056,'00_前提入力'!$B$19,'00_前提入力'!$B$20)))))) | I17: ='00_前提入力'!$B$23+(IF(AND($A17>='00_前提入力'!$B$8,$A17-'00_前提入力'!$B$8<=22),1,0)+IF(AND($A17>='00_前提入力'!$B$9,$A17-'00_前提入力'!$B$9<=22),1,0)+IF(AND($A17>='00_前提入力'!$B$10,$A17-'00_前提入力'!$B$10<=22),1,0))*'00_前提入力'!$B$24+(IF(AND($A17-'00_前提入力'!$B$8>=6,$A17-'00_前提入力'!$B$8<=22),1,0)+IF(AND($A17-'00_前提入力'!$B$9>=6,$A17-'00_前提入力'!$B$9<=22),1,0)+IF(AND($A17-'00_前提入力'!$B$10>=6,$A17-'00_前提入力'!$B$10<=22),1,0))*'00_前提入力'!$B$25+IF($A17<'00_前提入力'!$B$37,'00_前提入力'!$B$26,'00_前提入力'!$B$27)+IF(AND($A17>='00_前提入力'!$B$31,MOD($A17-'00_前提入力'!$B$31,'00_前提入力'!$B$32)=0),'00_前提入力'!$B$30,0)+(IF($A17-'00_前提入力'!$B$8='00_前提入力'!$B$34,1,0)+IF($A17-'00_前提入力'!$B$9='00_前提入力'!$B$34,1,0)+IF($A17-'00_前提入力'!$B$10='00_前提入力'!$B$34,1,0))*'00_前提入力'!$B$33+(IF($A17='00_前提入力'!$B$9,'00_前提入力'!$B$35,0)+IF($A17='00_前提入力'!$B$10,'00_前提入力'!$B$35,0))+IF($A17='00_前提入力'!$B$37,'00_前提入力'!$B$36,0) | J17: =H17-I17 | K17: =K16+J17
A18: 2039 | B18: =$A18-'00_前提入力'!$B$6 | C18: =$A18-'00_前提入力'!$B$7 | D18: =IF($A18>='00_前提入力'!$B$8,$A18-'00_前提入力'!$B$8,"") | E18: =IF($A18>='00_前提入力'!$B$9,$A18-'00_前提入力'!$B$9,"") | F18: =IF($A18>='00_前提入力'!$B$10,$A18-'00_前提入力'!$B$10,"") | G18: 葵斗 留学（マレーシア） | H18: =IF($A18<=2026,'00_前提入力'!$B$14,IF($A18=2027,'00_前提入力'!$B$15,IF($A18=2028,'00_前提入力'!$B$16,IF($A18=2029,'00_前提入力'!$B$17,IF($A18=2030,'00_前提入力'!$B$18,IF($A18<=2056,'00_前提入力'!$B$19,'00_前提入力'!$B$20)))))) | I18: ='00_前提入力'!$B$23+(IF(AND($A18>='00_前提入力'!$B$8,$A18-'00_前提入力'!$B$8<=22),1,0)+IF(AND($A18>='00_前提入力'!$B$9,$A18-'00_前提入力'!$B$9<=22),1,0)+IF(AND($A18>='00_前提入力'!$B$10,$A18-'00_前提入力'!$B$10<=22),1,0))*'00_前提入力'!$B$24+(IF(AND($A18-'00_前提入力'!$B$8>=6,$A18-'00_前提入力'!$B$8<=22),1,0)+IF(AND($A18-'00_前提入力'!$B$9>=6,$A18-'00_前提入力'!$B$9<=22),1,0)+IF(AND($A18-'00_前提入力'!$B$10>=6,$A18-'00_前提入力'!$B$10<=22),1,0))*'00_前提入力'!$B$25+IF($A18<'00_前提入力'!$B$37,'00_前提入力'!$B$26,'00_前提入力'!$B$27)+IF(AND($A18>='00_前提入力'!$B$31,MOD($A18-'00_前提入力'!$B$31,'00_前提入力'!$B$32)=0),'00_前提入力'!$B$30,0)+(IF($A18-'00_前提入力'!$B$8='00_前提入力'!$B$34,1,0)+IF($A18-'00_前提入力'!$B$9='00_前提入力'!$B$34,1,0)+IF($A18-'00_前提入力'!$B$10='00_前提入力'!$B$34,1,0))*'00_前提入力'!$B$33+(IF($A18='00_前提入力'!$B$9,'00_前提入力'!$B$35,0)+IF($A18='00_前提入力'!$B$10,'00_前提入力'!$B$35,0))+IF($A18='00_前提入力'!$B$37,'00_前提入力'!$B$36,0) | J18: =H18-I18 | K18: =K17+J18
A19: 2040 | B19: =$A19-'00_前提入力'!$B$6 | C19: =$A19-'00_前提入力'!$B$7 | D19: =IF($A19>='00_前提入力'!$B$8,$A19-'00_前提入力'!$B$8,"") | E19: =IF($A19>='00_前提入力'!$B$9,$A19-'00_前提入力'!$B$9,"") | F19: =IF($A19>='00_前提入力'!$B$10,$A19-'00_前提入力'!$B$10,"") | H19: =IF($A19<=2026,'00_前提入力'!$B$14,IF($A19=2027,'00_前提入力'!$B$15,IF($A19=2028,'00_前提入力'!$B$16,IF($A19=2029,'00_前提入力'!$B$17,IF($A19=2030,'00_前提入力'!$B$18,IF($A19<=2056,'00_前提入力'!$B$19,'00_前提入力'!$B$20)))))) | I19: ='00_前提入力'!$B$23+(IF(AND($A19>='00_前提入力'!$B$8,$A19-'00_前提入力'!$B$8<=22),1,0)+IF(AND($A19>='00_前提入力'!$B$9,$A19-'00_前提入力'!$B$9<=22),1,0)+IF(AND($A19>='00_前提入力'!$B$10,$A19-'00_前提入力'!$B$10<=22),1,0))*'00_前提入力'!$B$24+(IF(AND($A19-'00_前提入力'!$B$8>=6,$A19-'00_前提入力'!$B$8<=22),1,0)+IF(AND($A19-'00_前提入力'!$B$9>=6,$A19-'00_前提入力'!$B$9<=22),1,0)+IF(AND($A19-'00_前提入力'!$B$10>=6,$A19-'00_前提入力'!$B$10<=22),1,0))*'00_前提入力'!$B$25+IF($A19<'00_前提入力'!$B$37,'00_前提入力'!$B$26,'00_前提入力'!$B$27)+IF(AND($A19>='00_前提入力'!$B$31,MOD($A19-'00_前提入力'!$B$31,'00_前提入力'!$B$32)=0),'00_前提入力'!$B$30,0)+(IF($A19-'00_前提入力'!$B$8='00_前提入力'!$B$34,1,0)+IF($A19-'00_前提入力'!$B$9='00_前提入力'!$B$34,1,0)+IF($A19-'00_前提入力'!$B$10='00_前提入力'!$B$34,1,0))*'00_前提入力'!$B$33+(IF($A19='00_前提入力'!$B$9,'00_前提入力'!$B$35,0)+IF($A19='00_前提入力'!$B$10,'00_前提入力'!$B$35,0))+IF($A19='00_前提入力'!$B$37,'00_前提入力'!$B$36,0) | J19: =H19-I19 | K19: =K18+J19
A20: 2041 | B20: =$A20-'00_前提入力'!$B$6 | C20: =$A20-'00_前提入力'!$B$7 | D20: =IF($A20>='00_前提入力'!$B$8,$A20-'00_前提入力'!$B$8,"") | E20: =IF($A20>='00_前提入力'!$B$9,$A20-'00_前提入力'!$B$9,"") | F20: =IF($A20>='00_前提入力'!$B$10,$A20-'00_前提入力'!$B$10,"") | G20: 第2子 留学 | H20: =IF($A20<=2026,'00_前提入力'!$B$14,IF($A20=2027,'00_前提入力'!$B$15,IF($A20=2028,'00_前提入力'!$B$16,IF($A20=2029,'00_前提入力'!$B$17,IF($A20=2030,'00_前提入力'!$B$18,IF($A20<=2056,'00_前提入力'!$B$19,'00_前提入力'!$B$20)))))) | I20: ='00_前提入力'!$B$23+(IF(AND($A20>='00_前提入力'!$B$8,$A20-'00_前提入力'!$B$8<=22),1,0)+IF(AND($A20>='00_前提入力'!$B$9,$A20-'00_前提入力'!$B$9<=22),1,0)+IF(AND($A20>='00_前提入力'!$B$10,$A20-'00_前提入力'!$B$10<=22),1,0))*'00_前提入力'!$B$24+(IF(AND($A20-'00_前提入力'!$B$8>=6,$A20-'00_前提入力'!$B$8<=22),1,0)+IF(AND($A20-'00_前提入力'!$B$9>=6,$A20-'00_前提入力'!$B$9<=22),1,0)+IF(AND($A20-'00_前提入力'!$B$10>=6,$A20-'00_前提入力'!$B$10<=22),1,0))*'00_前提入力'!$B$25+IF($A20<'00_前提入力'!$B$37,'00_前提入力'!$B$26,'00_前提入力'!$B$27)+IF(AND($A20>='00_前提入力'!$B$31,MOD($A20-'00_前提入力'!$B$31,'00_前提入力'!$B$32)=0),'00_前提入力'!$B$30,0)+(IF($A20-'00_前提入力'!$B$8='00_前提入力'!$B$34,1,0)+IF($A20-'00_前提入力'!$B$9='00_前提入力'!$B$34,1,0)+IF($A20-'00_前提入力'!$B$10='00_前提入力'!$B$34,1,0))*'00_前提入力'!$B$33+(IF($A20='00_前提入力'!$B$9,'00_前提入力'!$B$35,0)+IF($A20='00_前提入力'!$B$10,'00_前提入力'!$B$35,0))+IF($A20='00_前提入力'!$B$37,'00_前提入力'!$B$36,0) | J20: =H20-I20 | K20: =K19+J20
A21: 2042 | B21: =$A21-'00_前提入力'!$B$6 | C21: =$A21-'00_前提入力'!$B$7 | D21: =IF($A21>='00_前提入力'!$B$8,$A21-'00_前提入力'!$B$8,"") | E21: =IF($A21>='00_前提入力'!$B$9,$A21-'00_前提入力'!$B$9,"") | F21: =IF($A21>='00_前提入力'!$B$10,$A21-'00_前提入力'!$B$10,"") | H21: =IF($A21<=2026,'00_前提入力'!$B$14,IF($A21=2027,'00_前提入力'!$B$15,IF($A21=2028,'00_前提入力'!$B$16,IF($A21=2029,'00_前提入力'!$B$17,IF($A21=2030,'00_前提入力'!$B$18,IF($A21<=2056,'00_前提入力'!$B$19,'00_前提入力'!$B$20)))))) | I21: ='00_前提入力'!$B$23+(IF(AND($A21>='00_前提入力'!$B$8,$A21-'00_前提入力'!$B$8<=22),1,0)+IF(AND($A21>='00_前提入力'!$B$9,$A21-'00_前提入力'!$B$9<=22),1,0)+IF(AND($A21>='00_前提入力'!$B$10,$A21-'00_前提入力'!$B$10<=22),1,0))*'00_前提入力'!$B$24+(IF(AND($A21-'00_前提入力'!$B$8>=6,$A21-'00_前提入力'!$B$8<=22),1,0)+IF(AND($A21-'00_前提入力'!$B$9>=6,$A21-'00_前提入力'!$B$9<=22),1,0)+IF(AND($A21-'00_前提入力'!$B$10>=6,$A21-'00_前提入力'!$B$10<=22),1,0))*'00_前提入力'!$B$25+IF($A21<'00_前提入力'!$B$37,'00_前提入力'!$B$26,'00_前提入力'!$B$27)+IF(AND($A21>='00_前提入力'!$B$31,MOD($A21-'00_前提入力'!$B$31,'00_前提入力'!$B$32)=0),'00_前提入力'!$B$30,0)+(IF($A21-'00_前提入力'!$B$8='00_前提入力'!$B$34,1,0)+IF($A21-'00_前提入力'!$B$9='00_前提入力'!$B$34,1,0)+IF($A21-'00_前提入力'!$B$10='00_前提入力'!$B$34,1,0))*'00_前提入力'!$B$33+(IF($A21='00_前提入力'!$B$9,'00_前提入力'!$B$35,0)+IF($A21='00_前提入力'!$B$10,'00_前提入力'!$B$35,0))+IF($A21='00_前提入力'!$B$37,'00_前提入力'!$B$36,0) | J21: =H21-I21 | K21: =K20+J21
A22: 2043 | B22: =$A22-'00_前提入力'!$B$6 | C22: =$A22-'00_前提入力'!$B$7 | D22: =IF($A22>='00_前提入力'!$B$8,$A22-'00_前提入力'!$B$8,"") | E22: =IF($A22>='00_前提入力'!$B$9,$A22-'00_前提入力'!$B$9,"") | F22: =IF($A22>='00_前提入力'!$B$10,$A22-'00_前提入力'!$B$10,"") | H22: =IF($A22<=2026,'00_前提入力'!$B$14,IF($A22=2027,'00_前提入力'!$B$15,IF($A22=2028,'00_前提入力'!$B$16,IF($A22=2029,'00_前提入力'!$B$17,IF($A22=2030,'00_前提入力'!$B$18,IF($A22<=2056,'00_前提入力'!$B$19,'00_前提入力'!$B$20)))))) | I22: ='00_前提入力'!$B$23+(IF(AND($A22>='00_前提入力'!$B$8,$A22-'00_前提入力'!$B$8<=22),1,0)+IF(AND($A22>='00_前提入力'!$B$9,$A22-'00_前提入力'!$B$9<=22),1,0)+IF(AND($A22>='00_前提入力'!$B$10,$A22-'00_前提入力'!$B$10<=22),1,0))*'00_前提入力'!$B$24+(IF(AND($A22-'00_前提入力'!$B$8>=6,$A22-'00_前提入力'!$B$8<=22),1,0)+IF(AND($A22-'00_前提入力'!$B$9>=6,$A22-'00_前提入力'!$B$9<=22),1,0)+IF(AND($A22-'00_前提入力'!$B$10>=6,$A22-'00_前提入力'!$B$10<=22),1,0))*'00_前提入力'!$B$25+IF($A22<'00_前提入力'!$B$37,'00_前提入力'!$B$26,'00_前提入力'!$B$27)+IF(AND($A22>='00_前提入力'!$B$31,MOD($A22-'00_前提入力'!$B$31,'00_前提入力'!$B$32)=0),'00_前提入力'!$B$30,0)+(IF($A22-'00_前提入力'!$B$8='00_前提入力'!$B$34,1,0)+IF($A22-'00_前提入力'!$B$9='00_前提入力'!$B$34,1,0)+IF($A22-'00_前提入力'!$B$10='00_前提入力'!$B$34,1,0))*'00_前提入力'!$B$33+(IF($A22='00_前提入力'!$B$9,'00_前提入力'!$B$35,0)+IF($A22='00_前提入力'!$B$10,'00_前提入力'!$B$35,0))+IF($A22='00_前提入力'!$B$37,'00_前提入力'!$B$36,0) | J22: =H22-I22 | K22: =K21+J22
A23: 2044 | B23: =$A23-'00_前提入力'!$B$6 | C23: =$A23-'00_前提入力'!$B$7 | D23: =IF($A23>='00_前提入力'!$B$8,$A23-'00_前提入力'!$B$8,"") | E23: =IF($A23>='00_前提入力'!$B$9,$A23-'00_前提入力'!$B$9,"") | F23: =IF($A23>='00_前提入力'!$B$10,$A23-'00_前提入力'!$B$10,"") | G23: 車 買替・第3子 留学 | H23: =IF($A23<=2026,'00_前提入力'!$B$14,IF($A23=2027,'00_前提入力'!$B$15,IF($A23=2028,'00_前提入力'!$B$16,IF($A23=2029,'00_前提入力'!$B$17,IF($A23=2030,'00_前提入力'!$B$18,IF($A23<=2056,'00_前提入力'!$B$19,'00_前提入力'!$B$20)))))) | I23: ='00_前提入力'!$B$23+(IF(AND($A23>='00_前提入力'!$B$8,$A23-'00_前提入力'!$B$8<=22),1,0)+IF(AND($A23>='00_前提入力'!$B$9,$A23-'00_前提入力'!$B$9<=22),1,0)+IF(AND($A23>='00_前提入力'!$B$10,$A23-'00_前提入力'!$B$10<=22),1,0))*'00_前提入力'!$B$24+(IF(AND($A23-'00_前提入力'!$B$8>=6,$A23-'00_前提入力'!$B$8<=22),1,0)+IF(AND($A23-'00_前提入力'!$B$9>=6,$A23-'00_前提入力'!$B$9<=22),1,0)+IF(AND($A23-'00_前提入力'!$B$10>=6,$A23-'00_前提入力'!$B$10<=22),1,0))*'00_前提入力'!$B$25+IF($A23<'00_前提入力'!$B$37,'00_前提入力'!$B$26,'00_前提入力'!$B$27)+IF(AND($A23>='00_前提入力'!$B$31,MOD($A23-'00_前提入力'!$B$31,'00_前提入力'!$B$32)=0),'00_前提入力'!$B$30,0)+(IF($A23-'00_前提入力'!$B$8='00_前提入力'!$B$34,1,0)+IF($A23-'00_前提入力'!$B$9='00_前提入力'!$B$34,1,0)+IF($A23-'00_前提入力'!$B$10='00_前提入力'!$B$34,1,0))*'00_前提入力'!$B$33+(IF($A23='00_前提入力'!$B$9,'00_前提入力'!$B$35,0)+IF($A23='00_前提入力'!$B$10,'00_前提入力'!$B$35,0))+IF($A23='00_前提入力'!$B$37,'00_前提入力'!$B$36,0) | J23: =H23-I23 | K23: =K22+J23
A24: 2045 | B24: =$A24-'00_前提入力'!$B$6 | C24: =$A24-'00_前提入力'!$B$7 | D24: =IF($A24>='00_前提入力'!$B$8,$A24-'00_前提入力'!$B$8,"") | E24: =IF($A24>='00_前提入力'!$B$9,$A24-'00_前提入力'!$B$9,"") | F24: =IF($A24>='00_前提入力'!$B$10,$A24-'00_前提入力'!$B$10,"") | G24: 葵斗 大学 | H24: =IF($A24<=2026,'00_前提入力'!$B$14,IF($A24=2027,'00_前提入力'!$B$15,IF($A24=2028,'00_前提入力'!$B$16,IF($A24=2029,'00_前提入力'!$B$17,IF($A24=2030,'00_前提入力'!$B$18,IF($A24<=2056,'00_前提入力'!$B$19,'00_前提入力'!$B$20)))))) | I24: ='00_前提入力'!$B$23+(IF(AND($A24>='00_前提入力'!$B$8,$A24-'00_前提入力'!$B$8<=22),1,0)+IF(AND($A24>='00_前提入力'!$B$9,$A24-'00_前提入力'!$B$9<=22),1,0)+IF(AND($A24>='00_前提入力'!$B$10,$A24-'00_前提入力'!$B$10<=22),1,0))*'00_前提入力'!$B$24+(IF(AND($A24-'00_前提入力'!$B$8>=6,$A24-'00_前提入力'!$B$8<=22),1,0)+IF(AND($A24-'00_前提入力'!$B$9>=6,$A24-'00_前提入力'!$B$9<=22),1,0)+IF(AND($A24-'00_前提入力'!$B$10>=6,$A24-'00_前提入力'!$B$10<=22),1,0))*'00_前提入力'!$B$25+IF($A24<'00_前提入力'!$B$37,'00_前提入力'!$B$26,'00_前提入力'!$B$27)+IF(AND($A24>='00_前提入力'!$B$31,MOD($A24-'00_前提入力'!$B$31,'00_前提入力'!$B$32)=0),'00_前提入力'!$B$30,0)+(IF($A24-'00_前提入力'!$B$8='00_前提入力'!$B$34,1,0)+IF($A24-'00_前提入力'!$B$9='00_前提入力'!$B$34,1,0)+IF($A24-'00_前提入力'!$B$10='00_前提入力'!$B$34,1,0))*'00_前提入力'!$B$33+(IF($A24='00_前提入力'!$B$9,'00_前提入力'!$B$35,0)+IF($A24='00_前提入力'!$B$10,'00_前提入力'!$B$35,0))+IF($A24='00_前提入力'!$B$37,'00_前提入力'!$B$36,0) | J24: =H24-I24 | K24: =K23+J24
A25: 2046 | B25: =$A25-'00_前提入力'!$B$6 | C25: =$A25-'00_前提入力'!$B$7 | D25: =IF($A25>='00_前提入力'!$B$8,$A25-'00_前提入力'!$B$8,"") | E25: =IF($A25>='00_前提入力'!$B$9,$A25-'00_前提入力'!$B$9,"") | F25: =IF($A25>='00_前提入力'!$B$10,$A25-'00_前提入力'!$B$10,"") | H25: =IF($A25<=2026,'00_前提入力'!$B$14,IF($A25=2027,'00_前提入力'!$B$15,IF($A25=2028,'00_前提入力'!$B$16,IF($A25=2029,'00_前提入力'!$B$17,IF($A25=2030,'00_前提入力'!$B$18,IF($A25<=2056,'00_前提入力'!$B$19,'00_前提入力'!$B$20)))))) | I25: ='00_前提入力'!$B$23+(IF(AND($A25>='00_前提入力'!$B$8,$A25-'00_前提入力'!$B$8<=22),1,0)+IF(AND($A25>='00_前提入力'!$B$9,$A25-'00_前提入力'!$B$9<=22),1,0)+IF(AND($A25>='00_前提入力'!$B$10,$A25-'00_前提入力'!$B$10<=22),1,0))*'00_前提入力'!$B$24+(IF(AND($A25-'00_前提入力'!$B$8>=6,$A25-'00_前提入力'!$B$8<=22),1,0)+IF(AND($A25-'00_前提入力'!$B$9>=6,$A25-'00_前提入力'!$B$9<=22),1,0)+IF(AND($A25-'00_前提入力'!$B$10>=6,$A25-'00_前提入力'!$B$10<=22),1,0))*'00_前提入力'!$B$25+IF($A25<'00_前提入力'!$B$37,'00_前提入力'!$B$26,'00_前提入力'!$B$27)+IF(AND($A25>='00_前提入力'!$B$31,MOD($A25-'00_前提入力'!$B$31,'00_前提入力'!$B$32)=0),'00_前提入力'!$B$30,0)+(IF($A25-'00_前提入力'!$B$8='00_前提入力'!$B$34,1,0)+IF($A25-'00_前提入力'!$B$9='00_前提入力'!$B$34,1,0)+IF($A25-'00_前提入力'!$B$10='00_前提入力'!$B$34,1,0))*'00_前提入力'!$B$33+(IF($A25='00_前提入力'!$B$9,'00_前提入力'!$B$35,0)+IF($A25='00_前提入力'!$B$10,'00_前提入力'!$B$35,0))+IF($A25='00_前提入力'!$B$37,'00_前提入力'!$B$36,0) | J25: =H25-I25 | K25: =K24+J25
A26: 2047 | B26: =$A26-'00_前提入力'!$B$6 | C26: =$A26-'00_前提入力'!$B$7 | D26: =IF($A26>='00_前提入力'!$B$8,$A26-'00_前提入力'!$B$8,"") | E26: =IF($A26>='00_前提入力'!$B$9,$A26-'00_前提入力'!$B$9,"") | F26: =IF($A26>='00_前提入力'!$B$10,$A26-'00_前提入力'!$B$10,"") | H26: =IF($A26<=2026,'00_前提入力'!$B$14,IF($A26=2027,'00_前提入力'!$B$15,IF($A26=2028,'00_前提入力'!$B$16,IF($A26=2029,'00_前提入力'!$B$17,IF($A26=2030,'00_前提入力'!$B$18,IF($A26<=2056,'00_前提入力'!$B$19,'00_前提入力'!$B$20)))))) | I26: ='00_前提入力'!$B$23+(IF(AND($A26>='00_前提入力'!$B$8,$A26-'00_前提入力'!$B$8<=22),1,0)+IF(AND($A26>='00_前提入力'!$B$9,$A26-'00_前提入力'!$B$9<=22),1,0)+IF(AND($A26>='00_前提入力'!$B$10,$A26-'00_前提入力'!$B$10<=22),1,0))*'00_前提入力'!$B$24+(IF(AND($A26-'00_前提入力'!$B$8>=6,$A26-'00_前提入力'!$B$8<=22),1,0)+IF(AND($A26-'00_前提入力'!$B$9>=6,$A26-'00_前提入力'!$B$9<=22),1,0)+IF(AND($A26-'00_前提入力'!$B$10>=6,$A26-'00_前提入力'!$B$10<=22),1,0))*'00_前提入力'!$B$25+IF($A26<'00_前提入力'!$B$37,'00_前提入力'!$B$26,'00_前提入力'!$B$27)+IF(AND($A26>='00_前提入力'!$B$31,MOD($A26-'00_前提入力'!$B$31,'00_前提入力'!$B$32)=0),'00_前提入力'!$B$30,0)+(IF($A26-'00_前提入力'!$B$8='00_前提入力'!$B$34,1,0)+IF($A26-'00_前提入力'!$B$9='00_前提入力'!$B$34,1,0)+IF($A26-'00_前提入力'!$B$10='00_前提入力'!$B$34,1,0))*'00_前提入力'!$B$33+(IF($A26='00_前提入力'!$B$9,'00_前提入力'!$B$35,0)+IF($A26='00_前提入力'!$B$10,'00_前提入力'!$B$35,0))+IF($A26='00_前提入力'!$B$37,'00_前提入力'!$B$36,0) | J26: =H26-I26 | K26: =K25+J26
A27: 2048 | B27: =$A27-'00_前提入力'!$B$6 | C27: =$A27-'00_前提入力'!$B$7 | D27: =IF($A27>='00_前提入力'!$B$8,$A27-'00_前提入力'!$B$8,"") | E27: =IF($A27>='00_前提入力'!$B$9,$A27-'00_前提入力'!$B$9,"") | F27: =IF($A27>='00_前提入力'!$B$10,$A27-'00_前提入力'!$B$10,"") | H27: =IF($A27<=2026,'00_前提入力'!$B$14,IF($A27=2027,'00_前提入力'!$B$15,IF($A27=2028,'00_前提入力'!$B$16,IF($A27=2029,'00_前提入力'!$B$17,IF($A27=2030,'00_前提入力'!$B$18,IF($A27<=2056,'00_前提入力'!$B$19,'00_前提入力'!$B$20)))))) | I27: ='00_前提入力'!$B$23+(IF(AND($A27>='00_前提入力'!$B$8,$A27-'00_前提入力'!$B$8<=22),1,0)+IF(AND($A27>='00_前提入力'!$B$9,$A27-'00_前提入力'!$B$9<=22),1,0)+IF(AND($A27>='00_前提入力'!$B$10,$A27-'00_前提入力'!$B$10<=22),1,0))*'00_前提入力'!$B$24+(IF(AND($A27-'00_前提入力'!$B$8>=6,$A27-'00_前提入力'!$B$8<=22),1,0)+IF(AND($A27-'00_前提入力'!$B$9>=6,$A27-'00_前提入力'!$B$9<=22),1,0)+IF(AND($A27-'00_前提入力'!$B$10>=6,$A27-'00_前提入力'!$B$10<=22),1,0))*'00_前提入力'!$B$25+IF($A27<'00_前提入力'!$B$37,'00_前提入力'!$B$26,'00_前提入力'!$B$27)+IF(AND($A27>='00_前提入力'!$B$31,MOD($A27-'00_前提入力'!$B$31,'00_前提入力'!$B$32)=0),'00_前提入力'!$B$30,0)+(IF($A27-'00_前提入力'!$B$8='00_前提入力'!$B$34,1,0)+IF($A27-'00_前提入力'!$B$9='00_前提入力'!$B$34,1,0)+IF($A27-'00_前提入力'!$B$10='00_前提入力'!$B$34,1,0))*'00_前提入力'!$B$33+(IF($A27='00_前提入力'!$B$9,'00_前提入力'!$B$35,0)+IF($A27='00_前提入力'!$B$10,'00_前提入力'!$B$35,0))+IF($A27='00_前提入力'!$B$37,'00_前提入力'!$B$36,0) | J27: =H27-I27 | K27: =K26+J27
A28: 2049 | B28: =$A28-'00_前提入力'!$B$6 | C28: =$A28-'00_前提入力'!$B$7 | D28: =IF($A28>='00_前提入力'!$B$8,$A28-'00_前提入力'!$B$8,"") | E28: =IF($A28>='00_前提入力'!$B$9,$A28-'00_前提入力'!$B$9,"") | F28: =IF($A28>='00_前提入力'!$B$10,$A28-'00_前提入力'!$B$10,"") | H28: =IF($A28<=2026,'00_前提入力'!$B$14,IF($A28=2027,'00_前提入力'!$B$15,IF($A28=2028,'00_前提入力'!$B$16,IF($A28=2029,'00_前提入力'!$B$17,IF($A28=2030,'00_前提入力'!$B$18,IF($A28<=2056,'00_前提入力'!$B$19,'00_前提入力'!$B$20)))))) | I28: ='00_前提入力'!$B$23+(IF(AND($A28>='00_前提入力'!$B$8,$A28-'00_前提入力'!$B$8<=22),1,0)+IF(AND($A28>='00_前提入力'!$B$9,$A28-'00_前提入力'!$B$9<=22),1,0)+IF(AND($A28>='00_前提入力'!$B$10,$A28-'00_前提入力'!$B$10<=22),1,0))*'00_前提入力'!$B$24+(IF(AND($A28-'00_前提入力'!$B$8>=6,$A28-'00_前提入力'!$B$8<=22),1,0)+IF(AND($A28-'00_前提入力'!$B$9>=6,$A28-'00_前提入力'!$B$9<=22),1,0)+IF(AND($A28-'00_前提入力'!$B$10>=6,$A28-'00_前提入力'!$B$10<=22),1,0))*'00_前提入力'!$B$25+IF($A28<'00_前提入力'!$B$37,'00_前提入力'!$B$26,'00_前提入力'!$B$27)+IF(AND($A28>='00_前提入力'!$B$31,MOD($A28-'00_前提入力'!$B$31,'00_前提入力'!$B$32)=0),'00_前提入力'!$B$30,0)+(IF($A28-'00_前提入力'!$B$8='00_前提入力'!$B$34,1,0)+IF($A28-'00_前提入力'!$B$9='00_前提入力'!$B$34,1,0)+IF($A28-'00_前提入力'!$B$10='00_前提入力'!$B$34,1,0))*'00_前提入力'!$B$33+(IF($A28='00_前提入力'!$B$9,'00_前提入力'!$B$35,0)+IF($A28='00_前提入力'!$B$10,'00_前提入力'!$B$35,0))+IF($A28='00_前提入力'!$B$37,'00_前提入力'!$B$36,0) | J28: =H28-I28 | K28: =K27+J28
A29: 2050 | B29: =$A29-'00_前提入力'!$B$6 | C29: =$A29-'00_前提入力'!$B$7 | D29: =IF($A29>='00_前提入力'!$B$8,$A29-'00_前提入力'!$B$8,"") | E29: =IF($A29>='00_前提入力'!$B$9,$A29-'00_前提入力'!$B$9,"") | F29: =IF($A29>='00_前提入力'!$B$10,$A29-'00_前提入力'!$B$10,"") | H29: =IF($A29<=2026,'00_前提入力'!$B$14,IF($A29=2027,'00_前提入力'!$B$15,IF($A29=2028,'00_前提入力'!$B$16,IF($A29=2029,'00_前提入力'!$B$17,IF($A29=2030,'00_前提入力'!$B$18,IF($A29<=2056,'00_前提入力'!$B$19,'00_前提入力'!$B$20)))))) | I29: ='00_前提入力'!$B$23+(IF(AND($A29>='00_前提入力'!$B$8,$A29-'00_前提入力'!$B$8<=22),1,0)+IF(AND($A29>='00_前提入力'!$B$9,$A29-'00_前提入力'!$B$9<=22),1,0)+IF(AND($A29>='00_前提入力'!$B$10,$A29-'00_前提入力'!$B$10<=22),1,0))*'00_前提入力'!$B$24+(IF(AND($A29-'00_前提入力'!$B$8>=6,$A29-'00_前提入力'!$B$8<=22),1,0)+IF(AND($A29-'00_前提入力'!$B$9>=6,$A29-'00_前提入力'!$B$9<=22),1,0)+IF(AND($A29-'00_前提入力'!$B$10>=6,$A29-'00_前提入力'!$B$10<=22),1,0))*'00_前提入力'!$B$25+IF($A29<'00_前提入力'!$B$37,'00_前提入力'!$B$26,'00_前提入力'!$B$27)+IF(AND($A29>='00_前提入力'!$B$31,MOD($A29-'00_前提入力'!$B$31,'00_前提入力'!$B$32)=0),'00_前提入力'!$B$30,0)+(IF($A29-'00_前提入力'!$B$8='00_前提入力'!$B$34,1,0)+IF($A29-'00_前提入力'!$B$9='00_前提入力'!$B$34,1,0)+IF($A29-'00_前提入力'!$B$10='00_前提入力'!$B$34,1,0))*'00_前提入力'!$B$33+(IF($A29='00_前提入力'!$B$9,'00_前提入力'!$B$35,0)+IF($A29='00_前提入力'!$B$10,'00_前提入力'!$B$35,0))+IF($A29='00_前提入力'!$B$37,'00_前提入力'!$B$36,0) | J29: =H29-I29 | K29: =K28+J29
A30: 2051 | B30: =$A30-'00_前提入力'!$B$6 | C30: =$A30-'00_前提入力'!$B$7 | D30: =IF($A30>='00_前提入力'!$B$8,$A30-'00_前提入力'!$B$8,"") | E30: =IF($A30>='00_前提入力'!$B$9,$A30-'00_前提入力'!$B$9,"") | F30: =IF($A30>='00_前提入力'!$B$10,$A30-'00_前提入力'!$B$10,"") | G30: 車 買替 | H30: =IF($A30<=2026,'00_前提入力'!$B$14,IF($A30=2027,'00_前提入力'!$B$15,IF($A30=2028,'00_前提入力'!$B$16,IF($A30=2029,'00_前提入力'!$B$17,IF($A30=2030,'00_前提入力'!$B$18,IF($A30<=2056,'00_前提入力'!$B$19,'00_前提入力'!$B$20)))))) | I30: ='00_前提入力'!$B$23+(IF(AND($A30>='00_前提入力'!$B$8,$A30-'00_前提入力'!$B$8<=22),1,0)+IF(AND($A30>='00_前提入力'!$B$9,$A30-'00_前提入力'!$B$9<=22),1,0)+IF(AND($A30>='00_前提入力'!$B$10,$A30-'00_前提入力'!$B$10<=22),1,0))*'00_前提入力'!$B$24+(IF(AND($A30-'00_前提入力'!$B$8>=6,$A30-'00_前提入力'!$B$8<=22),1,0)+IF(AND($A30-'00_前提入力'!$B$9>=6,$A30-'00_前提入力'!$B$9<=22),1,0)+IF(AND($A30-'00_前提入力'!$B$10>=6,$A30-'00_前提入力'!$B$10<=22),1,0))*'00_前提入力'!$B$25+IF($A30<'00_前提入力'!$B$37,'00_前提入力'!$B$26,'00_前提入力'!$B$27)+IF(AND($A30>='00_前提入力'!$B$31,MOD($A30-'00_前提入力'!$B$31,'00_前提入力'!$B$32)=0),'00_前提入力'!$B$30,0)+(IF($A30-'00_前提入力'!$B$8='00_前提入力'!$B$34,1,0)+IF($A30-'00_前提入力'!$B$9='00_前提入力'!$B$34,1,0)+IF($A30-'00_前提入力'!$B$10='00_前提入力'!$B$34,1,0))*'00_前提入力'!$B$33+(IF($A30='00_前提入力'!$B$9,'00_前提入力'!$B$35,0)+IF($A30='00_前提入力'!$B$10,'00_前提入力'!$B$35,0))+IF($A30='00_前提入力'!$B$37,'00_前提入力'!$B$36,0) | J30: =H30-I30 | K30: =K29+J30
A31: 2052 | B31: =$A31-'00_前提入力'!$B$6 | C31: =$A31-'00_前提入力'!$B$7 | D31: =IF($A31>='00_前提入力'!$B$8,$A31-'00_前提入力'!$B$8,"") | E31: =IF($A31>='00_前提入力'!$B$9,$A31-'00_前提入力'!$B$9,"") | F31: =IF($A31>='00_前提入力'!$B$10,$A31-'00_前提入力'!$B$10,"") | H31: =IF($A31<=2026,'00_前提入力'!$B$14,IF($A31=2027,'00_前提入力'!$B$15,IF($A31=2028,'00_前提入力'!$B$16,IF($A31=2029,'00_前提入力'!$B$17,IF($A31=2030,'00_前提入力'!$B$18,IF($A31<=2056,'00_前提入力'!$B$19,'00_前提入力'!$B$20)))))) | I31: ='00_前提入力'!$B$23+(IF(AND($A31>='00_前提入力'!$B$8,$A31-'00_前提入力'!$B$8<=22),1,0)+IF(AND($A31>='00_前提入力'!$B$9,$A31-'00_前提入力'!$B$9<=22),1,0)+IF(AND($A31>='00_前提入力'!$B$10,$A31-'00_前提入力'!$B$10<=22),1,0))*'00_前提入力'!$B$24+(IF(AND($A31-'00_前提入力'!$B$8>=6,$A31-'00_前提入力'!$B$8<=22),1,0)+IF(AND($A31-'00_前提入力'!$B$9>=6,$A31-'00_前提入力'!$B$9<=22),1,0)+IF(AND($A31-'00_前提入力'!$B$10>=6,$A31-'00_前提入力'!$B$10<=22),1,0))*'00_前提入力'!$B$25+IF($A31<'00_前提入力'!$B$37,'00_前提入力'!$B$26,'00_前提入力'!$B$27)+IF(AND($A31>='00_前提入力'!$B$31,MOD($A31-'00_前提入力'!$B$31,'00_前提入力'!$B$32)=0),'00_前提入力'!$B$30,0)+(IF($A31-'00_前提入力'!$B$8='00_前提入力'!$B$34,1,0)+IF($A31-'00_前提入力'!$B$9='00_前提入力'!$B$34,1,0)+IF($A31-'00_前提入力'!$B$10='00_前提入力'!$B$34,1,0))*'00_前提入力'!$B$33+(IF($A31='00_前提入力'!$B$9,'00_前提入力'!$B$35,0)+IF($A31='00_前提入力'!$B$10,'00_前提入力'!$B$35,0))+IF($A31='00_前提入力'!$B$37,'00_前提入力'!$B$36,0) | J31: =H31-I31 | K31: =K30+J31
A32: 2053 | B32: =$A32-'00_前提入力'!$B$6 | C32: =$A32-'00_前提入力'!$B$7 | D32: =IF($A32>='00_前提入力'!$B$8,$A32-'00_前提入力'!$B$8,"") | E32: =IF($A32>='00_前提入力'!$B$9,$A32-'00_前提入力'!$B$9,"") | F32: =IF($A32>='00_前提入力'!$B$10,$A32-'00_前提入力'!$B$10,"") | H32: =IF($A32<=2026,'00_前提入力'!$B$14,IF($A32=2027,'00_前提入力'!$B$15,IF($A32=2028,'00_前提入力'!$B$16,IF($A32=2029,'00_前提入力'!$B$17,IF($A32=2030,'00_前提入力'!$B$18,IF($A32<=2056,'00_前提入力'!$B$19,'00_前提入力'!$B$20)))))) | I32: ='00_前提入力'!$B$23+(IF(AND($A32>='00_前提入力'!$B$8,$A32-'00_前提入力'!$B$8<=22),1,0)+IF(AND($A32>='00_前提入力'!$B$9,$A32-'00_前提入力'!$B$9<=22),1,0)+IF(AND($A32>='00_前提入力'!$B$10,$A32-'00_前提入力'!$B$10<=22),1,0))*'00_前提入力'!$B$24+(IF(AND($A32-'00_前提入力'!$B$8>=6,$A32-'00_前提入力'!$B$8<=22),1,0)+IF(AND($A32-'00_前提入力'!$B$9>=6,$A32-'00_前提入力'!$B$9<=22),1,0)+IF(AND($A32-'00_前提入力'!$B$10>=6,$A32-'00_前提入力'!$B$10<=22),1,0))*'00_前提入力'!$B$25+IF($A32<'00_前提入力'!$B$37,'00_前提入力'!$B$26,'00_前提入力'!$B$27)+IF(AND($A32>='00_前提入力'!$B$31,MOD($A32-'00_前提入力'!$B$31,'00_前提入力'!$B$32)=0),'00_前提入力'!$B$30,0)+(IF($A32-'00_前提入力'!$B$8='00_前提入力'!$B$34,1,0)+IF($A32-'00_前提入力'!$B$9='00_前提入力'!$B$34,1,0)+IF($A32-'00_前提入力'!$B$10='00_前提入力'!$B$34,1,0))*'00_前提入力'!$B$33+(IF($A32='00_前提入力'!$B$9,'00_前提入力'!$B$35,0)+IF($A32='00_前提入力'!$B$10,'00_前提入力'!$B$35,0))+IF($A32='00_前提入力'!$B$37,'00_前提入力'!$B$36,0) | J32: =H32-I32 | K32: =K31+J32
A33: 2054 | B33: =$A33-'00_前提入力'!$B$6 | C33: =$A33-'00_前提入力'!$B$7 | D33: =IF($A33>='00_前提入力'!$B$8,$A33-'00_前提入力'!$B$8,"") | E33: =IF($A33>='00_前提入力'!$B$9,$A33-'00_前提入力'!$B$9,"") | F33: =IF($A33>='00_前提入力'!$B$10,$A33-'00_前提入力'!$B$10,"") | H33: =IF($A33<=2026,'00_前提入力'!$B$14,IF($A33=2027,'00_前提入力'!$B$15,IF($A33=2028,'00_前提入力'!$B$16,IF($A33=2029,'00_前提入力'!$B$17,IF($A33=2030,'00_前提入力'!$B$18,IF($A33<=2056,'00_前提入力'!$B$19,'00_前提入力'!$B$20)))))) | I33: ='00_前提入力'!$B$23+(IF(AND($A33>='00_前提入力'!$B$8,$A33-'00_前提入力'!$B$8<=22),1,0)+IF(AND($A33>='00_前提入力'!$B$9,$A33-'00_前提入力'!$B$9<=22),1,0)+IF(AND($A33>='00_前提入力'!$B$10,$A33-'00_前提入力'!$B$10<=22),1,0))*'00_前提入力'!$B$24+(IF(AND($A33-'00_前提入力'!$B$8>=6,$A33-'00_前提入力'!$B$8<=22),1,0)+IF(AND($A33-'00_前提入力'!$B$9>=6,$A33-'00_前提入力'!$B$9<=22),1,0)+IF(AND($A33-'00_前提入力'!$B$10>=6,$A33-'00_前提入力'!$B$10<=22),1,0))*'00_前提入力'!$B$25+IF($A33<'00_前提入力'!$B$37,'00_前提入力'!$B$26,'00_前提入力'!$B$27)+IF(AND($A33>='00_前提入力'!$B$31,MOD($A33-'00_前提入力'!$B$31,'00_前提入力'!$B$32)=0),'00_前提入力'!$B$30,0)+(IF($A33-'00_前提入力'!$B$8='00_前提入力'!$B$34,1,0)+IF($A33-'00_前提入力'!$B$9='00_前提入力'!$B$34,1,0)+IF($A33-'00_前提入力'!$B$10='00_前提入力'!$B$34,1,0))*'00_前提入力'!$B$33+(IF($A33='00_前提入力'!$B$9,'00_前提入力'!$B$35,0)+IF($A33='00_前提入力'!$B$10,'00_前提入力'!$B$35,0))+IF($A33='00_前提入力'!$B$37,'00_前提入力'!$B$36,0) | J33: =H33-I33 | K33: =K32+J33
A34: 2055 | B34: =$A34-'00_前提入力'!$B$6 | C34: =$A34-'00_前提入力'!$B$7 | D34: =IF($A34>='00_前提入力'!$B$8,$A34-'00_前提入力'!$B$8,"") | E34: =IF($A34>='00_前提入力'!$B$9,$A34-'00_前提入力'!$B$9,"") | F34: =IF($A34>='00_前提入力'!$B$10,$A34-'00_前提入力'!$B$10,"") | H34: =IF($A34<=2026,'00_前提入力'!$B$14,IF($A34=2027,'00_前提入力'!$B$15,IF($A34=2028,'00_前提入力'!$B$16,IF($A34=2029,'00_前提入力'!$B$17,IF($A34=2030,'00_前提入力'!$B$18,IF($A34<=2056,'00_前提入力'!$B$19,'00_前提入力'!$B$20)))))) | I34: ='00_前提入力'!$B$23+(IF(AND($A34>='00_前提入力'!$B$8,$A34-'00_前提入力'!$B$8<=22),1,0)+IF(AND($A34>='00_前提入力'!$B$9,$A34-'00_前提入力'!$B$9<=22),1,0)+IF(AND($A34>='00_前提入力'!$B$10,$A34-'00_前提入力'!$B$10<=22),1,0))*'00_前提入力'!$B$24+(IF(AND($A34-'00_前提入力'!$B$8>=6,$A34-'00_前提入力'!$B$8<=22),1,0)+IF(AND($A34-'00_前提入力'!$B$9>=6,$A34-'00_前提入力'!$B$9<=22),1,0)+IF(AND($A34-'00_前提入力'!$B$10>=6,$A34-'00_前提入力'!$B$10<=22),1,0))*'00_前提入力'!$B$25+IF($A34<'00_前提入力'!$B$37,'00_前提入力'!$B$26,'00_前提入力'!$B$27)+IF(AND($A34>='00_前提入力'!$B$31,MOD($A34-'00_前提入力'!$B$31,'00_前提入力'!$B$32)=0),'00_前提入力'!$B$30,0)+(IF($A34-'00_前提入力'!$B$8='00_前提入力'!$B$34,1,0)+IF($A34-'00_前提入力'!$B$9='00_前提入力'!$B$34,1,0)+IF($A34-'00_前提入力'!$B$10='00_前提入力'!$B$34,1,0))*'00_前提入力'!$B$33+(IF($A34='00_前提入力'!$B$9,'00_前提入力'!$B$35,0)+IF($A34='00_前提入力'!$B$10,'00_前提入力'!$B$35,0))+IF($A34='00_前提入力'!$B$37,'00_前提入力'!$B$36,0) | J34: =H34-I34 | K34: =K33+J34
A35: 2056 | B35: =$A35-'00_前提入力'!$B$6 | C35: =$A35-'00_前提入力'!$B$7 | D35: =IF($A35>='00_前提入力'!$B$8,$A35-'00_前提入力'!$B$8,"") | E35: =IF($A35>='00_前提入力'!$B$9,$A35-'00_前提入力'!$B$9,"") | F35: =IF($A35>='00_前提入力'!$B$10,$A35-'00_前提入力'!$B$10,"") | H35: =IF($A35<=2026,'00_前提入力'!$B$14,IF($A35=2027,'00_前提入力'!$B$15,IF($A35=2028,'00_前提入力'!$B$16,IF($A35=2029,'00_前提入力'!$B$17,IF($A35=2030,'00_前提入力'!$B$18,IF($A35<=2056,'00_前提入力'!$B$19,'00_前提入力'!$B$20)))))) | I35: ='00_前提入力'!$B$23+(IF(AND($A35>='00_前提入力'!$B$8,$A35-'00_前提入力'!$B$8<=22),1,0)+IF(AND($A35>='00_前提入力'!$B$9,$A35-'00_前提入力'!$B$9<=22),1,0)+IF(AND($A35>='00_前提入力'!$B$10,$A35-'00_前提入力'!$B$10<=22),1,0))*'00_前提入力'!$B$24+(IF(AND($A35-'00_前提入力'!$B$8>=6,$A35-'00_前提入力'!$B$8<=22),1,0)+IF(AND($A35-'00_前提入力'!$B$9>=6,$A35-'00_前提入力'!$B$9<=22),1,0)+IF(AND($A35-'00_前提入力'!$B$10>=6,$A35-'00_前提入力'!$B$10<=22),1,0))*'00_前提入力'!$B$25+IF($A35<'00_前提入力'!$B$37,'00_前提入力'!$B$26,'00_前提入力'!$B$27)+IF(AND($A35>='00_前提入力'!$B$31,MOD($A35-'00_前提入力'!$B$31,'00_前提入力'!$B$32)=0),'00_前提入力'!$B$30,0)+(IF($A35-'00_前提入力'!$B$8='00_前提入力'!$B$34,1,0)+IF($A35-'00_前提入力'!$B$9='00_前提入力'!$B$34,1,0)+IF($A35-'00_前提入力'!$B$10='00_前提入力'!$B$34,1,0))*'00_前提入力'!$B$33+(IF($A35='00_前提入力'!$B$9,'00_前提入力'!$B$35,0)+IF($A35='00_前提入力'!$B$10,'00_前提入力'!$B$35,0))+IF($A35='00_前提入力'!$B$37,'00_前提入力'!$B$36,0) | J35: =H35-I35 | K35: =K34+J35
A36: 2057 | B36: =$A36-'00_前提入力'!$B$6 | C36: =$A36-'00_前提入力'!$B$7 | D36: =IF($A36>='00_前提入力'!$B$8,$A36-'00_前提入力'!$B$8,"") | E36: =IF($A36>='00_前提入力'!$B$9,$A36-'00_前提入力'!$B$9,"") | F36: =IF($A36>='00_前提入力'!$B$10,$A36-'00_前提入力'!$B$10,"") | G36: 研太65歳・老後フェーズ（年金＋取崩し） | H36: =IF($A36<=2026,'00_前提入力'!$B$14,IF($A36=2027,'00_前提入力'!$B$15,IF($A36=2028,'00_前提入力'!$B$16,IF($A36=2029,'00_前提入力'!$B$17,IF($A36=2030,'00_前提入力'!$B$18,IF($A36<=2056,'00_前提入力'!$B$19,'00_前提入力'!$B$20)))))) | I36: ='00_前提入力'!$B$23+(IF(AND($A36>='00_前提入力'!$B$8,$A36-'00_前提入力'!$B$8<=22),1,0)+IF(AND($A36>='00_前提入力'!$B$9,$A36-'00_前提入力'!$B$9<=22),1,0)+IF(AND($A36>='00_前提入力'!$B$10,$A36-'00_前提入力'!$B$10<=22),1,0))*'00_前提入力'!$B$24+(IF(AND($A36-'00_前提入力'!$B$8>=6,$A36-'00_前提入力'!$B$8<=22),1,0)+IF(AND($A36-'00_前提入力'!$B$9>=6,$A36-'00_前提入力'!$B$9<=22),1,0)+IF(AND($A36-'00_前提入力'!$B$10>=6,$A36-'00_前提入力'!$B$10<=22),1,0))*'00_前提入力'!$B$25+IF($A36<'00_前提入力'!$B$37,'00_前提入力'!$B$26,'00_前提入力'!$B$27)+IF(AND($A36>='00_前提入力'!$B$31,MOD($A36-'00_前提入力'!$B$31,'00_前提入力'!$B$32)=0),'00_前提入力'!$B$30,0)+(IF($A36-'00_前提入力'!$B$8='00_前提入力'!$B$34,1,0)+IF($A36-'00_前提入力'!$B$9='00_前提入力'!$B$34,1,0)+IF($A36-'00_前提入力'!$B$10='00_前提入力'!$B$34,1,0))*'00_前提入力'!$B$33+(IF($A36='00_前提入力'!$B$9,'00_前提入力'!$B$35,0)+IF($A36='00_前提入力'!$B$10,'00_前提入力'!$B$35,0))+IF($A36='00_前提入力'!$B$37,'00_前提入力'!$B$36,0) | J36: =H36-I36 | K36: =K35+J36
A37: 2058 | B37: =$A37-'00_前提入力'!$B$6 | C37: =$A37-'00_前提入力'!$B$7 | D37: =IF($A37>='00_前提入力'!$B$8,$A37-'00_前提入力'!$B$8,"") | E37: =IF($A37>='00_前提入力'!$B$9,$A37-'00_前提入力'!$B$9,"") | F37: =IF($A37>='00_前提入力'!$B$10,$A37-'00_前提入力'!$B$10,"") | H37: =IF($A37<=2026,'00_前提入力'!$B$14,IF($A37=2027,'00_前提入力'!$B$15,IF($A37=2028,'00_前提入力'!$B$16,IF($A37=2029,'00_前提入力'!$B$17,IF($A37=2030,'00_前提入力'!$B$18,IF($A37<=2056,'00_前提入力'!$B$19,'00_前提入力'!$B$20)))))) | I37: ='00_前提入力'!$B$23+(IF(AND($A37>='00_前提入力'!$B$8,$A37-'00_前提入力'!$B$8<=22),1,0)+IF(AND($A37>='00_前提入力'!$B$9,$A37-'00_前提入力'!$B$9<=22),1,0)+IF(AND($A37>='00_前提入力'!$B$10,$A37-'00_前提入力'!$B$10<=22),1,0))*'00_前提入力'!$B$24+(IF(AND($A37-'00_前提入力'!$B$8>=6,$A37-'00_前提入力'!$B$8<=22),1,0)+IF(AND($A37-'00_前提入力'!$B$9>=6,$A37-'00_前提入力'!$B$9<=22),1,0)+IF(AND($A37-'00_前提入力'!$B$10>=6,$A37-'00_前提入力'!$B$10<=22),1,0))*'00_前提入力'!$B$25+IF($A37<'00_前提入力'!$B$37,'00_前提入力'!$B$26,'00_前提入力'!$B$27)+IF(AND($A37>='00_前提入力'!$B$31,MOD($A37-'00_前提入力'!$B$31,'00_前提入力'!$B$32)=0),'00_前提入力'!$B$30,0)+(IF($A37-'00_前提入力'!$B$8='00_前提入力'!$B$34,1,0)+IF($A37-'00_前提入力'!$B$9='00_前提入力'!$B$34,1,0)+IF($A37-'00_前提入力'!$B$10='00_前提入力'!$B$34,1,0))*'00_前提入力'!$B$33+(IF($A37='00_前提入力'!$B$9,'00_前提入力'!$B$35,0)+IF($A37='00_前提入力'!$B$10,'00_前提入力'!$B$35,0))+IF($A37='00_前提入力'!$B$37,'00_前提入力'!$B$36,0) | J37: =H37-I37 | K37: =K36+J37
A38: 2059 | B38: =$A38-'00_前提入力'!$B$6 | C38: =$A38-'00_前提入力'!$B$7 | D38: =IF($A38>='00_前提入力'!$B$8,$A38-'00_前提入力'!$B$8,"") | E38: =IF($A38>='00_前提入力'!$B$9,$A38-'00_前提入力'!$B$9,"") | F38: =IF($A38>='00_前提入力'!$B$10,$A38-'00_前提入力'!$B$10,"") | H38: =IF($A38<=2026,'00_前提入力'!$B$14,IF($A38=2027,'00_前提入力'!$B$15,IF($A38=2028,'00_前提入力'!$B$16,IF($A38=2029,'00_前提入力'!$B$17,IF($A38=2030,'00_前提入力'!$B$18,IF($A38<=2056,'00_前提入力'!$B$19,'00_前提入力'!$B$20)))))) | I38: ='00_前提入力'!$B$23+(IF(AND($A38>='00_前提入力'!$B$8,$A38-'00_前提入力'!$B$8<=22),1,0)+IF(AND($A38>='00_前提入力'!$B$9,$A38-'00_前提入力'!$B$9<=22),1,0)+IF(AND($A38>='00_前提入力'!$B$10,$A38-'00_前提入力'!$B$10<=22),1,0))*'00_前提入力'!$B$24+(IF(AND($A38-'00_前提入力'!$B$8>=6,$A38-'00_前提入力'!$B$8<=22),1,0)+IF(AND($A38-'00_前提入力'!$B$9>=6,$A38-'00_前提入力'!$B$9<=22),1,0)+IF(AND($A38-'00_前提入力'!$B$10>=6,$A38-'00_前提入力'!$B$10<=22),1,0))*'00_前提入力'!$B$25+IF($A38<'00_前提入力'!$B$37,'00_前提入力'!$B$26,'00_前提入力'!$B$27)+IF(AND($A38>='00_前提入力'!$B$31,MOD($A38-'00_前提入力'!$B$31,'00_前提入力'!$B$32)=0),'00_前提入力'!$B$30,0)+(IF($A38-'00_前提入力'!$B$8='00_前提入力'!$B$34,1,0)+IF($A38-'00_前提入力'!$B$9='00_前提入力'!$B$34,1,0)+IF($A38-'00_前提入力'!$B$10='00_前提入力'!$B$34,1,0))*'00_前提入力'!$B$33+(IF($A38='00_前提入力'!$B$9,'00_前提入力'!$B$35,0)+IF($A38='00_前提入力'!$B$10,'00_前提入力'!$B$35,0))+IF($A38='00_前提入力'!$B$37,'00_前提入力'!$B$36,0) | J38: =H38-I38 | K38: =K37+J38
A39: 2060 | B39: =$A39-'00_前提入力'!$B$6 | C39: =$A39-'00_前提入力'!$B$7 | D39: =IF($A39>='00_前提入力'!$B$8,$A39-'00_前提入力'!$B$8,"") | E39: =IF($A39>='00_前提入力'!$B$9,$A39-'00_前提入力'!$B$9,"") | F39: =IF($A39>='00_前提入力'!$B$10,$A39-'00_前提入力'!$B$10,"") | H39: =IF($A39<=2026,'00_前提入力'!$B$14,IF($A39=2027,'00_前提入力'!$B$15,IF($A39=2028,'00_前提入力'!$B$16,IF($A39=2029,'00_前提入力'!$B$17,IF($A39=2030,'00_前提入力'!$B$18,IF($A39<=2056,'00_前提入力'!$B$19,'00_前提入力'!$B$20)))))) | I39: ='00_前提入力'!$B$23+(IF(AND($A39>='00_前提入力'!$B$8,$A39-'00_前提入力'!$B$8<=22),1,0)+IF(AND($A39>='00_前提入力'!$B$9,$A39-'00_前提入力'!$B$9<=22),1,0)+IF(AND($A39>='00_前提入力'!$B$10,$A39-'00_前提入力'!$B$10<=22),1,0))*'00_前提入力'!$B$24+(IF(AND($A39-'00_前提入力'!$B$8>=6,$A39-'00_前提入力'!$B$8<=22),1,0)+IF(AND($A39-'00_前提入力'!$B$9>=6,$A39-'00_前提入力'!$B$9<=22),1,0)+IF(AND($A39-'00_前提入力'!$B$10>=6,$A39-'00_前提入力'!$B$10<=22),1,0))*'00_前提入力'!$B$25+IF($A39<'00_前提入力'!$B$37,'00_前提入力'!$B$26,'00_前提入力'!$B$27)+IF(AND($A39>='00_前提入力'!$B$31,MOD($A39-'00_前提入力'!$B$31,'00_前提入力'!$B$32)=0),'00_前提入力'!$B$30,0)+(IF($A39-'00_前提入力'!$B$8='00_前提入力'!$B$34,1,0)+IF($A39-'00_前提入力'!$B$9='00_前提入力'!$B$34,1,0)+IF($A39-'00_前提入力'!$B$10='00_前提入力'!$B$34,1,0))*'00_前提入力'!$B$33+(IF($A39='00_前提入力'!$B$9,'00_前提入力'!$B$35,0)+IF($A39='00_前提入力'!$B$10,'00_前提入力'!$B$35,0))+IF($A39='00_前提入力'!$B$37,'00_前提入力'!$B$36,0) | J39: =H39-I39 | K39: =K38+J39
A41: 老後資金 目標： | G41: ='00_前提入力'!$B$41 | H41: 万 | I41: 2057年の純資産見込： | K41: =K36
A43: ※純資産＝保守シナリオ。ここに事業の上振れ（オーロラ複数エリア・AI医療・物件売却益）が乗れば老後1.8億に到達。立上げ2年・住替・留学の年は収支が赤でも、純資産トレンドは右肩上がり。
